{
  "type": "Feature",
  "properties": {
    "gn:admin1_code":"15.0",
    "gn:asciiname":"Jiema",
    "gn:country_code":"LR",
    "gn:dem":39,
    "gn:feature_class":"P",
    "gn:feature_code":"PPL",
    "gn:name":"Jiema",
    "gn:population":0,
    "gn:timezone":"Africa/Monrovia",
    "iso:country":"LR",
    "wof:name":"Jiema",
    "wof:placetype":"locality"
},
  "geometry": {"coordinates":[-10.91667,6.73333],"type":"Point"}
}