{
  "type": "Feature",
  "properties": {
    "gn:admin1_code":"19.0",
    "gn:asciiname":"Botuzo",
    "gn:country_code":"LR",
    "gn:dem":196,
    "gn:feature_class":"P",
    "gn:feature_code":"PPL",
    "gn:name":"Botuzo",
    "gn:population":0,
    "gn:timezone":"Africa/Monrovia",
    "iso:country":"LR",
    "wof:name":"Botuzo",
    "wof:placetype":"locality"
},
  "geometry": {"coordinates":[-7.87972,5.80944],"type":"Point"}
}