{
  "type": "Feature",
  "properties": {
    "gn:admin1_code":"11.0",
    "gn:asciiname":"Gorzohn Camp",
    "gn:country_code":"LR",
    "gn:dem":119,
    "gn:feature_class":"P",
    "gn:feature_code":"PPL",
    "gn:name":"Gorzohn Camp",
    "gn:population":0,
    "gn:timezone":"Africa/Monrovia",
    "iso:country":"LR",
    "name:und_x_variant":[
        "Gozohn Camp",
        "Gorzohn Camp"
    ],
    "wof:name":"Gorzohn Camp",
    "wof:placetype":"locality"
},
  "geometry": {"coordinates":[-9.7516,6.0977],"type":"Point"}
}