{
  "type": "Feature",
  "properties": {
    "gn:admin1_code":"12.0",
    "gn:asciiname":"Zimidandai Town",
    "gn:country_code":"LR",
    "gn:dem":97,
    "gn:feature_class":"P",
    "gn:feature_code":"PPL",
    "gn:name":"Zimidandai Town",
    "gn:population":0,
    "gn:timezone":"Africa/Monrovia",
    "iso:country":"LR",
    "name:und_x_variant":[
        "Dandai",
        "Zimi",
        "Zimidandai Town",
        "Zimidandai Town Hall"
    ],
    "wof:name":"Zimidandai Town",
    "wof:placetype":"locality"
},
  "geometry": {"coordinates":[-11.15631,7.22356],"type":"Point"}
}