{
  "type": "Feature",
  "properties": {
    "gn:admin1_code":"1.0",
    "gn:asciiname":"Gonita",
    "gn:country_code":"LR",
    "gn:dem":151,
    "gn:feature_class":"P",
    "gn:feature_code":"PPL",
    "gn:name":"Gonita",
    "gn:population":0,
    "gn:timezone":"Africa/Monrovia",
    "iso:country":"LR",
    "name:eng_x_preferred":[
        "Gonita"
    ],
    "wof:name":"Gonita",
    "wof:placetype":"locality"
},
  "geometry": {"coordinates":[-10.26899,6.92797],"type":"Point"}
}