{
  "type": "Feature",
  "properties": {
    "gn:admin1_code":"18.0",
    "gn:asciiname":"Kontoseka",
    "gn:country_code":"LR",
    "gn:dem":115,
    "gn:feature_class":"P",
    "gn:feature_code":"PPL",
    "gn:name":"Kontoseka",
    "gn:population":0,
    "gn:timezone":"Africa/Monrovia",
    "iso:country":"LR",
    "wof:name":"Kontoseka",
    "wof:placetype":"locality"
},
  "geometry": {"coordinates":[-9.45254,5.89462],"type":"Point"}
}