{
  "type": "Feature",
  "properties": {
    "gn:admin1_code":"11.0",
    "gn:asciiname":"Kanta",
    "gn:country_code":"LR",
    "gn:dem":109,
    "gn:feature_class":"P",
    "gn:feature_code":"PPL",
    "gn:name":"Kanta",
    "gn:population":0,
    "gn:timezone":"Africa/Monrovia",
    "iso:country":"LR",
    "wof:name":"Kanta",
    "wof:placetype":"locality"
},
  "geometry": {"coordinates":[-10.01667,6.43333],"type":"Point"}
}