{
  "type": "Feature",
  "properties": {
    "gn:admin1_code":"18.0",
    "gn:asciiname":"Deort",
    "gn:country_code":"LR",
    "gn:dem":175,
    "gn:feature_class":"P",
    "gn:feature_code":"PPL",
    "gn:name":"Deort",
    "gn:population":0,
    "gn:timezone":"Africa/Monrovia",
    "iso:country":"LR",
    "wof:name":"Deort",
    "wof:placetype":"locality"
},
  "geometry": {"coordinates":[-9.27734,6.18272],"type":"Point"}
}