{
  "type": "Feature",
  "properties": {
    "gn:admin1_code":"1.0",
    "gn:asciiname":"Jowah",
    "gn:country_code":"LR",
    "gn:dem":237,
    "gn:feature_class":"P",
    "gn:feature_code":"PPL",
    "gn:name":"Jowah",
    "gn:population":0,
    "gn:timezone":"Africa/Monrovia",
    "iso:country":"LR",
    "name:eng_x_preferred":[
        "Jowah"
    ],
    "wof:name":"Jowah",
    "wof:placetype":"locality"
},
  "geometry": {"coordinates":[-9.19604,6.77731],"type":"Point"}
}