{
  "type": "Feature",
  "properties": {
    "gn:admin1_code":"15.0",
    "gn:asciiname":"Partior",
    "gn:country_code":"LR",
    "gn:dem":54,
    "gn:feature_class":"P",
    "gn:feature_code":"PPL",
    "gn:name":"Partior",
    "gn:population":0,
    "gn:timezone":"Africa/Monrovia",
    "iso:country":"LR",
    "wof:name":"Partior",
    "wof:placetype":"locality"
},
  "geometry": {"coordinates":[-10.79395,6.73759],"type":"Point"}
}