{
  "type": "Feature",
  "properties": {
    "gn:admin1_code":"9.0",
    "gn:asciiname":"Mali",
    "gn:country_code":"LR",
    "gn:dem":227,
    "gn:feature_class":"P",
    "gn:feature_code":"PPL",
    "gn:name":"Mali",
    "gn:population":0,
    "gn:timezone":"Africa/Monrovia",
    "iso:country":"LR",
    "wof:name":"Mali",
    "wof:placetype":"locality"
},
  "geometry": {"coordinates":[-8.6075,6.50833],"type":"Point"}
}