{
  "type": "Feature",
  "properties": {
    "gn:admin1_code":"17.0",
    "gn:asciiname":"Wynn Town",
    "gn:country_code":"LR",
    "gn:dem":14,
    "gn:feature_class":"P",
    "gn:feature_code":"PPL",
    "gn:name":"Wynn Town",
    "gn:population":0,
    "gn:timezone":"Africa/Monrovia",
    "iso:country":"LR",
    "name:und_x_variant":[
        "Wehn",
        "Wein",
        "Wynn Town"
    ],
    "wof:name":"Wynn Town",
    "wof:placetype":"locality"
},
  "geometry": {"coordinates":[-10.44119,6.19965],"type":"Point"}
}