{
  "type": "Feature",
  "properties": {
    "gn:admin1_code":"16.0",
    "gn:asciiname":"Glopluken",
    "gn:country_code":"LR",
    "gn:dem":14,
    "gn:feature_class":"P",
    "gn:feature_code":"PPL",
    "gn:name":"Glopluken",
    "gn:population":0,
    "gn:timezone":"Africa/Monrovia",
    "iso:country":"LR",
    "wof:name":"Glopluken",
    "wof:placetype":"locality"
},
  "geometry": {"coordinates":[-7.87423,4.49084],"type":"Point"}
}