{
  "type": "Feature",
  "properties": {
    "gn:admin1_code":"21.0",
    "gn:asciiname":"Masokua",
    "gn:country_code":"LR",
    "gn:dem":209,
    "gn:feature_class":"P",
    "gn:feature_code":"PPL",
    "gn:name":"Masokua",
    "gn:population":0,
    "gn:timezone":"Africa/Monrovia",
    "iso:country":"LR",
    "wof:name":"Masokua",
    "wof:placetype":"locality"
},
  "geometry": {"coordinates":[-10.29111,7.16389],"type":"Point"}
}