{
  "type": "Feature",
  "properties": {
    "gn:admin1_code":"17.0",
    "gn:asciiname":"Bondowehn Vai Town",
    "gn:country_code":"LR",
    "gn:dem":24,
    "gn:feature_class":"P",
    "gn:feature_code":"PPL",
    "gn:name":"Bondowehn Vai Town",
    "gn:population":0,
    "gn:timezone":"Africa/Monrovia",
    "iso:country":"LR",
    "name:eng_x_preferred":[
        "Bondowehn Vai Town"
    ],
    "wof:name":"Bondowehn Vai Town",
    "wof:placetype":"locality"
},
  "geometry": {"coordinates":[-10.41892,6.28752],"type":"Point"}
}