{
  "type": "Feature",
  "properties": {
    "gn:admin1_code":"16.0",
    "gn:asciiname":"Worepo",
    "gn:country_code":"LR",
    "gn:dem":64,
    "gn:feature_class":"P",
    "gn:feature_code":"PPL",
    "gn:name":"Worepo",
    "gn:population":0,
    "gn:timezone":"Africa/Monrovia",
    "iso:country":"LR",
    "wof:name":"Worepo",
    "wof:placetype":"locality"
},
  "geometry": {"coordinates":[-8.52377,4.85708],"type":"Point"}
}