{
  "type": "Feature",
  "properties": {
    "gn:admin1_code":"16.0",
    "gn:asciiname":"Jufokehn",
    "gn:country_code":"LR",
    "gn:dem":27,
    "gn:feature_class":"P",
    "gn:feature_code":"PPL",
    "gn:name":"Jufokehn",
    "gn:population":0,
    "gn:timezone":"Africa/Monrovia",
    "iso:country":"LR",
    "name:und_x_variant":[
        "Ufaka",
        "Jufokehn"
    ],
    "wof:name":"Jufokehn",
    "wof:placetype":"locality"
},
  "geometry": {"coordinates":[-8.21667,4.71667],"type":"Point"}
}