{
  "type": "Feature",
  "properties": {
    "gn:admin1_code":"1.0",
    "gn:asciiname":"Gleklay's Town",
    "gn:country_code":"LR",
    "gn:dem":220,
    "gn:feature_class":"P",
    "gn:feature_code":"PPL",
    "gn:name":"Gleklay\u2019s Town",
    "gn:population":0,
    "gn:timezone":"Africa/Monrovia",
    "iso:country":"LR",
    "name:eng_x_preferred":[
        "Gleklay\u2019s Town"
    ],
    "wof:name":"Gleklay's Town",
    "wof:placetype":"locality"
},
  "geometry": {"coordinates":[-9.13796,6.7862],"type":"Point"}
}