{
  "type": "Feature",
  "properties": {
    "gn:admin1_code":"10.0",
    "gn:asciiname":"Chair",
    "gn:country_code":"LR",
    "gn:dem":53,
    "gn:feature_class":"P",
    "gn:feature_code":"PPL",
    "gn:name":"Chair",
    "gn:population":0,
    "gn:timezone":"Africa/Monrovia",
    "iso:country":"LR",
    "wof:name":"Chair",
    "wof:placetype":"locality"
},
  "geometry": {"coordinates":[-9.06667,5.16667],"type":"Point"}
}