{
  "type": "Feature",
  "properties": {
    "gn:admin1_code":"22.0",
    "gn:asciiname":"Radja",
    "gn:country_code":"LR",
    "gn:dem":215,
    "gn:feature_class":"P",
    "gn:feature_code":"PPL",
    "gn:name":"Radja",
    "gn:population":0,
    "gn:timezone":"Africa/Monrovia",
    "iso:country":"LR",
    "wof:name":"Radja",
    "wof:placetype":"locality"
},
  "geometry": {"coordinates":[-8.16667,5.21667],"type":"Point"}
}