{
  "type": "Feature",
  "properties": {
    "gn:admin1_code":"17.0",
    "gn:asciiname":"Snafu",
    "gn:country_code":"LR",
    "gn:dem":7,
    "gn:feature_class":"P",
    "gn:feature_code":"PPL",
    "gn:name":"Snafu",
    "gn:population":0,
    "gn:timezone":"Africa/Monrovia",
    "iso:country":"LR",
    "name:eng_x_preferred":[
        "Snafu"
    ],
    "wof:name":"Snafu",
    "wof:placetype":"locality"
},
  "geometry": {"coordinates":[-10.38013,6.16682],"type":"Point"}
}