{
  "type": "Feature",
  "properties": {
    "gn:admin1_code":"12.0",
    "gn:asciiname":"Sowui",
    "gn:country_code":"LR",
    "gn:dem":7,
    "gn:feature_class":"P",
    "gn:feature_code":"PPL",
    "gn:name":"Sowui",
    "gn:population":0,
    "gn:timezone":"Africa/Monrovia",
    "iso:country":"LR",
    "name:und_x_variant":[
        "Sugari",
        "Shugari",
        "Sowi",
        "Shugri",
        "Sowui"
    ],
    "wof:name":"Sowui",
    "wof:placetype":"locality"
},
  "geometry": {"coordinates":[-11.38973,6.84426],"type":"Point"}
}