{
  "type": "Feature",
  "properties": {
    "gn:admin1_code":"1.0",
    "gn:asciiname":"Gbayamu",
    "gn:cc2":"LR",
    "gn:country_code":"LR",
    "gn:dem":191,
    "gn:feature_class":"P",
    "gn:feature_code":"PPL",
    "gn:name":"Gbayamu",
    "gn:population":0,
    "gn:timezone":"Africa/Monrovia",
    "iso:country":"LR",
    "name:und_x_variant":[
        "Gbana",
        "Gbayamu"
    ],
    "wof:name":"Gbayamu",
    "wof:placetype":"locality"
},
  "geometry": {"coordinates":[-10.24722,6.8475],"type":"Point"}
}