{
  "type": "Feature",
  "properties": {
    "gn:admin1_code":"11.0",
    "gn:asciiname":"Charlie Town",
    "gn:country_code":"LR",
    "gn:dem":217,
    "gn:feature_class":"P",
    "gn:feature_code":"PPL",
    "gn:name":"Charlie Town",
    "gn:population":0,
    "gn:timezone":"Africa/Monrovia",
    "iso:country":"LR",
    "wof:name":"Charlie Town",
    "wof:placetype":"locality"
},
  "geometry": {"coordinates":[-9.28196,6.57378],"type":"Point"}
}