{
  "type": "Feature",
  "properties": {
    "gn:admin1_code":"14.0",
    "gn:asciiname":"Nogaluta",
    "gn:country_code":"LR",
    "gn:dem":91,
    "gn:feature_class":"P",
    "gn:feature_code":"PPL",
    "gn:name":"Nogaluta",
    "gn:population":0,
    "gn:timezone":"Africa/Monrovia",
    "iso:country":"LR",
    "wof:name":"Nogaluta",
    "wof:placetype":"locality"
},
  "geometry": {"coordinates":[-10.41667,6.58333],"type":"Point"}
}