{
  "type": "Feature",
  "properties": {
    "gn:admin1_code":"13.0",
    "gn:asciiname":"Tugbaken",
    "gn:country_code":"LR",
    "gn:dem":67,
    "gn:feature_class":"P",
    "gn:feature_code":"PPL",
    "gn:name":"Tugbaken",
    "gn:population":0,
    "gn:timezone":"Africa/Monrovia",
    "iso:country":"LR",
    "name:und_x_variant":[
        "Tuboke",
        "Tubake",
        "Tugbake",
        "Tugbaken",
        "Tugbakeh"
    ],
    "wof:name":"Tugbaken",
    "wof:placetype":"locality"
},
  "geometry": {"coordinates":[-7.71101,4.66165],"type":"Point"}
}