{
  "type": "Feature",
  "properties": {
    "gn:admin1_code":"17.0",
    "gn:asciiname":"Gboryormu",
    "gn:country_code":"LR",
    "gn:dem":128,
    "gn:feature_class":"P",
    "gn:feature_code":"PPL",
    "gn:name":"Gboryormu",
    "gn:population":0,
    "gn:timezone":"Africa/Monrovia",
    "iso:country":"LR",
    "name:eng_x_preferred":[
        "Gboryormu"
    ],
    "wof:name":"Gboryormu",
    "wof:placetype":"locality"
},
  "geometry": {"coordinates":[-10.28303,6.74573],"type":"Point"}
}