{
  "type": "Feature",
  "properties": {
    "gn:admin1_code":"16.0",
    "gn:asciiname":"Jlukronken",
    "gn:country_code":"LR",
    "gn:dem":52,
    "gn:feature_class":"P",
    "gn:feature_code":"PPL",
    "gn:name":"Jlukronken",
    "gn:population":0,
    "gn:timezone":"Africa/Monrovia",
    "iso:country":"LR",
    "wof:name":"Jlukronken",
    "wof:placetype":"locality"
},
  "geometry": {"coordinates":[-8.09853,4.66371],"type":"Point"}
}