{
  "type": "Feature",
  "properties": {
    "gn:admin1_code":"1.0",
    "gn:asciiname":"Yakulo",
    "gn:country_code":"LR",
    "gn:dem":172,
    "gn:feature_class":"P",
    "gn:feature_code":"PPL",
    "gn:name":"Yakulo",
    "gn:population":0,
    "gn:timezone":"Africa/Monrovia",
    "iso:country":"LR",
    "name:eng_x_preferred":[
        "Yakulo"
    ],
    "wof:name":"Yakulo",
    "wof:placetype":"locality"
},
  "geometry": {"coordinates":[-10.27542,6.83799],"type":"Point"}
}