{
  "type": "Feature",
  "properties": {
    "gn:admin1_code":"17.0",
    "gn:asciiname":"Dennis Camp",
    "gn:country_code":"LR",
    "gn:dem":95,
    "gn:feature_class":"P",
    "gn:feature_code":"PPL",
    "gn:name":"Dennis Camp",
    "gn:population":0,
    "gn:timezone":"Africa/Monrovia",
    "iso:country":"LR",
    "name:eng_x_preferred":[
        "Dennis Camp"
    ],
    "wof:name":"Dennis Camp",
    "wof:placetype":"locality"
},
  "geometry": {"coordinates":[-10.25387,6.54552],"type":"Point"}
}