{
  "type": "Feature",
  "properties": {
    "gn:admin1_code":"21.0",
    "gn:asciiname":"Bondokai Town",
    "gn:country_code":"LR",
    "gn:dem":107,
    "gn:feature_class":"P",
    "gn:feature_code":"PPL",
    "gn:name":"Bondokai Town",
    "gn:population":0,
    "gn:timezone":"Africa/Monrovia",
    "iso:country":"LR",
    "wof:name":"Bondokai Town",
    "wof:placetype":"locality"
},
  "geometry": {"coordinates":[-10.65791,6.92175],"type":"Point"}
}