{
  "type": "Feature",
  "properties": {
    "gn:admin1_code":"20.0",
    "gn:asciiname":"Nundoni",
    "gn:country_code":"LR",
    "gn:dem":446,
    "gn:feature_class":"P",
    "gn:feature_code":"PPL",
    "gn:name":"Nundoni",
    "gn:population":0,
    "gn:timezone":"Africa/Monrovia",
    "iso:country":"LR",
    "wof:name":"Nundoni",
    "wof:placetype":"locality"
},
  "geometry": {"coordinates":[-10.21667,8.33333],"type":"Point"}
}