{
  "type": "Feature",
  "properties": {
    "gn:admin1_code":"9.0",
    "gn:asciiname":"Freeman Town",
    "gn:cc2":"LR",
    "gn:country_code":"LR",
    "gn:dem":200,
    "gn:feature_class":"P",
    "gn:feature_code":"PPL",
    "gn:name":"Freeman Town",
    "gn:population":0,
    "gn:timezone":"Africa/Monrovia",
    "iso:country":"LR",
    "name:und_x_variant":[
        "Flima Town",
        "Flima",
        "Freeman Town"
    ],
    "wof:name":"Freeman Town",
    "wof:placetype":"locality"
},
  "geometry": {"coordinates":[-9.00944,6.29917],"type":"Point"}
}