{
  "type": "Feature",
  "properties": {
    "gn:admin1_code":"17.0",
    "gn:asciiname":"Glikpata",
    "gn:country_code":"LR",
    "gn:dem":135,
    "gn:feature_class":"P",
    "gn:feature_code":"PPL",
    "gn:name":"Glikpata",
    "gn:population":0,
    "gn:timezone":"Africa/Monrovia",
    "iso:country":"LR",
    "wof:name":"Glikpata",
    "wof:placetype":"locality"
},
  "geometry": {"coordinates":[-10.01667,6.61667],"type":"Point"}
}