{
  "type": "Feature",
  "properties": {
    "gn:admin1_code":"11.0",
    "gn:asciiname":"Roberts",
    "gn:cc2":"LR",
    "gn:country_code":"LR",
    "gn:dem":126,
    "gn:feature_class":"P",
    "gn:feature_code":"PPL",
    "gn:name":"Roberts",
    "gn:population":0,
    "gn:timezone":"Africa/Monrovia",
    "iso:country":"LR",
    "name:bel_x_preferred":[
        "\u0420\u043e\u0431\u0435\u0440\u0442\u0441"
    ],
    "name:cat_x_preferred":[
        "Roberts"
    ],
    "name:ceb_x_preferred":[
        "Roberts"
    ],
    "name:ces_x_preferred":[
        "Roberts"
    ],
    "name:deu_x_preferred":[
        "Roberts"
    ],
    "name:fin_x_preferred":[
        "Roberts"
    ],
    "name:fra_x_preferred":[
        "Roberts"
    ],
    "name:heb_x_preferred":[
        "\u05e8\u05d5\u05d1\u05e8\u05d8\u05e1"
    ],
    "name:ita_x_preferred":[
        "Roberts"
    ],
    "name:jpn_x_preferred":[
        "\u30ed\u30d0\u30fc\u30c4"
    ],
    "name:kor_x_preferred":[
        "\ub85c\ubc84\uce20"
    ],
    "name:lav_x_preferred":[
        "Robertsa"
    ],
    "name:lit_x_preferred":[
        "Roberts"
    ],
    "name:nld_x_preferred":[
        "Roberts"
    ],
    "name:pol_x_preferred":[
        "Roberts"
    ],
    "name:por_x_preferred":[
        "Roberts"
    ],
    "name:ron_x_preferred":[
        "Roberts"
    ],
    "name:rus_x_preferred":[
        "\u0420\u043e\u0431\u0435\u0440\u0442\u0441"
    ],
    "name:snd_x_preferred":[
        "\u0631\u0627\u0628\u0631\u067d\u0633"
    ],
    "name:spa_x_preferred":[
        "Roberts"
    ],
    "name:srp_x_preferred":[
        "\u0420\u043e\u0431\u0435\u0440\u0442\u0441"
    ],
    "name:swe_x_preferred":[
        "Roberts"
    ],
    "name:ukr_x_preferred":[
        "\u0420\u043e\u0431\u0435\u0440\u0442\u0441"
    ],
    "name:und_x_variant":[
        "Honorable William Roberts Town",
        "Roberts"
    ],
    "name:vie_x_preferred":[
        "Roberts"
    ],
    "name:vol_x_preferred":[
        "Roberts"
    ],
    "wof:name":"Roberts",
    "wof:placetype":"locality"
},
  "geometry": {"coordinates":[-9.78333,6.16667],"type":"Point"}
}