{
  "type": "Feature",
  "properties": {
    "gn:admin1_code":"19.0",
    "gn:asciiname":"Jeeblo Town",
    "gn:cc2":"LR",
    "gn:country_code":"LR",
    "gn:dem":253,
    "gn:feature_class":"P",
    "gn:feature_code":"PPL",
    "gn:name":"Jeeblo Town",
    "gn:population":0,
    "gn:timezone":"Africa/Monrovia",
    "iso:country":"LR",
    "name:und_x_variant":[
        "Jiblobli",
        "Jeeblo Town"
    ],
    "wof:name":"Jeeblo Town",
    "wof:placetype":"locality"
},
  "geometry": {"coordinates":[-8.22306,5.58639],"type":"Point"}
}