{
  "type": "Feature",
  "properties": {
    "gn:admin1_code":"11.0",
    "gn:asciiname":"Five House Camp",
    "gn:country_code":"LR",
    "gn:dem":120,
    "gn:feature_class":"P",
    "gn:feature_code":"PPL",
    "gn:name":"Five House Camp",
    "gn:population":0,
    "gn:timezone":"Africa/Monrovia",
    "iso:country":"LR",
    "wof:name":"Five House Camp",
    "wof:placetype":"locality"
},
  "geometry": {"coordinates":[-9.78018,6.12947],"type":"Point"}
}