{
  "type": "Feature",
  "properties": {
    "gn:admin1_code":"18.0",
    "gn:asciiname":"Joson Town",
    "gn:country_code":"LR",
    "gn:dem":45,
    "gn:feature_class":"P",
    "gn:feature_code":"PPL",
    "gn:name":"Joson Town",
    "gn:population":0,
    "gn:timezone":"Africa/Monrovia",
    "iso:country":"LR",
    "name:und_x_variant":[
        "Joson",
        "Joson Town"
    ],
    "wof:name":"Joson Town",
    "wof:placetype":"locality"
},
  "geometry": {"coordinates":[-9.6663,5.67139],"type":"Point"}
}