{
  "type": "Feature",
  "properties": {
    "gn:admin1_code":"10.0",
    "gn:asciiname":"Niinpoin",
    "gn:country_code":"LR",
    "gn:dem":28,
    "gn:feature_class":"P",
    "gn:feature_code":"PPL",
    "gn:name":"Niinpoin",
    "gn:population":0,
    "gn:timezone":"Africa/Monrovia",
    "iso:country":"LR",
    "wof:name":"Niinpoin",
    "wof:placetype":"locality"
},
  "geometry": {"coordinates":[-8.51631,5.04429],"type":"Point"}
}