{
  "type": "Feature",
  "properties": {
    "gn:admin1_code":"12.0",
    "gn:asciiname":"Bawoima",
    "gn:country_code":"LR",
    "gn:dem":24,
    "gn:feature_class":"P",
    "gn:feature_code":"PPL",
    "gn:name":"Bawoima",
    "gn:population":0,
    "gn:timezone":"Africa/Monrovia",
    "iso:country":"LR",
    "name:und_x_variant":[
        "Bakiemei",
        "Baweima",
        "Bawoima"
    ],
    "wof:name":"Bawoima",
    "wof:placetype":"locality"
},
  "geometry": {"coordinates":[-11.30047,6.92814],"type":"Point"}
}