{
  "type": "Feature",
  "properties": {
    "gn:admin1_code":"15.0",
    "gn:asciiname":"Jenne Number Two",
    "gn:country_code":"LR",
    "gn:dem":22,
    "gn:feature_class":"P",
    "gn:feature_code":"PPL",
    "gn:name":"Jenne Number Two",
    "gn:population":0,
    "gn:timezone":"Africa/Monrovia",
    "iso:country":"LR",
    "name:und_x_variant":[
        "Jenne Number 2",
        "Jenne Number Two"
    ],
    "wof:name":"Jenne Number Two",
    "wof:placetype":"locality"
},
  "geometry": {"coordinates":[-10.84989,6.53369],"type":"Point"}
}