{
  "type": "Feature",
  "properties": {
    "gn:admin1_code":"16.0",
    "gn:asciiname":"Jorkortee",
    "gn:country_code":"LR",
    "gn:dem":30,
    "gn:feature_class":"P",
    "gn:feature_code":"PPL",
    "gn:name":"Jorkortee",
    "gn:population":0,
    "gn:timezone":"Africa/Monrovia",
    "iso:country":"LR",
    "wof:name":"Jorkortee",
    "wof:placetype":"locality"
},
  "geometry": {"coordinates":[-8.62975,4.82101],"type":"Point"}
}