{
  "type": "Feature",
  "properties": {
    "gn:admin1_code":"1.0",
    "gn:asciiname":"Wefata",
    "gn:country_code":"LR",
    "gn:dem":356,
    "gn:feature_class":"P",
    "gn:feature_code":"PPL",
    "gn:name":"Wefata",
    "gn:population":0,
    "gn:timezone":"Africa/Monrovia",
    "iso:country":"LR",
    "name:eng_x_preferred":[
        "Wefata"
    ],
    "wof:name":"Wefata",
    "wof:placetype":"locality"
},
  "geometry": {"coordinates":[-9.45,7.38333],"type":"Point"}
}