{
  "type": "Feature",
  "properties": {
    "gn:country":"LR",
    "gn:fcode":"PPLX",
    "gn:population":0,
    "iso:country":"LR",
    "name:eng_x_preferred":[
        "Bassa Community"
    ],
    "qs:gn_adm0_cc":"LR",
    "qs:gn_fcode":"PPLX",
    "qs:gn_local":2274895,
    "qs:gn_nam_loc":"Monrovia, Monrovia, Montserrado County, LR",
    "qs:gn_namadm1":"14",
    "qs:gn_name":"Bassa Community",
    "qs:local_max":1412,
    "qs:local_sum":1708,
    "qs:localhoods":5,
    "qs:name":"Bassa Community",
    "qs:name_adm0":"Liberia",
    "qs:name_adm1":"Monrovia",
    "qs:name_local":"Monrovia",
    "qs:photo_max":20,
    "qs:photo_sum":46,
    "qs:placetype":"Suburb",
    "qs:quad_count":5,
    "qs:woe_adm0":23424876,
    "qs:woe_adm1":2346102,
    "qs:woe_adm2":0,
    "qs:woe_lau":0,
    "qs:woe_local":1350536,
    "qs:woe_ver":"7.10.0",
    "qs_pg:aaroncc":"LR",
    "qs_pg:gn_country":"LR",
    "qs_pg:gn_fcode":"PPLX",
    "qs_pg:gn_pop":0,
    "qs_pg:name":"Bassa Community",
    "qs_pg:name_adm0":"Liberia",
    "qs_pg:name_adm1":"Monrovia",
    "qs_pg:photos":803,
    "qs_pg:photos_1k":163,
    "qs_pg:photos_9k":4,
    "qs_pg:photos_9r":6,
    "qs_pg:photos_all":803,
    "qs_pg:photos_sr":9,
    "qs_pg:pop_sr":0,
    "qs_pg:qs_pg_placetype":"neighbourhood",
    "qs_pg:qs_pg_placetype_gp":"Suburb",
    "qs_pg:woe_adm0":23424876,
    "wof:lang":[
        "eng"
    ],
    "wof:name":"Bassa Community",
    "wof:placetype":"neighbourhood"
},
  "geometry": {"coordinates":[-10.797983,6.301184],"type":"Point"}
}