{
  "type": "Feature",
  "properties": {
    "gn:admin1_code":"19.0",
    "gn:asciiname":"Fla Town",
    "gn:cc2":"LR",
    "gn:country_code":"LR",
    "gn:dem":217,
    "gn:feature_class":"P",
    "gn:feature_code":"PPL",
    "gn:name":"Fla Town",
    "gn:population":0,
    "gn:timezone":"Africa/Monrovia",
    "iso:country":"LR",
    "name:und_x_variant":[
        "Flehn",
        "Fla Town"
    ],
    "wof:name":"Fla Town",
    "wof:placetype":"locality"
},
  "geometry": {"coordinates":[-7.805,5.88972],"type":"Point"}
}