{
  "type": "Feature",
  "properties": {
    "gn:admin1_code":"9.0",
    "gn:asciiname":"Joahob",
    "gn:cc2":"LR",
    "gn:country_code":"LR",
    "gn:dem":210,
    "gn:feature_class":"P",
    "gn:feature_code":"PPL",
    "gn:name":"Joahob",
    "gn:population":0,
    "gn:timezone":"Africa/Monrovia",
    "iso:country":"LR",
    "name:und_x_variant":[
        "Joaho",
        "Joahob"
    ],
    "wof:name":"Joahob",
    "wof:placetype":"locality"
},
  "geometry": {"coordinates":[-9.05667,6.39417],"type":"Point"}
}