{
  "type": "Feature",
  "properties": {
    "gn:admin1_code":"12.0",
    "gn:asciiname":"Changoma",
    "gn:country_code":"LR",
    "gn:dem":18,
    "gn:feature_class":"P",
    "gn:feature_code":"PPL",
    "gn:name":"Changoma",
    "gn:population":0,
    "gn:timezone":"Africa/Monrovia",
    "iso:country":"LR",
    "name:und_x_variant":[
        "Jangoma",
        "Changoma"
    ],
    "wof:name":"Changoma",
    "wof:placetype":"locality"
},
  "geometry": {"coordinates":[-11.178,6.74204],"type":"Point"}
}