{
  "type": "Feature",
  "properties": {
    "gn:admin1_code":"18.0",
    "gn:asciiname":"Zammie Town",
    "gn:country_code":"LR",
    "gn:dem":130,
    "gn:feature_class":"P",
    "gn:feature_code":"PPL",
    "gn:name":"Zammie Town",
    "gn:population":0,
    "gn:timezone":"Africa/Monrovia",
    "iso:country":"LR",
    "wof:name":"Zammie Town",
    "wof:placetype":"locality"
},
  "geometry": {"coordinates":[-9.25065,5.85001],"type":"Point"}
}