{
  "type": "Feature",
  "properties": {
    "gn:admin1_code":"19.0",
    "gn:asciiname":"Zleh",
    "gn:country_code":"LR",
    "gn:dem":250,
    "gn:feature_class":"P",
    "gn:feature_code":"PPL",
    "gn:name":"Zleh",
    "gn:population":0,
    "gn:timezone":"Africa/Monrovia",
    "iso:country":"LR",
    "name:und_x_variant":[
        "Zle Town",
        "Zle",
        "Zleh Town",
        "Zleh"
    ],
    "wof:name":"Zleh",
    "wof:placetype":"locality"
},
  "geometry": {"coordinates":[-8.43535,6.22667],"type":"Point"}
}