{
  "type": "Feature",
  "properties": {
    "gn:admin1_code":"18.0",
    "gn:asciiname":"Blompa",
    "gn:country_code":"LR",
    "gn:dem":28,
    "gn:feature_class":"P",
    "gn:feature_code":"PPL",
    "gn:name":"Blompa",
    "gn:population":0,
    "gn:timezone":"Africa/Monrovia",
    "iso:country":"LR",
    "name:und_x_variant":[
        "Blomba"
    ],
    "wof:name":"Blompa",
    "wof:placetype":"locality"
},
  "geometry": {"coordinates":[-9.58776,5.56639],"type":"Point"}
}