{
  "type": "Feature",
  "properties": {
    "gn:admin1_code":"14.0",
    "gn:asciiname":"Nakun Town",
    "gn:country_code":"LR",
    "gn:dem":12,
    "gn:feature_class":"P",
    "gn:feature_code":"PPL",
    "gn:name":"Nakun Town",
    "gn:population":0,
    "gn:timezone":"Africa/Monrovia",
    "iso:country":"LR",
    "wof:name":"Nakun Town",
    "wof:placetype":"locality"
},
  "geometry": {"coordinates":[-10.63333,6.35],"type":"Point"}
}