{
  "type": "Feature",
  "properties": {
    "gn:admin1_code":"10.0",
    "gn:asciiname":"Jaba Wanabo",
    "gn:country_code":"LR",
    "gn:dem":95,
    "gn:feature_class":"P",
    "gn:feature_code":"PPL",
    "gn:name":"Jaba Wanabo",
    "gn:population":0,
    "gn:timezone":"Africa/Monrovia",
    "iso:country":"LR",
    "wof:name":"Jaba Wanabo",
    "wof:placetype":"locality"
},
  "geometry": {"coordinates":[-8.81361,5.24833],"type":"Point"}
}