{
  "type": "Feature",
  "properties": {
    "gn:admin1_code":"1.0",
    "gn:asciiname":"Belegenla",
    "gn:country_code":"LR",
    "gn:dem":238,
    "gn:feature_class":"P",
    "gn:feature_code":"PPL",
    "gn:name":"Belegenla",
    "gn:population":0,
    "gn:timezone":"Africa/Monrovia",
    "iso:country":"LR",
    "name:eng_x_preferred":[
        "Belegenla"
    ],
    "wof:name":"Belegenla",
    "wof:placetype":"locality"
},
  "geometry": {"coordinates":[-9.17871,6.89269],"type":"Point"}
}