{
  "type": "Feature",
  "properties": {
    "gn:admin1_code":"17.0",
    "gn:asciiname":"Numata",
    "gn:country_code":"LR",
    "gn:dem":144,
    "gn:feature_class":"P",
    "gn:feature_code":"PPL",
    "gn:name":"Numata",
    "gn:population":0,
    "gn:timezone":"Africa/Monrovia",
    "iso:country":"LR",
    "name:eng_x_preferred":[
        "Numata"
    ],
    "wof:name":"Numata",
    "wof:placetype":"locality"
},
  "geometry": {"coordinates":[-10.35512,6.68355],"type":"Point"}
}