{
  "type": "Feature",
  "properties": {
    "gn:admin1_code":"17.0",
    "gn:asciiname":"Lango Number Two",
    "gn:country_code":"LR",
    "gn:dem":124,
    "gn:feature_class":"P",
    "gn:feature_code":"PPL",
    "gn:name":"Lango Number Two",
    "gn:population":0,
    "gn:timezone":"Africa/Monrovia",
    "iso:country":"LR",
    "name:und_x_variant":[
        "Lango Number 2",
        "Lango Number Two"
    ],
    "wof:name":"Lango Number Two",
    "wof:placetype":"locality"
},
  "geometry": {"coordinates":[-10.35192,6.67105],"type":"Point"}
}