{
  "type": "Feature",
  "properties": {
    "gn:admin1_code":"21.0",
    "gn:asciiname":"Zuie",
    "gn:country_code":"LR",
    "gn:dem":351,
    "gn:feature_class":"P",
    "gn:feature_code":"PPL",
    "gn:name":"Zuie",
    "gn:population":0,
    "gn:timezone":"Africa/Monrovia",
    "iso:country":"LR",
    "name:und_x_variant":[
        "Zui",
        "Zoi",
        "Zuei",
        "Zuie"
    ],
    "wof:name":"Zuie",
    "wof:placetype":"locality"
},
  "geometry": {"coordinates":[-10.46278,7.66194],"type":"Point"}
}