{
  "type": "Feature",
  "properties": {
    "gn:admin1_code":"20.0",
    "gn:asciiname":"Chengeonin",
    "gn:country_code":"LR",
    "gn:dem":533,
    "gn:feature_class":"P",
    "gn:feature_code":"PPL",
    "gn:name":"Chengeonin",
    "gn:population":0,
    "gn:timezone":"Africa/Monrovia",
    "iso:country":"LR",
    "wof:name":"Chengeonin",
    "wof:placetype":"locality"
},
  "geometry": {"coordinates":[-10.17304,8.37367],"type":"Point"}
}