{
  "type": "Feature",
  "properties": {
    "gn:admin1_code":"17.0",
    "gn:asciiname":"Dala Camp",
    "gn:country_code":"LR",
    "gn:dem":91,
    "gn:feature_class":"P",
    "gn:feature_code":"PPL",
    "gn:name":"Dala Camp",
    "gn:population":0,
    "gn:timezone":"Africa/Monrovia",
    "iso:country":"LR",
    "name:eng_x_preferred":[
        "Dala Camp"
    ],
    "wof:name":"Dala Camp",
    "wof:placetype":"locality"
},
  "geometry": {"coordinates":[-10.37389,6.55694],"type":"Point"}
}