{
  "type": "Feature",
  "properties": {
    "gn:admin1_code":"20.0",
    "gn:asciiname":"Bua",
    "gn:country_code":"LR",
    "gn:dem":466,
    "gn:feature_class":"P",
    "gn:feature_code":"PPL",
    "gn:name":"Bua",
    "gn:population":0,
    "gn:timezone":"Africa/Monrovia",
    "iso:country":"LR",
    "name:ceb_x_preferred":[
        "Bua"
    ],
    "name:glg_x_preferred":[
        "Bua"
    ],
    "name:ind_x_preferred":[
        "Bua"
    ],
    "name:nld_x_preferred":[
        "Bua"
    ],
    "name:swe_x_preferred":[
        "Bua"
    ],
    "wof:name":"Bua",
    "wof:placetype":"locality"
},
  "geometry": {"coordinates":[-10.25,8.31667],"type":"Point"}
}