{
  "type": "Feature",
  "properties": {
    "gn:gn_country":"LR",
    "gn:gn_fcode":"PPLX",
    "gn:gn_pop":0,
    "iso:country":"LR",
    "name:eng_x_preferred":[
        "Sinkor"
    ],
    "name:nld_x_preferred":[
        "Sinkor"
    ],
    "name:unk_x_variant":[
        "Sinkor"
    ],
    "qs_pg:aaroncc":"LR",
    "qs_pg:gn_country":"LR",
    "qs_pg:gn_fcode":"PPLX",
    "qs_pg:gn_pop":0,
    "qs_pg:name":"Sinkor",
    "qs_pg:name_adm0":"Liberia",
    "qs_pg:name_adm1":"Montserrado",
    "qs_pg:photos":79,
    "qs_pg:photos_1k":16,
    "qs_pg:photos_9k":1,
    "qs_pg:photos_9r":3,
    "qs_pg:photos_all":79,
    "qs_pg:photos_sr":3,
    "qs_pg:pop_sr":0,
    "qs_pg:qs_pg_placetype":"neighbourhood",
    "qs_pg:qs_pg_placetype_gp":"Suburb",
    "qs_pg:woe_adm0":23424876,
    "woe:adm0_id":23424876,
    "woe:name_adm0":"Liberia",
    "woe:name_adm1":"Montserrado",
    "woe:placetype":"Suburb",
    "wof:name":"Sinkor",
    "wof:placetype":"neighbourhood"
},
  "geometry": {"coordinates":[-10.76667,6.3],"type":"Point"}
}