{
  "type": "Feature",
  "properties": {
    "gn:admin1_code":"12.0",
    "gn:asciiname":"Malina",
    "gn:country_code":"LR",
    "gn:dem":38,
    "gn:feature_class":"P",
    "gn:feature_code":"PPL",
    "gn:name":"Malina",
    "gn:population":0,
    "gn:timezone":"Africa/Monrovia",
    "iso:country":"LR",
    "wof:name":"Malina",
    "wof:placetype":"locality"
},
  "geometry": {"coordinates":[-11.18333,6.98333],"type":"Point"}
}