{
  "type": "Feature",
  "properties": {
    "gn:admin1_code":"12.0",
    "gn:asciiname":"Malina",
    "gn:country_code":"LR",
    "gn:dem":38,
    "gn:feature_class":"P",
    "gn:feature_code":"PPL",
    "gn:name":"Malina",
    "gn:population":0,
    "gn:timezone":"Africa/Monrovia",
    "iso:country":"LR",
    "name:bul_x_preferred":[
        "\u041c\u0430\u043b\u0438\u043d\u0430"
    ],
    "name:ceb_x_preferred":[
        "Malina"
    ],
    "name:ces_x_preferred":[
        "Malina"
    ],
    "name:deu_x_preferred":[
        "Malina"
    ],
    "name:fas_x_preferred":[
        "\u0645\u0627\u0644\u06cc\u0646\u0627"
    ],
    "name:fra_x_preferred":[
        "Malina"
    ],
    "name:ita_x_preferred":[
        "Malina"
    ],
    "name:pol_x_preferred":[
        "Malina"
    ],
    "name:por_x_preferred":[
        "Malina"
    ],
    "name:ron_x_preferred":[
        "Malina"
    ],
    "name:rus_x_preferred":[
        "\u041c\u0430\u043b\u0438\u043d\u0430"
    ],
    "name:slk_x_preferred":[
        "Malina"
    ],
    "name:sqi_x_preferred":[
        "Malina"
    ],
    "name:swe_x_preferred":[
        "Malina"
    ],
    "name:ukr_x_preferred":[
        "\u041c\u0430\u043b\u0438\u043d\u0430"
    ],
    "wof:name":"Malina",
    "wof:placetype":"locality"
},
  "geometry": {"coordinates":[-11.18333,6.98333],"type":"Point"}
}