{
  "type": "Feature",
  "properties": {
    "gn:admin1_code":"15.0",
    "gn:asciiname":"Vanjapolu",
    "gn:country_code":"LR",
    "gn:dem":46,
    "gn:feature_class":"P",
    "gn:feature_code":"PPL",
    "gn:name":"Vanjapolu",
    "gn:population":0,
    "gn:timezone":"Africa/Monrovia",
    "iso:country":"LR",
    "wof:name":"Vanjapolu",
    "wof:placetype":"locality"
},
  "geometry": {"coordinates":[-10.71667,6.61667],"type":"Point"}
}