{
  "type": "Feature",
  "properties": {
    "gn:admin1_code":"13.0",
    "gn:asciiname":"Bawolobo",
    "gn:country_code":"LR",
    "gn:dem":169,
    "gn:feature_class":"P",
    "gn:feature_code":"PPL",
    "gn:name":"Bawolobo",
    "gn:population":0,
    "gn:timezone":"Africa/Monrovia",
    "iso:country":"LR",
    "wof:name":"Bawolobo",
    "wof:placetype":"locality"
},
  "geometry": {"coordinates":[-7.91667,5.06667],"type":"Point"}
}