{
  "type": "Feature",
  "properties": {
    "gn:admin1_code":"11.0",
    "gn:asciiname":"Blosabli",
    "gn:country_code":"LR",
    "gn:dem":22,
    "gn:feature_class":"P",
    "gn:feature_code":"PPL",
    "gn:name":"Blosabli",
    "gn:population":0,
    "gn:timezone":"Africa/Monrovia",
    "iso:country":"LR",
    "wof:name":"Blosabli",
    "wof:placetype":"locality"
},
  "geometry": {"coordinates":[-9.98333,5.96667],"type":"Point"}
}