{
  "type": "Feature",
  "properties": {
    "gn:admin1_code":"22.0",
    "gn:asciiname":"Nyouken",
    "gn:country_code":"LR",
    "gn:dem":209,
    "gn:feature_class":"P",
    "gn:feature_code":"PPL",
    "gn:name":"Nyouken",
    "gn:population":0,
    "gn:timezone":"Africa/Monrovia",
    "iso:country":"LR",
    "name:und_x_variant":[
        "Kuan",
        "Kuan Town",
        "Nyohnken",
        "Nyouken",
        "Nyohnkehn"
    ],
    "wof:name":"Nyouken",
    "wof:placetype":"locality"
},
  "geometry": {"coordinates":[-8.09253,5.18733],"type":"Point"}
}