{
  "type": "Feature",
  "properties": {
    "gn:admin1_code":"9.0",
    "gn:asciiname":"Bobe",
    "gn:cc2":"LR",
    "gn:country_code":"LR",
    "gn:dem":424,
    "gn:feature_class":"P",
    "gn:feature_code":"PPL",
    "gn:name":"Bobe",
    "gn:population":0,
    "gn:timezone":"Africa/Monrovia",
    "iso:country":"LR",
    "name:und_x_variant":[
        "Bubui",
        "Bobei",
        "Bobe"
    ],
    "wof:name":"Bobe",
    "wof:placetype":"locality"
},
  "geometry": {"coordinates":[-8.605,7.36833],"type":"Point"}
}