{
  "type": "Feature",
  "properties": {
    "gn:admin1_code":"21.0",
    "gn:asciiname":"Gelahun",
    "gn:country_code":"LR",
    "gn:dem":253,
    "gn:feature_class":"P",
    "gn:feature_code":"PPL",
    "gn:name":"Gelahun",
    "gn:population":0,
    "gn:timezone":"Africa/Monrovia",
    "iso:country":"LR",
    "wof:name":"Gelahun",
    "wof:placetype":"locality"
},
  "geometry": {"coordinates":[-10.4725,7.82889],"type":"Point"}
}