{
  "type": "Feature",
  "properties": {
    "gn:admin1_code":"10.0",
    "gn:asciiname":"Pawroken",
    "gn:country_code":"LR",
    "gn:dem":142,
    "gn:feature_class":"P",
    "gn:feature_code":"PPL",
    "gn:name":"Pawroken",
    "gn:population":0,
    "gn:timezone":"Africa/Monrovia",
    "iso:country":"LR",
    "name:und_x_variant":[
        "Panworokehn"
    ],
    "wof:name":"Pawroken",
    "wof:placetype":"locality"
},
  "geometry": {"coordinates":[-8.29677,5.31738],"type":"Point"}
}