{
  "type": "Feature",
  "properties": {
    "gn:admin1_code":"19.0",
    "gn:asciiname":"Bawe Town",
    "gn:country_code":"LR",
    "gn:dem":210,
    "gn:feature_class":"P",
    "gn:feature_code":"PPL",
    "gn:name":"Bawe Town",
    "gn:population":0,
    "gn:timezone":"Africa/Monrovia",
    "iso:country":"LR",
    "wof:name":"Bawe Town",
    "wof:placetype":"locality"
},
  "geometry": {"coordinates":[-7.72535,5.81399],"type":"Point"}
}