{
  "type": "Feature",
  "properties": {
    "gn:admin1_code":"12.0",
    "gn:asciiname":"Zeba",
    "gn:country_code":"LR",
    "gn:dem":132,
    "gn:feature_class":"P",
    "gn:feature_code":"PPL",
    "gn:name":"Zeba",
    "gn:population":0,
    "gn:timezone":"Africa/Monrovia",
    "iso:country":"LR",
    "wof:name":"Zeba",
    "wof:placetype":"locality"
},
  "geometry": {"coordinates":[-10.66111,7.20806],"type":"Point"}
}