{
  "type": "Feature",
  "properties": {
    "gn:admin1_code":"1.0",
    "gn:asciiname":"Dowaeta",
    "gn:country_code":"LR",
    "gn:dem":183,
    "gn:feature_class":"P",
    "gn:feature_code":"PPL",
    "gn:name":"Dowaeta",
    "gn:population":0,
    "gn:timezone":"Africa/Monrovia",
    "iso:country":"LR",
    "name:eng_x_preferred":[
        "Dowaeta"
    ],
    "wof:name":"Dowaeta",
    "wof:placetype":"locality"
},
  "geometry": {"coordinates":[-9.51101,6.50809],"type":"Point"}
}