{
  "type": "Feature",
  "properties": {
    "gn:admin1_code":"1.0",
    "gn:asciiname":"Bameyea",
    "gn:country_code":"LR",
    "gn:dem":232,
    "gn:feature_class":"P",
    "gn:feature_code":"PPL",
    "gn:name":"Bameyea",
    "gn:population":0,
    "gn:timezone":"Africa/Monrovia",
    "iso:country":"LR",
    "name:eng_x_preferred":[
        "Bameyea"
    ],
    "name:und_x_variant":[
        "Bame"
    ],
    "wof:name":"Bameyea",
    "wof:placetype":"locality"
},
  "geometry": {"coordinates":[-9.46285,6.92292],"type":"Point"}
}