{
  "type": "Feature",
  "properties": {
    "gn:admin1_code":"12.0",
    "gn:asciiname":"Kowoma",
    "gn:cc2":"LR",
    "gn:country_code":"LR",
    "gn:dem":9,
    "gn:feature_class":"P",
    "gn:feature_code":"PPL",
    "gn:name":"Kowoma",
    "gn:population":0,
    "gn:timezone":"Africa/Monrovia",
    "iso:country":"LR",
    "name:und_x_variant":[
        "Sambola",
        "Joni",
        "Kowoma"
    ],
    "wof:name":"Kowoma",
    "wof:placetype":"locality"
},
  "geometry": {"coordinates":[-11.26667,6.85],"type":"Point"}
}