{
  "type": "Feature",
  "properties": {
    "gn:admin1_code":"22.0",
    "gn:asciiname":"Thebaken",
    "gn:country_code":"LR",
    "gn:dem":75,
    "gn:feature_class":"P",
    "gn:feature_code":"PPL",
    "gn:name":"Thebaken",
    "gn:population":0,
    "gn:timezone":"Africa/Monrovia",
    "iso:country":"LR",
    "wof:name":"Thebaken",
    "wof:placetype":"locality"
},
  "geometry": {"coordinates":[-7.61333,5.03944],"type":"Point"}
}