{
  "type": "Feature",
  "properties": {
    "gn:admin1_code":"1.0",
    "gn:asciiname":"Gbansukorloquoilee",
    "gn:country_code":"LR",
    "gn:dem":251,
    "gn:feature_class":"P",
    "gn:feature_code":"PPL",
    "gn:name":"Gbansukorloquoilee",
    "gn:population":0,
    "gn:timezone":"Africa/Monrovia",
    "iso:country":"LR",
    "name:eng_x_preferred":[
        "Gbansukorloquoilee"
    ],
    "name:und_x_variant":[
        "Banzu",
        "Gbanzu"
    ],
    "wof:name":"Gbansukorloquoilee",
    "wof:placetype":"locality"
},
  "geometry": {"coordinates":[-9.5957,7.24145],"type":"Point"}
}