{
  "type": "Feature",
  "properties": {
    "gn:admin1_code":"1.0",
    "gn:asciiname":"Wonkpala",
    "gn:country_code":"LR",
    "gn:dem":285,
    "gn:feature_class":"P",
    "gn:feature_code":"PPL",
    "gn:name":"Wonkpala",
    "gn:population":0,
    "gn:timezone":"Africa/Monrovia",
    "iso:country":"LR",
    "name:eng_x_preferred":[
        "Wonkpala"
    ],
    "name:und_x_variant":[
        "Wanakpala",
        "Wanakapala"
    ],
    "wof:name":"Wonkpala",
    "wof:placetype":"locality"
},
  "geometry": {"coordinates":[-9.48123,7.09435],"type":"Point"}
}