{
  "type": "Feature",
  "properties": {
    "gn:admin1_code":"1.0",
    "gn:asciiname":"Geleye",
    "gn:country_code":"LR",
    "gn:dem":226,
    "gn:feature_class":"P",
    "gn:feature_code":"PPL",
    "gn:name":"Geleye",
    "gn:population":0,
    "gn:timezone":"Africa/Monrovia",
    "iso:country":"LR",
    "name:eng_x_preferred":[
        "Geleye"
    ],
    "wof:name":"Geleye",
    "wof:placetype":"locality"
},
  "geometry": {"coordinates":[-9.18564,6.76998],"type":"Point"}
}