{
  "type": "Feature",
  "properties": {
    "gn:admin1_code":"16.0",
    "gn:asciiname":"Siibatu",
    "gn:country_code":"LR",
    "gn:dem":83,
    "gn:feature_class":"P",
    "gn:feature_code":"PPL",
    "gn:name":"Siibatu",
    "gn:population":0,
    "gn:timezone":"Africa/Monrovia",
    "iso:country":"LR",
    "wof:name":"Siibatu",
    "wof:placetype":"locality"
},
  "geometry": {"coordinates":[-8.28289,4.96378],"type":"Point"}
}