{
  "type": "Feature",
  "properties": {
    "gn:admin1_code":"11.0",
    "gn:asciiname":"Boubli",
    "gn:country_code":"LR",
    "gn:dem":213,
    "gn:feature_class":"P",
    "gn:feature_code":"PPL",
    "gn:name":"Boubli",
    "gn:population":0,
    "gn:timezone":"Africa/Monrovia",
    "iso:country":"LR",
    "wof:name":"Boubli",
    "wof:placetype":"locality"
},
  "geometry": {"coordinates":[-9.53333,6.36667],"type":"Point"}
}