{
  "type": "Feature",
  "properties": {
    "gn:admin1_code":"11.0",
    "gn:asciiname":"Plefebli",
    "gn:country_code":"LR",
    "gn:dem":102,
    "gn:feature_class":"P",
    "gn:feature_code":"PPL",
    "gn:name":"Plefebli",
    "gn:population":0,
    "gn:timezone":"Africa/Monrovia",
    "iso:country":"LR",
    "wof:name":"Plefebli",
    "wof:placetype":"locality"
},
  "geometry": {"coordinates":[-9.91667,6.16667],"type":"Point"}
}