{
  "type": "Feature",
  "properties": {
    "gn:admin1_code":"21.0",
    "gn:asciiname":"Tandila",
    "gn:country_code":"LR",
    "gn:dem":198,
    "gn:feature_class":"P",
    "gn:feature_code":"PPL",
    "gn:name":"Tandila",
    "gn:population":0,
    "gn:timezone":"Africa/Monrovia",
    "iso:country":"LR",
    "wof:name":"Tandila",
    "wof:placetype":"locality"
},
  "geometry": {"coordinates":[-10.46667,7.16667],"type":"Point"}
}