{
  "type": "Feature",
  "properties": {
    "gn:admin1_code":"17.0",
    "gn:asciiname":"Dodo Town",
    "gn:country_code":"LR",
    "gn:dem":13,
    "gn:feature_class":"P",
    "gn:feature_code":"PPL",
    "gn:name":"Dodo Town",
    "gn:population":0,
    "gn:timezone":"Africa/Monrovia",
    "iso:country":"LR",
    "name:und_x_variant":[
        "Dodo",
        "Dodo Town",
        "Dolo\u2019s Town"
    ],
    "wof:name":"Dodo Town",
    "wof:placetype":"locality"
},
  "geometry": {"coordinates":[-10.36,6.26139],"type":"Point"}
}