{
  "type": "Feature",
  "properties": {
    "gn:admin1_code":"1.0",
    "gn:asciiname":"Gbatala",
    "gn:country_code":"LR",
    "gn:dem":242,
    "gn:feature_class":"P",
    "gn:feature_code":"PPL",
    "gn:name":"Gbatala",
    "gn:population":0,
    "gn:timezone":"Africa/Monrovia",
    "iso:country":"LR",
    "name:eng_x_preferred":[
        "Gbatala"
    ],
    "wof:name":"Gbatala",
    "wof:placetype":"locality"
},
  "geometry": {"coordinates":[-9.67691,6.88647],"type":"Point"}
}