{
  "type": "Feature",
  "properties": {
    "gn:admin1_code":"22.0",
    "gn:asciiname":"Jawake",
    "gn:country_code":"LR",
    "gn:dem":111,
    "gn:feature_class":"P",
    "gn:feature_code":"PPL",
    "gn:name":"Jawake",
    "gn:population":0,
    "gn:timezone":"Africa/Monrovia",
    "iso:country":"LR",
    "name:und_x_variant":[
        "Towaken"
    ],
    "wof:name":"Jawake",
    "wof:placetype":"locality"
},
  "geometry": {"coordinates":[-7.57616,4.99091],"type":"Point"}
}