{
  "type": "Feature",
  "properties": {
    "gn:admin1_code":"1.0",
    "gn:asciiname":"Wheta",
    "gn:country_code":"LR",
    "gn:dem":219,
    "gn:feature_class":"P",
    "gn:feature_code":"PPL",
    "gn:name":"Wheta",
    "gn:population":0,
    "gn:timezone":"Africa/Monrovia",
    "iso:country":"LR",
    "name:eng_x_preferred":[
        "Wheta"
    ],
    "name:nld_x_preferred":[
        "Wheta"
    ],
    "wof:name":"Wheta",
    "wof:placetype":"locality"
},
  "geometry": {"coordinates":[-9.45007,6.56382],"type":"Point"}
}