{
  "type": "Feature",
  "properties": {
    "gn:admin1_code":"11.0",
    "gn:asciiname":"John Pasa Town",
    "gn:country_code":"LR",
    "gn:dem":39,
    "gn:feature_class":"P",
    "gn:feature_code":"PPL",
    "gn:name":"John Pasa Town",
    "gn:population":0,
    "gn:timezone":"Africa/Monrovia",
    "iso:country":"LR",
    "wof:name":"John Pasa Town",
    "wof:placetype":"locality"
},
  "geometry": {"coordinates":[-9.76667,5.76667],"type":"Point"}
}