{
  "type": "Feature",
  "properties": {
    "gn:admin1_code":"9.0",
    "gn:asciiname":"Komapie",
    "gn:country_code":"LR",
    "gn:dem":369,
    "gn:feature_class":"P",
    "gn:feature_code":"PPL",
    "gn:name":"Komapie",
    "gn:population":0,
    "gn:timezone":"Africa/Monrovia",
    "iso:country":"LR",
    "wof:name":"Komapie",
    "wof:placetype":"locality"
},
  "geometry": {"coordinates":[-8.45278,7.445],"type":"Point"}
}