{
  "type": "Feature",
  "properties": {
    "gn:admin1_code":"17.0",
    "gn:asciiname":"Kuatata",
    "gn:country_code":"LR",
    "gn:dem":109,
    "gn:feature_class":"P",
    "gn:feature_code":"PPL",
    "gn:name":"Kuatata",
    "gn:population":0,
    "gn:timezone":"Africa/Monrovia",
    "iso:country":"LR",
    "wof:name":"Kuatata",
    "wof:placetype":"locality"
},
  "geometry": {"coordinates":[-10.09967,6.68547],"type":"Point"}
}