{
  "type": "Feature",
  "properties": {
    "gn:admin1_code":"10.0",
    "gn:asciiname":"Geemon",
    "gn:country_code":"LR",
    "gn:dem":154,
    "gn:feature_class":"P",
    "gn:feature_code":"PPL",
    "gn:name":"Geemon",
    "gn:population":0,
    "gn:timezone":"Africa/Monrovia",
    "iso:country":"LR",
    "wof:name":"Geemon",
    "wof:placetype":"locality"
},
  "geometry": {"coordinates":[-8.60675,5.31499],"type":"Point"}
}