{
  "type": "Feature",
  "properties": {
    "gn:admin1_code":"11.0",
    "gn:asciiname":"Temabli",
    "gn:country_code":"LR",
    "gn:dem":60,
    "gn:feature_class":"P",
    "gn:feature_code":"PPL",
    "gn:name":"Temabli",
    "gn:population":0,
    "gn:timezone":"Africa/Monrovia",
    "iso:country":"LR",
    "wof:name":"Temabli",
    "wof:placetype":"locality"
},
  "geometry": {"coordinates":[-9.85,5.93333],"type":"Point"}
}