{
  "type": "Feature",
  "properties": {
    "gn:admin1_code":"17.0",
    "gn:asciiname":"Nienka",
    "gn:country_code":"LR",
    "gn:dem":92,
    "gn:feature_class":"P",
    "gn:feature_code":"PPL",
    "gn:name":"Nienka",
    "gn:population":0,
    "gn:timezone":"Africa/Monrovia",
    "iso:country":"LR",
    "name:und_x_variant":[
        "Noigata",
        "Niyata",
        "Niigata",
        "Nienka"
    ],
    "wof:name":"Nienka",
    "wof:placetype":"locality"
},
  "geometry": {"coordinates":[-10.18606,6.67715],"type":"Point"}
}