{
  "type": "Feature",
  "properties": {
    "gn:admin1_code":"11.0",
    "gn:asciiname":"Kokonya",
    "gn:cc2":"LR",
    "gn:country_code":"LR",
    "gn:dem":129,
    "gn:feature_class":"P",
    "gn:feature_code":"PPL",
    "gn:name":"Kokonya",
    "gn:population":0,
    "gn:timezone":"Africa/Monrovia",
    "iso:country":"LR",
    "name:und_x_variant":[
        "Vavosa Camp",
        "Kokonya"
    ],
    "wof:name":"Kokonya",
    "wof:placetype":"locality"
},
  "geometry": {"coordinates":[-9.76667,6.13333],"type":"Point"}
}