{
  "type": "Feature",
  "properties": {
    "gn:admin1_code":"11.0",
    "gn:asciiname":"Kongba",
    "gn:country_code":"LR",
    "gn:dem":65,
    "gn:feature_class":"P",
    "gn:feature_code":"PPL",
    "gn:name":"Kongba",
    "gn:population":0,
    "gn:timezone":"Africa/Monrovia",
    "iso:country":"LR",
    "wof:name":"Kongba",
    "wof:placetype":"locality"
},
  "geometry": {"coordinates":[-10.29501,6.26852],"type":"Point"}
}