{
  "type": "Feature",
  "properties": {
    "gn:admin1_code":"10.0",
    "gn:asciiname":"Duarnneh",
    "gn:country_code":"LR",
    "gn:dem":101,
    "gn:feature_class":"P",
    "gn:feature_code":"PPL",
    "gn:name":"Duarnneh",
    "gn:population":0,
    "gn:timezone":"Africa/Monrovia",
    "iso:country":"LR",
    "wof:name":"Duarnneh",
    "wof:placetype":"locality"
},
  "geometry": {"coordinates":[-8.99553,5.30896],"type":"Point"}
}