{
  "type": "Feature",
  "properties": {
    "gn:admin1_code":"13.0",
    "gn:asciiname":"Philadelphia Township",
    "gn:country_code":"LR",
    "gn:dem":10,
    "gn:feature_class":"P",
    "gn:feature_code":"PPL",
    "gn:name":"Philadelphia Township",
    "gn:population":0,
    "gn:timezone":"Africa/Monrovia",
    "iso:country":"LR",
    "wof:name":"Philadelphia Township",
    "wof:placetype":"locality"
},
  "geometry": {"coordinates":[-7.68756,4.40793],"type":"Point"}
}