{
  "type": "Feature",
  "properties": {
    "gn:admin1_code":"1.0",
    "gn:asciiname":"Bogota",
    "gn:country_code":"LR",
    "gn:dem":237,
    "gn:feature_class":"P",
    "gn:feature_code":"PPL",
    "gn:name":"Bogota",
    "gn:population":0,
    "gn:timezone":"Africa/Monrovia",
    "iso:country":"LR",
    "name:eng_x_preferred":[
        "Bogota"
    ],
    "wof:name":"Bogota",
    "wof:placetype":"locality"
},
  "geometry": {"coordinates":[-9.39417,6.79099],"type":"Point"}
}