{
  "type": "Feature",
  "properties": {
    "gn:admin1_code":"11.0",
    "gn:asciiname":"Zuzohn",
    "gn:country_code":"LR",
    "gn:dem":85,
    "gn:feature_class":"P",
    "gn:feature_code":"PPL",
    "gn:name":"Zuzohn",
    "gn:population":0,
    "gn:timezone":"Africa/Monrovia",
    "iso:country":"LR",
    "wof:name":"Zuzohn",
    "wof:placetype":"locality"
},
  "geometry": {"coordinates":[-10.15,6.18333],"type":"Point"}
}