{
  "type": "Feature",
  "properties": {
    "gn:admin1_code":"9.0",
    "gn:asciiname":"Zahn",
    "gn:country_code":"LR",
    "gn:dem":241,
    "gn:feature_class":"P",
    "gn:feature_code":"PPL",
    "gn:name":"Zahn",
    "gn:population":0,
    "gn:timezone":"Africa/Monrovia",
    "iso:country":"LR",
    "wof:name":"Zahn",
    "wof:placetype":"locality"
},
  "geometry": {"coordinates":[-9.0575,6.89333],"type":"Point"}
}