{
  "type": "Feature",
  "properties": {
    "gn:admin1_code":"9.0",
    "gn:asciiname":"Toabedi",
    "gn:country_code":"LR",
    "gn:dem":269,
    "gn:feature_class":"P",
    "gn:feature_code":"PPL",
    "gn:name":"Toabedi",
    "gn:population":0,
    "gn:timezone":"Africa/Monrovia",
    "iso:country":"LR",
    "wof:name":"Toabedi",
    "wof:placetype":"locality"
},
  "geometry": {"coordinates":[-9.11667,7.06667],"type":"Point"}
}