{
  "type": "Feature",
  "properties": {
    "gn:admin1_code":"16.0",
    "gn:asciiname":"Duogboken",
    "gn:country_code":"LR",
    "gn:dem":99,
    "gn:feature_class":"P",
    "gn:feature_code":"PPL",
    "gn:name":"Duogboken",
    "gn:population":0,
    "gn:timezone":"Africa/Monrovia",
    "iso:country":"LR",
    "wof:name":"Duogboken",
    "wof:placetype":"locality"
},
  "geometry": {"coordinates":[-8.04916,4.98459],"type":"Point"}
}