{
  "type": "Feature",
  "properties": {
    "gn:admin1_code":"11.0",
    "gn:asciiname":"Six Old Camp",
    "gn:country_code":"LR",
    "gn:dem":95,
    "gn:feature_class":"P",
    "gn:feature_code":"PPL",
    "gn:name":"Six Old Camp",
    "gn:population":0,
    "gn:timezone":"Africa/Monrovia",
    "iso:country":"LR",
    "wof:name":"Six Old Camp",
    "wof:placetype":"locality"
},
  "geometry": {"coordinates":[-9.77237,6.04078],"type":"Point"}
}