{
  "type": "Feature",
  "properties": {
    "gn:admin1_code":"19.0",
    "gn:asciiname":"Wamu",
    "gn:country_code":"LR",
    "gn:dem":222,
    "gn:feature_class":"P",
    "gn:feature_code":"PPL",
    "gn:name":"Wamu",
    "gn:population":0,
    "gn:timezone":"Africa/Monrovia",
    "iso:country":"LR",
    "wof:name":"Wamu",
    "wof:placetype":"locality"
},
  "geometry": {"coordinates":[-7.97419,6.2123],"type":"Point"}
}