{
  "type": "Feature",
  "properties": {
    "gn:admin1_code":"16.0",
    "gn:asciiname":"Sorroke",
    "gn:country_code":"LR",
    "gn:dem":18,
    "gn:feature_class":"P",
    "gn:feature_code":"PPL",
    "gn:name":"Sorroke",
    "gn:population":0,
    "gn:timezone":"Africa/Monrovia",
    "iso:country":"LR",
    "name:und_x_variant":[
        "Jlatakehn"
    ],
    "wof:name":"Sorroke",
    "wof:placetype":"locality"
},
  "geometry": {"coordinates":[-8.21407,4.64651],"type":"Point"}
}