{
  "type": "Feature",
  "properties": {
    "gn:admin1_code":"11.0",
    "gn:asciiname":"Magibli",
    "gn:country_code":"LR",
    "gn:dem":63,
    "gn:feature_class":"P",
    "gn:feature_code":"PPL",
    "gn:name":"Magibli",
    "gn:population":0,
    "gn:timezone":"Africa/Monrovia",
    "iso:country":"LR",
    "wof:name":"Magibli",
    "wof:placetype":"locality"
},
  "geometry": {"coordinates":[-9.81223,6.02824],"type":"Point"}
}