{
  "type": "Feature",
  "properties": {
    "gn:admin1_code":"22.0",
    "gn:asciiname":"Yarbekehn",
    "gn:country_code":"LR",
    "gn:dem":83,
    "gn:feature_class":"P",
    "gn:feature_code":"PPL",
    "gn:name":"Yarbekehn",
    "gn:population":0,
    "gn:timezone":"Africa/Monrovia",
    "iso:country":"LR",
    "wof:name":"Yarbekehn",
    "wof:placetype":"locality"
},
  "geometry": {"coordinates":[-7.59453,4.97269],"type":"Point"}
}