{
  "type": "Feature",
  "properties": {
    "gn:admin1_code":"17.0",
    "gn:asciiname":"Monkey Tailta",
    "gn:country_code":"LR",
    "gn:dem":145,
    "gn:feature_class":"P",
    "gn:feature_code":"PPL",
    "gn:name":"Monkey Tailta",
    "gn:population":0,
    "gn:timezone":"Africa/Monrovia",
    "iso:country":"LR",
    "wof:name":"Monkey Tailta",
    "wof:placetype":"locality"
},
  "geometry": {"coordinates":[-10.06667,6.66667],"type":"Point"}
}