{
  "type": "Feature",
  "properties": {
    "gn:admin1_code":"19.0",
    "gn:asciiname":"Penu",
    "gn:country_code":"LR",
    "gn:dem":206,
    "gn:feature_class":"P",
    "gn:feature_code":"PPL",
    "gn:name":"Penu",
    "gn:population":0,
    "gn:timezone":"Africa/Monrovia",
    "iso:country":"LR",
    "wof:name":"Penu",
    "wof:placetype":"locality"
},
  "geometry": {"coordinates":[-8.15139,5.73889],"type":"Point"}
}