{
  "type": "Feature",
  "properties": {
    "gn:admin1_code":"21.0",
    "gn:asciiname":"Konjele",
    "gn:country_code":"LR",
    "gn:dem":467,
    "gn:feature_class":"P",
    "gn:feature_code":"PPL",
    "gn:name":"Konjele",
    "gn:population":0,
    "gn:timezone":"Africa/Monrovia",
    "iso:country":"LR",
    "wof:name":"Konjele",
    "wof:placetype":"locality"
},
  "geometry": {"coordinates":[-9.96,7.54139],"type":"Point"}
}