{
  "type": "Feature",
  "properties": {
    "gn:admin1_code":"9.0",
    "gn:asciiname":"Sahnpa",
    "gn:country_code":"LR",
    "gn:dem":282,
    "gn:feature_class":"P",
    "gn:feature_code":"PPL",
    "gn:name":"Sahnpa",
    "gn:population":0,
    "gn:timezone":"Africa/Monrovia",
    "iso:country":"LR",
    "wof:name":"Sahnpa",
    "wof:placetype":"locality"
},
  "geometry": {"coordinates":[-9.0251,6.53959],"type":"Point"}
}