{
  "type": "Feature",
  "properties": {
    "gn:admin1_code":"15.0",
    "gn:asciiname":"Golodee Number Two",
    "gn:country_code":"LR",
    "gn:dem":27,
    "gn:feature_class":"P",
    "gn:feature_code":"PPL",
    "gn:name":"Golodee Number Two",
    "gn:population":0,
    "gn:timezone":"Africa/Monrovia",
    "iso:country":"LR",
    "name:und_x_variant":[
        "Bolagai",
        "Blagai",
        "Golodee Number Two",
        "Golodee No. 2"
    ],
    "wof:name":"Golodee Number Two",
    "wof:placetype":"locality"
},
  "geometry": {"coordinates":[-10.87284,6.56357],"type":"Point"}
}