{
  "type": "Feature",
  "properties": {
    "gn:admin1_code":"9.0",
    "gn:asciiname":"Balorplay",
    "gn:country_code":"LR",
    "gn:dem":274,
    "gn:feature_class":"P",
    "gn:feature_code":"PPL",
    "gn:name":"Balorplay",
    "gn:population":0,
    "gn:timezone":"Africa/Monrovia",
    "iso:country":"LR",
    "wof:name":"Balorplay",
    "wof:placetype":"locality"
},
  "geometry": {"coordinates":[-8.42471,6.87743],"type":"Point"}
}