{
  "type": "Feature",
  "properties": {
    "gn:admin1_code":"11.0",
    "gn:asciiname":"Debablah",
    "gn:country_code":"LR",
    "gn:dem":28,
    "gn:feature_class":"P",
    "gn:feature_code":"PPL",
    "gn:name":"Debablah",
    "gn:population":0,
    "gn:timezone":"Africa/Monrovia",
    "iso:country":"LR",
    "wof:name":"Debablah",
    "wof:placetype":"locality"
},
  "geometry": {"coordinates":[-9.90489,5.79492],"type":"Point"}
}