{
  "type": "Feature",
  "properties": {
    "gn:admin1_code":"1.0",
    "gn:asciiname":"Sinta",
    "gn:country_code":"LR",
    "gn:dem":278,
    "gn:feature_class":"P",
    "gn:feature_code":"PPL",
    "gn:name":"Sinta",
    "gn:population":0,
    "gn:timezone":"Africa/Monrovia",
    "iso:country":"LR",
    "wof:name":"Sinta",
    "wof:placetype":"locality"
},
  "geometry": {"coordinates":[-9.95,6.91667],"type":"Point"}
}