{
  "type": "Feature",
  "properties": {
    "gn:admin1_code":"12.0",
    "gn:asciiname":"Delja",
    "gn:country_code":"LR",
    "gn:dem":33,
    "gn:feature_class":"P",
    "gn:feature_code":"PPL",
    "gn:name":"Delja",
    "gn:population":0,
    "gn:timezone":"Africa/Monrovia",
    "iso:country":"LR",
    "name:und_x_variant":[
        "Dedeja",
        "Delja"
    ],
    "wof:name":"Delja",
    "wof:placetype":"locality"
},
  "geometry": {"coordinates":[-11.07783,6.67793],"type":"Point"}
}