{
  "type": "Feature",
  "properties": {
    "gn:admin1_code":"1.0",
    "gn:asciiname":"Toweleeta",
    "gn:country_code":"LR",
    "gn:dem":227,
    "gn:feature_class":"P",
    "gn:feature_code":"PPL",
    "gn:name":"Toweleeta",
    "gn:population":0,
    "gn:timezone":"Africa/Monrovia",
    "iso:country":"LR",
    "name:eng_x_preferred":[
        "Toweleeta"
    ],
    "wof:name":"Toweleeta",
    "wof:placetype":"locality"
},
  "geometry": {"coordinates":[-9.18931,6.82237],"type":"Point"}
}