{
  "type": "Feature",
  "properties": {
    "gn:admin1_code":"13.0",
    "gn:asciiname":"Doloka",
    "gn:country_code":"LR",
    "gn:dem":87,
    "gn:feature_class":"P",
    "gn:feature_code":"PPL",
    "gn:name":"Doloka",
    "gn:population":0,
    "gn:timezone":"Africa/Monrovia",
    "iso:country":"LR",
    "wof:name":"Doloka",
    "wof:placetype":"locality"
},
  "geometry": {"coordinates":[-7.69742,4.68492],"type":"Point"}
}