{
  "type": "Feature",
  "properties": {
    "gn:admin1_code":"20.0",
    "gn:asciiname":"Kwayama",
    "gn:country_code":"LR",
    "gn:dem":283,
    "gn:feature_class":"P",
    "gn:feature_code":"PPL",
    "gn:name":"Kwayama",
    "gn:population":0,
    "gn:timezone":"Africa/Monrovia",
    "iso:country":"LR",
    "wof:name":"Kwayama",
    "wof:placetype":"locality"
},
  "geometry": {"coordinates":[-10.48333,8.11667],"type":"Point"}
}