{
  "type": "Feature",
  "properties": {
    "gn:admin1_code":"17.0",
    "gn:asciiname":"Cooper Farm",
    "gn:country_code":"LR",
    "gn:dem":109,
    "gn:feature_class":"P",
    "gn:feature_code":"PPL",
    "gn:name":"Cooper Farm",
    "gn:population":0,
    "gn:timezone":"Africa/Monrovia",
    "iso:country":"LR",
    "name:eng_x_preferred":[
        "Cooper Farm"
    ],
    "name:und_x_variant":[
        "Cooper Farm (2)"
    ],
    "wof:name":"Cooper Farm",
    "wof:placetype":"locality"
},
  "geometry": {"coordinates":[-10.294,6.54944],"type":"Point"}
}