{
  "type": "Feature",
  "properties": {
    "gn:admin1_code":"20.0",
    "gn:asciiname":"Bilikilai",
    "gn:country_code":"LR",
    "gn:dem":416,
    "gn:feature_class":"P",
    "gn:feature_code":"PPL",
    "gn:name":"Bilikilai",
    "gn:population":0,
    "gn:timezone":"Africa/Monrovia",
    "iso:country":"LR",
    "wof:name":"Bilikilai",
    "wof:placetype":"locality"
},
  "geometry": {"coordinates":[-9.38333,7.68333],"type":"Point"}
}