{
  "type": "Feature",
  "properties": {
    "gn:admin1_code":"1.0",
    "gn:asciiname":"Frotema",
    "gn:cc2":"LR",
    "gn:country_code":"LR",
    "gn:dem":281,
    "gn:feature_class":"P",
    "gn:feature_code":"PPL",
    "gn:name":"Frotema",
    "gn:population":0,
    "gn:timezone":"Africa/Monrovia",
    "iso:country":"LR",
    "name:und_x_variant":[
        "Fromtema",
        "Frotema"
    ],
    "wof:name":"Frotema",
    "wof:placetype":"locality"
},
  "geometry": {"coordinates":[-9.29389,6.92722],"type":"Point"}
}