{
  "type": "Feature",
  "properties": {
    "gn:admin1_code":"19.0",
    "gn:asciiname":"Taa",
    "gn:country_code":"LR",
    "gn:dem":230,
    "gn:feature_class":"P",
    "gn:feature_code":"PPL",
    "gn:name":"Taa",
    "gn:population":0,
    "gn:timezone":"Africa/Monrovia",
    "iso:country":"LR",
    "wof:name":"Taa",
    "wof:placetype":"locality"
},
  "geometry": {"coordinates":[-8.03333,6.25],"type":"Point"}
}