{
  "type": "Feature",
  "properties": {
    "gn:admin1_code":"20.0",
    "gn:asciiname":"Foya Customs",
    "gn:cc2":"LR",
    "gn:country_code":"LR",
    "gn:dem":415,
    "gn:feature_class":"P",
    "gn:feature_code":"PPL",
    "gn:name":"Foya Customs",
    "gn:population":0,
    "gn:timezone":"Africa/Monrovia",
    "iso:country":"LR",
    "name:und_x_variant":[
        "Foya Customs Station",
        "Foya Customs"
    ],
    "wof:name":"Foya Customs",
    "wof:placetype":"locality"
},
  "geometry": {"coordinates":[-10.31667,8.26667],"type":"Point"}
}