{
  "type": "Feature",
  "properties": {
    "gn:admin1_code":"20.0",
    "gn:asciiname":"Yasselahun",
    "gn:cc2":"LR",
    "gn:country_code":"LR",
    "gn:dem":471,
    "gn:feature_class":"P",
    "gn:feature_code":"PPL",
    "gn:name":"Yasselahun",
    "gn:population":0,
    "gn:timezone":"Africa/Monrovia",
    "iso:country":"LR",
    "name:und_x_variant":[
        "Yaselahun",
        "Yaselelahun",
        "Yasselahun"
    ],
    "wof:name":"Yasselahun",
    "wof:placetype":"locality"
},
  "geometry": {"coordinates":[-10.10222,7.91194],"type":"Point"}
}