{
  "type": "Feature",
  "properties": {
    "gn:admin1_code":"1.0",
    "gn:asciiname":"Tucker's Farm",
    "gn:country_code":"LR",
    "gn:dem":254,
    "gn:feature_class":"P",
    "gn:feature_code":"PPL",
    "gn:name":"Tucker\u2019s Farm",
    "gn:population":0,
    "gn:timezone":"Africa/Monrovia",
    "iso:country":"LR",
    "name:eng_x_preferred":[
        "Tucker\u2019s Farm"
    ],
    "wof:name":"Tucker's Farm",
    "wof:placetype":"locality"
},
  "geometry": {"coordinates":[-9.46657,7.03865],"type":"Point"}
}