{
  "type": "Feature",
  "properties": {
    "gn:admin1_code":"11.0",
    "gn:asciiname":"Deeworh",
    "gn:country_code":"LR",
    "gn:dem":62,
    "gn:feature_class":"P",
    "gn:feature_code":"PPL",
    "gn:name":"Deeworh",
    "gn:population":0,
    "gn:timezone":"Africa/Monrovia",
    "iso:country":"LR",
    "wof:name":"Deeworh",
    "wof:placetype":"locality"
},
  "geometry": {"coordinates":[-9.72679,5.69497],"type":"Point"}
}