{
  "type": "Feature",
  "properties": {
    "gn:admin1_code":"9.0",
    "gn:asciiname":"Gompa City",
    "gn:country_code":"LR",
    "gn:dem":278,
    "gn:feature_class":"P",
    "gn:feature_code":"PPL",
    "gn:name":"Gompa City",
    "gn:population":0,
    "gn:timezone":"Africa/Monrovia",
    "iso:country":"LR",
    "wof:name":"Gompa City",
    "wof:placetype":"locality"
},
  "geometry": {"coordinates":[-8.98167,7.23639],"type":"Point"}
}