{
  "type": "Feature",
  "properties": {
    "gn:admin1_code":"1.0",
    "gn:asciiname":"J.P. Harris Farm",
    "gn:country_code":"LR",
    "gn:dem":346,
    "gn:feature_class":"P",
    "gn:feature_code":"PPL",
    "gn:name":"J.P. Harris Farm",
    "gn:population":0,
    "gn:timezone":"Africa/Monrovia",
    "iso:country":"LR",
    "name:eng_x_preferred":[
        "J.P. Harris Farm"
    ],
    "wof:name":"J.P. Harris Farm",
    "wof:placetype":"locality"
},
  "geometry": {"coordinates":[-9.44496,7.20151],"type":"Point"}
}