{
  "type": "Feature",
  "properties": {
    "gn:admin1_code":"1.0",
    "gn:asciiname":"Tamay",
    "gn:country_code":"LR",
    "gn:dem":239,
    "gn:feature_class":"P",
    "gn:feature_code":"PPL",
    "gn:name":"Tamay",
    "gn:population":0,
    "gn:timezone":"Africa/Monrovia",
    "iso:country":"LR",
    "name:azb_x_preferred":[
        "\u062a\u0645\u0627\u06cc"
    ],
    "name:aze_x_preferred":[
        "Tamay"
    ],
    "name:ceb_x_preferred":[
        "Tam\u0101k"
    ],
    "name:eng_x_preferred":[
        "Tamay"
    ],
    "name:fas_x_preferred":[
        "\u062a\u0645\u0627\u06cc"
    ],
    "name:msa_x_preferred":[
        "Tamay"
    ],
    "name:swe_x_preferred":[
        "Tam\u0101k"
    ],
    "name:und_x_variant":[
        "Tamita"
    ],
    "wof:name":"Tamay",
    "wof:placetype":"locality"
},
  "geometry": {"coordinates":[-9.46794,6.80559],"type":"Point"}
}