{
  "type": "Feature",
  "properties": {
    "gn:admin1_code":"16.0",
    "gn:asciiname":"Bila Togbaklee",
    "gn:country_code":"LR",
    "gn:dem":15,
    "gn:feature_class":"P",
    "gn:feature_code":"PPL",
    "gn:name":"Bila Togbaklee",
    "gn:population":0,
    "gn:timezone":"Africa/Monrovia",
    "iso:country":"LR",
    "wof:name":"Bila Togbaklee",
    "wof:placetype":"locality"
},
  "geometry": {"coordinates":[-8.31774,4.62804],"type":"Point"}
}