{
  "type": "Feature",
  "properties": {
    "gn:admin1_code":"14.0",
    "gn:asciiname":"Baatown",
    "gn:country_code":"LR",
    "gn:dem":126,
    "gn:feature_class":"P",
    "gn:feature_code":"PPL",
    "gn:name":"Baatown",
    "gn:population":0,
    "gn:timezone":"Africa/Monrovia",
    "iso:country":"LR",
    "wof:name":"Baatown",
    "wof:placetype":"locality"
},
  "geometry": {"coordinates":[-10.445,6.75306],"type":"Point"}
}