{
  "type": "Feature",
  "properties": {
    "gn:admin1_code":"18.0",
    "gn:asciiname":"Jomambabli",
    "gn:country_code":"LR",
    "gn:dem":90,
    "gn:feature_class":"P",
    "gn:feature_code":"PPL",
    "gn:name":"Jomambabli",
    "gn:population":0,
    "gn:timezone":"Africa/Monrovia",
    "iso:country":"LR",
    "wof:name":"Jomambabli",
    "wof:placetype":"locality"
},
  "geometry": {"coordinates":[-9.53323,5.86062],"type":"Point"}
}