{
  "type": "Feature",
  "properties": {
    "gn:admin1_code":"16.0",
    "gn:asciiname":"Klauke",
    "gn:country_code":"LR",
    "gn:dem":29,
    "gn:feature_class":"P",
    "gn:feature_code":"PPL",
    "gn:name":"Klauke",
    "gn:population":0,
    "gn:timezone":"Africa/Monrovia",
    "iso:country":"LR",
    "wof:name":"Klauke",
    "wof:placetype":"locality"
},
  "geometry": {"coordinates":[-8.05599,4.70395],"type":"Point"}
}