{
  "type": "Feature",
  "properties": {
    "gn:admin1_code":"11.0",
    "gn:asciiname":"Baunga",
    "gn:cc2":"LR",
    "gn:country_code":"LR",
    "gn:dem":131,
    "gn:feature_class":"P",
    "gn:feature_code":"PPL",
    "gn:name":"Baunga",
    "gn:population":0,
    "gn:timezone":"Africa/Monrovia",
    "iso:country":"LR",
    "name:und_x_variant":[
        "Balingabli",
        "Baunga"
    ],
    "wof:name":"Baunga",
    "wof:placetype":"locality"
},
  "geometry": {"coordinates":[-9.76667,6.18333],"type":"Point"}
}