{
  "type": "Feature",
  "properties": {
    "gn:admin1_code":"15.0",
    "gn:asciiname":"Gondama Free Town",
    "gn:cc2":"LR",
    "gn:country_code":"LR",
    "gn:dem":35,
    "gn:feature_class":"P",
    "gn:feature_code":"PPL",
    "gn:name":"Gondama Free Town",
    "gn:population":0,
    "gn:timezone":"Africa/Monrovia",
    "iso:country":"LR",
    "name:und_x_variant":[
        "Gangama",
        "Gondama Free Town"
    ],
    "wof:name":"Gondama Free Town",
    "wof:placetype":"locality"
},
  "geometry": {"coordinates":[-10.88333,6.56667],"type":"Point"}
}