{
  "type": "Feature",
  "properties": {
    "gn:admin1_code":"16.0",
    "gn:asciiname":"Dayakpo",
    "gn:country_code":"LR",
    "gn:dem":48,
    "gn:feature_class":"P",
    "gn:feature_code":"PPL",
    "gn:name":"Dayakpo",
    "gn:population":0,
    "gn:timezone":"Africa/Monrovia",
    "iso:country":"LR",
    "name:und_x_variant":[
        "Numakwia",
        "Dayapo",
        "Numokwia",
        "Kpeka",
        "Dayakpo"
    ],
    "wof:name":"Dayakpo",
    "wof:placetype":"locality"
},
  "geometry": {"coordinates":[-8.36244,4.74758],"type":"Point"}
}