{
  "type": "Feature",
  "properties": {
    "gn:admin1_code":"1.0",
    "gn:asciiname":"Dokpoimu",
    "gn:country_code":"LR",
    "gn:dem":137,
    "gn:feature_class":"P",
    "gn:feature_code":"PPL",
    "gn:name":"Dokpoimu",
    "gn:population":0,
    "gn:timezone":"Africa/Monrovia",
    "iso:country":"LR",
    "name:eng_x_preferred":[
        "Dokpoimu"
    ],
    "wof:name":"Dokpoimu",
    "wof:placetype":"locality"
},
  "geometry": {"coordinates":[-10.448,6.89606],"type":"Point"}
}