{
  "type": "Feature",
  "properties": {
    "gn:admin1_code":"18.0",
    "gn:asciiname":"Sanogabli",
    "gn:country_code":"LR",
    "gn:dem":80,
    "gn:feature_class":"P",
    "gn:feature_code":"PPL",
    "gn:name":"Sanogabli",
    "gn:population":0,
    "gn:timezone":"Africa/Monrovia",
    "iso:country":"LR",
    "wof:name":"Sanogabli",
    "wof:placetype":"locality"
},
  "geometry": {"coordinates":[-9.56667,5.88333],"type":"Point"}
}