{
  "type": "Feature",
  "properties": {
    "gn:admin1_code":"13.0",
    "gn:asciiname":"Wlowen",
    "gn:country_code":"LR",
    "gn:dem":37,
    "gn:feature_class":"P",
    "gn:feature_code":"PPL",
    "gn:name":"Wlowen",
    "gn:population":0,
    "gn:timezone":"Africa/Monrovia",
    "iso:country":"LR",
    "name:und_x_variant":[
        "Wlowin",
        "Wloween",
        "Wlowein",
        "Wlowen"
    ],
    "wof:name":"Wlowen",
    "wof:placetype":"locality"
},
  "geometry": {"coordinates":[-7.80302,4.63196],"type":"Point"}
}