{
  "type": "Feature",
  "properties": {
    "gn:admin1_code":"16.0",
    "gn:asciiname":"Nyankunkpo",
    "gn:country_code":"LR",
    "gn:dem":33,
    "gn:feature_class":"P",
    "gn:feature_code":"PPL",
    "gn:name":"Nyankunkpo",
    "gn:population":0,
    "gn:timezone":"Africa/Monrovia",
    "iso:country":"LR",
    "name:und_x_variant":[
        "Nakumpo",
        "Nyankupon",
        "Nyankunkpo"
    ],
    "wof:name":"Nyankunkpo",
    "wof:placetype":"locality"
},
  "geometry": {"coordinates":[-8.38299,4.88362],"type":"Point"}
}