{
  "type": "Feature",
  "properties": {
    "gn:admin1_code":"19.0",
    "gn:asciiname":"Kwear",
    "gn:cc2":"LR",
    "gn:country_code":"LR",
    "gn:dem":186,
    "gn:feature_class":"P",
    "gn:feature_code":"PPL",
    "gn:name":"Kwear",
    "gn:population":0,
    "gn:timezone":"Africa/Monrovia",
    "iso:country":"LR",
    "name:und_x_variant":[
        "Dibli",
        "Kwear"
    ],
    "wof:name":"Kwear",
    "wof:placetype":"locality"
},
  "geometry": {"coordinates":[-8.63194,6.04694],"type":"Point"}
}