{
  "type": "Feature",
  "properties": {
    "gn:admin1_code":"1.0",
    "gn:asciiname":"Gwelita",
    "gn:country_code":"LR",
    "gn:dem":258,
    "gn:feature_class":"P",
    "gn:feature_code":"PPL",
    "gn:name":"Gwelita",
    "gn:population":0,
    "gn:timezone":"Africa/Monrovia",
    "iso:country":"LR",
    "name:eng_x_preferred":[
        "Gwelita"
    ],
    "name:und_x_variant":[
        "Goleta",
        "Koleta",
        "Gueta"
    ],
    "wof:name":"Gwelita",
    "wof:placetype":"locality"
},
  "geometry": {"coordinates":[-9.58344,6.89109],"type":"Point"}
}