{
  "type": "Feature",
  "properties": {
    "gn:admin1_code":"11.0",
    "gn:asciiname":"Jumgboi",
    "gn:country_code":"LR",
    "gn:dem":198,
    "gn:feature_class":"P",
    "gn:feature_code":"PPL",
    "gn:name":"Jumgboi",
    "gn:population":0,
    "gn:timezone":"Africa/Monrovia",
    "iso:country":"LR",
    "name:eng_x_preferred":[
        "Jumgboi"
    ],
    "wof:name":"Jumgboi",
    "wof:placetype":"locality"
},
  "geometry": {"coordinates":[-9.64154,6.64444],"type":"Point"}
}