{
  "type": "Feature",
  "properties": {
    "gn:admin1_code":"18.0",
    "gn:asciiname":"Blosobli",
    "gn:country_code":"LR",
    "gn:dem":61,
    "gn:feature_class":"P",
    "gn:feature_code":"PPL",
    "gn:name":"Blosobli",
    "gn:population":0,
    "gn:timezone":"Africa/Monrovia",
    "iso:country":"LR",
    "wof:name":"Blosobli",
    "wof:placetype":"locality"
},
  "geometry": {"coordinates":[-9.63557,5.83034],"type":"Point"}
}