{
  "type": "Feature",
  "properties": {
    "gn:admin1_code":"9.0",
    "gn:asciiname":"Samba",
    "gn:cc2":"LR",
    "gn:country_code":"LR",
    "gn:dem":249,
    "gn:feature_class":"P",
    "gn:feature_code":"PPL",
    "gn:name":"Samba",
    "gn:population":0,
    "gn:timezone":"Africa/Monrovia",
    "iso:country":"LR",
    "name:und_x_variant":[
        "Zanpah",
        "Samba"
    ],
    "wof:name":"Samba",
    "wof:placetype":"locality"
},
  "geometry": {"coordinates":[-9.01889,6.54028],"type":"Point"}
}