{
  "type": "Feature",
  "properties": {
    "gn:admin1_code":"19.0",
    "gn:asciiname":"Bentley Mining Camp",
    "gn:country_code":"LR",
    "gn:dem":210,
    "gn:feature_class":"P",
    "gn:feature_code":"PPL",
    "gn:name":"Bentley Mining Camp",
    "gn:population":0,
    "gn:timezone":"Africa/Monrovia",
    "iso:country":"LR",
    "wof:name":"Bentley Mining Camp",
    "wof:placetype":"locality"
},
  "geometry": {"coordinates":[-7.94731,6.07904],"type":"Point"}
}