{
  "type": "Feature",
  "properties": {
    "gn:admin1_code":"1.0",
    "gn:asciiname":"Camp Jackson",
    "gn:country_code":"LR",
    "gn:dem":375,
    "gn:feature_class":"P",
    "gn:feature_code":"PPL",
    "gn:name":"Camp Jackson",
    "gn:population":0,
    "gn:timezone":"Africa/Monrovia",
    "iso:country":"LR",
    "name:eng_x_preferred":[
        "Camp Jackson"
    ],
    "wof:name":"Camp Jackson",
    "wof:placetype":"locality"
},
  "geometry": {"coordinates":[-9.34497,7.26235],"type":"Point"}
}