{
  "type": "Feature",
  "properties": {
    "gn:admin1_code":"20.0",
    "gn:asciiname":"Kotuhun",
    "gn:country_code":"LR",
    "gn:dem":513,
    "gn:feature_class":"P",
    "gn:feature_code":"PPL",
    "gn:name":"Kotuhun",
    "gn:population":0,
    "gn:timezone":"Africa/Monrovia",
    "iso:country":"LR",
    "wof:name":"Kotuhun",
    "wof:placetype":"locality"
},
  "geometry": {"coordinates":[-10.14,8.30278],"type":"Point"}
}