{
  "type": "Feature",
  "properties": {
    "gn:admin1_code":"10.0",
    "gn:asciiname":"Bia",
    "gn:cc2":"LR",
    "gn:country_code":"LR",
    "gn:dem":99,
    "gn:feature_class":"P",
    "gn:feature_code":"PPL",
    "gn:name":"Bia",
    "gn:population":0,
    "gn:timezone":"Africa/Monrovia",
    "iso:country":"LR",
    "name:und_x_variant":[
        "Bestman Town",
        "Bia"
    ],
    "wof:name":"Bia",
    "wof:placetype":"locality"
},
  "geometry": {"coordinates":[-8.98333,5.31667],"type":"Point"}
}