{
  "type": "Feature",
  "properties": {
    "gn:admin1_code":"20.0",
    "gn:asciiname":"Njalolohun",
    "gn:country_code":"LR",
    "gn:dem":459,
    "gn:feature_class":"P",
    "gn:feature_code":"PPL",
    "gn:name":"Njalolohun",
    "gn:population":0,
    "gn:timezone":"Africa/Monrovia",
    "iso:country":"LR",
    "wof:name":"Njalolohun",
    "wof:placetype":"locality"
},
  "geometry": {"coordinates":[-10.16667,8.21667],"type":"Point"}
}