{
  "type": "Feature",
  "properties": {
    "gn:admin1_code":"11.0",
    "gn:asciiname":"Jampakohn",
    "gn:country_code":"LR",
    "gn:dem":134,
    "gn:feature_class":"P",
    "gn:feature_code":"PPL",
    "gn:name":"Jampakohn",
    "gn:population":0,
    "gn:timezone":"Africa/Monrovia",
    "iso:country":"LR",
    "wof:name":"Jampakohn",
    "wof:placetype":"locality"
},
  "geometry": {"coordinates":[-9.63333,6.13333],"type":"Point"}
}