{
  "type": "Feature",
  "properties": {
    "gn:admin1_code":"13.0",
    "gn:asciiname":"Sedeka",
    "gn:country_code":"LR",
    "gn:dem":50,
    "gn:feature_class":"P",
    "gn:feature_code":"PPL",
    "gn:name":"Sedeka",
    "gn:population":0,
    "gn:timezone":"Africa/Monrovia",
    "iso:country":"LR",
    "name:und_x_variant":[
        "Sedekehn",
        "Sedeka",
        "Sidike",
        "Sedeke"
    ],
    "wof:name":"Sedeka",
    "wof:placetype":"locality"
},
  "geometry": {"coordinates":[-7.66938,4.5471],"type":"Point"}
}