{
  "type": "Feature",
  "properties": {
    "gn:admin1_code":"12.0",
    "gn:asciiname":"Fali",
    "gn:country_code":"LR",
    "gn:dem":46,
    "gn:feature_class":"P",
    "gn:feature_code":"PPL",
    "gn:name":"Fali",
    "gn:population":0,
    "gn:timezone":"Africa/Monrovia",
    "iso:country":"LR",
    "name:deu_x_preferred":[
        "Fali"
    ],
    "name:fra_x_preferred":[
        "Fali"
    ],
    "wof:name":"Fali",
    "wof:placetype":"locality"
},
  "geometry": {"coordinates":[-11.07261,6.86457],"type":"Point"}
}