{
  "type": "Feature",
  "properties": {
    "gn:admin1_code":"10.0",
    "gn:asciiname":"Sayone",
    "gn:country_code":"LR",
    "gn:dem":46,
    "gn:feature_class":"P",
    "gn:feature_code":"PPL",
    "gn:name":"Sayone",
    "gn:population":0,
    "gn:timezone":"Africa/Monrovia",
    "iso:country":"LR",
    "wof:name":"Sayone",
    "wof:placetype":"locality"
},
  "geometry": {"coordinates":[-8.8782,5.00603],"type":"Point"}
}