{
  "type": "Feature",
  "properties": {
    "gn:admin1_code":"1.0",
    "gn:asciiname":"Blameyea",
    "gn:country_code":"LR",
    "gn:dem":264,
    "gn:feature_class":"P",
    "gn:feature_code":"PPL",
    "gn:name":"Blameyea",
    "gn:population":0,
    "gn:timezone":"Africa/Monrovia",
    "iso:country":"LR",
    "name:eng_x_preferred":[
        "Blameyea"
    ],
    "name:und_x_variant":[
        "Blamiyie",
        "Pomgba"
    ],
    "wof:name":"Blameyea",
    "wof:placetype":"locality"
},
  "geometry": {"coordinates":[-9.42056,6.91889],"type":"Point"}
}