{
  "type": "Feature",
  "properties": {
    "gn:admin1_code":"22.0",
    "gn:asciiname":"Pronoken",
    "gn:country_code":"LR",
    "gn:dem":202,
    "gn:feature_class":"P",
    "gn:feature_code":"PPL",
    "gn:name":"Pronoken",
    "gn:population":0,
    "gn:timezone":"Africa/Monrovia",
    "iso:country":"LR",
    "name:und_x_variant":[
        "Datoda",
        "Prowrokehn",
        "Filoke",
        "Powrenken",
        "Flewrokehn",
        "Pronoken"
    ],
    "wof:name":"Pronoken",
    "wof:placetype":"locality"
},
  "geometry": {"coordinates":[-7.96472,5.18694],"type":"Point"}
}