{
  "type": "Feature",
  "properties": {
    "gn:admin1_code":"11.0",
    "gn:asciiname":"Jorkor Town",
    "gn:country_code":"LR",
    "gn:dem":204,
    "gn:feature_class":"P",
    "gn:feature_code":"PPL",
    "gn:name":"Jorkor Town",
    "gn:population":0,
    "gn:timezone":"Africa/Monrovia",
    "iso:country":"LR",
    "wof:name":"Jorkor Town",
    "wof:placetype":"locality"
},
  "geometry": {"coordinates":[-9.36694,6.55103],"type":"Point"}
}