{
  "type": "Feature",
  "properties": {
    "gn:admin1_code":"10.0",
    "gn:asciiname":"Jupua",
    "gn:country_code":"LR",
    "gn:dem":24,
    "gn:feature_class":"P",
    "gn:feature_code":"PPL",
    "gn:name":"Jupua",
    "gn:population":0,
    "gn:timezone":"Africa/Monrovia",
    "iso:country":"LR",
    "wof:name":"Jupua",
    "wof:placetype":"locality"
},
  "geometry": {"coordinates":[-8.96667,5.03333],"type":"Point"}
}