{
  "type": "Feature",
  "properties": {
    "gn:admin1_code":"11.0",
    "gn:asciiname":"Gabo",
    "gn:country_code":"LR",
    "gn:dem":96,
    "gn:feature_class":"P",
    "gn:feature_code":"PPL",
    "gn:name":"Gabo",
    "gn:population":0,
    "gn:timezone":"Africa/Monrovia",
    "iso:country":"LR",
    "wof:name":"Gabo",
    "wof:placetype":"locality"
},
  "geometry": {"coordinates":[-9.95464,6.21604],"type":"Point"}
}