{
  "type": "Feature",
  "properties": {
    "gn:admin1_code":"11.0",
    "gn:asciiname":"Bongobli",
    "gn:country_code":"LR",
    "gn:dem":185,
    "gn:feature_class":"P",
    "gn:feature_code":"PPL",
    "gn:name":"Bongobli",
    "gn:population":0,
    "gn:timezone":"Africa/Monrovia",
    "iso:country":"LR",
    "wof:name":"Bongobli",
    "wof:placetype":"locality"
},
  "geometry": {"coordinates":[-9.59205,6.28123],"type":"Point"}
}