{
  "type": "Feature",
  "properties": {
    "gn:admin1_code":"10.0",
    "gn:asciiname":"Totrokpo",
    "gn:country_code":"LR",
    "gn:dem":29,
    "gn:feature_class":"P",
    "gn:feature_code":"PPL",
    "gn:name":"Totrokpo",
    "gn:population":0,
    "gn:timezone":"Africa/Monrovia",
    "iso:country":"LR",
    "wof:name":"Totrokpo",
    "wof:placetype":"locality"
},
  "geometry": {"coordinates":[-8.66876,5.00084],"type":"Point"}
}