{
  "type": "Feature",
  "properties": {
    "gn:admin1_code":"9.0",
    "gn:asciiname":"Ba Town",
    "gn:cc2":"LR",
    "gn:country_code":"LR",
    "gn:dem":213,
    "gn:feature_class":"P",
    "gn:feature_code":"PPL",
    "gn:name":"Ba Town",
    "gn:population":0,
    "gn:timezone":"Africa/Monrovia",
    "iso:country":"LR",
    "name:und_x_variant":[
        "Batwain",
        "Ba Town"
    ],
    "wof:name":"Ba Town",
    "wof:placetype":"locality"
},
  "geometry": {"coordinates":[-9.13639,6.7325],"type":"Point"}
}