{
  "type": "Feature",
  "properties": {
    "gn:admin1_code":"9.0",
    "gn:asciiname":"Bapie",
    "gn:cc2":"LR",
    "gn:country_code":"LR",
    "gn:dem":374,
    "gn:feature_class":"P",
    "gn:feature_code":"PPL",
    "gn:name":"Bapie",
    "gn:population":0,
    "gn:timezone":"Africa/Monrovia",
    "iso:country":"LR",
    "name:und_x_variant":[
        "Lali",
        "Bapie"
    ],
    "wof:name":"Bapie",
    "wof:placetype":"locality"
},
  "geometry": {"coordinates":[-8.55972,7.17722],"type":"Point"}
}