{
  "type": "Feature",
  "properties": {
    "gn:admin1_code":"17.0",
    "gn:asciiname":"Unification Village",
    "gn:cc2":"LR",
    "gn:country_code":"LR",
    "gn:dem":12,
    "gn:feature_class":"P",
    "gn:feature_code":"PPL",
    "gn:name":"Unification Village",
    "gn:population":0,
    "gn:timezone":"Africa/Monrovia",
    "iso:country":"LR",
    "name:und_x_variant":[
        "Unification Town",
        "Unification Village"
    ],
    "wof:name":"Unification Village",
    "wof:placetype":"locality"
},
  "geometry": {"coordinates":[-10.36278,6.24806],"type":"Point"}
}