{
  "type": "Feature",
  "properties": {
    "gn:admin1_code":"1.0",
    "gn:asciiname":"Gonegaleta",
    "gn:country_code":"LR",
    "gn:dem":238,
    "gn:feature_class":"P",
    "gn:feature_code":"PPL",
    "gn:name":"Gonegaleta",
    "gn:population":0,
    "gn:timezone":"Africa/Monrovia",
    "iso:country":"LR",
    "name:eng_x_preferred":[
        "Gonegaleta"
    ],
    "wof:name":"Gonegaleta",
    "wof:placetype":"locality"
},
  "geometry": {"coordinates":[-9.67978,6.77148],"type":"Point"}
}