{
  "type": "Feature",
  "properties": {
    "gn:admin1_code":"18.0",
    "gn:asciiname":"Firestone",
    "gn:country_code":"LR",
    "gn:dem":76,
    "gn:feature_class":"P",
    "gn:feature_code":"PPL",
    "gn:name":"Firestone",
    "gn:population":0,
    "gn:timezone":"Africa/Monrovia",
    "iso:country":"LR",
    "name:und_x_variant":[
        "Firestown",
        "Jida",
        "Firestone"
    ],
    "wof:name":"Firestone",
    "wof:placetype":"locality"
},
  "geometry": {"coordinates":[-9.63261,5.92854],"type":"Point"}
}