{
  "type": "Feature",
  "properties": {
    "gn:admin1_code":"11.0",
    "gn:asciiname":"Douna",
    "gn:country_code":"LR",
    "gn:dem":216,
    "gn:feature_class":"P",
    "gn:feature_code":"PPL",
    "gn:name":"Douna",
    "gn:population":0,
    "gn:timezone":"Africa/Monrovia",
    "iso:country":"LR",
    "name:ceb_x_preferred":[
        "Douna"
    ],
    "name:fra_x_preferred":[
        "Douna"
    ],
    "name:swe_x_preferred":[
        "Douna"
    ],
    "wof:name":"Douna",
    "wof:placetype":"locality"
},
  "geometry": {"coordinates":[-9.28353,6.57391],"type":"Point"}
}