{
  "type": "Feature",
  "properties": {
    "gn:admin1_code":"19.0",
    "gn:asciiname":"Baubli",
    "gn:country_code":"LR",
    "gn:dem":179,
    "gn:feature_class":"P",
    "gn:feature_code":"PPL",
    "gn:name":"Baubli",
    "gn:population":0,
    "gn:timezone":"Africa/Monrovia",
    "iso:country":"LR",
    "name:und_x_variant":[
        "Puobli",
        "Paubli",
        "Baubli"
    ],
    "wof:name":"Baubli",
    "wof:placetype":"locality"
},
  "geometry": {"coordinates":[-7.71948,5.90213],"type":"Point"}
}