{
  "type": "Feature",
  "properties": {
    "gn:admin1_code":"22.0",
    "gn:asciiname":"Wutuke",
    "gn:country_code":"LR",
    "gn:dem":64,
    "gn:feature_class":"P",
    "gn:feature_code":"PPL",
    "gn:name":"Wutuke",
    "gn:population":0,
    "gn:timezone":"Africa/Monrovia",
    "iso:country":"LR",
    "wof:name":"Wutuke",
    "wof:placetype":"locality"
},
  "geometry": {"coordinates":[-7.56578,4.96231],"type":"Point"}
}