{
  "type": "Feature",
  "properties": {
    "gn:admin1_code":"1.0",
    "gn:asciiname":"Shiengbwa",
    "gn:cc2":"LR",
    "gn:country_code":"LR",
    "gn:dem":291,
    "gn:feature_class":"P",
    "gn:feature_code":"PPL",
    "gn:name":"Shiengbwa",
    "gn:population":0,
    "gn:timezone":"Africa/Monrovia",
    "iso:country":"LR",
    "name:und_x_variant":[
        "Shienbwa",
        "Shiengbwa"
    ],
    "wof:name":"Shiengbwa",
    "wof:placetype":"locality"
},
  "geometry": {"coordinates":[-9.1425,7.17111],"type":"Point"}
}