{
  "type": "Feature",
  "properties": {
    "gn:admin1_code":"12.0",
    "gn:asciiname":"Toso",
    "gn:country_code":"LR",
    "gn:dem":39,
    "gn:feature_class":"P",
    "gn:feature_code":"PPL",
    "gn:name":"Toso",
    "gn:population":0,
    "gn:timezone":"Africa/Monrovia",
    "iso:country":"LR",
    "wof:name":"Toso",
    "wof:placetype":"locality"
},
  "geometry": {"coordinates":[-11.3025,7.15417],"type":"Point"}
}