{
  "type": "Feature",
  "properties": {
    "gn:admin1_code":"16.0",
    "gn:asciiname":"Poliken",
    "gn:country_code":"LR",
    "gn:dem":37,
    "gn:feature_class":"P",
    "gn:feature_code":"PPL",
    "gn:name":"Poliken",
    "gn:population":0,
    "gn:timezone":"Africa/Monrovia",
    "iso:country":"LR",
    "name:und_x_variant":[
        "Poporelekehn"
    ],
    "wof:name":"Poliken",
    "wof:placetype":"locality"
},
  "geometry": {"coordinates":[-7.91702,4.78043],"type":"Point"}
}