{
  "type": "Feature",
  "properties": {
    "gn:admin1_code":"11.0",
    "gn:asciiname":"Gue",
    "gn:country_code":"LR",
    "gn:dem":54,
    "gn:feature_class":"P",
    "gn:feature_code":"PPL",
    "gn:name":"Gue",
    "gn:population":0,
    "gn:timezone":"Africa/Monrovia",
    "iso:country":"LR",
    "name:spa_x_preferred":[
        "Gue"
    ],
    "wof:name":"Gue",
    "wof:placetype":"locality"
},
  "geometry": {"coordinates":[-9.95,6.06667],"type":"Point"}
}