{
  "type": "Feature",
  "properties": {
    "gn:admin1_code":"9.0",
    "gn:asciiname":"Cocopa",
    "gn:country_code":"LR",
    "gn:dem":254,
    "gn:feature_class":"P",
    "gn:feature_code":"PPL",
    "gn:name":"Cocopa",
    "gn:population":0,
    "gn:timezone":"Africa/Monrovia",
    "iso:country":"LR",
    "wof:name":"Cocopa",
    "wof:placetype":"locality"
},
  "geometry": {"coordinates":[-8.89417,7.10194],"type":"Point"}
}