{
  "type": "Feature",
  "properties": {
    "gn:admin1_code":"14.0",
    "gn:asciiname":"Koon",
    "gn:country_code":"LR",
    "gn:dem":62,
    "gn:feature_class":"P",
    "gn:feature_code":"PPL",
    "gn:name":"Koon",
    "gn:population":0,
    "gn:timezone":"Africa/Monrovia",
    "iso:country":"LR",
    "name:und_x_variant":[
        "Be Kung"
    ],
    "wof:name":"Koon",
    "wof:placetype":"locality"
},
  "geometry": {"coordinates":[-10.53944,6.60254],"type":"Point"}
}