{
  "type": "Feature",
  "properties": {
    "gn:admin1_code":"11.0",
    "gn:asciiname":"Bawadla",
    "gn:country_code":"LR",
    "gn:dem":124,
    "gn:feature_class":"P",
    "gn:feature_code":"PPL",
    "gn:name":"Bawadla",
    "gn:population":0,
    "gn:timezone":"Africa/Monrovia",
    "iso:country":"LR",
    "wof:name":"Bawadla",
    "wof:placetype":"locality"
},
  "geometry": {"coordinates":[-9.66667,6.11667],"type":"Point"}
}