{
  "type": "Feature",
  "properties": {
    "gn:admin1_code":"10.0",
    "gn:asciiname":"Joseph Boe",
    "gn:country_code":"LR",
    "gn:dem":186,
    "gn:feature_class":"P",
    "gn:feature_code":"PPL",
    "gn:name":"Joseph Boe",
    "gn:population":0,
    "gn:timezone":"Africa/Monrovia",
    "iso:country":"LR",
    "wof:name":"Joseph Boe",
    "wof:placetype":"locality"
},
  "geometry": {"coordinates":[-8.49217,5.37349],"type":"Point"}
}