{
  "type": "Feature",
  "properties": {
    "gn:admin1_code":"1.0",
    "gn:asciiname":"Baokole",
    "gn:country_code":"LR",
    "gn:dem":270,
    "gn:feature_class":"P",
    "gn:feature_code":"PPL",
    "gn:name":"Baokole",
    "gn:population":0,
    "gn:timezone":"Africa/Monrovia",
    "iso:country":"LR",
    "name:eng_x_preferred":[
        "Baokole"
    ],
    "name:und_x_variant":[
        "Gbaokole"
    ],
    "wof:name":"Baokole",
    "wof:placetype":"locality"
},
  "geometry": {"coordinates":[-9.60559,7.06973],"type":"Point"}
}