{
  "type": "Feature",
  "properties": {
    "gn:admin1_code":"22.0",
    "gn:asciiname":"Geeken",
    "gn:country_code":"LR",
    "gn:dem":263,
    "gn:feature_class":"P",
    "gn:feature_code":"PPL",
    "gn:name":"Geeken",
    "gn:population":0,
    "gn:timezone":"Africa/Monrovia",
    "iso:country":"LR",
    "name:und_x_variant":[
        "Bawia",
        "Geeken"
    ],
    "wof:name":"Geeken",
    "wof:placetype":"locality"
},
  "geometry": {"coordinates":[-7.91611,5.40528],"type":"Point"}
}