{
  "type": "Feature",
  "properties": {
    "gn:admin1_code":"10.0",
    "gn:asciiname":"New Town",
    "gn:country_code":"LR",
    "gn:dem":92,
    "gn:feature_class":"P",
    "gn:feature_code":"PPL",
    "gn:name":"New Town",
    "gn:population":0,
    "gn:timezone":"Africa/Monrovia",
    "iso:country":"LR",
    "name:bre_x_preferred":[
        "New Town"
    ],
    "name:ceb_x_preferred":[
        "New Town"
    ],
    "name:dan_x_preferred":[
        "New Town"
    ],
    "name:deu_x_preferred":[
        "New Town"
    ],
    "name:fin_x_preferred":[
        "New Town"
    ],
    "name:mlg_x_preferred":[
        "New Town"
    ],
    "name:nld_x_preferred":[
        "New Town"
    ],
    "name:sco_x_preferred":[
        "New Town"
    ],
    "name:swe_x_preferred":[
        "New Town"
    ],
    "wof:name":"New Town",
    "wof:placetype":"locality"
},
  "geometry": {"coordinates":[-9.01667,5.27917],"type":"Point"}
}