{
  "type": "Feature",
  "properties": {
    "gn:admin1_code":"13.0",
    "gn:asciiname":"Henogba",
    "gn:country_code":"LR",
    "gn:dem":47,
    "gn:feature_class":"P",
    "gn:feature_code":"PPL",
    "gn:name":"Henogba",
    "gn:population":0,
    "gn:timezone":"Africa/Monrovia",
    "iso:country":"LR",
    "name:und_x_variant":[
        "Baike",
        "Henogba",
        "Hanugbe",
        "Henogbe"
    ],
    "wof:name":"Henogba",
    "wof:placetype":"locality"
},
  "geometry": {"coordinates":[-7.76272,4.66296],"type":"Point"}
}