{
  "type": "Feature",
  "properties": {
    "gn:admin1_code":"20.0",
    "gn:asciiname":"Honehun Number Two",
    "gn:cc2":"LR",
    "gn:country_code":"LR",
    "gn:dem":526,
    "gn:feature_class":"P",
    "gn:feature_code":"PPL",
    "gn:name":"Honehun Number Two",
    "gn:population":0,
    "gn:timezone":"Africa/Monrovia",
    "iso:country":"LR",
    "name:und_x_variant":[
        "Honehun Number 2",
        "Honehun Number Two"
    ],
    "wof:name":"Honehun Number Two",
    "wof:placetype":"locality"
},
  "geometry": {"coordinates":[-10.00111,8.355],"type":"Point"}
}