{
  "type": "Feature",
  "properties": {
    "gn:admin1_code":"22.0",
    "gn:asciiname":"Kanweaken",
    "gn:country_code":"LR",
    "gn:dem":213,
    "gn:feature_class":"P",
    "gn:feature_code":"PPL",
    "gn:name":"Kanweaken",
    "gn:population":0,
    "gn:timezone":"Africa/Monrovia",
    "iso:country":"LR",
    "name:und_x_variant":[
        "Kahnwia",
        "Kaweaken",
        "Kanweaken"
    ],
    "wof:name":"Kanweaken",
    "wof:placetype":"locality"
},
  "geometry": {"coordinates":[-8.02116,5.23396],"type":"Point"}
}