{
  "type": "Feature",
  "properties": {
    "gn:admin1_code":"1.0",
    "gn:asciiname":"Lawa",
    "gn:cc2":"LR",
    "gn:country_code":"LR",
    "gn:dem":270,
    "gn:feature_class":"P",
    "gn:feature_code":"PPL",
    "gn:name":"Lawa",
    "gn:population":0,
    "gn:timezone":"Africa/Monrovia",
    "iso:country":"LR",
    "name:ceb_x_preferred":[
        "Lawa"
    ],
    "name:deu_x_preferred":[
        "Lawa"
    ],
    "name:fra_x_preferred":[
        "Lawa"
    ],
    "name:ita_x_preferred":[
        "Lawa"
    ],
    "name:swe_x_preferred":[
        "Lawa"
    ],
    "name:und_x_variant":[
        "Yea Willy Town",
        "Laouwi"
    ],
    "wof:name":"Lawa",
    "wof:placetype":"locality"
},
  "geometry": {"coordinates":[-9.21667,6.95],"type":"Point"}
}