{
  "type": "Feature",
  "properties": {
    "gn:admin1_code":"16.0",
    "gn:asciiname":"Plaplakehn",
    "gn:country_code":"LR",
    "gn:dem":77,
    "gn:feature_class":"P",
    "gn:feature_code":"PPL",
    "gn:name":"Plaplakehn",
    "gn:population":0,
    "gn:timezone":"Africa/Monrovia",
    "iso:country":"LR",
    "name:und_x_variant":[
        "Wedo"
    ],
    "wof:name":"Plaplakehn",
    "wof:placetype":"locality"
},
  "geometry": {"coordinates":[-8.27113,4.87853],"type":"Point"}
}