{
  "type": "Feature",
  "properties": {
    "gn:admin1_code":"10.0",
    "gn:asciiname":"Joseph",
    "gn:country_code":"LR",
    "gn:dem":134,
    "gn:feature_class":"P",
    "gn:feature_code":"PPL",
    "gn:name":"Joseph",
    "gn:population":0,
    "gn:timezone":"Africa/Monrovia",
    "iso:country":"LR",
    "name:und_x_variant":[
        "Kalo",
        "Kedi",
        "Geedor",
        "Joseph"
    ],
    "wof:name":"Joseph",
    "wof:placetype":"locality"
},
  "geometry": {"coordinates":[-8.72969,5.43607],"type":"Point"}
}