{
  "type": "Feature",
  "properties": {
    "gn:admin1_code":"10.0",
    "gn:asciiname":"Joseph",
    "gn:country_code":"LR",
    "gn:dem":134,
    "gn:feature_class":"P",
    "gn:feature_code":"PPL",
    "gn:name":"Joseph",
    "gn:population":0,
    "gn:timezone":"Africa/Monrovia",
    "iso:country":"LR",
    "name:ara_x_preferred":[
        "\u062c\u0648\u0632\u064a\u0641"
    ],
    "name:fra_x_preferred":[
        "Joseph"
    ],
    "name:hyw_x_preferred":[
        "\u0545\u0578\u057e\u057d\u0567\u0583"
    ],
    "name:jpn_x_preferred":[
        "\u30e8\u30bb\u30d5"
    ],
    "name:kat_x_preferred":[
        "\u10d8\u10dd\u10e1\u10d4\u10d1\u10d8"
    ],
    "name:kor_x_preferred":[
        "\uc694\uc149"
    ],
    "name:nds_x_preferred":[
        "Joseph"
    ],
    "name:und_x_variant":[
        "Kalo",
        "Kedi",
        "Geedor"
    ],
    "name:zho_x_preferred":[
        "\u7ea6\u745f\u592b"
    ],
    "wof:name":"Joseph",
    "wof:placetype":"locality"
},
  "geometry": {"coordinates":[-8.72969,5.43607],"type":"Point"}
}