{
  "type": "Feature",
  "properties": {
    "gn:admin1_code":"20.0",
    "gn:asciiname":"Gbonyea",
    "gn:cc2":"LR",
    "gn:country_code":"LR",
    "gn:dem":295,
    "gn:feature_class":"P",
    "gn:feature_code":"PPL",
    "gn:name":"Gbonyea",
    "gn:population":0,
    "gn:timezone":"Africa/Monrovia",
    "iso:country":"LR",
    "name:und_x_variant":[
        "Bangye",
        "Gbongie",
        "Gbonga",
        "Gbonyea"
    ],
    "wof:name":"Gbonyea",
    "wof:placetype":"locality"
},
  "geometry": {"coordinates":[-9.55694,7.50611],"type":"Point"}
}