{
  "type": "Feature",
  "properties": {
    "gn:admin1_code":"1.0",
    "gn:asciiname":"Kpowula Hil",
    "gn:country_code":"LR",
    "gn:dem":390,
    "gn:feature_class":"P",
    "gn:feature_code":"PPL",
    "gn:name":"Kpowula Hil",
    "gn:population":0,
    "gn:timezone":"Africa/Monrovia",
    "iso:country":"LR",
    "name:eng_x_preferred":[
        "Kpowula Hil"
    ],
    "wof:name":"Kpowula Hil",
    "wof:placetype":"locality"
},
  "geometry": {"coordinates":[-9.7241,6.9979],"type":"Point"}
}