{
  "type": "Feature",
  "properties": {
    "gn:admin1_code":"11.0",
    "gn:asciiname":"Moses Karnga Town",
    "gn:country_code":"LR",
    "gn:dem":26,
    "gn:feature_class":"P",
    "gn:feature_code":"PPL",
    "gn:name":"Moses Karnga Town",
    "gn:population":0,
    "gn:timezone":"Africa/Monrovia",
    "iso:country":"LR",
    "wof:name":"Moses Karnga Town",
    "wof:placetype":"locality"
},
  "geometry": {"coordinates":[-9.89111,5.88417],"type":"Point"}
}