{
  "type": "Feature",
  "properties": {
    "gn:admin1_code":"20.0",
    "gn:asciiname":"Nyandemolahun",
    "gn:cc2":"LR",
    "gn:country_code":"LR",
    "gn:dem":515,
    "gn:feature_class":"P",
    "gn:feature_code":"PPL",
    "gn:name":"Nyandemolahun",
    "gn:population":0,
    "gn:timezone":"Africa/Monrovia",
    "iso:country":"LR",
    "name:und_x_variant":[
        "Lalasu",
        "Nyandemolahun"
    ],
    "wof:name":"Nyandemolahun",
    "wof:placetype":"locality"
},
  "geometry": {"coordinates":[-9.95917,8.44694],"type":"Point"}
}