{
  "type": "Feature",
  "properties": {
    "gn:admin1_code":"20.0",
    "gn:asciiname":"Kesini",
    "gn:country_code":"LR",
    "gn:dem":442,
    "gn:feature_class":"P",
    "gn:feature_code":"PPL",
    "gn:name":"Kesini",
    "gn:population":0,
    "gn:timezone":"Africa/Monrovia",
    "iso:country":"LR",
    "wof:name":"Kesini",
    "wof:placetype":"locality"
},
  "geometry": {"coordinates":[-10.22083,8.405],"type":"Point"}
}