{
  "type": "Feature",
  "properties": {
    "gn:admin1_code":"19.0",
    "gn:asciiname":"Duwa",
    "gn:country_code":"LR",
    "gn:dem":237,
    "gn:feature_class":"P",
    "gn:feature_code":"PPL",
    "gn:name":"Duwa",
    "gn:population":0,
    "gn:timezone":"Africa/Monrovia",
    "iso:country":"LR",
    "wof:name":"Duwa",
    "wof:placetype":"locality"
},
  "geometry": {"coordinates":[-8.16982,6.2735],"type":"Point"}
}