{
  "type": "Feature",
  "properties": {
    "gn:admin1_code":"19.0",
    "gn:asciiname":"Duwa",
    "gn:country_code":"LR",
    "gn:dem":237,
    "gn:feature_class":"P",
    "gn:feature_code":"PPL",
    "gn:name":"Duwa",
    "gn:population":0,
    "gn:timezone":"Africa/Monrovia",
    "iso:country":"LR",
    "name:azb_x_preferred":[
        "\u062f\u0648\u0627"
    ],
    "name:aze_x_preferred":[
        "Duva xan"
    ],
    "name:cat_x_preferred":[
        "Duwa"
    ],
    "name:fas_x_preferred":[
        "\u062f\u0648\u0627"
    ],
    "name:fra_x_preferred":[
        "Douwa"
    ],
    "name:jpn_x_preferred":[
        "\u30c9\u30a5\u30a2"
    ],
    "name:mon_x_preferred":[
        "\u0414\u0443\u0432\u0430"
    ],
    "name:nld_x_preferred":[
        "Duwa"
    ],
    "name:rus_x_preferred":[
        "\u0414\u0443\u0432\u0430"
    ],
    "name:srp_x_preferred":[
        "\u0414\u0443\u0432\u0430"
    ],
    "name:uig_x_preferred":[
        "\u062f\u06c7\u06cb\u0627"
    ],
    "name:ukr_x_preferred":[
        "\u0414\u0443\u0432\u0430"
    ],
    "name:uzb_x_preferred":[
        "Duva"
    ],
    "wof:name":"Duwa",
    "wof:placetype":"locality"
},
  "geometry": {"coordinates":[-8.16982,6.2735],"type":"Point"}
}