{
  "type": "Feature",
  "properties": {
    "gn:admin1_code":"17.0",
    "gn:asciiname":"Bulorkollen",
    "gn:country_code":"LR",
    "gn:dem":106,
    "gn:feature_class":"P",
    "gn:feature_code":"PPL",
    "gn:name":"Bulorkollen",
    "gn:population":0,
    "gn:timezone":"Africa/Monrovia",
    "iso:country":"LR",
    "name:und_x_variant":[
        "Dukai",
        "Bauakla",
        "Dukata",
        "Bulorkollen"
    ],
    "wof:name":"Bulorkollen",
    "wof:placetype":"locality"
},
  "geometry": {"coordinates":[-10.15309,6.68902],"type":"Point"}
}