{
  "type": "Feature",
  "properties": {
    "gn:admin1_code":"9.0",
    "gn:asciiname":"Nyahplay",
    "gn:cc2":"LR",
    "gn:country_code":"LR",
    "gn:dem":286,
    "gn:feature_class":"P",
    "gn:feature_code":"PPL",
    "gn:name":"Nyahplay",
    "gn:population":0,
    "gn:timezone":"Africa/Monrovia",
    "iso:country":"LR",
    "name:und_x_variant":[
        "Yale",
        "Nyale",
        "Yala",
        "Nyali",
        "Yaley",
        "Nala",
        "Nyahplay"
    ],
    "wof:name":"Nyahplay",
    "wof:placetype":"locality"
},
  "geometry": {"coordinates":[-8.47083,6.96083],"type":"Point"}
}