{
  "type": "Feature",
  "properties": {
    "gn:admin1_code":"13.0",
    "gn:asciiname":"Bulu Town",
    "gn:country_code":"LR",
    "gn:dem":7,
    "gn:feature_class":"P",
    "gn:feature_code":"PPL",
    "gn:name":"Bulu Town",
    "gn:population":0,
    "gn:timezone":"Africa/Monrovia",
    "iso:country":"LR",
    "name:und_x_variant":[
        "Bulu"
    ],
    "wof:name":"Bulu Town",
    "wof:placetype":"locality"
},
  "geometry": {"coordinates":[-7.6527,4.36712],"type":"Point"}
}