{
  "type": "Feature",
  "properties": {
    "gn:admin1_code":"14.0",
    "gn:asciiname":"Zubaba Town",
    "gn:country_code":"LR",
    "gn:dem":80,
    "gn:feature_class":"P",
    "gn:feature_code":"PPL",
    "gn:name":"Zubaba Town",
    "gn:population":0,
    "gn:timezone":"Africa/Monrovia",
    "iso:country":"LR",
    "wof:name":"Zubaba Town",
    "wof:placetype":"locality"
},
  "geometry": {"coordinates":[-10.51667,6.51667],"type":"Point"}
}