{
  "type": "Feature",
  "properties": {
    "gn:admin1_code":"19.0",
    "gn:asciiname":"Vleyee",
    "gn:country_code":"LR",
    "gn:dem":222,
    "gn:feature_class":"P",
    "gn:feature_code":"PPL",
    "gn:name":"Vleyee",
    "gn:population":0,
    "gn:timezone":"Africa/Monrovia",
    "iso:country":"LR",
    "name:und_x_variant":[
        "Fry",
        "Fry Town",
        "Vleyee"
    ],
    "wof:name":"Vleyee",
    "wof:placetype":"locality"
},
  "geometry": {"coordinates":[-7.87818,6.23014],"type":"Point"}
}