{
  "type": "Feature",
  "properties": {
    "gn:admin1_code":"12.0",
    "gn:asciiname":"Weilor Town",
    "gn:country_code":"LR",
    "gn:dem":44,
    "gn:feature_class":"P",
    "gn:feature_code":"PPL",
    "gn:name":"Weilor Town",
    "gn:population":0,
    "gn:timezone":"Africa/Monrovia",
    "iso:country":"LR",
    "name:und_x_variant":[
        "Wilo",
        "Vilo",
        "Wieloh",
        "Wila",
        "Wuilo",
        "Weilor Town"
    ],
    "wof:name":"Weilor Town",
    "wof:placetype":"locality"
},
  "geometry": {"coordinates":[-11.32423,7.00338],"type":"Point"}
}