{
  "type": "Feature",
  "properties": {
    "gn:admin1_code":"11.0",
    "gn:asciiname":"Luyubli",
    "gn:country_code":"LR",
    "gn:dem":117,
    "gn:feature_class":"P",
    "gn:feature_code":"PPL",
    "gn:name":"Luyubli",
    "gn:population":0,
    "gn:timezone":"Africa/Monrovia",
    "iso:country":"LR",
    "wof:name":"Luyubli",
    "wof:placetype":"locality"
},
  "geometry": {"coordinates":[-10.13333,6.48333],"type":"Point"}
}