{
  "type": "Feature",
  "properties": {
    "gn:admin1_code":"20.0",
    "gn:asciiname":"Lawalazu",
    "gn:country_code":"LR",
    "gn:dem":561,
    "gn:feature_class":"P",
    "gn:feature_code":"PPL",
    "gn:name":"Lawalazu",
    "gn:population":0,
    "gn:timezone":"Africa/Monrovia",
    "iso:country":"LR",
    "wof:name":"Lawalazu",
    "wof:placetype":"locality"
},
  "geometry": {"coordinates":[-9.8475,8.45167],"type":"Point"}
}