{
  "type": "Feature",
  "properties": {
    "gn:admin1_code":"12.0",
    "gn:asciiname":"Gbakite",
    "gn:cc2":"LR",
    "gn:country_code":"LR",
    "gn:dem":102,
    "gn:feature_class":"P",
    "gn:feature_code":"PPL",
    "gn:name":"Gbakite",
    "gn:population":0,
    "gn:timezone":"Africa/Monrovia",
    "iso:country":"LR",
    "name:und_x_variant":[
        "Gbakote",
        "Gbakite"
    ],
    "wof:name":"Gbakite",
    "wof:placetype":"locality"
},
  "geometry": {"coordinates":[-10.85,7.11667],"type":"Point"}
}