{
  "type": "Feature",
  "properties": {
    "gn:admin1_code":"20.0",
    "gn:asciiname":"Kpakumai",
    "gn:cc2":"LR",
    "gn:country_code":"LR",
    "gn:dem":526,
    "gn:feature_class":"P",
    "gn:feature_code":"PPL",
    "gn:name":"Kpakumai",
    "gn:population":0,
    "gn:timezone":"Africa/Monrovia",
    "iso:country":"LR",
    "name:und_x_variant":[
        "Jolowu",
        "Jlou",
        "Kpakumai"
    ],
    "wof:name":"Kpakumai",
    "wof:placetype":"locality"
},
  "geometry": {"coordinates":[-9.69167,8.27389],"type":"Point"}
}