{
  "type": "Feature",
  "properties": {
    "gn:admin1_code":"17.0",
    "gn:asciiname":"Bubon",
    "gn:country_code":"LR",
    "gn:dem":16,
    "gn:feature_class":"P",
    "gn:feature_code":"PPL",
    "gn:name":"Bubon",
    "gn:population":0,
    "gn:timezone":"Africa/Monrovia",
    "iso:country":"LR",
    "name:eng_x_preferred":[
        "Bubon"
    ],
    "wof:name":"Bubon",
    "wof:placetype":"locality"
},
  "geometry": {"coordinates":[-10.56436,6.28282],"type":"Point"}
}