{
  "type": "Feature",
  "properties": {
    "gn:admin1_code":"11.0",
    "gn:asciiname":"Meunbli Number One",
    "gn:cc2":"LR",
    "gn:country_code":"LR",
    "gn:dem":48,
    "gn:feature_class":"P",
    "gn:feature_code":"PPL",
    "gn:name":"Meunbli Number One",
    "gn:population":0,
    "gn:timezone":"Africa/Monrovia",
    "iso:country":"LR",
    "name:und_x_variant":[
        "Meunbli Number 1",
        "Meunbli Number One"
    ],
    "wof:name":"Meunbli Number One",
    "wof:placetype":"locality"
},
  "geometry": {"coordinates":[-9.96667,5.96667],"type":"Point"}
}