{
  "type": "Feature",
  "properties": {
    "gn:admin1_code":"10.0",
    "gn:asciiname":"Tahomi",
    "gn:country_code":"LR",
    "gn:dem":208,
    "gn:feature_class":"P",
    "gn:feature_code":"PPL",
    "gn:name":"Tahomi",
    "gn:population":0,
    "gn:timezone":"Africa/Monrovia",
    "iso:country":"LR",
    "name:und_x_variant":[
        "Galue",
        "Tahomi"
    ],
    "wof:name":"Tahomi",
    "wof:placetype":"locality"
},
  "geometry": {"coordinates":[-8.43167,5.82444],"type":"Point"}
}