{
  "type": "Feature",
  "properties": {
    "gn:admin1_code":"20.0",
    "gn:asciiname":"Lukamai",
    "gn:cc2":"LR",
    "gn:country_code":"LR",
    "gn:dem":542,
    "gn:feature_class":"P",
    "gn:feature_code":"PPL",
    "gn:name":"Lukamai",
    "gn:population":0,
    "gn:timezone":"Africa/Monrovia",
    "iso:country":"LR",
    "name:und_x_variant":[
        "Lokamai",
        "Lukamai"
    ],
    "wof:name":"Lukamai",
    "wof:placetype":"locality"
},
  "geometry": {"coordinates":[-9.49083,8.36],"type":"Point"}
}