{
  "type": "Feature",
  "properties": {
    "gn:admin1_code":"15.0",
    "gn:asciiname":"Free Heart",
    "gn:country_code":"LR",
    "gn:dem":45,
    "gn:feature_class":"P",
    "gn:feature_code":"PPL",
    "gn:name":"Free Heart",
    "gn:population":0,
    "gn:timezone":"Africa/Monrovia",
    "iso:country":"LR",
    "wof:name":"Free Heart",
    "wof:placetype":"locality"
},
  "geometry": {"coordinates":[-10.94969,6.61393],"type":"Point"}
}