{
  "type": "Feature",
  "properties": {
    "gn:admin1_code":"9.0",
    "gn:asciiname":"Kpla",
    "gn:cc2":"LR",
    "gn:country_code":"LR",
    "gn:dem":231,
    "gn:feature_class":"P",
    "gn:feature_code":"PPL",
    "gn:name":"Kpla",
    "gn:population":0,
    "gn:timezone":"Africa/Monrovia",
    "iso:country":"LR",
    "name:und_x_variant":[
        "Dahn",
        "Kpla"
    ],
    "wof:name":"Kpla",
    "wof:placetype":"locality"
},
  "geometry": {"coordinates":[-8.91861,6.97889],"type":"Point"}
}