{
  "type": "Feature",
  "properties": {
    "gn:admin1_code":"15.0",
    "gn:asciiname":"Amadu",
    "gn:country_code":"LR",
    "gn:dem":36,
    "gn:feature_class":"P",
    "gn:feature_code":"PPL",
    "gn:name":"Amadu",
    "gn:population":0,
    "gn:timezone":"Africa/Monrovia",
    "iso:country":"LR",
    "name:und_x_variant":[
        "Amina Number One",
        "Amina Number 1",
        "Amina",
        "Amadu"
    ],
    "wof:name":"Amadu",
    "wof:placetype":"locality"
},
  "geometry": {"coordinates":[-10.84658,6.52706],"type":"Point"}
}