{
  "type": "Feature",
  "properties": {
    "gn:admin1_code":"9.0",
    "gn:asciiname":"Kosia",
    "gn:cc2":"LR",
    "gn:country_code":"LR",
    "gn:dem":258,
    "gn:feature_class":"P",
    "gn:feature_code":"PPL",
    "gn:name":"Kosia",
    "gn:population":0,
    "gn:timezone":"Africa/Monrovia",
    "iso:country":"LR",
    "name:und_x_variant":[
        "Sirun",
        "Kosia"
    ],
    "wof:name":"Kosia",
    "wof:placetype":"locality"
},
  "geometry": {"coordinates":[-8.92,6.34083],"type":"Point"}
}