{
  "type": "Feature",
  "properties": {
    "gn:admin1_code":"19.0",
    "gn:asciiname":"Drugbor",
    "gn:country_code":"LR",
    "gn:dem":213,
    "gn:feature_class":"P",
    "gn:feature_code":"PPL",
    "gn:name":"Drugbor",
    "gn:population":0,
    "gn:timezone":"Africa/Monrovia",
    "iso:country":"LR",
    "wof:name":"Drugbor",
    "wof:placetype":"locality"
},
  "geometry": {"coordinates":[-7.67139,5.85694],"type":"Point"}
}