{
  "type": "Feature",
  "properties": {
    "gn:admin1_code":"11.0",
    "gn:asciiname":"Blesi",
    "gn:country_code":"LR",
    "gn:dem":204,
    "gn:feature_class":"P",
    "gn:feature_code":"PPL",
    "gn:name":"Blesi",
    "gn:population":0,
    "gn:timezone":"Africa/Monrovia",
    "iso:country":"LR",
    "wof:name":"Blesi",
    "wof:placetype":"locality"
},
  "geometry": {"coordinates":[-9.63333,6.35],"type":"Point"}
}