{
  "type": "Feature",
  "properties": {
    "gn:admin1_code":"9.0",
    "gn:asciiname":"Dama",
    "gn:cc2":"LR",
    "gn:country_code":"LR",
    "gn:dem":232,
    "gn:feature_class":"P",
    "gn:feature_code":"PPL",
    "gn:name":"Dama",
    "gn:population":0,
    "gn:timezone":"Africa/Monrovia",
    "iso:country":"LR",
    "name:und_x_variant":[
        "Dan",
        "Dama"
    ],
    "wof:name":"Dama",
    "wof:placetype":"locality"
},
  "geometry": {"coordinates":[-9.06222,6.54556],"type":"Point"}
}