{
  "type": "Feature",
  "properties": {
    "gn:admin1_code":"20.0",
    "gn:asciiname":"Ngaylayhun",
    "gn:cc2":"LR",
    "gn:country_code":"LR",
    "gn:dem":546,
    "gn:feature_class":"P",
    "gn:feature_code":"PPL",
    "gn:name":"Ngaylayhun",
    "gn:population":0,
    "gn:timezone":"Africa/Monrovia",
    "iso:country":"LR",
    "name:und_x_variant":[
        "Laobengu",
        "Langbama",
        "Ngaylayhun"
    ],
    "wof:name":"Ngaylayhun",
    "wof:placetype":"locality"
},
  "geometry": {"coordinates":[-10.16056,8.29333],"type":"Point"}
}