{
  "type": "Feature",
  "properties": {
    "gn:admin1_code":"18.0",
    "gn:asciiname":"Bodowin",
    "gn:country_code":"LR",
    "gn:dem":133,
    "gn:feature_class":"P",
    "gn:feature_code":"PPL",
    "gn:name":"Bodowin",
    "gn:population":0,
    "gn:timezone":"Africa/Monrovia",
    "iso:country":"LR",
    "name:und_x_variant":[
        "Geowla",
        "Giowla",
        "Bodowin"
    ],
    "wof:name":"Bodowin",
    "wof:placetype":"locality"
},
  "geometry": {"coordinates":[-9.43686,5.98345],"type":"Point"}
}