{
  "type": "Feature",
  "properties": {
    "gn:admin1_code":"12.0",
    "gn:asciiname":"Sengama",
    "gn:cc2":"LR",
    "gn:country_code":"LR",
    "gn:dem":52,
    "gn:feature_class":"P",
    "gn:feature_code":"PPL",
    "gn:name":"Sengama",
    "gn:population":0,
    "gn:timezone":"Africa/Monrovia",
    "iso:country":"LR",
    "name:und_x_variant":[
        "Sembehun",
        "Sengama"
    ],
    "wof:name":"Sengama",
    "wof:placetype":"locality"
},
  "geometry": {"coordinates":[-11.31667,7.15],"type":"Point"}
}