{
  "type": "Feature",
  "properties": {
    "gn:admin1_code":"9.0",
    "gn:asciiname":"Zortaple",
    "gn:cc2":"LR",
    "gn:country_code":"LR",
    "gn:dem":442,
    "gn:feature_class":"P",
    "gn:feature_code":"PPL",
    "gn:name":"Zortaple",
    "gn:population":0,
    "gn:timezone":"Africa/Monrovia",
    "iso:country":"LR",
    "name:und_x_variant":[
        "Zotaple",
        "Zortaple"
    ],
    "wof:name":"Zortaple",
    "wof:placetype":"locality"
},
  "geometry": {"coordinates":[-8.56194,7.38167],"type":"Point"}
}