{
  "type": "Feature",
  "properties": {
    "gn:admin1_code":"21.0",
    "gn:asciiname":"Saviama",
    "gn:country_code":"LR",
    "gn:dem":363,
    "gn:feature_class":"P",
    "gn:feature_code":"PPL",
    "gn:name":"Saviama",
    "gn:population":0,
    "gn:timezone":"Africa/Monrovia",
    "iso:country":"LR",
    "wof:name":"Saviama",
    "wof:placetype":"locality"
},
  "geometry": {"coordinates":[-10.20667,7.38444],"type":"Point"}
}