{
  "type": "Feature",
  "properties": {
    "gn:admin1_code":"9.0",
    "gn:asciiname":"Voba",
    "gn:cc2":"LR",
    "gn:country_code":"LR",
    "gn:dem":238,
    "gn:feature_class":"P",
    "gn:feature_code":"PPL",
    "gn:name":"Voba",
    "gn:population":0,
    "gn:timezone":"Africa/Monrovia",
    "iso:country":"LR",
    "name:und_x_variant":[
        "Vui",
        "Vuipa",
        "Voba"
    ],
    "wof:name":"Voba",
    "wof:placetype":"locality"
},
  "geometry": {"coordinates":[-9.09083,6.68667],"type":"Point"}
}