{
  "type": "Feature",
  "properties": {
    "gn:admin1_code":"17.0",
    "gn:asciiname":"Vena",
    "gn:cc2":"LR",
    "gn:country_code":"LR",
    "gn:dem":125,
    "gn:feature_class":"P",
    "gn:feature_code":"PPL",
    "gn:name":"Vena",
    "gn:population":0,
    "gn:timezone":"Africa/Monrovia",
    "iso:country":"LR",
    "name:arg_x_preferred":[
        "Vena"
    ],
    "name:ceb_x_preferred":[
        "Vena"
    ],
    "name:deu_x_preferred":[
        "Vena"
    ],
    "name:fin_x_preferred":[
        "Vena"
    ],
    "name:fra_x_preferred":[
        "Vena"
    ],
    "name:ita_x_preferred":[
        "Vena"
    ],
    "name:nld_x_preferred":[
        "Vena"
    ],
    "name:spa_x_preferred":[
        "Vena"
    ],
    "name:srp_x_preferred":[
        "\u0412\u0435\u043d\u0430"
    ],
    "name:swe_x_preferred":[
        "Vena"
    ],
    "name:und_x_variant":[
        "Noigata"
    ],
    "name:uzb_x_preferred":[
        "Vena"
    ],
    "wof:name":"Vena",
    "wof:placetype":"locality"
},
  "geometry": {"coordinates":[-10.10639,6.72361],"type":"Point"}
}