{
  "type": "Feature",
  "properties": {
    "gn:admin1_code":"20.0",
    "gn:asciiname":"Duogmai",
    "gn:cc2":"LR",
    "gn:country_code":"LR",
    "gn:dem":527,
    "gn:feature_class":"P",
    "gn:feature_code":"PPL",
    "gn:name":"Duogmai",
    "gn:population":0,
    "gn:timezone":"Africa/Monrovia",
    "iso:country":"LR",
    "name:und_x_variant":[
        "Dourgomai",
        "Duogomai",
        "Duorgumai",
        "Duoyamai",
        "Duogmai"
    ],
    "wof:name":"Duogmai",
    "wof:placetype":"locality"
},
  "geometry": {"coordinates":[-9.73167,8.18389],"type":"Point"}
}