{
  "type": "Feature",
  "properties": {
    "gn:admin1_code":"19.0",
    "gn:asciiname":"Franzay",
    "gn:country_code":"LR",
    "gn:dem":239,
    "gn:feature_class":"P",
    "gn:feature_code":"PPL",
    "gn:name":"Franzay",
    "gn:population":0,
    "gn:timezone":"Africa/Monrovia",
    "iso:country":"LR",
    "name:und_x_variant":[
        "Bagohn"
    ],
    "wof:name":"Franzay",
    "wof:placetype":"locality"
},
  "geometry": {"coordinates":[-8.13648,6.13599],"type":"Point"}
}