{
  "type": "Feature",
  "properties": {
    "gn:admin1_code":"21.0",
    "gn:asciiname":"Totoquelle",
    "gn:country_code":"LR",
    "gn:dem":185,
    "gn:feature_class":"P",
    "gn:feature_code":"PPL",
    "gn:name":"Totoquelle",
    "gn:population":0,
    "gn:timezone":"Africa/Monrovia",
    "iso:country":"LR",
    "name:und_x_variant":[
        "Totokole",
        "Totakwelle",
        "Totokwele",
        "Totoquelle"
    ],
    "wof:name":"Totoquelle",
    "wof:placetype":"locality"
},
  "geometry": {"coordinates":[-10.3975,7.05417],"type":"Point"}
}