{
  "type": "Feature",
  "properties": {
    "gn:admin1_code":"9.0",
    "gn:asciiname":"Bentonwin",
    "gn:cc2":"LR",
    "gn:country_code":"LR",
    "gn:dem":429,
    "gn:feature_class":"P",
    "gn:feature_code":"PPL",
    "gn:name":"Bentonwin",
    "gn:population":0,
    "gn:timezone":"Africa/Monrovia",
    "iso:country":"LR",
    "name:und_x_variant":[
        "Gbentowen",
        "Batonwe",
        "Betonwi",
        "Baytonwee",
        "Bentonwin"
    ],
    "wof:name":"Bentonwin",
    "wof:placetype":"locality"
},
  "geometry": {"coordinates":[-8.68361,7.66556],"type":"Point"}
}