{
  "type": "Feature",
  "properties": {
    "gn:admin1_code":"19.0",
    "gn:asciiname":"Garleo",
    "gn:country_code":"LR",
    "gn:dem":211,
    "gn:feature_class":"P",
    "gn:feature_code":"PPL",
    "gn:name":"Garleo",
    "gn:population":0,
    "gn:timezone":"Africa/Monrovia",
    "iso:country":"LR",
    "wof:name":"Garleo",
    "wof:placetype":"locality"
},
  "geometry": {"coordinates":[-7.56304,5.78331],"type":"Point"}
}