{
  "type": "Feature",
  "properties": {
    "gn:admin1_code":"1.0",
    "gn:asciiname":"Gbartota",
    "gn:country_code":"LR",
    "gn:dem":228,
    "gn:feature_class":"P",
    "gn:feature_code":"PPL",
    "gn:name":"Gbartota",
    "gn:population":0,
    "gn:timezone":"Africa/Monrovia",
    "iso:country":"LR",
    "name:eng_x_preferred":[
        "Gbartota"
    ],
    "wof:name":"Gbartota",
    "wof:placetype":"locality"
},
  "geometry": {"coordinates":[-9.71606,6.79181],"type":"Point"}
}