{
  "type": "Feature",
  "properties": {
    "gn:admin1_code":"17.0",
    "gn:asciiname":"Maniama",
    "gn:country_code":"LR",
    "gn:dem":157,
    "gn:feature_class":"P",
    "gn:feature_code":"PPL",
    "gn:name":"Maniama",
    "gn:population":0,
    "gn:timezone":"Africa/Monrovia",
    "iso:country":"LR",
    "name:eng_x_preferred":[
        "Maniama"
    ],
    "wof:name":"Maniama",
    "wof:placetype":"locality"
},
  "geometry": {"coordinates":[-10.36101,6.77057],"type":"Point"}
}