{
  "type": "Feature",
  "properties": {
    "gn:admin1_code":"20.0",
    "gn:asciiname":"Lolo",
    "gn:country_code":"LR",
    "gn:dem":482,
    "gn:feature_class":"P",
    "gn:feature_code":"PPL",
    "gn:name":"Lolo",
    "gn:population":0,
    "gn:timezone":"Africa/Monrovia",
    "iso:country":"LR",
    "name:ceb_x_preferred":[
        "Lolo"
    ],
    "name:deu_x_preferred":[
        "Lolo"
    ],
    "name:fra_x_preferred":[
        "Lolo"
    ],
    "name:heb_x_preferred":[
        "\u05dc\u05d5\u05dc\u05d5"
    ],
    "name:ind_x_preferred":[
        "Lolo"
    ],
    "name:ita_x_preferred":[
        "Lolo"
    ],
    "name:nld_x_preferred":[
        "Lolo"
    ],
    "name:por_x_preferred":[
        "Lolo"
    ],
    "name:rus_x_preferred":[
        "\u041b\u043e\u043b\u043e"
    ],
    "name:spa_x_preferred":[
        "Lolo"
    ],
    "name:swe_x_preferred":[
        "Lolo"
    ],
    "wof:name":"Lolo",
    "wof:placetype":"locality"
},
  "geometry": {"coordinates":[-10.10556,8.50194],"type":"Point"}
}