{
  "type": "Feature",
  "properties": {
    "gn:admin1_code":"1.0",
    "gn:asciiname":"Milenta",
    "gn:country_code":"LR",
    "gn:dem":248,
    "gn:feature_class":"P",
    "gn:feature_code":"PPL",
    "gn:name":"Milenta",
    "gn:population":0,
    "gn:timezone":"Africa/Monrovia",
    "iso:country":"LR",
    "name:eng_x_preferred":[
        "Milenta"
    ],
    "wof:name":"Milenta",
    "wof:placetype":"locality"
},
  "geometry": {"coordinates":[-9.26951,6.84983],"type":"Point"}
}