{
  "type": "Feature",
  "properties": {
    "gn:admin1_code":"9.0",
    "gn:asciiname":"Bleto",
    "gn:country_code":"LR",
    "gn:dem":242,
    "gn:feature_class":"P",
    "gn:feature_code":"PPL",
    "gn:name":"Bleto",
    "gn:population":0,
    "gn:timezone":"Africa/Monrovia",
    "iso:country":"LR",
    "wof:name":"Bleto",
    "wof:placetype":"locality"
},
  "geometry": {"coordinates":[-8.865,6.76861],"type":"Point"}
}