{
  "type": "Feature",
  "properties": {
    "gn:admin1_code":"10.0",
    "gn:asciiname":"Bosma Town",
    "gn:country_code":"LR",
    "gn:dem":73,
    "gn:feature_class":"P",
    "gn:feature_code":"PPL",
    "gn:name":"Bosma Town",
    "gn:population":0,
    "gn:timezone":"Africa/Monrovia",
    "iso:country":"LR",
    "wof:name":"Bosma Town",
    "wof:placetype":"locality"
},
  "geometry": {"coordinates":[-8.98283,5.43486],"type":"Point"}
}