{
  "type": "Feature",
  "properties": {
    "gn:admin1_code":"12.0",
    "gn:asciiname":"Buluma",
    "gn:country_code":"LR",
    "gn:dem":12,
    "gn:feature_class":"P",
    "gn:feature_code":"PPL",
    "gn:name":"Buluma",
    "gn:population":0,
    "gn:timezone":"Africa/Monrovia",
    "iso:country":"LR",
    "wof:name":"Buluma",
    "wof:placetype":"locality"
},
  "geometry": {"coordinates":[-11.18489,6.73073],"type":"Point"}
}