{
  "type": "Feature",
  "properties": {
    "gn:admin1_code":"11.0",
    "gn:asciiname":"Zardeh",
    "gn:country_code":"LR",
    "gn:dem":9,
    "gn:feature_class":"P",
    "gn:feature_code":"PPL",
    "gn:name":"Zardeh",
    "gn:population":0,
    "gn:timezone":"Africa/Monrovia",
    "iso:country":"LR",
    "wof:name":"Zardeh",
    "wof:placetype":"locality"
},
  "geometry": {"coordinates":[-9.9383,5.8137],"type":"Point"}
}