{
  "type": "Feature",
  "properties": {
    "gn:admin1_code":"1.0",
    "gn:asciiname":"Nanata",
    "gn:country_code":"LR",
    "gn:dem":242,
    "gn:feature_class":"P",
    "gn:feature_code":"PPL",
    "gn:name":"Nanata",
    "gn:population":0,
    "gn:timezone":"Africa/Monrovia",
    "iso:country":"LR",
    "name:eng_x_preferred":[
        "Nanata"
    ],
    "wof:name":"Nanata",
    "wof:placetype":"locality"
},
  "geometry": {"coordinates":[-9.42319,6.65088],"type":"Point"}
}