{
  "type": "Feature",
  "properties": {
    "gn:admin1_code":"12.0",
    "gn:asciiname":"Gobla",
    "gn:country_code":"LR",
    "gn:dem":13,
    "gn:feature_class":"P",
    "gn:feature_code":"PPL",
    "gn:name":"Gobla",
    "gn:population":0,
    "gn:timezone":"Africa/Monrovia",
    "iso:country":"LR",
    "wof:name":"Gobla",
    "wof:placetype":"locality"
},
  "geometry": {"coordinates":[-11.25623,6.8198],"type":"Point"}
}