{
  "type": "Feature",
  "properties": {
    "gn:admin1_code":"9.0",
    "gn:asciiname":"Gaaple",
    "gn:cc2":"LR",
    "gn:country_code":"LR",
    "gn:dem":270,
    "gn:feature_class":"P",
    "gn:feature_code":"PPL",
    "gn:name":"Gaaple",
    "gn:population":0,
    "gn:timezone":"Africa/Monrovia",
    "iso:country":"LR",
    "name:und_x_variant":[
        "Pokwi",
        "Gaaple"
    ],
    "wof:name":"Gaaple",
    "wof:placetype":"locality"
},
  "geometry": {"coordinates":[-8.88833,6.54361],"type":"Point"}
}