{
  "type": "Feature",
  "properties": {
    "gn:admin1_code":"12.0",
    "gn:asciiname":"Te",
    "gn:country_code":"LR",
    "gn:dem":15,
    "gn:feature_class":"P",
    "gn:feature_code":"PPL",
    "gn:name":"Te",
    "gn:population":0,
    "gn:timezone":"Africa/Monrovia",
    "iso:country":"LR",
    "name:und_x_variant":[
        "Teh",
        "Te",
        "Tee"
    ],
    "wof:name":"Te",
    "wof:placetype":"locality"
},
  "geometry": {"coordinates":[-11.10516,6.69462],"type":"Point"}
}