{
  "type": "Feature",
  "properties": {
    "gn:admin1_code":"12.0",
    "gn:asciiname":"Butter Hill",
    "gn:country_code":"LR",
    "gn:dem":132,
    "gn:feature_class":"P",
    "gn:feature_code":"PPL",
    "gn:name":"Butter Hill",
    "gn:population":0,
    "gn:timezone":"Africa/Monrovia",
    "iso:country":"LR",
    "wof:name":"Butter Hill",
    "wof:placetype":"locality"
},
  "geometry": {"coordinates":[-11.03479,7.25737],"type":"Point"}
}