{
  "type": "Feature",
  "properties": {
    "gn:admin1_code":"1.0",
    "gn:asciiname":"Harter Farm",
    "gn:country_code":"LR",
    "gn:dem":198,
    "gn:feature_class":"P",
    "gn:feature_code":"PPL",
    "gn:name":"Harter Farm",
    "gn:population":0,
    "gn:timezone":"Africa/Monrovia",
    "iso:country":"LR",
    "name:eng_x_preferred":[
        "Harter Farm"
    ],
    "name:und_x_variant":[
        "Harter Farm (1)",
        "Harter Farm One"
    ],
    "wof:name":"Harter Farm",
    "wof:placetype":"locality"
},
  "geometry": {"coordinates":[-9.30682,6.61095],"type":"Point"}
}