{
  "type": "Feature",
  "properties": {
    "gn:admin1_code":"1.0",
    "gn:asciiname":"Airfield",
    "gn:country_code":"LR",
    "gn:dem":221,
    "gn:feature_class":"P",
    "gn:feature_code":"PPL",
    "gn:name":"Airfield",
    "gn:population":0,
    "gn:timezone":"Africa/Monrovia",
    "iso:country":"LR",
    "name:eng_x_preferred":[
        "Airfield"
    ],
    "wof:name":"Airfield",
    "wof:placetype":"locality"
},
  "geometry": {"coordinates":[-9.37303,6.65064],"type":"Point"}
}