{
  "type": "Feature",
  "properties": {
    "gn:admin1_code":"17.0",
    "gn:asciiname":"Richard Holder Farm",
    "gn:country_code":"LR",
    "gn:dem":152,
    "gn:feature_class":"P",
    "gn:feature_code":"PPL",
    "gn:name":"Richard Holder Farm",
    "gn:population":0,
    "gn:timezone":"Africa/Monrovia",
    "iso:country":"LR",
    "wof:name":"Richard Holder Farm",
    "wof:placetype":"locality"
},
  "geometry": {"coordinates":[-10.19561,6.7731],"type":"Point"}
}