{
  "type": "Feature",
  "properties": {
    "gn:admin1_code":"9.0",
    "gn:asciiname":"Lole",
    "gn:cc2":"LR",
    "gn:country_code":"LR",
    "gn:dem":355,
    "gn:feature_class":"P",
    "gn:feature_code":"PPL",
    "gn:name":"Lole",
    "gn:population":0,
    "gn:timezone":"Africa/Monrovia",
    "iso:country":"LR",
    "name:ceb_x_preferred":[
        "Lole"
    ],
    "name:ita_x_preferred":[
        "Lole"
    ],
    "name:swe_x_preferred":[
        "Lole"
    ],
    "name:und_x_variant":[
        "Loe",
        "Lelu",
        "Dolie",
        "Lolay",
        "Lole"
    ],
    "wof:name":"Lole",
    "wof:placetype":"locality"
},
  "geometry": {"coordinates":[-8.5225,7.23972],"type":"Point"}
}