{
  "type": "Feature",
  "properties": {
    "gn:admin1_code":"19.0",
    "gn:asciiname":"Bahai",
    "gn:country_code":"LR",
    "gn:dem":251,
    "gn:feature_class":"P",
    "gn:feature_code":"PPL",
    "gn:name":"Bahai",
    "gn:population":0,
    "gn:timezone":"Africa/Monrovia",
    "iso:country":"LR",
    "wof:name":"Bahai",
    "wof:placetype":"locality"
},
  "geometry": {"coordinates":[-8.55471,6.31719],"type":"Point"}
}