{
  "type": "Feature",
  "properties": {
    "gn:admin1_code":"11.0",
    "gn:asciiname":"Joe 25",
    "gn:country_code":"LR",
    "gn:dem":36,
    "gn:feature_class":"P",
    "gn:feature_code":"PPL",
    "gn:name":"Joe 25",
    "gn:population":0,
    "gn:timezone":"Africa/Monrovia",
    "iso:country":"LR",
    "wof:name":"Joe 25",
    "wof:placetype":"locality"
},
  "geometry": {"coordinates":[-10.29882,6.29249],"type":"Point"}
}