{
  "type": "Feature",
  "properties": {
    "gn:admin1_code":"20.0",
    "gn:asciiname":"Popalahun",
    "gn:cc2":"LR",
    "gn:country_code":"LR",
    "gn:dem":496,
    "gn:feature_class":"P",
    "gn:feature_code":"PPL",
    "gn:name":"Popalahun",
    "gn:population":0,
    "gn:timezone":"Africa/Monrovia",
    "iso:country":"LR",
    "name:und_x_variant":[
        "Popolahun",
        "Popolahuh",
        "Populahun",
        "Popalahun"
    ],
    "wof:name":"Popalahun",
    "wof:placetype":"locality"
},
  "geometry": {"coordinates":[-10.22917,8.17889],"type":"Point"}
}