{
  "type": "Feature",
  "properties": {
    "gn:admin1_code":"20.0",
    "gn:asciiname":"Dayzebah",
    "gn:cc2":"LR",
    "gn:country_code":"LR",
    "gn:dem":525,
    "gn:feature_class":"P",
    "gn:feature_code":"PPL",
    "gn:name":"Dayzebah",
    "gn:population":0,
    "gn:timezone":"Africa/Monrovia",
    "iso:country":"LR",
    "name:und_x_variant":[
        "Wagonidu",
        "Deziba",
        "Waiglomai",
        "Dayzebah"
    ],
    "wof:name":"Dayzebah",
    "wof:placetype":"locality"
},
  "geometry": {"coordinates":[-9.65472,8.31694],"type":"Point"}
}