{
  "type": "Feature",
  "properties": {
    "gn:admin1_code":"11.0",
    "gn:asciiname":"Peterta",
    "gn:country_code":"LR",
    "gn:dem":199,
    "gn:feature_class":"P",
    "gn:feature_code":"PPL",
    "gn:name":"Peterta",
    "gn:population":0,
    "gn:timezone":"Africa/Monrovia",
    "iso:country":"LR",
    "wof:name":"Peterta",
    "wof:placetype":"locality"
},
  "geometry": {"coordinates":[-9.70698,6.62706],"type":"Point"}
}