{
  "type": "Feature",
  "properties": {
    "gn:admin1_code":"1.0",
    "gn:asciiname":"Gboata",
    "gn:country_code":"LR",
    "gn:dem":309,
    "gn:feature_class":"P",
    "gn:feature_code":"PPL",
    "gn:name":"Gboata",
    "gn:population":0,
    "gn:timezone":"Africa/Monrovia",
    "iso:country":"LR",
    "wof:name":"Gboata",
    "wof:placetype":"locality"
},
  "geometry": {"coordinates":[-9.18361,7.28417],"type":"Point"}
}