{
  "type": "Feature",
  "properties": {
    "gn:admin1_code":"10.0",
    "gn:asciiname":"Wakepo",
    "gn:country_code":"LR",
    "gn:dem":42,
    "gn:feature_class":"P",
    "gn:feature_code":"PPL",
    "gn:name":"Wakepo",
    "gn:population":0,
    "gn:timezone":"Africa/Monrovia",
    "iso:country":"LR",
    "wof:name":"Wakepo",
    "wof:placetype":"locality"
},
  "geometry": {"coordinates":[-8.65,4.88333],"type":"Point"}
}