{
  "type": "Feature",
  "properties": {
    "gn:admin1_code":"19.0",
    "gn:asciiname":"Peter Tarlue",
    "gn:country_code":"LR",
    "gn:dem":208,
    "gn:feature_class":"P",
    "gn:feature_code":"PPL",
    "gn:name":"Peter Tarlue",
    "gn:population":0,
    "gn:timezone":"Africa/Monrovia",
    "iso:country":"LR",
    "wof:name":"Peter Tarlue",
    "wof:placetype":"locality"
},
  "geometry": {"coordinates":[-7.77798,5.80507],"type":"Point"}
}