{
  "type": "Feature",
  "properties": {
    "gn:admin1_code":"10.0",
    "gn:asciiname":"Weyee Wesseh",
    "gn:country_code":"LR",
    "gn:dem":232,
    "gn:feature_class":"P",
    "gn:feature_code":"PPL",
    "gn:name":"Weyee Wesseh",
    "gn:population":0,
    "gn:timezone":"Africa/Monrovia",
    "iso:country":"LR",
    "wof:name":"Weyee Wesseh",
    "wof:placetype":"locality"
},
  "geometry": {"coordinates":[-8.7025,5.11516],"type":"Point"}
}