{
  "type": "Feature",
  "properties": {
    "gn:admin1_code":"18.0",
    "gn:asciiname":"Simodabli",
    "gn:country_code":"LR",
    "gn:dem":77,
    "gn:feature_class":"P",
    "gn:feature_code":"PPL",
    "gn:name":"Simodabli",
    "gn:population":0,
    "gn:timezone":"Africa/Monrovia",
    "iso:country":"LR",
    "wof:name":"Simodabli",
    "wof:placetype":"locality"
},
  "geometry": {"coordinates":[-9.61002,5.74954],"type":"Point"}
}