{
  "type": "Feature",
  "properties": {
    "gn:admin1_code":"9.0",
    "gn:asciiname":"Bluntuo",
    "gn:country_code":"LR",
    "gn:dem":256,
    "gn:feature_class":"P",
    "gn:feature_code":"PPL",
    "gn:name":"Bluntuo",
    "gn:population":0,
    "gn:timezone":"Africa/Monrovia",
    "iso:country":"LR",
    "wof:name":"Bluntuo",
    "wof:placetype":"locality"
},
  "geometry": {"coordinates":[-8.35836,6.88255],"type":"Point"}
}