{
  "type": "Feature",
  "properties": {
    "gn:admin1_code":"11.0",
    "gn:asciiname":"Dei Wenzohn",
    "gn:country_code":"LR",
    "gn:dem":84,
    "gn:feature_class":"P",
    "gn:feature_code":"PPL",
    "gn:name":"Dei Wenzohn",
    "gn:population":0,
    "gn:timezone":"Africa/Monrovia",
    "iso:country":"LR",
    "wof:name":"Dei Wenzohn",
    "wof:placetype":"locality"
},
  "geometry": {"coordinates":[-9.8693,6.01526],"type":"Point"}
}