{
  "type": "Feature",
  "properties": {
    "gn:admin1_code":"15.0",
    "gn:asciiname":"Sugbon",
    "gn:country_code":"LR",
    "gn:dem":39,
    "gn:feature_class":"P",
    "gn:feature_code":"PPL",
    "gn:name":"Sugbon",
    "gn:population":0,
    "gn:timezone":"Africa/Monrovia",
    "iso:country":"LR",
    "name:und_x_variant":[
        "Sugblun",
        "Sombu",
        "Sugbon"
    ],
    "wof:name":"Sugbon",
    "wof:placetype":"locality"
},
  "geometry": {"coordinates":[-10.89054,6.62077],"type":"Point"}
}