{
  "type": "Feature",
  "properties": {
    "gn:admin1_code":"20.0",
    "gn:asciiname":"Jomaha",
    "gn:cc2":"LR",
    "gn:country_code":"LR",
    "gn:dem":448,
    "gn:feature_class":"P",
    "gn:feature_code":"PPL",
    "gn:name":"Jomaha",
    "gn:population":0,
    "gn:timezone":"Africa/Monrovia",
    "iso:country":"LR",
    "name:und_x_variant":[
        "Jomata",
        "Jomaha"
    ],
    "wof:name":"Jomaha",
    "wof:placetype":"locality"
},
  "geometry": {"coordinates":[-10.14639,8.41389],"type":"Point"}
}