{
  "type": "Feature",
  "properties": {
    "gn:admin1_code":"11.0",
    "gn:asciiname":"Blowhen Sayon",
    "gn:country_code":"LR",
    "gn:dem":211,
    "gn:feature_class":"P",
    "gn:feature_code":"PPL",
    "gn:name":"Blowhen Sayon",
    "gn:population":0,
    "gn:timezone":"Africa/Monrovia",
    "iso:country":"LR",
    "name:und_x_variant":[
        "Yondo",
        "Blowhen Sayon"
    ],
    "wof:name":"Blowhen Sayon",
    "wof:placetype":"locality"
},
  "geometry": {"coordinates":[-9.38068,6.33057],"type":"Point"}
}