{
  "type": "Feature",
  "properties": {
    "gn:admin1_code":"18.0",
    "gn:asciiname":"Nema Town",
    "gn:country_code":"LR",
    "gn:dem":88,
    "gn:feature_class":"P",
    "gn:feature_code":"PPL",
    "gn:name":"Nema Town",
    "gn:population":0,
    "gn:timezone":"Africa/Monrovia",
    "iso:country":"LR",
    "wof:name":"Nema Town",
    "wof:placetype":"locality"
},
  "geometry": {"coordinates":[-9.16139,5.70139],"type":"Point"}
}