{
  "type": "Feature",
  "properties": {
    "gn:admin1_code":"1.0",
    "gn:asciiname":"Toemoi",
    "gn:country_code":"LR",
    "gn:dem":237,
    "gn:feature_class":"P",
    "gn:feature_code":"PPL",
    "gn:name":"Toemoi",
    "gn:population":0,
    "gn:timezone":"Africa/Monrovia",
    "iso:country":"LR",
    "wof:name":"Toemoi",
    "wof:placetype":"locality"
},
  "geometry": {"coordinates":[-9.41667,6.83333],"type":"Point"}
}