{
  "type": "Feature",
  "properties": {
    "gn:admin1_code":"17.0",
    "gn:asciiname":"Bofata",
    "gn:country_code":"LR",
    "gn:dem":113,
    "gn:feature_class":"P",
    "gn:feature_code":"PPL",
    "gn:name":"Bofata",
    "gn:population":0,
    "gn:timezone":"Africa/Monrovia",
    "iso:country":"LR",
    "name:und_x_variant":[
        "Belefanai",
        "Bofata"
    ],
    "wof:name":"Bofata",
    "wof:placetype":"locality"
},
  "geometry": {"coordinates":[-10.02628,6.51049],"type":"Point"}
}