{
  "type": "Feature",
  "properties": {
    "gn:admin1_code":"1.0",
    "gn:asciiname":"Crusoe Town",
    "gn:country_code":"LR",
    "gn:dem":213,
    "gn:feature_class":"P",
    "gn:feature_code":"PPL",
    "gn:name":"Crusoe Town",
    "gn:population":0,
    "gn:timezone":"Africa/Monrovia",
    "iso:country":"LR",
    "name:und_x_variant":[
        "Crusoe"
    ],
    "wof:name":"Crusoe Town",
    "wof:placetype":"locality"
},
  "geometry": {"coordinates":[-9.44388,6.57899],"type":"Point"}
}