{
  "type": "Feature",
  "properties": {
    "gn:admin1_code":"18.0",
    "gn:asciiname":"Mape",
    "gn:country_code":"LR",
    "gn:dem":146,
    "gn:feature_class":"P",
    "gn:feature_code":"PPL",
    "gn:name":"Mape",
    "gn:population":0,
    "gn:timezone":"Africa/Monrovia",
    "iso:country":"LR",
    "wof:name":"Mape",
    "wof:placetype":"locality"
},
  "geometry": {"coordinates":[-9.45,5.88333],"type":"Point"}
}