{
  "type": "Feature",
  "properties": {
    "gn:admin1_code":"9.0",
    "gn:asciiname":"Nyoanplay",
    "gn:country_code":"LR",
    "gn:dem":261,
    "gn:feature_class":"P",
    "gn:feature_code":"PPL",
    "gn:name":"Nyoanplay",
    "gn:population":0,
    "gn:timezone":"Africa/Monrovia",
    "iso:country":"LR",
    "wof:name":"Nyoanplay",
    "wof:placetype":"locality"
},
  "geometry": {"coordinates":[-8.31722,6.99361],"type":"Point"}
}