{
  "type": "Feature",
  "properties": {
    "gn:admin1_code":"19.0",
    "gn:asciiname":"Bazohn",
    "gn:country_code":"LR",
    "gn:dem":222,
    "gn:feature_class":"P",
    "gn:feature_code":"PPL",
    "gn:name":"Bazohn",
    "gn:population":0,
    "gn:timezone":"Africa/Monrovia",
    "iso:country":"LR",
    "wof:name":"Bazohn",
    "wof:placetype":"locality"
},
  "geometry": {"coordinates":[-8.18083,5.98528],"type":"Point"}
}