{
  "type": "Feature",
  "properties": {
    "gn:admin1_code":"20.0",
    "gn:asciiname":"Bakiedou",
    "gn:cc2":"LR",
    "gn:country_code":"LR",
    "gn:dem":505,
    "gn:feature_class":"P",
    "gn:feature_code":"PPL",
    "gn:name":"Bakiedou",
    "gn:population":0,
    "gn:timezone":"Africa/Monrovia",
    "iso:country":"LR",
    "name:und_x_variant":[
        "Bahk\u00e8doe",
        "Bakamai",
        "Bak\u00e9dou",
        "Bakiemai",
        "Bakedu",
        "Bamai",
        "Bakiedou"
    ],
    "wof:name":"Bakiedou",
    "wof:placetype":"locality"
},
  "geometry": {"coordinates":[-9.63417,8.29333],"type":"Point"}
}