{
  "type": "Feature",
  "properties": {
    "gn:admin1_code":"15.0",
    "gn:asciiname":"Geba",
    "gn:country_code":"LR",
    "gn:dem":119,
    "gn:feature_class":"P",
    "gn:feature_code":"PPL",
    "gn:name":"Geba",
    "gn:population":0,
    "gn:timezone":"Africa/Monrovia",
    "iso:country":"LR",
    "name:cat_x_preferred":[
        "Geba"
    ],
    "name:deu_x_preferred":[
        "Geba"
    ],
    "name:pol_x_preferred":[
        "Geba"
    ],
    "name:und_x_variant":[
        "Gebe",
        "Geba"
    ],
    "wof:name":"Geba",
    "wof:placetype":"locality"
},
  "geometry": {"coordinates":[-10.58713,6.81391],"type":"Point"}
}