{
  "type": "Feature",
  "properties": {
    "gn:admin1_code":"21.0",
    "gn:asciiname":"Dusa Number One",
    "gn:country_code":"LR",
    "gn:dem":109,
    "gn:feature_class":"P",
    "gn:feature_code":"PPL",
    "gn:name":"Dusa Number One",
    "gn:population":0,
    "gn:timezone":"Africa/Monrovia",
    "iso:country":"LR",
    "name:und_x_variant":[
        "Dusa",
        "Dusa Number One"
    ],
    "wof:name":"Dusa Number One",
    "wof:placetype":"locality"
},
  "geometry": {"coordinates":[-10.82636,6.99814],"type":"Point"}
}