{
  "type": "Feature",
  "properties": {
    "gn:admin1_code":"14.0",
    "gn:asciiname":"Bawehn",
    "gn:country_code":"LR",
    "gn:dem":33,
    "gn:feature_class":"P",
    "gn:feature_code":"PPL",
    "gn:name":"Bawehn",
    "gn:population":0,
    "gn:timezone":"Africa/Monrovia",
    "iso:country":"LR",
    "wof:name":"Bawehn",
    "wof:placetype":"locality"
},
  "geometry": {"coordinates":[-10.32389,6.27028],"type":"Point"}
}