{
  "type": "Feature",
  "properties": {
    "gn:admin1_code":"1.0",
    "gn:asciiname":"Totota",
    "gn:country_code":"LR",
    "gn:dem":260,
    "gn:feature_class":"P",
    "gn:feature_code":"PPL",
    "gn:name":"Totota",
    "gn:population":0,
    "gn:timezone":"Africa/Monrovia",
    "iso:country":"LR",
    "wof:name":"Totota",
    "wof:placetype":"locality"
},
  "geometry": {"coordinates":[-9.93862,6.81219],"type":"Point"}
}