{
  "type": "Feature",
  "properties": {
    "gn:admin1_code":"14.0",
    "gn:asciiname":"Gbonjema",
    "gn:country_code":"LR",
    "gn:dem":25,
    "gn:feature_class":"P",
    "gn:feature_code":"PPL",
    "gn:name":"Gbonjema",
    "gn:population":0,
    "gn:timezone":"Africa/Monrovia",
    "iso:country":"LR",
    "wof:name":"Gbonjema",
    "wof:placetype":"locality"
},
  "geometry": {"coordinates":[-10.81667,6.53333],"type":"Point"}
}