{
  "type": "Feature",
  "properties": {
    "gn:admin1_code":"11.0",
    "gn:asciiname":"Boswahn",
    "gn:cc2":"LR",
    "gn:country_code":"LR",
    "gn:dem":113,
    "gn:feature_class":"P",
    "gn:feature_code":"PPL",
    "gn:name":"Boswahn",
    "gn:population":0,
    "gn:timezone":"Africa/Monrovia",
    "iso:country":"LR",
    "name:und_x_variant":[
        "Floyo",
        "Boswahn"
    ],
    "wof:name":"Boswahn",
    "wof:placetype":"locality"
},
  "geometry": {"coordinates":[-9.78333,6.08333],"type":"Point"}
}