{
  "type": "Feature",
  "properties": {
    "gn:admin1_code":"17.0",
    "gn:asciiname":"Gliegba",
    "gn:country_code":"LR",
    "gn:dem":141,
    "gn:feature_class":"P",
    "gn:feature_code":"PPL",
    "gn:name":"Gliegba",
    "gn:population":0,
    "gn:timezone":"Africa/Monrovia",
    "iso:country":"LR",
    "name:und_x_variant":[
        "Gliba",
        "Gligbea",
        "Gligba",
        "Gliegba"
    ],
    "wof:name":"Gliegba",
    "wof:placetype":"locality"
},
  "geometry": {"coordinates":[-10.02056,6.64071],"type":"Point"}
}