{
  "type": "Feature",
  "properties": {
    "gn:admin1_code":"20.0",
    "gn:asciiname":"Movimai",
    "gn:country_code":"LR",
    "gn:dem":580,
    "gn:feature_class":"P",
    "gn:feature_code":"PPL",
    "gn:name":"Movimai",
    "gn:population":0,
    "gn:timezone":"Africa/Monrovia",
    "iso:country":"LR",
    "wof:name":"Movimai",
    "wof:placetype":"locality"
},
  "geometry": {"coordinates":[-9.92667,8.30639],"type":"Point"}
}