{
  "type": "Feature",
  "properties": {
    "gn:admin1_code":"19.0",
    "gn:asciiname":"Zamu",
    "gn:country_code":"LR",
    "gn:dem":240,
    "gn:feature_class":"P",
    "gn:feature_code":"PPL",
    "gn:name":"Zamu",
    "gn:population":0,
    "gn:timezone":"Africa/Monrovia",
    "iso:country":"LR",
    "wof:name":"Zamu",
    "wof:placetype":"locality"
},
  "geometry": {"coordinates":[-8.52417,6.46306],"type":"Point"}
}