{
  "type": "Feature",
  "properties": {
    "gn:admin1_code":"1.0",
    "gn:asciiname":"Gorta",
    "gn:country_code":"LR",
    "gn:dem":257,
    "gn:feature_class":"P",
    "gn:feature_code":"PPL",
    "gn:name":"Gorta",
    "gn:population":0,
    "gn:timezone":"Africa/Monrovia",
    "iso:country":"LR",
    "name:eng_x_preferred":[
        "Gorta"
    ],
    "wof:name":"Gorta",
    "wof:placetype":"locality"
},
  "geometry": {"coordinates":[-9.54303,7.04084],"type":"Point"}
}