{
  "type": "Feature",
  "properties": {
    "gn:admin1_code":"10.0",
    "gn:asciiname":"Konwonkpo",
    "gn:country_code":"LR",
    "gn:dem":97,
    "gn:feature_class":"P",
    "gn:feature_code":"PPL",
    "gn:name":"Konwonkpo",
    "gn:population":0,
    "gn:timezone":"Africa/Monrovia",
    "iso:country":"LR",
    "wof:name":"Konwonkpo",
    "wof:placetype":"locality"
},
  "geometry": {"coordinates":[-8.67796,5.07568],"type":"Point"}
}