{
  "type": "Feature",
  "properties": {
    "gn:admin1_code":"14.0",
    "gn:asciiname":"Malony",
    "gn:country_code":"LR",
    "gn:dem":124,
    "gn:feature_class":"P",
    "gn:feature_code":"PPL",
    "gn:name":"Malony",
    "gn:population":0,
    "gn:timezone":"Africa/Monrovia",
    "iso:country":"LR",
    "name:und_x_variant":[
        "Lava Camp",
        "Malony"
    ],
    "wof:name":"Malony",
    "wof:placetype":"locality"
},
  "geometry": {"coordinates":[-10.43306,6.66441],"type":"Point"}
}