{
  "type": "Feature",
  "properties": {
    "gn:admin1_code":"11.0",
    "gn:asciiname":"Tutubli",
    "gn:country_code":"LR",
    "gn:dem":79,
    "gn:feature_class":"P",
    "gn:feature_code":"PPL",
    "gn:name":"Tutubli",
    "gn:population":0,
    "gn:timezone":"Africa/Monrovia",
    "iso:country":"LR",
    "wof:name":"Tutubli",
    "wof:placetype":"locality"
},
  "geometry": {"coordinates":[-9.96667,6.08333],"type":"Point"}
}