{
  "type": "Feature",
  "properties": {
    "gn:admin1_code":"18.0",
    "gn:asciiname":"Plaw",
    "gn:country_code":"LR",
    "gn:dem":123,
    "gn:feature_class":"P",
    "gn:feature_code":"PPL",
    "gn:name":"Plaw",
    "gn:population":0,
    "gn:timezone":"Africa/Monrovia",
    "iso:country":"LR",
    "name:und_x_variant":[
        "Zami",
        "Zammie",
        "Plaw"
    ],
    "wof:name":"Plaw",
    "wof:placetype":"locality"
},
  "geometry": {"coordinates":[-9.2315,5.85287],"type":"Point"}
}