{
  "type": "Feature",
  "properties": {
    "gn:admin1_code":"20.0",
    "gn:asciiname":"Bengizima",
    "gn:country_code":"LR",
    "gn:dem":466,
    "gn:feature_class":"P",
    "gn:feature_code":"PPL",
    "gn:name":"Bengizima",
    "gn:population":0,
    "gn:timezone":"Africa/Monrovia",
    "iso:country":"LR",
    "wof:name":"Bengizima",
    "wof:placetype":"locality"
},
  "geometry": {"coordinates":[-9.45,7.76667],"type":"Point"}
}