{
  "type": "Feature",
  "properties": {
    "gn:admin1_code":"16.0",
    "gn:asciiname":"Wlakehn",
    "gn:country_code":"LR",
    "gn:dem":91,
    "gn:feature_class":"P",
    "gn:feature_code":"PPL",
    "gn:name":"Wlakehn",
    "gn:population":0,
    "gn:timezone":"Africa/Monrovia",
    "iso:country":"LR",
    "name:und_x_variant":[
        "Wloken Number One"
    ],
    "wof:name":"Wlakehn",
    "wof:placetype":"locality"
},
  "geometry": {"coordinates":[-8.22577,4.90935],"type":"Point"}
}