{
  "type": "Feature",
  "properties": {
    "gn:admin1_code":"14.0",
    "gn:asciiname":"Kiangai",
    "gn:country_code":"LR",
    "gn:dem":103,
    "gn:feature_class":"P",
    "gn:feature_code":"PPL",
    "gn:name":"Kiangai",
    "gn:population":0,
    "gn:timezone":"Africa/Monrovia",
    "iso:country":"LR",
    "name:und_x_variant":[
        "Kiayago",
        "Kiayaglo",
        "Kienga",
        "Kiangai"
    ],
    "wof:name":"Kiangai",
    "wof:placetype":"locality"
},
  "geometry": {"coordinates":[-10.45608,6.63167],"type":"Point"}
}