{
  "type": "Feature",
  "properties": {
    "gn:admin1_code":"1.0",
    "gn:asciiname":"Vengeleta",
    "gn:country_code":"LR",
    "gn:dem":300,
    "gn:feature_class":"P",
    "gn:feature_code":"PPL",
    "gn:name":"Vengeleta",
    "gn:population":0,
    "gn:timezone":"Africa/Monrovia",
    "iso:country":"LR",
    "wof:name":"Vengeleta",
    "wof:placetype":"locality"
},
  "geometry": {"coordinates":[-10.26667,6.81667],"type":"Point"}
}