{
  "type": "Feature",
  "properties": {
    "gn:admin1_code":"10.0",
    "gn:asciiname":"Meninli",
    "gn:country_code":"LR",
    "gn:dem":28,
    "gn:feature_class":"P",
    "gn:feature_code":"PPL",
    "gn:name":"Meninli",
    "gn:population":0,
    "gn:timezone":"Africa/Monrovia",
    "iso:country":"LR",
    "wof:name":"Meninli",
    "wof:placetype":"locality"
},
  "geometry": {"coordinates":[-8.54181,5.03938],"type":"Point"}
}