{
  "type": "Feature",
  "properties": {
    "gn:admin1_code":"13.0",
    "gn:asciiname":"Bloke (2)",
    "gn:country_code":"LR",
    "gn:dem":32,
    "gn:feature_class":"P",
    "gn:feature_code":"PPL",
    "gn:name":"Bloke (2)",
    "gn:population":0,
    "gn:timezone":"Africa/Monrovia",
    "iso:country":"LR",
    "wof:name":"Bloke (2)",
    "wof:placetype":"locality"
},
  "geometry": {"coordinates":[-7.65,4.51667],"type":"Point"}
}