{
  "type": "Feature",
  "properties": {
    "gn:admin1_code":"1.0",
    "gn:asciiname":"Jarmu",
    "gn:country_code":"LR",
    "gn:dem":283,
    "gn:feature_class":"P",
    "gn:feature_code":"PPL",
    "gn:name":"Jarmu",
    "gn:population":0,
    "gn:timezone":"Africa/Monrovia",
    "iso:country":"LR",
    "name:eng_x_preferred":[
        "Jarmu"
    ],
    "wof:name":"Jarmu",
    "wof:placetype":"locality"
},
  "geometry": {"coordinates":[-9.21254,7.05699],"type":"Point"}
}