{
  "type": "Feature",
  "properties": {
    "gn:admin1_code":"10.0",
    "gn:asciiname":"Bokali",
    "gn:country_code":"LR",
    "gn:dem":40,
    "gn:feature_class":"P",
    "gn:feature_code":"PPL",
    "gn:name":"Bokali",
    "gn:population":0,
    "gn:timezone":"Africa/Monrovia",
    "iso:country":"LR",
    "wof:name":"Bokali",
    "wof:placetype":"locality"
},
  "geometry": {"coordinates":[-8.59536,4.98075],"type":"Point"}
}