{
  "type": "Feature",
  "properties": {
    "gn:admin1_code":"12.0",
    "gn:asciiname":"Botoye",
    "gn:country_code":"LR",
    "gn:dem":130,
    "gn:feature_class":"P",
    "gn:feature_code":"PPL",
    "gn:name":"Botoye",
    "gn:population":0,
    "gn:timezone":"Africa/Monrovia",
    "iso:country":"LR",
    "wof:name":"Botoye",
    "wof:placetype":"locality"
},
  "geometry": {"coordinates":[-11.03333,7.25],"type":"Point"}
}