{
  "type": "Feature",
  "properties": {
    "gn:admin1_code":"11.0",
    "gn:asciiname":"Sue",
    "gn:country_code":"LR",
    "gn:dem":251,
    "gn:feature_class":"P",
    "gn:feature_code":"PPL",
    "gn:name":"Sue",
    "gn:population":0,
    "gn:timezone":"Africa/Monrovia",
    "iso:country":"LR",
    "name:bre_x_preferred":[
        "Sue"
    ],
    "name:ceb_x_preferred":[
        "Sue"
    ],
    "name:ces_x_preferred":[
        "Sue"
    ],
    "name:deu_x_preferred":[
        "Sue"
    ],
    "name:fra_x_preferred":[
        "Sue"
    ],
    "name:nld_x_preferred":[
        "Sue"
    ],
    "name:nor_x_preferred":[
        "Sue"
    ],
    "name:por_x_preferred":[
        "Sue"
    ],
    "name:swe_x_preferred":[
        "Sue"
    ],
    "name:und_x_variant":[
        "Tloba"
    ],
    "wof:name":"Sue",
    "wof:placetype":"locality"
},
  "geometry": {"coordinates":[-9.21134,6.55928],"type":"Point"}
}