{
  "type": "Feature",
  "properties": {
    "gn:admin1_code":"10.0",
    "gn:asciiname":"Joegbawon",
    "gn:country_code":"LR",
    "gn:dem":53,
    "gn:feature_class":"P",
    "gn:feature_code":"PPL",
    "gn:name":"Joegbawon",
    "gn:population":0,
    "gn:timezone":"Africa/Monrovia",
    "iso:country":"LR",
    "wof:name":"Joegbawon",
    "wof:placetype":"locality"
},
  "geometry": {"coordinates":[-8.68465,5.00459],"type":"Point"}
}