{
  "type": "Feature",
  "properties": {
    "gn:admin1_code":"13.0",
    "gn:asciiname":"Wesake",
    "gn:country_code":"LR",
    "gn:dem":16,
    "gn:feature_class":"P",
    "gn:feature_code":"PPL",
    "gn:name":"Wesake",
    "gn:population":0,
    "gn:timezone":"Africa/Monrovia",
    "iso:country":"LR",
    "name:und_x_variant":[
        "Wusike",
        "Wesake"
    ],
    "wof:name":"Wesake",
    "wof:placetype":"locality"
},
  "geometry": {"coordinates":[-7.5737,4.68671],"type":"Point"}
}