{
  "type": "Feature",
  "properties": {
    "gn:admin1_code":"17.0",
    "gn:asciiname":"Kpla",
    "gn:country_code":"LR",
    "gn:dem":127,
    "gn:feature_class":"P",
    "gn:feature_code":"PPL",
    "gn:name":"Kpla",
    "gn:population":0,
    "gn:timezone":"Africa/Monrovia",
    "iso:country":"LR",
    "wof:name":"Kpla",
    "wof:placetype":"locality"
},
  "geometry": {"coordinates":[-10.22472,6.75374],"type":"Point"}
}