{
  "type": "Feature",
  "properties": {
    "gn:admin1_code":"15.0",
    "gn:asciiname":"Zohn",
    "gn:country_code":"LR",
    "gn:dem":35,
    "gn:feature_class":"P",
    "gn:feature_code":"PPL",
    "gn:name":"Zohn",
    "gn:population":0,
    "gn:timezone":"Africa/Monrovia",
    "iso:country":"LR",
    "name:und_x_variant":[
        "Zong",
        "Zohn"
    ],
    "wof:name":"Zohn",
    "wof:placetype":"locality"
},
  "geometry": {"coordinates":[-10.80316,6.60916],"type":"Point"}
}