{
  "type": "Feature",
  "properties": {
    "gn:admin1_code":"18.0",
    "gn:asciiname":"Wiasohnbli",
    "gn:country_code":"LR",
    "gn:dem":56,
    "gn:feature_class":"P",
    "gn:feature_code":"PPL",
    "gn:name":"Wiasohnbli",
    "gn:population":0,
    "gn:timezone":"Africa/Monrovia",
    "iso:country":"LR",
    "wof:name":"Wiasohnbli",
    "wof:placetype":"locality"
},
  "geometry": {"coordinates":[-9.6046,5.69561],"type":"Point"}
}