{
  "type": "Feature",
  "properties": {
    "gn:admin1_code":"21.0",
    "gn:asciiname":"Boinu",
    "gn:country_code":"LR",
    "gn:dem":191,
    "gn:feature_class":"P",
    "gn:feature_code":"PPL",
    "gn:name":"Boinu",
    "gn:population":0,
    "gn:timezone":"Africa/Monrovia",
    "iso:country":"LR",
    "wof:name":"Boinu",
    "wof:placetype":"locality"
},
  "geometry": {"coordinates":[-10.58333,7.03333],"type":"Point"}
}