{
  "type": "Feature",
  "properties": {
    "gn:admin1_code":"20.0",
    "gn:asciiname":"Mimolahun",
    "gn:cc2":"LR",
    "gn:country_code":"LR",
    "gn:dem":256,
    "gn:feature_class":"P",
    "gn:feature_code":"PPL",
    "gn:name":"Mimolahun",
    "gn:population":0,
    "gn:timezone":"Africa/Monrovia",
    "iso:country":"LR",
    "name:und_x_variant":[
        "Memolahun",
        "Memolhun",
        "Mimalahun",
        "Mimolahun"
    ],
    "wof:name":"Mimolahun",
    "wof:placetype":"locality"
},
  "geometry": {"coordinates":[-10.46611,8.06556],"type":"Point"}
}