{
  "type": "Feature",
  "properties": {
    "gn:admin1_code":"15.0",
    "gn:asciiname":"Hill Town",
    "gn:country_code":"LR",
    "gn:dem":50,
    "gn:feature_class":"P",
    "gn:feature_code":"PPL",
    "gn:name":"Hill Town",
    "gn:population":0,
    "gn:timezone":"Africa/Monrovia",
    "iso:country":"LR",
    "wof:name":"Hill Town",
    "wof:placetype":"locality"
},
  "geometry": {"coordinates":[-10.78333,6.61667],"type":"Point"}
}