{
  "type": "Feature",
  "properties": {
    "gn:admin1_code":"10.0",
    "gn:asciiname":"Saso Town",
    "gn:country_code":"LR",
    "gn:dem":89,
    "gn:feature_class":"P",
    "gn:feature_code":"PPL",
    "gn:name":"Saso Town",
    "gn:population":0,
    "gn:timezone":"Africa/Monrovia",
    "iso:country":"LR",
    "name:und_x_variant":[
        "New Sass Town"
    ],
    "wof:name":"Saso Town",
    "wof:placetype":"locality"
},
  "geometry": {"coordinates":[-8.74052,5.11109],"type":"Point"}
}