{
  "type": "Feature",
  "properties": {
    "gn:admin1_code":"12.0",
    "gn:asciiname":"Manivalor",
    "gn:country_code":"LR",
    "gn:dem":15,
    "gn:feature_class":"P",
    "gn:feature_code":"PPL",
    "gn:name":"Manivalor",
    "gn:population":0,
    "gn:timezone":"Africa/Monrovia",
    "iso:country":"LR",
    "name:und_x_variant":[
        "Masuadao"
    ],
    "wof:name":"Manivalor",
    "wof:placetype":"locality"
},
  "geometry": {"coordinates":[-11.13383,6.77785],"type":"Point"}
}