{
  "type": "Feature",
  "properties": {
    "gn:admin1_code":"18.0",
    "gn:asciiname":"Gofabli",
    "gn:country_code":"LR",
    "gn:dem":25,
    "gn:feature_class":"P",
    "gn:feature_code":"PPL",
    "gn:name":"Gofabli",
    "gn:population":0,
    "gn:timezone":"Africa/Monrovia",
    "iso:country":"LR",
    "wof:name":"Gofabli",
    "wof:placetype":"locality"
},
  "geometry": {"coordinates":[-9.61358,5.52881],"type":"Point"}
}