{
  "type": "Feature",
  "properties": {
    "gn:admin1_code":"10.0",
    "gn:asciiname":"Tweh",
    "gn:country_code":"LR",
    "gn:dem":84,
    "gn:feature_class":"P",
    "gn:feature_code":"PPL",
    "gn:name":"Tweh",
    "gn:population":0,
    "gn:timezone":"Africa/Monrovia",
    "iso:country":"LR",
    "wof:name":"Tweh",
    "wof:placetype":"locality"
},
  "geometry": {"coordinates":[-8.91004,5.30256],"type":"Point"}
}