{
  "type": "Feature",
  "properties": {
    "gn:admin1_code":"12.0",
    "gn:asciiname":"Bombor Old Town",
    "gn:country_code":"LR",
    "gn:dem":101,
    "gn:feature_class":"P",
    "gn:feature_code":"PPL",
    "gn:name":"Bombor Old Town",
    "gn:population":0,
    "gn:timezone":"Africa/Monrovia",
    "iso:country":"LR",
    "name:und_x_variant":[
        "Bombahun",
        "Bando",
        "Bomboh",
        "Bombo",
        "Bombor Old Town"
    ],
    "wof:name":"Bombor Old Town",
    "wof:placetype":"locality"
},
  "geometry": {"coordinates":[-11.10083,7.26444],"type":"Point"}
}