{
  "type": "Feature",
  "properties": {
    "gn:admin1_code":"14.0",
    "gn:asciiname":"Jakata",
    "gn:country_code":"LR",
    "gn:dem":71,
    "gn:feature_class":"P",
    "gn:feature_code":"PPL",
    "gn:name":"Jakata",
    "gn:population":0,
    "gn:timezone":"Africa/Monrovia",
    "iso:country":"LR",
    "name:und_x_variant":[
        "Zimgbo",
        "Jakata"
    ],
    "wof:name":"Jakata",
    "wof:placetype":"locality"
},
  "geometry": {"coordinates":[-10.51882,6.51576],"type":"Point"}
}