{
  "type": "Feature",
  "properties": {
    "gn:admin1_code":"1.0",
    "gn:asciiname":"Gbeleta",
    "gn:country_code":"LR",
    "gn:dem":150,
    "gn:feature_class":"P",
    "gn:feature_code":"PPL",
    "gn:name":"Gbeleta",
    "gn:population":0,
    "gn:timezone":"Africa/Monrovia",
    "iso:country":"LR",
    "wof:name":"Gbeleta",
    "wof:placetype":"locality"
},
  "geometry": {"coordinates":[-10.23333,6.91667],"type":"Point"}
}