{
  "type": "Feature",
  "properties": {
    "gn:admin1_code":"20.0",
    "gn:asciiname":"Foya Kamara",
    "gn:cc2":"LR",
    "gn:country_code":"LR",
    "gn:dem":484,
    "gn:feature_class":"P",
    "gn:feature_code":"PPL",
    "gn:name":"Foya Kamara",
    "gn:population":0,
    "gn:timezone":"Africa/Monrovia",
    "iso:country":"LR",
    "name:pol_x_preferred":[
        "Foya"
    ],
    "name:rus_x_preferred":[
        "\u0424\u043e\u0439\u0430"
    ],
    "name:und_x_variant":[
        "Foya Kamala Number 2",
        "Foya Kamara Number Two",
        "Foya Kamara Number 2",
        "Foya Kamara"
    ],
    "wof:name":"Foya Kamara",
    "wof:placetype":"locality"
},
  "geometry": {"coordinates":[-10.20639,8.36028],"type":"Point"}
}