{
  "type": "Feature",
  "properties": {
    "gn:admin1_code":"20.0",
    "gn:asciiname":"Saint Pauls Ville",
    "gn:country_code":"LR",
    "gn:dem":274,
    "gn:feature_class":"P",
    "gn:feature_code":"PPL",
    "gn:name":"Saint Pauls Ville",
    "gn:population":0,
    "gn:timezone":"Africa/Monrovia",
    "iso:country":"LR",
    "name:eng_x_preferred":[
        "Saint Pauls Ville"
    ],
    "name:und_x_variant":[
        "Saint Paulsville"
    ],
    "wof:name":"Saint Pauls Ville",
    "wof:placetype":"locality"
},
  "geometry": {"coordinates":[-9.50102,7.3342],"type":"Point"}
}