{
  "type": "Feature",
  "properties": {
    "gn:admin1_code":"20.0",
    "gn:asciiname":"Taydu",
    "gn:cc2":"LR",
    "gn:country_code":"LR",
    "gn:dem":403,
    "gn:feature_class":"P",
    "gn:feature_code":"PPL",
    "gn:name":"Taydu",
    "gn:population":0,
    "gn:timezone":"Africa/Monrovia",
    "iso:country":"LR",
    "name:und_x_variant":[
        "Kedui",
        "Tedu",
        "Taydu"
    ],
    "wof:name":"Taydu",
    "wof:placetype":"locality"
},
  "geometry": {"coordinates":[-10.29472,8.28861],"type":"Point"}
}