{
  "type": "Feature",
  "properties": {
    "gn:admin1_code":"1.0",
    "gn:asciiname":"Clapwa",
    "gn:country_code":"LR",
    "gn:dem":232,
    "gn:feature_class":"P",
    "gn:feature_code":"PPL",
    "gn:name":"Clapwa",
    "gn:population":0,
    "gn:timezone":"Africa/Monrovia",
    "iso:country":"LR",
    "name:eng_x_preferred":[
        "Clapwa"
    ],
    "name:und_x_variant":[
        "Glepua",
        "Glapua"
    ],
    "wof:name":"Clapwa",
    "wof:placetype":"locality"
},
  "geometry": {"coordinates":[-9.50819,6.6601],"type":"Point"}
}