{
  "type": "Feature",
  "properties": {
    "gn:admin1_code":"22.0",
    "gn:asciiname":"Flehwrokehn",
    "gn:country_code":"LR",
    "gn:dem":214,
    "gn:feature_class":"P",
    "gn:feature_code":"PPL",
    "gn:name":"Flehwrokehn",
    "gn:population":0,
    "gn:timezone":"Africa/Monrovia",
    "iso:country":"LR",
    "name:und_x_variant":[
        "Flareville",
        "Flehwroken",
        "Flehwrokehn"
    ],
    "wof:name":"Flehwrokehn",
    "wof:placetype":"locality"
},
  "geometry": {"coordinates":[-8.01508,5.2641],"type":"Point"}
}