{
  "type": "Feature",
  "properties": {
    "gn:admin1_code":"19.0",
    "gn:asciiname":"Kpelu",
    "gn:country_code":"LR",
    "gn:dem":195,
    "gn:feature_class":"P",
    "gn:feature_code":"PPL",
    "gn:name":"Kpelu",
    "gn:population":0,
    "gn:timezone":"Africa/Monrovia",
    "iso:country":"LR",
    "wof:name":"Kpelu",
    "wof:placetype":"locality"
},
  "geometry": {"coordinates":[-8.0375,5.90778],"type":"Point"}
}