{
  "type": "Feature",
  "properties": {
    "gn:admin1_code":"1.0",
    "gn:asciiname":"Sulongorta",
    "gn:country_code":"LR",
    "gn:dem":237,
    "gn:feature_class":"P",
    "gn:feature_code":"PPL",
    "gn:name":"Sulongorta",
    "gn:population":0,
    "gn:timezone":"Africa/Monrovia",
    "iso:country":"LR",
    "name:eng_x_preferred":[
        "Sulongorta"
    ],
    "name:und_x_variant":[
        "Sulongorta Number One",
        "Sulongorta No. 1"
    ],
    "wof:name":"Sulongorta",
    "wof:placetype":"locality"
},
  "geometry": {"coordinates":[-9.64376,6.85521],"type":"Point"}
}