{
  "type": "Feature",
  "properties": {
    "gn:admin1_code":"10.0",
    "gn:asciiname":"Lexington",
    "gn:country_code":"LR",
    "gn:dem":11,
    "gn:feature_class":"P",
    "gn:feature_code":"PPL",
    "gn:name":"Lexington",
    "gn:population":0,
    "gn:timezone":"Africa/Monrovia",
    "iso:country":"LR",
    "wof:name":"Lexington",
    "wof:placetype":"locality"
},
  "geometry": {"coordinates":[-9.03806,5.04056],"type":"Point"}
}