{
  "type": "Feature",
  "properties": {
    "gn:admin1_code":"10.0",
    "gn:asciiname":"Tennewehn",
    "gn:country_code":"LR",
    "gn:dem":174,
    "gn:feature_class":"P",
    "gn:feature_code":"PPL",
    "gn:name":"Tennewehn",
    "gn:population":0,
    "gn:timezone":"Africa/Monrovia",
    "iso:country":"LR",
    "wof:name":"Tennewehn",
    "wof:placetype":"locality"
},
  "geometry": {"coordinates":[-8.44306,5.65083],"type":"Point"}
}