{
  "type": "Feature",
  "properties": {
    "gn:admin1_code":"15.0",
    "gn:asciiname":"Browns Farm",
    "gn:country_code":"LR",
    "gn:dem":64,
    "gn:feature_class":"P",
    "gn:feature_code":"PPL",
    "gn:name":"Browns Farm",
    "gn:population":0,
    "gn:timezone":"Africa/Monrovia",
    "iso:country":"LR",
    "wof:name":"Browns Farm",
    "wof:placetype":"locality"
},
  "geometry": {"coordinates":[-10.86188,6.73394],"type":"Point"}
}