{
  "type": "Feature",
  "properties": {
    "gn:admin1_code":"14.0",
    "gn:asciiname":"Todi",
    "gn:country_code":"LR",
    "gn:dem":101,
    "gn:feature_class":"P",
    "gn:feature_code":"PPL",
    "gn:name":"Todi",
    "gn:population":0,
    "gn:timezone":"Africa/Monrovia",
    "iso:country":"LR",
    "name:ara_x_preferred":[
        "\u062a\u0648\u062f\u064a"
    ],
    "name:ast_x_preferred":[
        "Todi"
    ],
    "name:azb_x_preferred":[
        "\u062a\u0648\u062f\u06cc"
    ],
    "name:aze_x_preferred":[
        "Todi"
    ],
    "name:bul_x_preferred":[
        "\u0422\u043e\u0434\u0438"
    ],
    "name:cat_x_preferred":[
        "Todi"
    ],
    "name:ceb_x_preferred":[
        "Todi"
    ],
    "name:ces_x_preferred":[
        "Todi"
    ],
    "name:dan_x_preferred":[
        "Todi"
    ],
    "name:deu_x_preferred":[
        "Todi"
    ],
    "name:ell_x_preferred":[
        "\u03a4\u03cc\u03bd\u03c4\u03b9"
    ],
    "name:epo_x_preferred":[
        "Todi"
    ],
    "name:est_x_preferred":[
        "Todi"
    ],
    "name:eus_x_preferred":[
        "Todi"
    ],
    "name:fas_x_preferred":[
        "\u062a\u0648\u062f\u06cc"
    ],
    "name:fin_x_preferred":[
        "Todi"
    ],
    "name:fra_x_preferred":[
        "Todi"
    ],
    "name:heb_x_preferred":[
        "\u05d8\u05d5\u05d3\u05d9"
    ],
    "name:hun_x_preferred":[
        "Todi"
    ],
    "name:hye_x_preferred":[
        "\u054f\u0578\u0564\u056b"
    ],
    "name:ido_x_preferred":[
        "Todi"
    ],
    "name:ind_x_preferred":[
        "Todi"
    ],
    "name:ita_x_preferred":[
        "Todi"
    ],
    "name:jpn_x_preferred":[
        "\u30c8\u30fc\u30c7\u30a3"
    ],
    "name:kaz_x_preferred":[
        "\u0422\u043e\u0434\u0438"
    ],
    "name:lat_x_preferred":[
        "Tuder"
    ],
    "name:lmo_x_preferred":[
        "Todi"
    ],
    "name:ltz_x_preferred":[
        "Todi"
    ],
    "name:msa_x_preferred":[
        "Todi"
    ],
    "name:nap_x_preferred":[
        "Todi"
    ],
    "name:nld_x_preferred":[
        "Todi"
    ],
    "name:nno_x_preferred":[
        "Todi"
    ],
    "name:pan_x_preferred":[
        "\u0a1f\u0a4b\u0a21\u0a40"
    ],
    "name:pms_x_preferred":[
        "Todi"
    ],
    "name:pol_x_preferred":[
        "Todi"
    ],
    "name:por_x_preferred":[
        "Todi"
    ],
    "name:ron_x_preferred":[
        "Todi"
    ],
    "name:rus_x_preferred":[
        "\u0422\u043e\u0434\u0438"
    ],
    "name:scn_x_preferred":[
        "Todi"
    ],
    "name:sco_x_preferred":[
        "Todi"
    ],
    "name:slv_x_preferred":[
        "Todi"
    ],
    "name:spa_x_preferred":[
        "Todi"
    ],
    "name:srd_x_preferred":[
        "Todi"
    ],
    "name:srp_x_preferred":[
        "\u0422\u043e\u0434\u0438"
    ],
    "name:swe_x_preferred":[
        "Todi"
    ],
    "name:tgl_x_preferred":[
        "Todi"
    ],
    "name:tur_x_preferred":[
        "Todi"
    ],
    "name:ukr_x_preferred":[
        "\u0422\u043e\u0434\u0456"
    ],
    "name:uzb_x_preferred":[
        "Todi"
    ],
    "name:vol_x_preferred":[
        "Todi"
    ],
    "name:war_x_preferred":[
        "Todi"
    ],
    "name:zho_x_preferred":[
        "\u6258\u8fea"
    ],
    "wof:name":"Todi",
    "wof:placetype":"locality"
},
  "geometry": {"coordinates":[-10.53333,6.55],"type":"Point"}
}