{
  "type": "Feature",
  "properties": {
    "gn:admin1_code":"14.0",
    "gn:asciiname":"Todi",
    "gn:country_code":"LR",
    "gn:dem":101,
    "gn:feature_class":"P",
    "gn:feature_code":"PPL",
    "gn:name":"Todi",
    "gn:population":0,
    "gn:timezone":"Africa/Monrovia",
    "iso:country":"LR",
    "wof:name":"Todi",
    "wof:placetype":"locality"
},
  "geometry": {"coordinates":[-10.53333,6.55],"type":"Point"}
}