{
  "type": "Feature",
  "properties": {
    "gn:admin1_code":"1.0",
    "gn:asciiname":"Kayata",
    "gn:country_code":"LR",
    "gn:dem":372,
    "gn:feature_class":"P",
    "gn:feature_code":"PPL",
    "gn:name":"Kayata",
    "gn:population":0,
    "gn:timezone":"Africa/Monrovia",
    "iso:country":"LR",
    "name:eng_x_preferred":[
        "Kayata"
    ],
    "wof:name":"Kayata",
    "wof:placetype":"locality"
},
  "geometry": {"coordinates":[-9.54681,7.16304],"type":"Point"}
}