{
  "type": "Feature",
  "properties": {
    "gn:admin1_code":"1.0",
    "gn:asciiname":"Sinyea",
    "gn:country_code":"LR",
    "gn:dem":274,
    "gn:feature_class":"P",
    "gn:feature_code":"PPL",
    "gn:name":"Sinyea",
    "gn:population":0,
    "gn:timezone":"Africa/Monrovia",
    "iso:country":"LR",
    "name:eng_x_preferred":[
        "Sinyea"
    ],
    "name:und_x_variant":[
        "Saini"
    ],
    "wof:name":"Sinyea",
    "wof:placetype":"locality"
},
  "geometry": {"coordinates":[-9.55627,7.05308],"type":"Point"}
}