{
  "type": "Feature",
  "properties": {
    "gn:admin1_code":"9.0",
    "gn:asciiname":"Koiple",
    "gn:cc2":"LR",
    "gn:country_code":"LR",
    "gn:dem":308,
    "gn:feature_class":"P",
    "gn:feature_code":"PPL",
    "gn:name":"Koiple",
    "gn:population":0,
    "gn:timezone":"Africa/Monrovia",
    "iso:country":"LR",
    "name:und_x_variant":[
        "Koyple",
        "Koiple"
    ],
    "wof:name":"Koiple",
    "wof:placetype":"locality"
},
  "geometry": {"coordinates":[-8.56667,6.91667],"type":"Point"}
}