{
  "type": "Feature",
  "properties": {
    "gn:admin1_code":"9.0",
    "gn:asciiname":"Gbeeah",
    "gn:country_code":"LR",
    "gn:dem":401,
    "gn:feature_class":"P",
    "gn:feature_code":"PPL",
    "gn:name":"Gbeeah",
    "gn:population":0,
    "gn:timezone":"Africa/Monrovia",
    "iso:country":"LR",
    "wof:name":"Gbeeah",
    "wof:placetype":"locality"
},
  "geometry": {"coordinates":[-8.75861,7.17889],"type":"Point"}
}