{
  "type": "Feature",
  "properties": {
    "gn:admin1_code":"17.0",
    "gn:asciiname":"Padmore Farm",
    "gn:country_code":"LR",
    "gn:dem":147,
    "gn:feature_class":"P",
    "gn:feature_code":"PPL",
    "gn:name":"Padmore Farm",
    "gn:population":0,
    "gn:timezone":"Africa/Monrovia",
    "iso:country":"LR",
    "name:eng_x_preferred":[
        "Padmore Farm"
    ],
    "wof:name":"Padmore Farm",
    "wof:placetype":"locality"
},
  "geometry": {"coordinates":[-10.35568,6.72292],"type":"Point"}
}