{
  "type": "Feature",
  "properties": {
    "gn:admin1_code":"11.0",
    "gn:asciiname":"Nah",
    "gn:country_code":"LR",
    "gn:dem":129,
    "gn:feature_class":"P",
    "gn:feature_code":"PPL",
    "gn:name":"Nah",
    "gn:population":0,
    "gn:timezone":"Africa/Monrovia",
    "iso:country":"LR",
    "name:spa_x_preferred":[
        "Nah"
    ],
    "name:und_x_variant":[
        "Nabli"
    ],
    "wof:name":"Nah",
    "wof:placetype":"locality"
},
  "geometry": {"coordinates":[-9.66937,6.38183],"type":"Point"}
}