{
  "type": "Feature",
  "properties": {
    "gn:admin1_code":"9.0",
    "gn:asciiname":"Tifi Town",
    "gn:cc2":"LR",
    "gn:country_code":"LR",
    "gn:dem":236,
    "gn:feature_class":"P",
    "gn:feature_code":"PPL",
    "gn:name":"Tifi Town",
    "gn:population":0,
    "gn:timezone":"Africa/Monrovia",
    "iso:country":"LR",
    "name:und_x_variant":[
        "Tifi",
        "Tifi Town"
    ],
    "wof:name":"Tifi Town",
    "wof:placetype":"locality"
},
  "geometry": {"coordinates":[-9.02889,6.62472],"type":"Point"}
}