{
  "type": "Feature",
  "properties": {
    "gn:admin1_code":"19.0",
    "gn:asciiname":"Kamatu",
    "gn:country_code":"LR",
    "gn:dem":171,
    "gn:feature_class":"P",
    "gn:feature_code":"PPL",
    "gn:name":"Kamatu",
    "gn:population":0,
    "gn:timezone":"Africa/Monrovia",
    "iso:country":"LR",
    "name:und_x_variant":[
        "Sawe",
        "Kamatu"
    ],
    "wof:name":"Kamatu",
    "wof:placetype":"locality"
},
  "geometry": {"coordinates":[-7.62664,5.67218],"type":"Point"}
}