{
  "type": "Feature",
  "properties": {
    "gn:admin1_code":"19.0",
    "gn:asciiname":"Kwla Town",
    "gn:country_code":"LR",
    "gn:dem":206,
    "gn:feature_class":"P",
    "gn:feature_code":"PPL",
    "gn:name":"Kwla Town",
    "gn:population":0,
    "gn:timezone":"Africa/Monrovia",
    "iso:country":"LR",
    "name:und_x_variant":[
        "Kra",
        "Kwla Town"
    ],
    "wof:name":"Kwla Town",
    "wof:placetype":"locality"
},
  "geometry": {"coordinates":[-8.09621,6.01592],"type":"Point"}
}