{
  "type": "Feature",
  "properties": {
    "gn:admin1_code":"14.0",
    "gn:asciiname":"Virginia",
    "gn:country_code":"LR",
    "gn:dem":27,
    "gn:feature_class":"P",
    "gn:feature_code":"PPL",
    "gn:name":"Virginia",
    "gn:population":0,
    "gn:timezone":"Africa/Monrovia",
    "iso:country":"LR",
    "wof:name":"Virginia",
    "wof:placetype":"locality"
},
  "geometry": {"coordinates":[-10.79895,6.48704],"type":"Point"}
}