{
  "type": "Feature",
  "properties": {
    "gn:admin1_code":"14.0",
    "gn:asciiname":"White Plains",
    "gn:country_code":"LR",
    "gn:dem":20,
    "gn:feature_class":"P",
    "gn:feature_code":"PPL",
    "gn:name":"White Plains",
    "gn:population":0,
    "gn:timezone":"Africa/Monrovia",
    "iso:country":"LR",
    "wof:name":"White Plains",
    "wof:placetype":"locality"
},
  "geometry": {"coordinates":[-10.66667,6.45],"type":"Point"}
}