{
  "type": "Feature",
  "properties": {
    "gn:admin1_code":"14.0",
    "gn:asciiname":"White Plains",
    "gn:country_code":"LR",
    "gn:dem":20,
    "gn:feature_class":"P",
    "gn:feature_code":"PPL",
    "gn:name":"White Plains",
    "gn:population":0,
    "gn:timezone":"Africa/Monrovia",
    "iso:country":"LR",
    "name:arg_x_preferred":[
        "White Plains"
    ],
    "name:cat_x_preferred":[
        "White Plains"
    ],
    "name:ceb_x_preferred":[
        "White Plains"
    ],
    "name:ces_x_preferred":[
        "White Plains"
    ],
    "name:deu_x_preferred":[
        "White Plains"
    ],
    "name:fra_x_preferred":[
        "White Plains"
    ],
    "name:ita_x_preferred":[
        "White Plains"
    ],
    "name:jpn_x_preferred":[
        "\u30db\u30ef\u30a4\u30c8\u30fb\u30d7\u30ec\u30a4\u30f3\u30ba"
    ],
    "name:kor_x_preferred":[
        "\ud654\uc774\ud2b8\ud50c\ub808\uc778\uc2a4"
    ],
    "name:nld_x_preferred":[
        "White Plains"
    ],
    "name:nor_x_preferred":[
        "White Plains"
    ],
    "name:pol_x_preferred":[
        "White Plains"
    ],
    "name:por_x_preferred":[
        "White Plains"
    ],
    "name:slk_x_preferred":[
        "White Plains"
    ],
    "name:spa_x_preferred":[
        "White Plains"
    ],
    "name:srp_x_preferred":[
        "\u0412\u0430\u0458\u0442 \u041f\u043b\u0435\u0458\u043d\u0441"
    ],
    "name:swe_x_preferred":[
        "White Plains"
    ],
    "name:urd_x_preferred":[
        "\u0648\u0627\u0626\u0679 \u067e\u0644\u06cc\u0646\u0632"
    ],
    "name:vol_x_preferred":[
        "White Plains"
    ],
    "name:zho_x_preferred":[
        "\u6000\u7279\u666e\u83b1\u6069\u65af"
    ],
    "wof:name":"White Plains",
    "wof:placetype":"locality"
},
  "geometry": {"coordinates":[-10.66667,6.45],"type":"Point"}
}