{
  "type": "Feature",
  "properties": {
    "gn:admin1_code":"17.0",
    "gn:asciiname":"Kasavam",
    "gn:country_code":"LR",
    "gn:dem":110,
    "gn:feature_class":"P",
    "gn:feature_code":"PPL",
    "gn:name":"Kasavam",
    "gn:population":0,
    "gn:timezone":"Africa/Monrovia",
    "iso:country":"LR",
    "name:eng_x_preferred":[
        "Kasavam"
    ],
    "wof:name":"Kasavam",
    "wof:placetype":"locality"
},
  "geometry": {"coordinates":[-10.35287,6.64481],"type":"Point"}
}