{
  "type": "Feature",
  "properties": {
    "gn:admin1_code":"16.0",
    "gn:asciiname":"Funkpo",
    "gn:country_code":"LR",
    "gn:dem":6,
    "gn:feature_class":"P",
    "gn:feature_code":"PPL",
    "gn:name":"Funkpo",
    "gn:population":0,
    "gn:timezone":"Africa/Monrovia",
    "iso:country":"LR",
    "wof:name":"Funkpo",
    "wof:placetype":"locality"
},
  "geometry": {"coordinates":[-8.2827,4.62879],"type":"Point"}
}