{
  "type": "Feature",
  "properties": {
    "gn:admin1_code":"11.0",
    "gn:asciiname":"Fabli",
    "gn:country_code":"LR",
    "gn:dem":105,
    "gn:feature_class":"P",
    "gn:feature_code":"PPL",
    "gn:name":"Fabli",
    "gn:population":0,
    "gn:timezone":"Africa/Monrovia",
    "iso:country":"LR",
    "wof:name":"Fabli",
    "wof:placetype":"locality"
},
  "geometry": {"coordinates":[-9.85,6.08333],"type":"Point"}
}