{
  "type": "Feature",
  "properties": {
    "gn:admin1_code":"19.0",
    "gn:asciiname":"Solobli",
    "gn:country_code":"LR",
    "gn:dem":294,
    "gn:feature_class":"P",
    "gn:feature_code":"PPL",
    "gn:name":"Solobli",
    "gn:population":0,
    "gn:timezone":"Africa/Monrovia",
    "iso:country":"LR",
    "wof:name":"Solobli",
    "wof:placetype":"locality"
},
  "geometry": {"coordinates":[-8.37936,6.30067],"type":"Point"}
}