{
  "type": "Feature",
  "properties": {
    "gn:admin1_code":"16.0",
    "gn:asciiname":"Wilsonville",
    "gn:cc2":"LR",
    "gn:country_code":"LR",
    "gn:dem":31,
    "gn:feature_class":"P",
    "gn:feature_code":"PPL",
    "gn:name":"Wilsonville",
    "gn:population":0,
    "gn:timezone":"Africa/Monrovia",
    "iso:country":"LR",
    "name:und_x_variant":[
        "Kebeke",
        "Wilsonville (1)",
        "Nemiah",
        "Wilsonville"
    ],
    "wof:name":"Wilsonville",
    "wof:placetype":"locality"
},
  "geometry": {"coordinates":[-7.89361,4.54444],"type":"Point"}
}