{
  "type": "Feature",
  "properties": {
    "gn:admin1_code":"16.0",
    "gn:asciiname":"Wilsonville",
    "gn:cc2":"LR",
    "gn:country_code":"LR",
    "gn:dem":31,
    "gn:feature_class":"P",
    "gn:feature_code":"PPL",
    "gn:name":"Wilsonville",
    "gn:population":0,
    "gn:timezone":"Africa/Monrovia",
    "iso:country":"LR",
    "name:ara_x_preferred":[
        "\u0648\u064a\u0644\u0633\u0648\u0646\u0641\u064a\u0644"
    ],
    "name:cat_x_preferred":[
        "Wilsonville"
    ],
    "name:ceb_x_preferred":[
        "Wilsonville"
    ],
    "name:deu_x_preferred":[
        "Wilsonville"
    ],
    "name:est_x_preferred":[
        "Wilsonville"
    ],
    "name:fra_x_preferred":[
        "Wilsonville"
    ],
    "name:hun_x_preferred":[
        "Wilsonville"
    ],
    "name:ita_x_preferred":[
        "Wilsonville"
    ],
    "name:nld_x_preferred":[
        "Wilsonville"
    ],
    "name:pol_x_preferred":[
        "Wilsonville"
    ],
    "name:por_x_preferred":[
        "Wilsonville"
    ],
    "name:srp_x_preferred":[
        "\u0412\u0438\u043b\u0441\u043e\u043d\u0432\u0438\u043b"
    ],
    "name:und_x_variant":[
        "Kebeke",
        "Wilsonville (1)",
        "Nemiah",
        "Wilsonville"
    ],
    "name:vol_x_preferred":[
        "Wilsonville"
    ],
    "wof:name":"Wilsonville",
    "wof:placetype":"locality"
},
  "geometry": {"coordinates":[-7.89361,4.54444],"type":"Point"}
}