{
  "type": "Feature",
  "properties": {
    "gn:admin1_code":"11.0",
    "gn:asciiname":"Gadwebli",
    "gn:country_code":"LR",
    "gn:dem":48,
    "gn:feature_class":"P",
    "gn:feature_code":"PPL",
    "gn:name":"Gadwebli",
    "gn:population":0,
    "gn:timezone":"Africa/Monrovia",
    "iso:country":"LR",
    "wof:name":"Gadwebli",
    "wof:placetype":"locality"
},
  "geometry": {"coordinates":[-10.23333,6.16667],"type":"Point"}
}