{
  "type": "Feature",
  "properties": {
    "gn:admin1_code":"10.0",
    "gn:asciiname":"Jolloh Camp",
    "gn:country_code":"LR",
    "gn:dem":121,
    "gn:feature_class":"P",
    "gn:feature_code":"PPL",
    "gn:name":"Jolloh Camp",
    "gn:population":0,
    "gn:timezone":"Africa/Monrovia",
    "iso:country":"LR",
    "wof:name":"Jolloh Camp",
    "wof:placetype":"locality"
},
  "geometry": {"coordinates":[-8.59701,5.09926],"type":"Point"}
}