{
  "type": "Feature",
  "properties": {
    "gn:admin1_code":"1.0",
    "gn:asciiname":"Kolonta",
    "gn:country_code":"LR",
    "gn:dem":356,
    "gn:feature_class":"P",
    "gn:feature_code":"PPL",
    "gn:name":"Kolonta",
    "gn:population":0,
    "gn:timezone":"Africa/Monrovia",
    "iso:country":"LR",
    "name:eng_x_preferred":[
        "Kolonta"
    ],
    "name:und_x_variant":[
        "Konda"
    ],
    "wof:name":"Kolonta",
    "wof:placetype":"locality"
},
  "geometry": {"coordinates":[-9.39026,7.37005],"type":"Point"}
}