{
  "type": "Feature",
  "properties": {
    "gn:admin1_code":"1.0",
    "gn:asciiname":"Dininta",
    "gn:country_code":"LR",
    "gn:dem":207,
    "gn:feature_class":"P",
    "gn:feature_code":"PPL",
    "gn:name":"Dininta",
    "gn:population":0,
    "gn:timezone":"Africa/Monrovia",
    "iso:country":"LR",
    "name:eng_x_preferred":[
        "Dininta"
    ],
    "wof:name":"Dininta",
    "wof:placetype":"locality"
},
  "geometry": {"coordinates":[-9.61481,6.78703],"type":"Point"}
}