{
  "type": "Feature",
  "properties": {
    "gn:admin1_code":"19.0",
    "gn:asciiname":"Garglor",
    "gn:country_code":"LR",
    "gn:dem":191,
    "gn:feature_class":"P",
    "gn:feature_code":"PPL",
    "gn:name":"Garglor",
    "gn:population":0,
    "gn:timezone":"Africa/Monrovia",
    "iso:country":"LR",
    "name:und_x_variant":[
        "Garezohn"
    ],
    "wof:name":"Garglor",
    "wof:placetype":"locality"
},
  "geometry": {"coordinates":[-7.76246,5.93442],"type":"Point"}
}