{
  "type": "Feature",
  "properties": {
    "iso:country":"LR",
    "name:bel_x_preferred":[
        "\u0413\u043e\u0440\u0430\u0434 \u0413\u0430\u043d\u0442\u0430"
    ],
    "name:deu_x_preferred":[
        "Ganta"
    ],
    "name:eng_x_preferred":[
        "Ganta"
    ],
    "name:fra_x_preferred":[
        "Ganta"
    ],
    "name:ita_x_preferred":[
        "Ganta"
    ],
    "name:kat_x_preferred":[
        "\u10d2\u10d0\u10dc\u10e2\u10d0"
    ],
    "name:lit_x_preferred":[
        "Ganta"
    ],
    "name:nld_x_preferred":[
        "Ganta"
    ],
    "name:pol_x_preferred":[
        "Ganta"
    ],
    "name:rus_x_preferred":[
        "\u0413\u0430\u043d\u0442\u0430"
    ],
    "name:swe_x_preferred":[
        "Ganta"
    ],
    "name:und_x_variant":[
        "Gahnpa"
    ],
    "name:urd_x_preferred":[
        "\u06af\u0627\u0646\u062a\u0627"
    ],
    "name:zho_x_preferred":[
        "\u7518\u5854"
    ],
    "qs:gn_country":"LR",
    "qs:gn_fcode":"PPL",
    "qs:gn_pop":0,
    "qs:name":"Ganta",
    "qs:name_adm0":"Liberia",
    "qs:name_adm1":"Nimba",
    "qs:photos":56,
    "qs:photos_1k":11,
    "qs:photos_9k":1,
    "qs:photos_9r":2,
    "qs:photos_all":56,
    "qs:photos_sr":2,
    "qs:placetype":"Town",
    "qs:pop_sr":"0",
    "qs:woe_adm0":23424876,
    "wd:wordcount":473,
    "wof:name":"Ganta",
    "wof:placetype":"locality"
},
  "geometry": {"coordinates":[-8.98444,7.235],"type":"Point"}
}