{
  "type": "Feature",
  "properties": {
    "gn:admin1_code":"1.0",
    "gn:asciiname":"Smart's Town",
    "gn:country_code":"LR",
    "gn:dem":249,
    "gn:feature_class":"P",
    "gn:feature_code":"PPL",
    "gn:name":"Smart\u2019s Town",
    "gn:population":0,
    "gn:timezone":"Africa/Monrovia",
    "iso:country":"LR",
    "name:eng_x_preferred":[
        "Smart\u2019s Town"
    ],
    "wof:name":"Smart's Town",
    "wof:placetype":"locality"
},
  "geometry": {"coordinates":[-9.18002,6.8987],"type":"Point"}
}