{
  "type": "Feature",
  "properties": {
    "gn:admin1_code":"11.0",
    "gn:asciiname":"Gbolijiabli",
    "gn:country_code":"LR",
    "gn:dem":18,
    "gn:feature_class":"P",
    "gn:feature_code":"PPL",
    "gn:name":"Gbolijiabli",
    "gn:population":0,
    "gn:timezone":"Africa/Monrovia",
    "iso:country":"LR",
    "wof:name":"Gbolijiabli",
    "wof:placetype":"locality"
},
  "geometry": {"coordinates":[-9.86667,5.88333],"type":"Point"}
}