{
  "type": "Feature",
  "properties": {
    "gn:admin1_code":"1.0",
    "gn:asciiname":"Giemita",
    "gn:country_code":"LR",
    "gn:dem":251,
    "gn:feature_class":"P",
    "gn:feature_code":"PPL",
    "gn:name":"Giemita",
    "gn:population":0,
    "gn:timezone":"Africa/Monrovia",
    "iso:country":"LR",
    "name:eng_x_preferred":[
        "Giemita"
    ],
    "wof:name":"Giemita",
    "wof:placetype":"locality"
},
  "geometry": {"coordinates":[-9.16694,6.86122],"type":"Point"}
}