{
  "type": "Feature",
  "properties": {
    "gn:admin1_code":"18.0",
    "gn:asciiname":"Gorzohn",
    "gn:country_code":"LR",
    "gn:dem":66,
    "gn:feature_class":"P",
    "gn:feature_code":"PPL",
    "gn:name":"Gorzohn",
    "gn:population":0,
    "gn:timezone":"Africa/Monrovia",
    "iso:country":"LR",
    "wof:name":"Gorzohn",
    "wof:placetype":"locality"
},
  "geometry": {"coordinates":[-9.57424,5.6543],"type":"Point"}
}