{
  "type": "Feature",
  "properties": {
    "gn:admin1_code":"1.0",
    "gn:asciiname":"Gehta",
    "gn:country_code":"LR",
    "gn:dem":312,
    "gn:feature_class":"P",
    "gn:feature_code":"PPL",
    "gn:name":"Gehta",
    "gn:population":0,
    "gn:timezone":"Africa/Monrovia",
    "iso:country":"LR",
    "name:eng_x_preferred":[
        "Gehta"
    ],
    "wof:name":"Gehta",
    "wof:placetype":"locality"
},
  "geometry": {"coordinates":[-9.44621,7.17479],"type":"Point"}
}