{
  "type": "Feature",
  "properties": {
    "gn:admin1_code":"15.0",
    "gn:asciiname":"Jawajeh",
    "gn:country_code":"LR",
    "gn:dem":81,
    "gn:feature_class":"P",
    "gn:feature_code":"PPL",
    "gn:name":"Jawajeh",
    "gn:population":0,
    "gn:timezone":"Africa/Monrovia",
    "iso:country":"LR",
    "wof:name":"Jawajeh",
    "wof:placetype":"locality"
},
  "geometry": {"coordinates":[-10.62053,6.71665],"type":"Point"}
}