{
  "type": "Feature",
  "properties": {
    "gn:admin1_code":"20.0",
    "gn:asciiname":"Koniadu Number One",
    "gn:cc2":"LR",
    "gn:country_code":"LR",
    "gn:dem":530,
    "gn:feature_class":"P",
    "gn:feature_code":"PPL",
    "gn:name":"Koniadu Number One",
    "gn:population":0,
    "gn:timezone":"Africa/Monrovia",
    "iso:country":"LR",
    "name:und_x_variant":[
        "Koniadu Number 1",
        "Koniadu Number One"
    ],
    "wof:name":"Koniadu Number One",
    "wof:placetype":"locality"
},
  "geometry": {"coordinates":[-10.21667,8.26667],"type":"Point"}
}