{
  "type": "Feature",
  "properties": {
    "gn:admin1_code":"21.0",
    "gn:asciiname":"Gbarma A",
    "gn:country_code":"LR",
    "gn:dem":106,
    "gn:feature_class":"P",
    "gn:feature_code":"PPL",
    "gn:name":"Gbarma A",
    "gn:population":0,
    "gn:timezone":"Africa/Monrovia",
    "iso:country":"LR",
    "name:und_x_variant":[
        "Bahama",
        "Gbarhama",
        "Gbama",
        "Gbaama",
        "Gbarma",
        "Gbarma A"
    ],
    "wof:name":"Gbarma A",
    "wof:placetype":"locality"
},
  "geometry": {"coordinates":[-10.78875,6.99543],"type":"Point"}
}