{
  "type": "Feature",
  "properties": {
    "gn:admin1_code":"1.0",
    "gn:asciiname":"Grebo Town",
    "gn:country_code":"LR",
    "gn:dem":190,
    "gn:feature_class":"P",
    "gn:feature_code":"PPL",
    "gn:name":"Grebo Town",
    "gn:population":0,
    "gn:timezone":"Africa/Monrovia",
    "iso:country":"LR",
    "name:und_x_variant":[
        "Glebo",
        "Grebo Town",
        "Gebo Town"
    ],
    "wof:name":"Grebo Town",
    "wof:placetype":"locality"
},
  "geometry": {"coordinates":[-9.50635,6.51305],"type":"Point"}
}