{
  "type": "Feature",
  "properties": {
    "gn:admin1_code":"20.0",
    "gn:asciiname":"Kenyatahun",
    "gn:country_code":"LR",
    "gn:dem":515,
    "gn:feature_class":"P",
    "gn:feature_code":"PPL",
    "gn:name":"Kenyatahun",
    "gn:population":0,
    "gn:timezone":"Africa/Monrovia",
    "iso:country":"LR",
    "wof:name":"Kenyatahun",
    "wof:placetype":"locality"
},
  "geometry": {"coordinates":[-10.21806,8.16417],"type":"Point"}
}