{
  "type": "Feature",
  "properties": {
    "gn:admin1_code":"11.0",
    "gn:asciiname":"Baryou-gar Nam Village",
    "gn:country_code":"LR",
    "gn:dem":86,
    "gn:feature_class":"P",
    "gn:feature_code":"PPL",
    "gn:name":"Baryou-gar Nam Village",
    "gn:population":0,
    "gn:timezone":"Africa/Monrovia",
    "iso:country":"LR",
    "wof:name":"Baryou-gar Nam Village",
    "wof:placetype":"locality"
},
  "geometry": {"coordinates":[-9.9869,6.13501],"type":"Point"}
}