{
  "type": "Feature",
  "properties": {
    "gn:admin1_code":"20.0",
    "gn:asciiname":"Gabuzu",
    "gn:country_code":"LR",
    "gn:dem":520,
    "gn:feature_class":"P",
    "gn:feature_code":"PPL",
    "gn:name":"Gabuzu",
    "gn:population":0,
    "gn:timezone":"Africa/Monrovia",
    "iso:country":"LR",
    "wof:name":"Gabuzu",
    "wof:placetype":"locality"
},
  "geometry": {"coordinates":[-9.62278,8.33806],"type":"Point"}
}