{
  "type": "Feature",
  "properties": {
    "gn:admin1_code":"10.0",
    "gn:asciiname":"Nyanneon",
    "gn:country_code":"LR",
    "gn:dem":88,
    "gn:feature_class":"P",
    "gn:feature_code":"PPL",
    "gn:name":"Nyanneon",
    "gn:population":0,
    "gn:timezone":"Africa/Monrovia",
    "iso:country":"LR",
    "wof:name":"Nyanneon",
    "wof:placetype":"locality"
},
  "geometry": {"coordinates":[-9.03639,5.23694],"type":"Point"}
}