{
  "type": "Feature",
  "properties": {
    "gn:admin1_code":"20.0",
    "gn:asciiname":"Manguasu",
    "gn:country_code":"LR",
    "gn:dem":470,
    "gn:feature_class":"P",
    "gn:feature_code":"PPL",
    "gn:name":"Manguasu",
    "gn:population":0,
    "gn:timezone":"Africa/Monrovia",
    "iso:country":"LR",
    "wof:name":"Manguasu",
    "wof:placetype":"locality"
},
  "geometry": {"coordinates":[-10.09444,8.1475],"type":"Point"}
}