{
  "type": "Feature",
  "properties": {
    "gn:admin1_code":"10.0",
    "gn:asciiname":"Murraysville Township",
    "gn:country_code":"LR",
    "gn:dem":18,
    "gn:feature_class":"P",
    "gn:feature_code":"PPL",
    "gn:name":"Murraysville Township",
    "gn:population":0,
    "gn:timezone":"Africa/Monrovia",
    "iso:country":"LR",
    "wof:name":"Murraysville Township",
    "wof:placetype":"locality"
},
  "geometry": {"coordinates":[-9.06333,5.04667],"type":"Point"}
}