{
  "type": "Feature",
  "properties": {
    "gn:admin1_code":"10.0",
    "gn:asciiname":"Camoko",
    "gn:country_code":"LR",
    "gn:dem":166,
    "gn:feature_class":"P",
    "gn:feature_code":"PPL",
    "gn:name":"Camoko",
    "gn:population":0,
    "gn:timezone":"Africa/Monrovia",
    "iso:country":"LR",
    "wof:name":"Camoko",
    "wof:placetype":"locality"
},
  "geometry": {"coordinates":[-8.55968,5.32056],"type":"Point"}
}