{
  "type": "Feature",
  "properties": {
    "gn:admin1_code":"19.0",
    "gn:asciiname":"Tarley Nayou",
    "gn:country_code":"LR",
    "gn:dem":205,
    "gn:feature_class":"P",
    "gn:feature_code":"PPL",
    "gn:name":"Tarley Nayou",
    "gn:population":0,
    "gn:timezone":"Africa/Monrovia",
    "iso:country":"LR",
    "wof:name":"Tarley Nayou",
    "wof:placetype":"locality"
},
  "geometry": {"coordinates":[-7.79304,5.89836],"type":"Point"}
}