{
  "type": "Feature",
  "properties": {
    "gn:admin1_code":"20.0",
    "gn:asciiname":"Smith Camp",
    "gn:country_code":"LR",
    "gn:dem":139,
    "gn:feature_class":"P",
    "gn:feature_code":"PPL",
    "gn:name":"Smith Camp",
    "gn:population":0,
    "gn:timezone":"Africa/Monrovia",
    "iso:country":"LR",
    "wof:name":"Smith Camp",
    "wof:placetype":"locality"
},
  "geometry": {"coordinates":[-10.63722,7.20861],"type":"Point"}
}