{
  "type": "Feature",
  "properties": {
    "gn:admin1_code":"17.0",
    "gn:asciiname":"Bian",
    "gn:country_code":"LR",
    "gn:dem":17,
    "gn:feature_class":"P",
    "gn:feature_code":"PPL",
    "gn:name":"Bian",
    "gn:population":0,
    "gn:timezone":"Africa/Monrovia",
    "iso:country":"LR",
    "name:ceb_x_preferred":[
        "Bian"
    ],
    "name:deu_x_preferred":[
        "Bian"
    ],
    "name:fra_x_preferred":[
        "Bian"
    ],
    "name:nor_x_preferred":[
        "Bian"
    ],
    "name:rus_x_preferred":[
        "\u0411\u044f\u043d\u044c"
    ],
    "name:swe_x_preferred":[
        "Bian"
    ],
    "name:und_x_variant":[
        "Gape Tu",
        "Gbien",
        "Gbliniueh"
    ],
    "wof:name":"Bian",
    "wof:placetype":"locality"
},
  "geometry": {"coordinates":[-10.62056,6.33472],"type":"Point"}
}