{
  "type": "Feature",
  "properties": {
    "gn:admin1_code":"20.0",
    "gn:asciiname":"Tekpelembu",
    "gn:country_code":"LR",
    "gn:dem":531,
    "gn:feature_class":"P",
    "gn:feature_code":"PPL",
    "gn:name":"Tekpelembu",
    "gn:population":0,
    "gn:timezone":"Africa/Monrovia",
    "iso:country":"LR",
    "wof:name":"Tekpelembu",
    "wof:placetype":"locality"
},
  "geometry": {"coordinates":[-9.98972,8.44194],"type":"Point"}
}