{
  "type": "Feature",
  "properties": {
    "gn:admin1_code":"20.0",
    "gn:asciiname":"Wuomai",
    "gn:cc2":"LR",
    "gn:country_code":"LR",
    "gn:dem":355,
    "gn:feature_class":"P",
    "gn:feature_code":"PPL",
    "gn:name":"Wuomai",
    "gn:population":0,
    "gn:timezone":"Africa/Monrovia",
    "iso:country":"LR",
    "name:und_x_variant":[
        "Womai",
        "Wuoami",
        "Wuomai"
    ],
    "wof:name":"Wuomai",
    "wof:placetype":"locality"
},
  "geometry": {"coordinates":[-9.63556,7.76944],"type":"Point"}
}