{
  "type": "Feature",
  "properties": {
    "gn:admin1_code":"10.0",
    "gn:asciiname":"King Williams Town",
    "gn:country_code":"LR",
    "gn:dem":14,
    "gn:feature_class":"P",
    "gn:feature_code":"PPL",
    "gn:name":"King Williams Town",
    "gn:population":0,
    "gn:timezone":"Africa/Monrovia",
    "iso:country":"LR",
    "name:und_x_variant":[
        "King Willis",
        "King Williams Town"
    ],
    "wof:name":"King Williams Town",
    "wof:placetype":"locality"
},
  "geometry": {"coordinates":[-8.71954,4.82065],"type":"Point"}
}