{
  "type": "Feature",
  "properties": {
    "gn:admin1_code":"15.0",
    "gn:asciiname":"Jawajei",
    "gn:cc2":"LR",
    "gn:country_code":"LR",
    "gn:dem":41,
    "gn:feature_class":"P",
    "gn:feature_code":"PPL",
    "gn:name":"Jawajei",
    "gn:population":0,
    "gn:timezone":"Africa/Monrovia",
    "iso:country":"LR",
    "name:und_x_variant":[
        "Towajei",
        "Jawajei"
    ],
    "wof:name":"Jawajei",
    "wof:placetype":"locality"
},
  "geometry": {"coordinates":[-10.8875,6.73278],"type":"Point"}
}