{
  "type": "Feature",
  "properties": {
    "gn:admin1_code":"11.0",
    "gn:asciiname":"Ganbli",
    "gn:country_code":"LR",
    "gn:dem":146,
    "gn:feature_class":"P",
    "gn:feature_code":"PPL",
    "gn:name":"Ganbli",
    "gn:population":0,
    "gn:timezone":"Africa/Monrovia",
    "iso:country":"LR",
    "wof:name":"Ganbli",
    "wof:placetype":"locality"
},
  "geometry": {"coordinates":[-9.75,6.21667],"type":"Point"}
}