{
  "type": "Feature",
  "properties": {
    "gn:admin1_code":"11.0",
    "gn:asciiname":"Bowgbawai",
    "gn:country_code":"LR",
    "gn:dem":196,
    "gn:feature_class":"P",
    "gn:feature_code":"PPL",
    "gn:name":"Bowgbawai",
    "gn:population":0,
    "gn:timezone":"Africa/Monrovia",
    "iso:country":"LR",
    "wof:name":"Bowgbawai",
    "wof:placetype":"locality"
},
  "geometry": {"coordinates":[-9.66237,6.56114],"type":"Point"}
}