{
  "type": "Feature",
  "properties": {
    "gn:admin1_code":"18.0",
    "gn:asciiname":"Johnson Sayubli",
    "gn:country_code":"LR",
    "gn:dem":165,
    "gn:feature_class":"P",
    "gn:feature_code":"PPL",
    "gn:name":"Johnson Sayubli",
    "gn:population":0,
    "gn:timezone":"Africa/Monrovia",
    "iso:country":"LR",
    "name:und_x_variant":[
        "Sayubli",
        "Seubli",
        "Johnson Sayubli"
    ],
    "wof:name":"Johnson Sayubli",
    "wof:placetype":"locality"
},
  "geometry": {"coordinates":[-9.55831,6.04561],"type":"Point"}
}