{
  "type": "Feature",
  "properties": {
    "gn:admin1_code":"11.0",
    "gn:asciiname":"Seven Camp",
    "gn:country_code":"LR",
    "gn:dem":58,
    "gn:feature_class":"P",
    "gn:feature_code":"PPL",
    "gn:name":"Seven Camp",
    "gn:population":0,
    "gn:timezone":"Africa/Monrovia",
    "iso:country":"LR",
    "wof:name":"Seven Camp",
    "wof:placetype":"locality"
},
  "geometry": {"coordinates":[-9.80409,6.02511],"type":"Point"}
}