{
  "type": "Feature",
  "properties": {
    "gn:admin1_code":"15.0",
    "gn:asciiname":"Lakanda",
    "gn:country_code":"LR",
    "gn:dem":9,
    "gn:feature_class":"P",
    "gn:feature_code":"PPL",
    "gn:name":"Lakanda",
    "gn:population":0,
    "gn:timezone":"Africa/Monrovia",
    "iso:country":"LR",
    "wof:name":"Lakanda",
    "wof:placetype":"locality"
},
  "geometry": {"coordinates":[-11.01737,6.58771],"type":"Point"}
}