{
  "type": "Feature",
  "properties": {
    "gn:admin1_code":"9.0",
    "gn:asciiname":"Bonla",
    "gn:cc2":"LR",
    "gn:country_code":"LR",
    "gn:dem":424,
    "gn:feature_class":"P",
    "gn:feature_code":"PPL",
    "gn:name":"Bonla",
    "gn:population":0,
    "gn:timezone":"Africa/Monrovia",
    "iso:country":"LR",
    "name:und_x_variant":[
        "Bona",
        "Bonla"
    ],
    "wof:name":"Bonla",
    "wof:placetype":"locality"
},
  "geometry": {"coordinates":[-8.67444,7.56889],"type":"Point"}
}