{
  "type": "Feature",
  "properties": {
    "gn:admin1_code":"1.0",
    "gn:asciiname":"Selenta",
    "gn:country_code":"LR",
    "gn:dem":267,
    "gn:feature_class":"P",
    "gn:feature_code":"PPL",
    "gn:name":"Selenta",
    "gn:population":0,
    "gn:timezone":"Africa/Monrovia",
    "iso:country":"LR",
    "name:eng_x_preferred":[
        "Selenta"
    ],
    "wof:name":"Selenta",
    "wof:placetype":"locality"
},
  "geometry": {"coordinates":[-9.18912,7.06118],"type":"Point"}
}