{
  "type": "Feature",
  "properties": {
    "gn:admin1_code":"12.0",
    "gn:asciiname":"Gohn",
    "gn:country_code":"LR",
    "gn:dem":26,
    "gn:feature_class":"P",
    "gn:feature_code":"PPL",
    "gn:name":"Gohn",
    "gn:population":0,
    "gn:timezone":"Africa/Monrovia",
    "iso:country":"LR",
    "name:und_x_variant":[
        "Gon",
        "Gong",
        "Gohn"
    ],
    "wof:name":"Gohn",
    "wof:placetype":"locality"
},
  "geometry": {"coordinates":[-11.10173,6.84318],"type":"Point"}
}