{
  "type": "Feature",
  "properties": {
    "gn:admin1_code":"19.0",
    "gn:asciiname":"Slobali",
    "gn:country_code":"LR",
    "gn:dem":214,
    "gn:feature_class":"P",
    "gn:feature_code":"PPL",
    "gn:name":"Slobali",
    "gn:population":0,
    "gn:timezone":"Africa/Monrovia",
    "iso:country":"LR",
    "wof:name":"Slobali",
    "wof:placetype":"locality"
},
  "geometry": {"coordinates":[-8.27139,5.63778],"type":"Point"}
}