{
  "type": "Feature",
  "properties": {
    "gn:admin1_code":"20.0",
    "gn:asciiname":"Yeila",
    "gn:cc2":"LR",
    "gn:country_code":"LR",
    "gn:dem":455,
    "gn:feature_class":"P",
    "gn:feature_code":"PPL",
    "gn:name":"Yeila",
    "gn:population":0,
    "gn:timezone":"Africa/Monrovia",
    "iso:country":"LR",
    "name:und_x_variant":[
        "Yeala",
        "Yella",
        "Yela",
        "Yeila"
    ],
    "wof:name":"Yeila",
    "wof:placetype":"locality"
},
  "geometry": {"coordinates":[-9.4025,7.82583],"type":"Point"}
}