{
  "type": "Feature",
  "properties": {
    "gn:admin1_code":"1.0",
    "gn:asciiname":"Baker's Farm",
    "gn:country_code":"LR",
    "gn:dem":262,
    "gn:feature_class":"P",
    "gn:feature_code":"PPL",
    "gn:name":"Baker\u2019s Farm",
    "gn:population":0,
    "gn:timezone":"Africa/Monrovia",
    "iso:country":"LR",
    "name:eng_x_preferred":[
        "Baker\u2019s Farm"
    ],
    "wof:name":"Baker's Farm",
    "wof:placetype":"locality"
},
  "geometry": {"coordinates":[-9.52428,7.04265],"type":"Point"}
}