{
  "type": "Feature",
  "properties": {
    "gn:admin1_code":"10.0",
    "gn:asciiname":"Niaklan",
    "gn:country_code":"LR",
    "gn:dem":144,
    "gn:feature_class":"P",
    "gn:feature_code":"PPL",
    "gn:name":"Niaklan",
    "gn:population":0,
    "gn:timezone":"Africa/Monrovia",
    "iso:country":"LR",
    "wof:name":"Niaklan",
    "wof:placetype":"locality"
},
  "geometry": {"coordinates":[-8.63982,5.19714],"type":"Point"}
}