{
  "type": "Feature",
  "properties": {
    "gn:admin1_code":"10.0",
    "gn:asciiname":"Potoma",
    "gn:country_code":"LR",
    "gn:dem":4,
    "gn:feature_class":"P",
    "gn:feature_code":"PPL",
    "gn:name":"Potoma",
    "gn:population":0,
    "gn:timezone":"Africa/Monrovia",
    "iso:country":"LR",
    "wof:name":"Potoma",
    "wof:placetype":"locality"
},
  "geometry": {"coordinates":[-8.93804,4.99318],"type":"Point"}
}