{
  "type": "Feature",
  "properties": {
    "gn:admin1_code":"18.0",
    "gn:asciiname":"Sam Beach Gold Mine",
    "gn:country_code":"LR",
    "gn:dem":109,
    "gn:feature_class":"P",
    "gn:feature_code":"PPL",
    "gn:name":"Sam Beach Gold Mine",
    "gn:population":0,
    "gn:timezone":"Africa/Monrovia",
    "iso:country":"LR",
    "wof:name":"Sam Beach Gold Mine",
    "wof:placetype":"locality"
},
  "geometry": {"coordinates":[-9.27875,5.76511],"type":"Point"}
}