{
  "type": "Feature",
  "properties": {
    "gn:admin1_code":"10.0",
    "gn:asciiname":"Saygbeken",
    "gn:country_code":"LR",
    "gn:dem":155,
    "gn:feature_class":"P",
    "gn:feature_code":"PPL",
    "gn:name":"Saygbeken",
    "gn:population":0,
    "gn:timezone":"Africa/Monrovia",
    "iso:country":"LR",
    "wof:name":"Saygbeken",
    "wof:placetype":"locality"
},
  "geometry": {"coordinates":[-8.5591,5.37145],"type":"Point"}
}