{
  "type": "Feature",
  "properties": {
    "gn:admin1_code":"10.0",
    "gn:asciiname":"Mrenkpo",
    "gn:country_code":"LR",
    "gn:dem":85,
    "gn:feature_class":"P",
    "gn:feature_code":"PPL",
    "gn:name":"Mrenkpo",
    "gn:population":0,
    "gn:timezone":"Africa/Monrovia",
    "iso:country":"LR",
    "wof:name":"Mrenkpo",
    "wof:placetype":"locality"
},
  "geometry": {"coordinates":[-8.55114,5.0373],"type":"Point"}
}