{
  "type": "Feature",
  "properties": {
    "gn:admin1_code":"19.0",
    "gn:asciiname":"Pellezon",
    "gn:country_code":"LR",
    "gn:dem":199,
    "gn:feature_class":"P",
    "gn:feature_code":"PPL",
    "gn:name":"Pellezon",
    "gn:population":0,
    "gn:timezone":"Africa/Monrovia",
    "iso:country":"LR",
    "name:und_x_variant":[
        "Pellizon"
    ],
    "wof:name":"Pellezon",
    "wof:placetype":"locality"
},
  "geometry": {"coordinates":[-8.18135,5.98181],"type":"Point"}
}