{
  "type": "Feature",
  "properties": {
    "gn:admin1_code":"20.0",
    "gn:asciiname":"Dodo",
    "gn:country_code":"LR",
    "gn:dem":528,
    "gn:feature_class":"P",
    "gn:feature_code":"PPL",
    "gn:name":"Dodo",
    "gn:population":0,
    "gn:timezone":"Africa/Monrovia",
    "iso:country":"LR",
    "wof:name":"Dodo",
    "wof:placetype":"locality"
},
  "geometry": {"coordinates":[-10.13167,8.37972],"type":"Point"}
}