{
  "type": "Feature",
  "properties": {
    "gn:admin1_code":"1.0",
    "gn:asciiname":"Neteme",
    "gn:country_code":"LR",
    "gn:dem":300,
    "gn:feature_class":"P",
    "gn:feature_code":"PPL",
    "gn:name":"Neteme",
    "gn:population":0,
    "gn:timezone":"Africa/Monrovia",
    "iso:country":"LR",
    "name:eng_x_preferred":[
        "Neteme"
    ],
    "wof:name":"Neteme",
    "wof:placetype":"locality"
},
  "geometry": {"coordinates":[-9.48333,7.15],"type":"Point"}
}