{
  "type": "Feature",
  "properties": {
    "gn:admin1_code":"11.0",
    "gn:asciiname":"Wrenya",
    "gn:cc2":"LR",
    "gn:country_code":"LR",
    "gn:dem":100,
    "gn:feature_class":"P",
    "gn:feature_code":"PPL",
    "gn:name":"Wrenya",
    "gn:population":0,
    "gn:timezone":"Africa/Monrovia",
    "iso:country":"LR",
    "name:und_x_variant":[
        "Vrenjah",
        "Wrenya"
    ],
    "wof:name":"Wrenya",
    "wof:placetype":"locality"
},
  "geometry": {"coordinates":[-9.71667,6.06667],"type":"Point"}
}