{
  "type": "Feature",
  "properties": {
    "gn:admin1_code":"10.0",
    "gn:asciiname":"Pindalebo",
    "gn:country_code":"LR",
    "gn:dem":80,
    "gn:feature_class":"P",
    "gn:feature_code":"PPL",
    "gn:name":"Pindalebo",
    "gn:population":0,
    "gn:timezone":"Africa/Monrovia",
    "iso:country":"LR",
    "name:und_x_variant":[
        "Plenabo",
        "Plandabalebo",
        "Pindalebo"
    ],
    "wof:name":"Pindalebo",
    "wof:placetype":"locality"
},
  "geometry": {"coordinates":[-8.9301,5.43818],"type":"Point"}
}