{
  "type": "Feature",
  "properties": {
    "gn:admin1_code":"1.0",
    "gn:asciiname":"Dunfah",
    "gn:country_code":"LR",
    "gn:dem":379,
    "gn:feature_class":"P",
    "gn:feature_code":"PPL",
    "gn:name":"Dunfah",
    "gn:population":0,
    "gn:timezone":"Africa/Monrovia",
    "iso:country":"LR",
    "name:eng_x_preferred":[
        "Dunfah"
    ],
    "wof:name":"Dunfah",
    "wof:placetype":"locality"
},
  "geometry": {"coordinates":[-9.26957,7.32105],"type":"Point"}
}