{
  "type": "Feature",
  "properties": {
    "gn:admin1_code":"16.0",
    "gn:asciiname":"Jlatakehn",
    "gn:country_code":"LR",
    "gn:dem":89,
    "gn:feature_class":"P",
    "gn:feature_code":"PPL",
    "gn:name":"Jlatakehn",
    "gn:population":0,
    "gn:timezone":"Africa/Monrovia",
    "iso:country":"LR",
    "name:und_x_variant":[
        "Jebokehn",
        "Jufokehn",
        "Jlatakehn",
        "Jlateken",
        "Tarlu City"
    ],
    "wof:name":"Jlatakehn",
    "wof:placetype":"locality"
},
  "geometry": {"coordinates":[-8.20463,4.91773],"type":"Point"}
}