{
  "type": "Feature",
  "properties": {
    "gn:admin1_code":"9.0",
    "gn:asciiname":"Yehn",
    "gn:country_code":"LR",
    "gn:dem":380,
    "gn:feature_class":"P",
    "gn:feature_code":"PPL",
    "gn:name":"Yehn",
    "gn:population":0,
    "gn:timezone":"Africa/Monrovia",
    "iso:country":"LR",
    "wof:name":"Yehn",
    "wof:placetype":"locality"
},
  "geometry": {"coordinates":[-8.41667,7.48333],"type":"Point"}
}