{
  "type": "Feature",
  "properties": {
    "gn:admin1_code":"12.0",
    "gn:asciiname":"Jawajei Mavov",
    "gn:country_code":"LR",
    "gn:dem":59,
    "gn:feature_class":"P",
    "gn:feature_code":"PPL",
    "gn:name":"Jawajei Mavov",
    "gn:population":0,
    "gn:timezone":"Africa/Monrovia",
    "iso:country":"LR",
    "name:und_x_variant":[
        "Jawajei",
        "Jawaje",
        "Javajei",
        "Javajai",
        "Nyanye",
        "Jawajei Mavo"
    ],
    "wof:name":"Jawajei Mavov",
    "wof:placetype":"locality"
},
  "geometry": {"coordinates":[-11.1067,7.03005],"type":"Point"}
}