{
  "type": "Feature",
  "properties": {
    "gn:admin1_code":"1.0",
    "gn:asciiname":"Shadrackta",
    "gn:country_code":"LR",
    "gn:dem":233,
    "gn:feature_class":"P",
    "gn:feature_code":"PPL",
    "gn:name":"Shadrackta",
    "gn:population":0,
    "gn:timezone":"Africa/Monrovia",
    "iso:country":"LR",
    "name:eng_x_preferred":[
        "Shadrackta"
    ],
    "wof:name":"Shadrackta",
    "wof:placetype":"locality"
},
  "geometry": {"coordinates":[-9.50846,6.76912],"type":"Point"}
}