{
  "type": "Feature",
  "properties": {
    "gn:admin1_code":"12.0",
    "gn:asciiname":"Bombohun",
    "gn:country_code":"LR",
    "gn:dem":19,
    "gn:feature_class":"P",
    "gn:feature_code":"PPL",
    "gn:name":"Bombohun",
    "gn:population":0,
    "gn:timezone":"Africa/Monrovia",
    "iso:country":"LR",
    "name:und_x_variant":[
        "Meinke",
        "Mainke",
        "Bombohun"
    ],
    "wof:name":"Bombohun",
    "wof:placetype":"locality"
},
  "geometry": {"coordinates":[-11.37228,7.06901],"type":"Point"}
}