{
  "type": "Feature",
  "properties": {
    "gn:admin1_code":"1.0",
    "gn:asciiname":"Moses Town",
    "gn:country_code":"LR",
    "gn:dem":249,
    "gn:feature_class":"P",
    "gn:feature_code":"PPL",
    "gn:name":"Moses Town",
    "gn:population":0,
    "gn:timezone":"Africa/Monrovia",
    "iso:country":"LR",
    "name:und_x_variant":[
        "Moses"
    ],
    "wof:name":"Moses Town",
    "wof:placetype":"locality"
},
  "geometry": {"coordinates":[-9.41028,6.73011],"type":"Point"}
}