{
  "type": "Feature",
  "properties": {
    "gn:admin1_code":"15.0",
    "gn:asciiname":"Gabajia",
    "gn:country_code":"LR",
    "gn:dem":52,
    "gn:feature_class":"P",
    "gn:feature_code":"PPL",
    "gn:name":"Gabajia",
    "gn:population":0,
    "gn:timezone":"Africa/Monrovia",
    "iso:country":"LR",
    "wof:name":"Gabajia",
    "wof:placetype":"locality"
},
  "geometry": {"coordinates":[-10.77188,6.73941],"type":"Point"}
}