{
  "type": "Feature",
  "properties": {
    "gn:admin1_code":"1.0",
    "gn:asciiname":"Sarwoloh",
    "gn:country_code":"LR",
    "gn:dem":285,
    "gn:feature_class":"P",
    "gn:feature_code":"PPL",
    "gn:name":"Sarwoloh",
    "gn:population":0,
    "gn:timezone":"Africa/Monrovia",
    "iso:country":"LR",
    "name:eng_x_preferred":[
        "Sarwoloh"
    ],
    "name:und_x_variant":[
        "Sawalo",
        "Sawota",
        "Sawolo"
    ],
    "wof:name":"Sarwoloh",
    "wof:placetype":"locality"
},
  "geometry": {"coordinates":[-9.22452,7.09016],"type":"Point"}
}