{
  "type": "Feature",
  "properties": {
    "gn:admin1_code":"22.0",
    "gn:asciiname":"Putuken",
    "gn:country_code":"LR",
    "gn:dem":248,
    "gn:feature_class":"P",
    "gn:feature_code":"PPL",
    "gn:name":"Putuken",
    "gn:population":0,
    "gn:timezone":"Africa/Monrovia",
    "iso:country":"LR",
    "name:und_x_variant":[
        "Putukehn",
        "Putuke",
        "Petukahn",
        "Putukehn Number One"
    ],
    "wof:name":"Putuken",
    "wof:placetype":"locality"
},
  "geometry": {"coordinates":[-8.00192,5.36285],"type":"Point"}
}