{
  "type": "Feature",
  "properties": {
    "gn:admin1_code":"10.0",
    "gn:asciiname":"Kajiliken",
    "gn:country_code":"LR",
    "gn:dem":133,
    "gn:feature_class":"P",
    "gn:feature_code":"PPL",
    "gn:name":"Kajiliken",
    "gn:population":0,
    "gn:timezone":"Africa/Monrovia",
    "iso:country":"LR",
    "name:und_x_variant":[
        "Keyedekehn"
    ],
    "wof:name":"Kajiliken",
    "wof:placetype":"locality"
},
  "geometry": {"coordinates":[-8.4269,5.24691],"type":"Point"}
}