{
  "type": "Feature",
  "properties": {
    "gn:admin1_code":"13.0",
    "gn:asciiname":"Yookudi",
    "gn:country_code":"LR",
    "gn:dem":21,
    "gn:feature_class":"P",
    "gn:feature_code":"PPL",
    "gn:name":"Yookudi",
    "gn:population":0,
    "gn:timezone":"Africa/Monrovia",
    "iso:country":"LR",
    "wof:name":"Yookudi",
    "wof:placetype":"locality"
},
  "geometry": {"coordinates":[-7.60472,4.44647],"type":"Point"}
}