{
  "type": "Feature",
  "properties": {
    "gn:admin1_code":"17.0",
    "gn:asciiname":"Ba",
    "gn:cc2":"LR",
    "gn:country_code":"LR",
    "gn:dem":130,
    "gn:feature_class":"P",
    "gn:feature_code":"PPL",
    "gn:name":"Ba",
    "gn:population":0,
    "gn:timezone":"Africa/Monrovia",
    "iso:country":"LR",
    "name:und_x_variant":[
        "Bah",
        "Ba"
    ],
    "wof:name":"Ba",
    "wof:placetype":"locality"
},
  "geometry": {"coordinates":[-9.96667,6.65],"type":"Point"}
}