{
  "type": "Feature",
  "properties": {
    "gn:admin1_code":"1.0",
    "gn:asciiname":"Gaigbelei",
    "gn:country_code":"LR",
    "gn:dem":131,
    "gn:feature_class":"P",
    "gn:feature_code":"PPL",
    "gn:name":"Gaigbelei",
    "gn:population":0,
    "gn:timezone":"Africa/Monrovia",
    "iso:country":"LR",
    "name:eng_x_preferred":[
        "Gaigbelei"
    ],
    "wof:name":"Gaigbelei",
    "wof:placetype":"locality"
},
  "geometry": {"coordinates":[-10.39202,6.88718],"type":"Point"}
}