{
  "type": "Feature",
  "properties": {
    "gn:admin1_code":"1.0",
    "gn:asciiname":"Chaletuta",
    "gn:country_code":"LR",
    "gn:dem":243,
    "gn:feature_class":"P",
    "gn:feature_code":"PPL",
    "gn:name":"Chaletuta",
    "gn:population":0,
    "gn:timezone":"Africa/Monrovia",
    "iso:country":"LR",
    "name:eng_x_preferred":[
        "Chaletuta"
    ],
    "wof:name":"Chaletuta",
    "wof:placetype":"locality"
},
  "geometry": {"coordinates":[-9.17322,6.8694],"type":"Point"}
}