{
  "type": "Feature",
  "properties": {
    "gn:admin1_code":"18.0",
    "gn:asciiname":"Yarpa",
    "gn:country_code":"LR",
    "gn:dem":82,
    "gn:feature_class":"P",
    "gn:feature_code":"PPL",
    "gn:name":"Yarpa",
    "gn:population":0,
    "gn:timezone":"Africa/Monrovia",
    "iso:country":"LR",
    "name:und_x_variant":[
        "Yarpa Town"
    ],
    "wof:name":"Yarpa",
    "wof:placetype":"locality"
},
  "geometry": {"coordinates":[-9.62519,5.73239],"type":"Point"}
}