{
  "type": "Feature",
  "properties": {
    "gn:admin1_code":"10.0",
    "gn:asciiname":"Gbatamoh",
    "gn:country_code":"LR",
    "gn:dem":157,
    "gn:feature_class":"P",
    "gn:feature_code":"PPL",
    "gn:name":"Gbatamoh",
    "gn:population":0,
    "gn:timezone":"Africa/Monrovia",
    "iso:country":"LR",
    "wof:name":"Gbatamoh",
    "wof:placetype":"locality"
},
  "geometry": {"coordinates":[-8.57887,5.3194],"type":"Point"}
}