{
  "type": "Feature",
  "properties": {
    "gn:admin1_code":"13.0",
    "gn:asciiname":"Sawtoken",
    "gn:country_code":"LR",
    "gn:dem":150,
    "gn:feature_class":"P",
    "gn:feature_code":"PPL",
    "gn:name":"Sawtoken",
    "gn:population":0,
    "gn:timezone":"Africa/Monrovia",
    "iso:country":"LR",
    "name:und_x_variant":[
        "Sotokehn",
        "Sawtoken"
    ],
    "wof:name":"Sawtoken",
    "wof:placetype":"locality"
},
  "geometry": {"coordinates":[-8.02636,4.9181],"type":"Point"}
}