{
  "type": "Feature",
  "properties": {
    "gn:admin1_code":"11.0",
    "gn:asciiname":"Paynesberry",
    "gn:country_code":"LR",
    "gn:dem":11,
    "gn:feature_class":"P",
    "gn:feature_code":"PPL",
    "gn:name":"Paynesberry",
    "gn:population":0,
    "gn:timezone":"Africa/Monrovia",
    "iso:country":"LR",
    "wof:name":"Paynesberry",
    "wof:placetype":"locality"
},
  "geometry": {"coordinates":[-10.05,5.91667],"type":"Point"}
}