{
  "type": "Feature",
  "properties": {
    "gn:admin1_code":"12.0",
    "gn:asciiname":"Kpesseh",
    "gn:country_code":"LR",
    "gn:dem":63,
    "gn:feature_class":"P",
    "gn:feature_code":"PPL",
    "gn:name":"Kpesseh",
    "gn:population":0,
    "gn:timezone":"Africa/Monrovia",
    "iso:country":"LR",
    "name:und_x_variant":[
        "Kpesse",
        "Kpessch",
        "Kpessi",
        "Kpese"
    ],
    "wof:name":"Kpesseh",
    "wof:placetype":"locality"
},
  "geometry": {"coordinates":[-11.20902,7.16147],"type":"Point"}
}