{
  "type": "Feature",
  "properties": {
    "gn:admin1_code":"1.0",
    "gn:asciiname":"Gbaikotuta",
    "gn:country_code":"LR",
    "gn:dem":215,
    "gn:feature_class":"P",
    "gn:feature_code":"PPL",
    "gn:name":"Gbaikotuta",
    "gn:population":0,
    "gn:timezone":"Africa/Monrovia",
    "iso:country":"LR",
    "name:eng_x_preferred":[
        "Gbaikotuta"
    ],
    "wof:name":"Gbaikotuta",
    "wof:placetype":"locality"
},
  "geometry": {"coordinates":[-9.63311,6.75232],"type":"Point"}
}