{
  "type": "Feature",
  "properties": {
    "gn:admin1_code":"22.0",
    "gn:asciiname":"Freetown",
    "gn:country_code":"LR",
    "gn:dem":100,
    "gn:feature_class":"P",
    "gn:feature_code":"PPL",
    "gn:name":"Freetown",
    "gn:population":0,
    "gn:timezone":"Africa/Monrovia",
    "iso:country":"LR",
    "wof:name":"Freetown",
    "wof:placetype":"locality"
},
  "geometry": {"coordinates":[-7.52972,5.34472],"type":"Point"}
}