{
  "type": "Feature",
  "properties": {
    "gn:admin1_code":"22.0",
    "gn:asciiname":"Saywonken",
    "gn:country_code":"LR",
    "gn:dem":253,
    "gn:feature_class":"P",
    "gn:feature_code":"PPL",
    "gn:name":"Saywonken",
    "gn:population":0,
    "gn:timezone":"Africa/Monrovia",
    "iso:country":"LR",
    "name:und_x_variant":[
        "Swoke",
        "Sorwiekehn"
    ],
    "wof:name":"Saywonken",
    "wof:placetype":"locality"
},
  "geometry": {"coordinates":[-8.13992,5.26242],"type":"Point"}
}