{
  "type": "Feature",
  "properties": {
    "gn:admin1_code":"10.0",
    "gn:asciiname":"Boubou",
    "gn:country_code":"LR",
    "gn:dem":119,
    "gn:feature_class":"P",
    "gn:feature_code":"PPL",
    "gn:name":"Boubou",
    "gn:population":0,
    "gn:timezone":"Africa/Monrovia",
    "iso:country":"LR",
    "wof:name":"Boubou",
    "wof:placetype":"locality"
},
  "geometry": {"coordinates":[-8.38333,5.05],"type":"Point"}
}