{
  "type": "Feature",
  "properties": {
    "gn:admin1_code":"11.0",
    "gn:asciiname":"Sowkon Village",
    "gn:country_code":"LR",
    "gn:dem":21,
    "gn:feature_class":"P",
    "gn:feature_code":"PPL",
    "gn:name":"Sowkon Village",
    "gn:population":0,
    "gn:timezone":"Africa/Monrovia",
    "iso:country":"LR",
    "wof:name":"Sowkon Village",
    "wof:placetype":"locality"
},
  "geometry": {"coordinates":[-10.15915,6.0975],"type":"Point"}
}