{
  "type": "Feature",
  "properties": {
    "gn:admin1_code":"1.0",
    "gn:asciiname":"Peebodyta",
    "gn:country_code":"LR",
    "gn:dem":250,
    "gn:feature_class":"P",
    "gn:feature_code":"PPL",
    "gn:name":"Peebodyta",
    "gn:population":0,
    "gn:timezone":"Africa/Monrovia",
    "iso:country":"LR",
    "name:eng_x_preferred":[
        "Peebodyta"
    ],
    "wof:name":"Peebodyta",
    "wof:placetype":"locality"
},
  "geometry": {"coordinates":[-9.44618,6.94895],"type":"Point"}
}