{
  "type": "Feature",
  "properties": {
    "gn:admin1_code":"17.0",
    "gn:asciiname":"Bagger Farm",
    "gn:country_code":"LR",
    "gn:dem":112,
    "gn:feature_class":"P",
    "gn:feature_code":"PPL",
    "gn:name":"Bagger Farm",
    "gn:population":0,
    "gn:timezone":"Africa/Monrovia",
    "iso:country":"LR",
    "name:eng_x_preferred":[
        "Bagger Farm"
    ],
    "wof:name":"Bagger Farm",
    "wof:placetype":"locality"
},
  "geometry": {"coordinates":[-10.29944,6.58383],"type":"Point"}
}