{
  "type": "Feature",
  "properties": {
    "gn:admin1_code":"15.0",
    "gn:asciiname":"Tarweh",
    "gn:country_code":"LR",
    "gn:dem":31,
    "gn:feature_class":"P",
    "gn:feature_code":"PPL",
    "gn:name":"Tarweh",
    "gn:population":0,
    "gn:timezone":"Africa/Monrovia",
    "iso:country":"LR",
    "name:und_x_variant":[
        "Be Nor"
    ],
    "wof:name":"Tarweh",
    "wof:placetype":"locality"
},
  "geometry": {"coordinates":[-10.96507,6.79968],"type":"Point"}
}