{
  "type": "Feature",
  "properties": {
    "gn:admin1_code":"12.0",
    "gn:asciiname":"Dawa",
    "gn:country_code":"LR",
    "gn:dem":130,
    "gn:feature_class":"P",
    "gn:feature_code":"PPL",
    "gn:name":"Dawa",
    "gn:population":0,
    "gn:timezone":"Africa/Monrovia",
    "iso:country":"LR",
    "name:ceb_x_preferred":[
        "Dawa"
    ],
    "name:deu_x_preferred":[
        "Dawa"
    ],
    "name:fra_x_preferred":[
        "Dawa"
    ],
    "name:nor_x_preferred":[
        "Dawa"
    ],
    "name:por_x_preferred":[
        "Dawa"
    ],
    "name:swe_x_preferred":[
        "Dawa"
    ],
    "name:und_x_variant":[
        "Wueda"
    ],
    "wof:name":"Dawa",
    "wof:placetype":"locality"
},
  "geometry": {"coordinates":[-10.74909,7.23403],"type":"Point"}
}