{
  "type": "Feature",
  "properties": {
    "gn:admin1_code":"20.0",
    "gn:asciiname":"Gomba",
    "gn:country_code":"LR",
    "gn:dem":128,
    "gn:feature_class":"P",
    "gn:feature_code":"PPL",
    "gn:name":"Gomba",
    "gn:population":0,
    "gn:timezone":"Africa/Monrovia",
    "iso:country":"LR",
    "wof:name":"Gomba",
    "wof:placetype":"locality"
},
  "geometry": {"coordinates":[-10.65694,7.1775],"type":"Point"}
}