{
  "type": "Feature",
  "properties": {
    "gn:admin1_code":"20.0",
    "gn:asciiname":"Gomba",
    "gn:country_code":"LR",
    "gn:dem":128,
    "gn:feature_class":"P",
    "gn:feature_code":"PPL",
    "gn:name":"Gomba",
    "gn:population":0,
    "gn:timezone":"Africa/Monrovia",
    "iso:country":"LR",
    "name:ceb_x_preferred":[
        "Gomba"
    ],
    "name:epo_x_preferred":[
        "Gomba"
    ],
    "name:fas_x_preferred":[
        "\u06af\u0648\u0645\u0628\u0627"
    ],
    "name:fra_x_preferred":[
        "Gomba"
    ],
    "name:hun_x_preferred":[
        "Gomba"
    ],
    "name:ita_x_preferred":[
        "Gomba"
    ],
    "name:msa_x_preferred":[
        "Gomba"
    ],
    "name:nld_x_preferred":[
        "Gomba"
    ],
    "name:ron_x_preferred":[
        "Gomba"
    ],
    "name:slk_x_preferred":[
        "Gomba"
    ],
    "name:slv_x_preferred":[
        "Gomba"
    ],
    "name:swe_x_preferred":[
        "Gomba"
    ],
    "name:vie_x_preferred":[
        "Gomba"
    ],
    "wof:name":"Gomba",
    "wof:placetype":"locality"
},
  "geometry": {"coordinates":[-10.65694,7.1775],"type":"Point"}
}