{
  "type": "Feature",
  "properties": {
    "gn:admin1_code":"1.0",
    "gn:asciiname":"Tomala",
    "gn:country_code":"LR",
    "gn:dem":161,
    "gn:feature_class":"P",
    "gn:feature_code":"PPL",
    "gn:name":"Tomala",
    "gn:population":0,
    "gn:timezone":"Africa/Monrovia",
    "iso:country":"LR",
    "wof:name":"Tomala",
    "wof:placetype":"locality"
},
  "geometry": {"coordinates":[-10.15083,6.84361],"type":"Point"}
}