{
  "type": "Feature",
  "properties": {
    "gn:admin1_code":"1.0",
    "gn:asciiname":"Jesuta",
    "gn:country_code":"LR",
    "gn:dem":252,
    "gn:feature_class":"P",
    "gn:feature_code":"PPL",
    "gn:name":"Jesuta",
    "gn:population":0,
    "gn:timezone":"Africa/Monrovia",
    "iso:country":"LR",
    "name:eng_x_preferred":[
        "Jesuta"
    ],
    "wof:name":"Jesuta",
    "wof:placetype":"locality"
},
  "geometry": {"coordinates":[-9.51529,6.71789],"type":"Point"}
}