{
  "type": "Feature",
  "properties": {
    "gn:admin1_code":"11.0",
    "gn:asciiname":"Kalota",
    "gn:country_code":"LR",
    "gn:dem":239,
    "gn:feature_class":"P",
    "gn:feature_code":"PPL",
    "gn:name":"Kalota",
    "gn:population":0,
    "gn:timezone":"Africa/Monrovia",
    "iso:country":"LR",
    "wof:name":"Kalota",
    "wof:placetype":"locality"
},
  "geometry": {"coordinates":[-9.26667,6.51667],"type":"Point"}
}