{
  "type": "Feature",
  "properties": {
    "gn:admin1_code":"16.0",
    "gn:asciiname":"Bailakpo",
    "gn:country_code":"LR",
    "gn:dem":8,
    "gn:feature_class":"P",
    "gn:feature_code":"PPL",
    "gn:name":"Bailakpo",
    "gn:population":0,
    "gn:timezone":"Africa/Monrovia",
    "iso:country":"LR",
    "name:und_x_variant":[
        "Picnicess",
        "Bilapo",
        "Pickaninny Cess",
        "Pickaninny Sesters",
        "Pickininy Sesters",
        "Pikanini Sesters",
        "Picanniny Cess",
        "Bilakpo",
        "Bailakpo"
    ],
    "wof:name":"Bailakpo",
    "wof:placetype":"locality"
},
  "geometry": {"coordinates":[-8.31338,4.62576],"type":"Point"}
}