{
  "type": "Feature",
  "properties": {
    "gn:admin1_code":"19.0",
    "gn:asciiname":"Kosmoso",
    "gn:country_code":"LR",
    "gn:dem":229,
    "gn:feature_class":"P",
    "gn:feature_code":"PPL",
    "gn:name":"Kosmoso",
    "gn:population":0,
    "gn:timezone":"Africa/Monrovia",
    "iso:country":"LR",
    "wof:name":"Kosmoso",
    "wof:placetype":"locality"
},
  "geometry": {"coordinates":[-8.26615,6.02233],"type":"Point"}
}