{
  "type": "Feature",
  "properties": {
    "gn:admin1_code":"10.0",
    "gn:asciiname":"Potuken",
    "gn:country_code":"LR",
    "gn:dem":111,
    "gn:feature_class":"P",
    "gn:feature_code":"PPL",
    "gn:name":"Potuken",
    "gn:population":0,
    "gn:timezone":"Africa/Monrovia",
    "iso:country":"LR",
    "wof:name":"Potuken",
    "wof:placetype":"locality"
},
  "geometry": {"coordinates":[-8.44088,5.22696],"type":"Point"}
}