{
  "type": "Feature",
  "properties": {
    "gn:admin1_code":"11.0",
    "gn:asciiname":"Macreekbli",
    "gn:country_code":"LR",
    "gn:dem":58,
    "gn:feature_class":"P",
    "gn:feature_code":"PPL",
    "gn:name":"Macreekbli",
    "gn:population":0,
    "gn:timezone":"Africa/Monrovia",
    "iso:country":"LR",
    "name:und_x_variant":[
        "Mocra Town",
        "Macreekbli"
    ],
    "wof:name":"Macreekbli",
    "wof:placetype":"locality"
},
  "geometry": {"coordinates":[-9.90223,6.00411],"type":"Point"}
}