{
  "type": "Feature",
  "properties": {
    "gn:admin1_code":"9.0",
    "gn:asciiname":"Keka",
    "gn:country_code":"LR",
    "gn:dem":229,
    "gn:feature_class":"P",
    "gn:feature_code":"PPL",
    "gn:name":"Keka",
    "gn:population":0,
    "gn:timezone":"Africa/Monrovia",
    "iso:country":"LR",
    "name:ceb_x_preferred":[
        "Keka"
    ],
    "name:swe_x_preferred":[
        "Keka"
    ],
    "wof:name":"Keka",
    "wof:placetype":"locality"
},
  "geometry": {"coordinates":[-8.99583,6.28667],"type":"Point"}
}