{
  "type": "Feature",
  "properties": {
    "gn:admin1_code":"10.0",
    "gn:asciiname":"Jadit",
    "gn:country_code":"LR",
    "gn:dem":117,
    "gn:feature_class":"P",
    "gn:feature_code":"PPL",
    "gn:name":"Jadit",
    "gn:population":0,
    "gn:timezone":"Africa/Monrovia",
    "iso:country":"LR",
    "name:und_x_variant":[
        "Jiadiflu",
        "Jadit"
    ],
    "wof:name":"Jadit",
    "wof:placetype":"locality"
},
  "geometry": {"coordinates":[-8.36309,5.27612],"type":"Point"}
}