{
  "type": "Feature",
  "properties": {
    "gn:admin1_code":"20.0",
    "gn:asciiname":"Baziwehn",
    "gn:cc2":"LR",
    "gn:country_code":"LR",
    "gn:dem":445,
    "gn:feature_class":"P",
    "gn:feature_code":"PPL",
    "gn:name":"Baziwehn",
    "gn:population":0,
    "gn:timezone":"Africa/Monrovia",
    "iso:country":"LR",
    "name:und_x_variant":[
        "Bazalima",
        "Baziewehn",
        "Bahsiwayn",
        "Baziama",
        "Baziwehn"
    ],
    "wof:name":"Baziwehn",
    "wof:placetype":"locality"
},
  "geometry": {"coordinates":[-9.65194,8.15278],"type":"Point"}
}