{
  "type": "Feature",
  "properties": {
    "gn:admin1_code":"11.0",
    "gn:asciiname":"Garlueata",
    "gn:country_code":"LR",
    "gn:dem":194,
    "gn:feature_class":"P",
    "gn:feature_code":"PPL",
    "gn:name":"Garlueata",
    "gn:population":0,
    "gn:timezone":"Africa/Monrovia",
    "iso:country":"LR",
    "wof:name":"Garlueata",
    "wof:placetype":"locality"
},
  "geometry": {"coordinates":[-9.71229,6.58883],"type":"Point"}
}