{
  "type": "Feature",
  "properties": {
    "gn:admin1_code":"18.0",
    "gn:asciiname":"Botaveri",
    "gn:country_code":"LR",
    "gn:dem":145,
    "gn:feature_class":"P",
    "gn:feature_code":"PPL",
    "gn:name":"Botaveri",
    "gn:population":0,
    "gn:timezone":"Africa/Monrovia",
    "iso:country":"LR",
    "name:und_x_variant":[
        "Wea",
        "Botaveri"
    ],
    "wof:name":"Botaveri",
    "wof:placetype":"locality"
},
  "geometry": {"coordinates":[-9.40349,6.00212],"type":"Point"}
}