{
  "type": "Feature",
  "properties": {
    "gn:admin1_code":"10.0",
    "gn:asciiname":"S.B.I. Mission",
    "gn:country_code":"LR",
    "gn:dem":24,
    "gn:feature_class":"P",
    "gn:feature_code":"PPL",
    "gn:name":"S.B.I. Mission",
    "gn:population":0,
    "gn:timezone":"Africa/Monrovia",
    "iso:country":"LR",
    "name:und_x_variant":[
        "Donewehn"
    ],
    "wof:name":"S.B.I. Mission",
    "wof:placetype":"locality"
},
  "geometry": {"coordinates":[-8.63781,4.99236],"type":"Point"}
}