{
  "type": "Feature",
  "properties": {
    "gn:admin1_code":"20.0",
    "gn:asciiname":"Hengbelahun",
    "gn:cc2":"LR",
    "gn:country_code":"LR",
    "gn:dem":561,
    "gn:feature_class":"P",
    "gn:feature_code":"PPL",
    "gn:name":"Hengbelahun",
    "gn:population":0,
    "gn:timezone":"Africa/Monrovia",
    "iso:country":"LR",
    "name:und_x_variant":[
        "Mbembalahun",
        "Hibilahun",
        "Libilahun",
        "Hengbelahun"
    ],
    "wof:name":"Hengbelahun",
    "wof:placetype":"locality"
},
  "geometry": {"coordinates":[-10.02694,8.39167],"type":"Point"}
}