{
  "type": "Feature",
  "properties": {
    "gn:admin1_code":"1.0",
    "gn:asciiname":"Dongfai",
    "gn:country_code":"LR",
    "gn:dem":258,
    "gn:feature_class":"P",
    "gn:feature_code":"PPL",
    "gn:name":"Dongfai",
    "gn:population":0,
    "gn:timezone":"Africa/Monrovia",
    "iso:country":"LR",
    "wof:name":"Dongfai",
    "wof:placetype":"locality"
},
  "geometry": {"coordinates":[-9.81667,6.85],"type":"Point"}
}