{
  "type": "Feature",
  "properties": {
    "gn:admin1_code":"17.0",
    "gn:asciiname":"Saieatro Town",
    "gn:country_code":"LR",
    "gn:dem":19,
    "gn:feature_class":"P",
    "gn:feature_code":"PPL",
    "gn:name":"Saieatro Town",
    "gn:population":0,
    "gn:timezone":"Africa/Monrovia",
    "iso:country":"LR",
    "wof:name":"Saieatro Town",
    "wof:placetype":"locality"
},
  "geometry": {"coordinates":[-10.33722,6.24278],"type":"Point"}
}