{
  "type": "Feature",
  "properties": {
    "gn:admin1_code":"11.0",
    "gn:asciiname":"Jacob Lateg Town",
    "gn:country_code":"LR",
    "gn:dem":76,
    "gn:feature_class":"P",
    "gn:feature_code":"PPL",
    "gn:name":"Jacob Lateg Town",
    "gn:population":0,
    "gn:timezone":"Africa/Monrovia",
    "iso:country":"LR",
    "name:und_x_variant":[
        "Langota",
        "Jacob Lateg Town"
    ],
    "wof:name":"Jacob Lateg Town",
    "wof:placetype":"locality"
},
  "geometry": {"coordinates":[-10.23432,6.4439],"type":"Point"}
}