{
  "type": "Feature",
  "properties": {
    "gn:admin1_code":"1.0",
    "gn:asciiname":"Diggs",
    "gn:country_code":"LR",
    "gn:dem":214,
    "gn:feature_class":"P",
    "gn:feature_code":"PPL",
    "gn:name":"Diggs",
    "gn:population":0,
    "gn:timezone":"Africa/Monrovia",
    "iso:country":"LR",
    "name:deu_x_preferred":[
        "Diggs"
    ],
    "name:eng_x_preferred":[
        "Diggs"
    ],
    "name:fra_x_preferred":[
        "Diggs"
    ],
    "name:rus_x_preferred":[
        "\u0414\u0438\u0433\u0433\u0437"
    ],
    "wof:name":"Diggs",
    "wof:placetype":"locality"
},
  "geometry": {"coordinates":[-9.41667,6.63333],"type":"Point"}
}