{
  "type": "Feature",
  "properties": {
    "gn:admin1_code":"11.0",
    "gn:asciiname":"Debabli",
    "gn:country_code":"LR",
    "gn:dem":60,
    "gn:feature_class":"P",
    "gn:feature_code":"PPL",
    "gn:name":"Debabli",
    "gn:population":0,
    "gn:timezone":"Africa/Monrovia",
    "iso:country":"LR",
    "wof:name":"Debabli",
    "wof:placetype":"locality"
},
  "geometry": {"coordinates":[-9.83333,5.98333],"type":"Point"}
}