{
  "type": "Feature",
  "properties": {
    "gn:admin1_code":"19.0",
    "gn:asciiname":"Walto",
    "gn:country_code":"LR",
    "gn:dem":272,
    "gn:feature_class":"P",
    "gn:feature_code":"PPL",
    "gn:name":"Walto",
    "gn:population":0,
    "gn:timezone":"Africa/Monrovia",
    "iso:country":"LR",
    "wof:name":"Walto",
    "wof:placetype":"locality"
},
  "geometry": {"coordinates":[-8.575,6.38389],"type":"Point"}
}