{
  "type": "Feature",
  "properties": {
    "gn:admin1_code":"1.0",
    "gn:asciiname":"Jawata Town",
    "gn:cc2":"LR",
    "gn:country_code":"LR",
    "gn:dem":279,
    "gn:feature_class":"P",
    "gn:feature_code":"PPL",
    "gn:name":"Jawata Town",
    "gn:population":0,
    "gn:timezone":"Africa/Monrovia",
    "iso:country":"LR",
    "name:und_x_variant":[
        "Jawata",
        "Jawata Town"
    ],
    "wof:name":"Jawata Town",
    "wof:placetype":"locality"
},
  "geometry": {"coordinates":[-9.60694,7.02833],"type":"Point"}
}