{
  "type": "Feature",
  "properties": {
    "gn:admin1_code":"19.0",
    "gn:asciiname":"Slah",
    "gn:country_code":"LR",
    "gn:dem":250,
    "gn:feature_class":"P",
    "gn:feature_code":"PPL",
    "gn:name":"Slah",
    "gn:population":0,
    "gn:timezone":"Africa/Monrovia",
    "iso:country":"LR",
    "wof:name":"Slah",
    "wof:placetype":"locality"
},
  "geometry": {"coordinates":[-8.1677,6.13905],"type":"Point"}
}