{
  "type": "Feature",
  "properties": {
    "gn:admin1_code":"10.0",
    "gn:asciiname":"Bia Town",
    "gn:cc2":"LR",
    "gn:country_code":"LR",
    "gn:dem":60,
    "gn:feature_class":"P",
    "gn:feature_code":"PPL",
    "gn:name":"Bia Town",
    "gn:population":0,
    "gn:timezone":"Africa/Monrovia",
    "iso:country":"LR",
    "name:und_x_variant":[
        "Bolo",
        "Bia Town"
    ],
    "wof:name":"Bia Town",
    "wof:placetype":"locality"
},
  "geometry": {"coordinates":[-9.23611,5.50083],"type":"Point"}
}