{
  "type": "Feature",
  "properties": {
    "gn:admin1_code":"21.0",
    "gn:asciiname":"Jojoma",
    "gn:country_code":"LR",
    "gn:dem":146,
    "gn:feature_class":"P",
    "gn:feature_code":"PPL",
    "gn:name":"Jojoma",
    "gn:population":0,
    "gn:timezone":"Africa/Monrovia",
    "iso:country":"LR",
    "name:und_x_variant":[
        "Jojomo",
        "Jojoma"
    ],
    "wof:name":"Jojoma",
    "wof:placetype":"locality"
},
  "geometry": {"coordinates":[-10.62833,7.02556],"type":"Point"}
}