{
  "type": "Feature",
  "properties": {
    "gn:admin1_code":"9.0",
    "gn:asciiname":"Teazegboplay",
    "gn:country_code":"LR",
    "gn:dem":313,
    "gn:feature_class":"P",
    "gn:feature_code":"PPL",
    "gn:name":"Teazegboplay",
    "gn:population":0,
    "gn:timezone":"Africa/Monrovia",
    "iso:country":"LR",
    "wof:name":"Teazegboplay",
    "wof:placetype":"locality"
},
  "geometry": {"coordinates":[-8.34944,7.13306],"type":"Point"}
}