{
  "type": "Feature",
  "properties": {
    "gn:admin1_code":"18.0",
    "gn:asciiname":"Gbortoe Town",
    "gn:country_code":"LR",
    "gn:dem":170,
    "gn:feature_class":"P",
    "gn:feature_code":"PPL",
    "gn:name":"Gbortoe Town",
    "gn:population":0,
    "gn:timezone":"Africa/Monrovia",
    "iso:country":"LR",
    "name:und_x_variant":[
        "Bato",
        "Bato Town",
        "Gbortoe Town"
    ],
    "wof:name":"Gbortoe Town",
    "wof:placetype":"locality"
},
  "geometry": {"coordinates":[-9.2543,6.08417],"type":"Point"}
}