{
  "type": "Feature",
  "properties": {
    "gn:admin1_code":"20.0",
    "gn:asciiname":"Sefudu",
    "gn:country_code":"LR",
    "gn:dem":540,
    "gn:feature_class":"P",
    "gn:feature_code":"PPL",
    "gn:name":"Sefudu",
    "gn:population":0,
    "gn:timezone":"Africa/Monrovia",
    "iso:country":"LR",
    "wof:name":"Sefudu",
    "wof:placetype":"locality"
},
  "geometry": {"coordinates":[-9.55,8.36667],"type":"Point"}
}