{
  "type": "Feature",
  "properties": {
    "gn:admin1_code":"19.0",
    "gn:asciiname":"Tojallah",
    "gn:country_code":"LR",
    "gn:dem":222,
    "gn:feature_class":"P",
    "gn:feature_code":"PPL",
    "gn:name":"Tojallah",
    "gn:population":0,
    "gn:timezone":"Africa/Monrovia",
    "iso:country":"LR",
    "name:und_x_variant":[
        "Toyelabli",
        "Togau Town",
        "Tojallah"
    ],
    "wof:name":"Tojallah",
    "wof:placetype":"locality"
},
  "geometry": {"coordinates":[-8.31611,6.09167],"type":"Point"}
}