{
  "type": "Feature",
  "properties": {
    "gn:admin1_code":"21.0",
    "gn:asciiname":"Gumgbeta",
    "gn:country_code":"LR",
    "gn:dem":212,
    "gn:feature_class":"P",
    "gn:feature_code":"PPL",
    "gn:name":"Gumgbeta",
    "gn:population":0,
    "gn:timezone":"Africa/Monrovia",
    "iso:country":"LR",
    "name:und_x_variant":[
        "Gombella",
        "Koenbita",
        "Gombeita",
        "Koonbita",
        "Gumgbela",
        "Gumgbeta"
    ],
    "wof:name":"Gumgbeta",
    "wof:placetype":"locality"
},
  "geometry": {"coordinates":[-10.09556,7.25944],"type":"Point"}
}