{
  "type": "Feature",
  "properties": {
    "gn:admin1_code":"1.0",
    "gn:asciiname":"Brown Town",
    "gn:country_code":"LR",
    "gn:dem":258,
    "gn:feature_class":"P",
    "gn:feature_code":"PPL",
    "gn:name":"Brown Town",
    "gn:population":0,
    "gn:timezone":"Africa/Monrovia",
    "iso:country":"LR",
    "name:eng_x_preferred":[
        "Brown Town"
    ],
    "wof:name":"Brown Town",
    "wof:placetype":"locality"
},
  "geometry": {"coordinates":[-9.58,7.03639],"type":"Point"}
}