{
  "type": "Feature",
  "properties": {
    "gn:admin1_code":"11.0",
    "gn:asciiname":"Sawubli",
    "gn:country_code":"LR",
    "gn:dem":140,
    "gn:feature_class":"P",
    "gn:feature_code":"PPL",
    "gn:name":"Sawubli",
    "gn:population":0,
    "gn:timezone":"Africa/Monrovia",
    "iso:country":"LR",
    "wof:name":"Sawubli",
    "wof:placetype":"locality"
},
  "geometry": {"coordinates":[-9.73333,6.18333],"type":"Point"}
}