{
  "type": "Feature",
  "properties": {
    "gn:admin1_code":"22.0",
    "gn:asciiname":"Penokehn",
    "gn:country_code":"LR",
    "gn:dem":234,
    "gn:feature_class":"P",
    "gn:feature_code":"PPL",
    "gn:name":"Penokehn",
    "gn:population":0,
    "gn:timezone":"Africa/Monrovia",
    "iso:country":"LR",
    "wof:name":"Penokehn",
    "wof:placetype":"locality"
},
  "geometry": {"coordinates":[-8.12684,5.21231],"type":"Point"}
}