{
  "type": "Feature",
  "properties": {
    "gn:admin1_code":"12.0",
    "gn:asciiname":"Selfula Village",
    "gn:country_code":"LR",
    "gn:dem":31,
    "gn:feature_class":"P",
    "gn:feature_code":"PPL",
    "gn:name":"Selfula Village",
    "gn:population":0,
    "gn:timezone":"Africa/Monrovia",
    "iso:country":"LR",
    "wof:name":"Selfula Village",
    "wof:placetype":"locality"
},
  "geometry": {"coordinates":[-11.31626,7.12967],"type":"Point"}
}