{
  "type": "Feature",
  "properties": {
    "gn:admin1_code":"9.0",
    "gn:asciiname":"Bolduye",
    "gn:country_code":"LR",
    "gn:dem":263,
    "gn:feature_class":"P",
    "gn:feature_code":"PPL",
    "gn:name":"Bolduye",
    "gn:population":0,
    "gn:timezone":"Africa/Monrovia",
    "iso:country":"LR",
    "wof:name":"Bolduye",
    "wof:placetype":"locality"
},
  "geometry": {"coordinates":[-8.42194,6.9125],"type":"Point"}
}