{
  "type": "Feature",
  "properties": {
    "gn:admin1_code":"15.0",
    "gn:asciiname":"Guie Town",
    "gn:country_code":"LR",
    "gn:dem":38,
    "gn:feature_class":"P",
    "gn:feature_code":"PPL",
    "gn:name":"Guie Town",
    "gn:population":0,
    "gn:timezone":"Africa/Monrovia",
    "iso:country":"LR",
    "name:und_x_variant":[
        "Kava",
        "Be Grale",
        "Be Gole",
        "Guie Town"
    ],
    "wof:name":"Guie Town",
    "wof:placetype":"locality"
},
  "geometry": {"coordinates":[-10.8503,6.75907],"type":"Point"}
}