{
  "type": "Feature",
  "properties": {
    "gn:admin1_code":"12.0",
    "gn:asciiname":"Domagbe",
    "gn:country_code":"LR",
    "gn:dem":51,
    "gn:feature_class":"P",
    "gn:feature_code":"PPL",
    "gn:name":"Domagbe",
    "gn:population":0,
    "gn:timezone":"Africa/Monrovia",
    "iso:country":"LR",
    "wof:name":"Domagbe",
    "wof:placetype":"locality"
},
  "geometry": {"coordinates":[-11.23333,7.13333],"type":"Point"}
}