{
  "type": "Feature",
  "properties": {
    "gn:admin1_code":"11.0",
    "gn:asciiname":"Jacobta",
    "gn:country_code":"LR",
    "gn:dem":176,
    "gn:feature_class":"P",
    "gn:feature_code":"PPL",
    "gn:name":"Jacobta",
    "gn:population":0,
    "gn:timezone":"Africa/Monrovia",
    "iso:country":"LR",
    "wof:name":"Jacobta",
    "wof:placetype":"locality"
},
  "geometry": {"coordinates":[-9.70639,6.53139],"type":"Point"}
}