{
  "type": "Feature",
  "properties": {
    "gn:admin1_code":"14.0",
    "gn:asciiname":"Babu Town",
    "gn:country_code":"LR",
    "gn:dem":15,
    "gn:feature_class":"P",
    "gn:feature_code":"PPL",
    "gn:name":"Babu Town",
    "gn:population":0,
    "gn:timezone":"Africa/Monrovia",
    "iso:country":"LR",
    "wof:name":"Babu Town",
    "wof:placetype":"locality"
},
  "geometry": {"coordinates":[-10.76667,6.43333],"type":"Point"}
}