{
  "type": "Feature",
  "properties": {
    "gn:admin1_code":"1.0",
    "gn:asciiname":"Gunie",
    "gn:country_code":"LR",
    "gn:dem":245,
    "gn:feature_class":"P",
    "gn:feature_code":"PPL",
    "gn:name":"Gunie",
    "gn:population":0,
    "gn:timezone":"Africa/Monrovia",
    "iso:country":"LR",
    "name:eng_x_preferred":[
        "Gunie"
    ],
    "wof:name":"Gunie",
    "wof:placetype":"locality"
},
  "geometry": {"coordinates":[-9.20285,6.84461],"type":"Point"}
}