{
  "type": "Feature",
  "properties": {
    "gn:admin1_code":"10.0",
    "gn:asciiname":"Diatodie",
    "gn:country_code":"LR",
    "gn:dem":116,
    "gn:feature_class":"P",
    "gn:feature_code":"PPL",
    "gn:name":"Diatodie",
    "gn:population":0,
    "gn:timezone":"Africa/Monrovia",
    "iso:country":"LR",
    "name:und_x_variant":[
        "Kwiatuo",
        "Diatodie"
    ],
    "wof:name":"Diatodie",
    "wof:placetype":"locality"
},
  "geometry": {"coordinates":[-8.66807,5.08983],"type":"Point"}
}