{
  "type": "Feature",
  "properties": {
    "gn:admin1_code":"18.0",
    "gn:asciiname":"Bahn Town",
    "gn:country_code":"LR",
    "gn:dem":117,
    "gn:feature_class":"P",
    "gn:feature_code":"PPL",
    "gn:name":"Bahn Town",
    "gn:population":0,
    "gn:timezone":"Africa/Monrovia",
    "iso:country":"LR",
    "name:und_x_variant":[
        "Bedue",
        "Bahn Town"
    ],
    "wof:name":"Bahn Town",
    "wof:placetype":"locality"
},
  "geometry": {"coordinates":[-9.46536,5.96155],"type":"Point"}
}