{
  "type": "Feature",
  "properties": {
    "gn:admin1_code":"21.0",
    "gn:asciiname":"Baikole",
    "gn:country_code":"LR",
    "gn:dem":204,
    "gn:feature_class":"P",
    "gn:feature_code":"PPL",
    "gn:name":"Baikole",
    "gn:population":0,
    "gn:timezone":"Africa/Monrovia",
    "iso:country":"LR",
    "wof:name":"Baikole",
    "wof:placetype":"locality"
},
  "geometry": {"coordinates":[-9.99056,7.13917],"type":"Point"}
}