{
  "type": "Feature",
  "properties": {
    "gn:admin1_code":"1.0",
    "gn:asciiname":"Balama",
    "gn:country_code":"LR",
    "gn:dem":278,
    "gn:feature_class":"P",
    "gn:feature_code":"PPL",
    "gn:name":"Balama",
    "gn:population":0,
    "gn:timezone":"Africa/Monrovia",
    "iso:country":"LR",
    "name:eng_x_preferred":[
        "Balama"
    ],
    "name:ita_x_preferred":[
        "Balama"
    ],
    "name:swa_x_preferred":[
        "Balama"
    ],
    "name:zho_x_preferred":[
        "\u5df4\u62c9\u99ac"
    ],
    "wof:name":"Balama",
    "wof:placetype":"locality"
},
  "geometry": {"coordinates":[-9.58594,7.06961],"type":"Point"}
}