{
  "type": "Feature",
  "properties": {
    "gn:admin1_code":"1.0",
    "gn:asciiname":"Ziata",
    "gn:country_code":"LR",
    "gn:dem":215,
    "gn:feature_class":"P",
    "gn:feature_code":"PPL",
    "gn:name":"Ziata",
    "gn:population":0,
    "gn:timezone":"Africa/Monrovia",
    "iso:country":"LR",
    "name:eng_x_preferred":[
        "Ziata"
    ],
    "name:und_x_variant":[
        "Ziata (1)",
        "Ziata One"
    ],
    "wof:name":"Ziata",
    "wof:placetype":"locality"
},
  "geometry": {"coordinates":[-9.45581,6.57658],"type":"Point"}
}