{
  "type": "Feature",
  "properties": {
    "gn:admin1_code":"1.0",
    "gn:asciiname":"Vanjata",
    "gn:country_code":"LR",
    "gn:dem":146,
    "gn:feature_class":"P",
    "gn:feature_code":"PPL",
    "gn:name":"Vanjata",
    "gn:population":0,
    "gn:timezone":"Africa/Monrovia",
    "iso:country":"LR",
    "name:eng_x_preferred":[
        "Vanjata"
    ],
    "wof:name":"Vanjata",
    "wof:placetype":"locality"
},
  "geometry": {"coordinates":[-10.3277,6.93939],"type":"Point"}
}