{
  "type": "Feature",
  "properties": {
    "gn:admin1_code":"9.0",
    "gn:asciiname":"Glalie",
    "gn:cc2":"LR",
    "gn:country_code":"LR",
    "gn:dem":297,
    "gn:feature_class":"P",
    "gn:feature_code":"PPL",
    "gn:name":"Glalie",
    "gn:population":0,
    "gn:timezone":"Africa/Monrovia",
    "iso:country":"LR",
    "name:und_x_variant":[
        "Mabli",
        "Maplay",
        "Miaple",
        "Maiple",
        "Glalie"
    ],
    "wof:name":"Glalie",
    "wof:placetype":"locality"
},
  "geometry": {"coordinates":[-8.50944,6.95139],"type":"Point"}
}