{
  "type": "Feature",
  "properties": {
    "gn:admin1_code":"1.0",
    "gn:asciiname":"Lenguluta",
    "gn:country_code":"LR",
    "gn:dem":228,
    "gn:feature_class":"P",
    "gn:feature_code":"PPL",
    "gn:name":"Lenguluta",
    "gn:population":0,
    "gn:timezone":"Africa/Monrovia",
    "iso:country":"LR",
    "name:eng_x_preferred":[
        "Lenguluta"
    ],
    "wof:name":"Lenguluta",
    "wof:placetype":"locality"
},
  "geometry": {"coordinates":[-9.71033,7.0833],"type":"Point"}
}