{
  "type": "Feature",
  "properties": {
    "gn:admin1_code":"16.0",
    "gn:asciiname":"Jadakehn",
    "gn:country_code":"LR",
    "gn:dem":104,
    "gn:feature_class":"P",
    "gn:feature_code":"PPL",
    "gn:name":"Jadakehn",
    "gn:population":0,
    "gn:timezone":"Africa/Monrovia",
    "iso:country":"LR",
    "wof:name":"Jadakehn",
    "wof:placetype":"locality"
},
  "geometry": {"coordinates":[-8.09003,4.75446],"type":"Point"}
}