{
  "type": "Feature",
  "properties": {
    "gn:admin1_code":"1.0",
    "gn:asciiname":"Gaolita",
    "gn:country_code":"LR",
    "gn:dem":240,
    "gn:feature_class":"P",
    "gn:feature_code":"PPL",
    "gn:name":"Gaolita",
    "gn:population":0,
    "gn:timezone":"Africa/Monrovia",
    "iso:country":"LR",
    "name:eng_x_preferred":[
        "Gaolita"
    ],
    "name:und_x_variant":[
        "Koalite"
    ],
    "wof:name":"Gaolita",
    "wof:placetype":"locality"
},
  "geometry": {"coordinates":[-9.55352,6.84143],"type":"Point"}
}