{
  "type": "Feature",
  "properties": {
    "gn:admin1_code":"12.0",
    "gn:asciiname":"Bomie",
    "gn:country_code":"LR",
    "gn:dem":12,
    "gn:feature_class":"P",
    "gn:feature_code":"PPL",
    "gn:name":"Bomie",
    "gn:population":0,
    "gn:timezone":"Africa/Monrovia",
    "iso:country":"LR",
    "name:und_x_variant":[
        "Bomi"
    ],
    "wof:name":"Bomie",
    "wof:placetype":"locality"
},
  "geometry": {"coordinates":[-11.16625,6.66386],"type":"Point"}
}