{
  "type": "Feature",
  "properties": {
    "gn:admin1_code":"1.0",
    "gn:asciiname":"Lelai",
    "gn:country_code":"LR",
    "gn:dem":322,
    "gn:feature_class":"P",
    "gn:feature_code":"PPL",
    "gn:name":"Lelai",
    "gn:population":0,
    "gn:timezone":"Africa/Monrovia",
    "iso:country":"LR",
    "wof:name":"Lelai",
    "wof:placetype":"locality"
},
  "geometry": {"coordinates":[-9.92944,6.855],"type":"Point"}
}