{
  "type": "Feature",
  "properties": {
    "gn:admin1_code":"14.0",
    "gn:asciiname":"Wota",
    "gn:country_code":"LR",
    "gn:dem":118,
    "gn:feature_class":"P",
    "gn:feature_code":"PPL",
    "gn:name":"Wota",
    "gn:population":0,
    "gn:timezone":"Africa/Monrovia",
    "iso:country":"LR",
    "wof:name":"Wota",
    "wof:placetype":"locality"
},
  "geometry": {"coordinates":[-10.44861,6.48694],"type":"Point"}
}