{
  "type": "Feature",
  "properties": {
    "gn:admin1_code":"11.0",
    "gn:asciiname":"Bosikobli",
    "gn:country_code":"LR",
    "gn:dem":189,
    "gn:feature_class":"P",
    "gn:feature_code":"PPL",
    "gn:name":"Bosikobli",
    "gn:population":0,
    "gn:timezone":"Africa/Monrovia",
    "iso:country":"LR",
    "wof:name":"Bosikobli",
    "wof:placetype":"locality"
},
  "geometry": {"coordinates":[-9.55,6.45],"type":"Point"}
}