{
  "type": "Feature",
  "properties": {
    "gn:admin1_code":"11.0",
    "gn:asciiname":"Kassian Village",
    "gn:country_code":"LR",
    "gn:dem":189,
    "gn:feature_class":"P",
    "gn:feature_code":"PPL",
    "gn:name":"Kassian Village",
    "gn:population":0,
    "gn:timezone":"Africa/Monrovia",
    "iso:country":"LR",
    "wof:name":"Kassian Village",
    "wof:placetype":"locality"
},
  "geometry": {"coordinates":[-9.62402,6.36786],"type":"Point"}
}