{
  "type": "Feature",
  "properties": {
    "gn:admin1_code":"11.0",
    "gn:asciiname":"Ben Loganbli",
    "gn:country_code":"LR",
    "gn:dem":26,
    "gn:feature_class":"P",
    "gn:feature_code":"PPL",
    "gn:name":"Ben Loganbli",
    "gn:population":0,
    "gn:timezone":"Africa/Monrovia",
    "iso:country":"LR",
    "wof:name":"Ben Loganbli",
    "wof:placetype":"locality"
},
  "geometry": {"coordinates":[-10.20354,6.08995],"type":"Point"}
}