{
  "type": "Feature",
  "properties": {
    "gn:admin1_code":"16.0",
    "gn:asciiname":"Betu Villale",
    "gn:country_code":"LR",
    "gn:dem":36,
    "gn:feature_class":"P",
    "gn:feature_code":"PPL",
    "gn:name":"Betu Villale",
    "gn:population":0,
    "gn:timezone":"Africa/Monrovia",
    "iso:country":"LR",
    "wof:name":"Betu Villale",
    "wof:placetype":"locality"
},
  "geometry": {"coordinates":[-8.41472,4.86325],"type":"Point"}
}