{
  "type": "Feature",
  "properties": {
    "gn:admin1_code":"11.0",
    "gn:asciiname":"Jacob Miler",
    "gn:country_code":"LR",
    "gn:dem":203,
    "gn:feature_class":"P",
    "gn:feature_code":"PPL",
    "gn:name":"Jacob Miler",
    "gn:population":0,
    "gn:timezone":"Africa/Monrovia",
    "iso:country":"LR",
    "wof:name":"Jacob Miler",
    "wof:placetype":"locality"
},
  "geometry": {"coordinates":[-9.58652,6.41143],"type":"Point"}
}