{
  "type": "Feature",
  "properties": {
    "gn:admin1_code":"20.0",
    "gn:asciiname":"Faseima",
    "gn:country_code":"LR",
    "gn:dem":417,
    "gn:feature_class":"P",
    "gn:feature_code":"PPL",
    "gn:name":"Faseima",
    "gn:population":0,
    "gn:timezone":"Africa/Monrovia",
    "iso:country":"LR",
    "wof:name":"Faseima",
    "wof:placetype":"locality"
},
  "geometry": {"coordinates":[-10.27639,8.29972],"type":"Point"}
}