{
  "type": "Feature",
  "properties": {
    "gn:admin1_code":"16.0",
    "gn:asciiname":"Jlakroken",
    "gn:country_code":"LR",
    "gn:dem":75,
    "gn:feature_class":"P",
    "gn:feature_code":"PPL",
    "gn:name":"Jlakroken",
    "gn:population":0,
    "gn:timezone":"Africa/Monrovia",
    "iso:country":"LR",
    "name:und_x_variant":[
        "Otikehn"
    ],
    "wof:name":"Jlakroken",
    "wof:placetype":"locality"
},
  "geometry": {"coordinates":[-8.07262,4.73351],"type":"Point"}
}