{
  "type": "Feature",
  "properties": {
    "gn:admin1_code":"1.0",
    "gn:asciiname":"Vanwali",
    "gn:country_code":"LR",
    "gn:dem":201,
    "gn:feature_class":"P",
    "gn:feature_code":"PPL",
    "gn:name":"Vanwali",
    "gn:population":0,
    "gn:timezone":"Africa/Monrovia",
    "iso:country":"LR",
    "name:eng_x_preferred":[
        "Vanwali"
    ],
    "wof:name":"Vanwali",
    "wof:placetype":"locality"
},
  "geometry": {"coordinates":[-9.65713,6.67145],"type":"Point"}
}