{
  "type": "Feature",
  "properties": {
    "gn:admin1_code":"1.0",
    "gn:asciiname":"Kwoita",
    "gn:country_code":"LR",
    "gn:dem":233,
    "gn:feature_class":"P",
    "gn:feature_code":"PPL",
    "gn:name":"Kwoita",
    "gn:population":0,
    "gn:timezone":"Africa/Monrovia",
    "iso:country":"LR",
    "name:eng_x_preferred":[
        "Kwoita"
    ],
    "wof:name":"Kwoita",
    "wof:placetype":"locality"
},
  "geometry": {"coordinates":[-9.50369,6.63593],"type":"Point"}
}