{
  "type": "Feature",
  "properties": {
    "gn:admin1_code":"16.0",
    "gn:asciiname":"Kawrokehn",
    "gn:country_code":"LR",
    "gn:dem":26,
    "gn:feature_class":"P",
    "gn:feature_code":"PPL",
    "gn:name":"Kawrokehn",
    "gn:population":0,
    "gn:timezone":"Africa/Monrovia",
    "iso:country":"LR",
    "wof:name":"Kawrokehn",
    "wof:placetype":"locality"
},
  "geometry": {"coordinates":[-7.98809,4.70264],"type":"Point"}
}