{
  "type": "Feature",
  "properties": {
    "gn:admin1_code":"17.0",
    "gn:asciiname":"Voni",
    "gn:country_code":"LR",
    "gn:dem":149,
    "gn:feature_class":"P",
    "gn:feature_code":"PPL",
    "gn:name":"Voni",
    "gn:population":0,
    "gn:timezone":"Africa/Monrovia",
    "iso:country":"LR",
    "name:ceb_x_preferred":[
        "V\u00f3ni"
    ],
    "name:ell_x_preferred":[
        "\u0393\u03ba\u03b9\u03bf\u03ba\u03c7\u03ac\u03bd"
    ],
    "name:eng_x_preferred":[
        "Voni"
    ],
    "name:hye_x_preferred":[
        "\u054e\u0578\u0576\u056b"
    ],
    "name:pol_x_preferred":[
        "Woni"
    ],
    "name:por_x_preferred":[
        "Voni"
    ],
    "name:swe_x_preferred":[
        "V\u00f3ni"
    ],
    "name:urd_x_preferred":[
        "\u0624\u0646\u06cc"
    ],
    "wof:name":"Voni",
    "wof:placetype":"locality"
},
  "geometry": {"coordinates":[-10.28982,6.79697],"type":"Point"}
}