{
  "type": "Feature",
  "properties": {
    "gn:admin1_code":"17.0",
    "gn:asciiname":"Voni",
    "gn:country_code":"LR",
    "gn:dem":149,
    "gn:feature_class":"P",
    "gn:feature_code":"PPL",
    "gn:name":"Voni",
    "gn:population":0,
    "gn:timezone":"Africa/Monrovia",
    "iso:country":"LR",
    "name:eng_x_preferred":[
        "Voni"
    ],
    "wof:name":"Voni",
    "wof:placetype":"locality"
},
  "geometry": {"coordinates":[-10.28982,6.79697],"type":"Point"}
}