{
  "type": "Feature",
  "properties": {
    "gn:admin1_code":"16.0",
    "gn:asciiname":"Bassa",
    "gn:country_code":"LR",
    "gn:dem":50,
    "gn:feature_class":"P",
    "gn:feature_code":"PPL",
    "gn:name":"Bassa",
    "gn:population":0,
    "gn:timezone":"Africa/Monrovia",
    "iso:country":"LR",
    "wof:name":"Bassa",
    "wof:placetype":"locality"
},
  "geometry": {"coordinates":[-8.40026,4.78793],"type":"Point"}
}