{
  "type": "Feature",
  "properties": {
    "gn:admin1_code":"16.0",
    "gn:asciiname":"Bassa",
    "gn:country_code":"LR",
    "gn:dem":50,
    "gn:feature_class":"P",
    "gn:feature_code":"PPL",
    "gn:name":"Bassa",
    "gn:population":0,
    "gn:timezone":"Africa/Monrovia",
    "iso:country":"LR",
    "name:cat_x_preferred":[
        "Bassa"
    ],
    "name:ceb_x_preferred":[
        "Bassa"
    ],
    "name:deu_x_preferred":[
        "Bassa"
    ],
    "name:fra_x_preferred":[
        "Bassa"
    ],
    "name:ita_x_preferred":[
        "Bassa"
    ],
    "name:rus_x_preferred":[
        "\u0411\u0430\u0441\u0441\u0430"
    ],
    "name:srp_x_preferred":[
        "Bassa"
    ],
    "name:swe_x_preferred":[
        "Bassa"
    ],
    "name:ukr_x_preferred":[
        "\u0411\u0430\u0441\u0441\u0430"
    ],
    "wof:name":"Bassa",
    "wof:placetype":"locality"
},
  "geometry": {"coordinates":[-8.40026,4.78793],"type":"Point"}
}