{
  "type": "Feature",
  "properties": {
    "gn:admin1_code":"20.0",
    "gn:asciiname":"Velezala",
    "gn:cc2":"LR",
    "gn:country_code":"LR",
    "gn:dem":514,
    "gn:feature_class":"P",
    "gn:feature_code":"PPL",
    "gn:name":"Velezala",
    "gn:population":0,
    "gn:timezone":"Africa/Monrovia",
    "iso:country":"LR",
    "name:und_x_variant":[
        "Vilisala",
        "Yezala",
        "Valasala",
        "Velezala"
    ],
    "wof:name":"Velezala",
    "wof:placetype":"locality"
},
  "geometry": {"coordinates":[-9.90389,8.36972],"type":"Point"}
}