{
  "type": "Feature",
  "properties": {
    "gn:admin1_code":"1.0",
    "gn:asciiname":"Bellemu",
    "gn:country_code":"LR",
    "gn:dem":266,
    "gn:feature_class":"P",
    "gn:feature_code":"PPL",
    "gn:name":"Bellemu",
    "gn:population":0,
    "gn:timezone":"Africa/Monrovia",
    "iso:country":"LR",
    "name:eng_x_preferred":[
        "Bellemu"
    ],
    "wof:name":"Bellemu",
    "wof:placetype":"locality"
},
  "geometry": {"coordinates":[-9.11851,7.20481],"type":"Point"}
}