{
  "type": "Feature",
  "properties": {
    "gn:admin1_code":"18.0",
    "gn:asciiname":"Gua Town",
    "gn:country_code":"LR",
    "gn:dem":178,
    "gn:feature_class":"P",
    "gn:feature_code":"PPL",
    "gn:name":"Gua Town",
    "gn:population":0,
    "gn:timezone":"Africa/Monrovia",
    "iso:country":"LR",
    "name:und_x_variant":[
        "Guabli",
        "Guata",
        "Gua Town"
    ],
    "wof:name":"Gua Town",
    "wof:placetype":"locality"
},
  "geometry": {"coordinates":[-9.25897,6.19814],"type":"Point"}
}