{
  "type": "Feature",
  "properties": {
    "gn:admin1_code":"20.0",
    "gn:asciiname":"Kialima",
    "gn:cc2":"LR",
    "gn:country_code":"LR",
    "gn:dem":438,
    "gn:feature_class":"P",
    "gn:feature_code":"PPL",
    "gn:name":"Kialima",
    "gn:population":0,
    "gn:timezone":"Africa/Monrovia",
    "iso:country":"LR",
    "name:und_x_variant":[
        "Kialema",
        "Kialima"
    ],
    "wof:name":"Kialima",
    "wof:placetype":"locality"
},
  "geometry": {"coordinates":[-10.25278,8.46028],"type":"Point"}
}