{
  "type": "Feature",
  "properties": {
    "gn:admin1_code":"11.0",
    "gn:asciiname":"Joekpor",
    "gn:country_code":"LR",
    "gn:dem":123,
    "gn:feature_class":"P",
    "gn:feature_code":"PPL",
    "gn:name":"Joekpor",
    "gn:population":0,
    "gn:timezone":"Africa/Monrovia",
    "iso:country":"LR",
    "name:und_x_variant":[
        "Ashford Village"
    ],
    "wof:name":"Joekpor",
    "wof:placetype":"locality"
},
  "geometry": {"coordinates":[-9.73634,6.2871],"type":"Point"}
}