{
  "type": "Feature",
  "properties": {
    "gn:admin1_code":"9.0",
    "gn:asciiname":"Jesseple",
    "gn:country_code":"LR",
    "gn:dem":271,
    "gn:feature_class":"P",
    "gn:feature_code":"PPL",
    "gn:name":"Jesseple",
    "gn:population":0,
    "gn:timezone":"Africa/Monrovia",
    "iso:country":"LR",
    "wof:name":"Jesseple",
    "wof:placetype":"locality"
},
  "geometry": {"coordinates":[-8.70222,6.72139],"type":"Point"}
}