{
  "type": "Feature",
  "properties": {
    "gn:admin1_code":"1.0",
    "gn:asciiname":"Sama",
    "gn:country_code":"LR",
    "gn:dem":145,
    "gn:feature_class":"P",
    "gn:feature_code":"PPL",
    "gn:name":"Sama",
    "gn:population":0,
    "gn:timezone":"Africa/Monrovia",
    "iso:country":"LR",
    "name:ast_x_preferred":[
        "Sama"
    ],
    "name:ceb_x_preferred":[
        "Sama"
    ],
    "name:deu_x_preferred":[
        "Sama"
    ],
    "name:eng_x_preferred":[
        "Sama"
    ],
    "name:fin_x_preferred":[
        "Sama"
    ],
    "name:fra_x_preferred":[
        "Sama"
    ],
    "name:ind_x_preferred":[
        "Sama"
    ],
    "name:ita_x_preferred":[
        "Sama"
    ],
    "name:por_x_preferred":[
        "Sama"
    ],
    "name:spa_x_preferred":[
        "Sama"
    ],
    "name:swe_x_preferred":[
        "Sama"
    ],
    "name:urd_x_preferred":[
        "\u0633\u0627\u0645\u0627"
    ],
    "wof:name":"Sama",
    "wof:placetype":"locality"
},
  "geometry": {"coordinates":[-10.36254,6.89313],"type":"Point"}
}