{
  "type": "Feature",
  "properties": {
    "gn:admin1_code":"19.0",
    "gn:asciiname":"Baawu",
    "gn:country_code":"LR",
    "gn:dem":215,
    "gn:feature_class":"P",
    "gn:feature_code":"PPL",
    "gn:name":"Baawu",
    "gn:population":0,
    "gn:timezone":"Africa/Monrovia",
    "iso:country":"LR",
    "wof:name":"Baawu",
    "wof:placetype":"locality"
},
  "geometry": {"coordinates":[-7.73278,5.88194],"type":"Point"}
}