{
  "type": "Feature",
  "properties": {
    "gn:admin1_code":"21.0",
    "gn:asciiname":"Vaina",
    "gn:country_code":"LR",
    "gn:dem":204,
    "gn:feature_class":"P",
    "gn:feature_code":"PPL",
    "gn:name":"Vaina",
    "gn:population":0,
    "gn:timezone":"Africa/Monrovia",
    "iso:country":"LR",
    "wof:name":"Vaina",
    "wof:placetype":"locality"
},
  "geometry": {"coordinates":[-10.05083,7.12167],"type":"Point"}
}