{
  "type": "Feature",
  "properties": {
    "gn:admin1_code":"14.0",
    "gn:asciiname":"Division Fifteen Camp",
    "gn:country_code":"LR",
    "gn:dem":35,
    "gn:feature_class":"P",
    "gn:feature_code":"PPL",
    "gn:name":"Division Fifteen Camp",
    "gn:population":0,
    "gn:timezone":"Africa/Monrovia",
    "iso:country":"LR",
    "name:und_x_variant":[
        "Division 15 Camp",
        "Division Fifteen Camp"
    ],
    "wof:name":"Division Fifteen Camp",
    "wof:placetype":"locality"
},
  "geometry": {"coordinates":[-10.45968,6.39761],"type":"Point"}
}