{
  "type": "Feature",
  "properties": {
    "gn:admin1_code":"12.0",
    "gn:asciiname":"Kohnma",
    "gn:country_code":"LR",
    "gn:dem":55,
    "gn:feature_class":"P",
    "gn:feature_code":"PPL",
    "gn:name":"Kohnma",
    "gn:population":0,
    "gn:timezone":"Africa/Monrovia",
    "iso:country":"LR",
    "wof:name":"Kohnma",
    "wof:placetype":"locality"
},
  "geometry": {"coordinates":[-11.1029,6.75238],"type":"Point"}
}