{
  "type": "Feature",
  "properties": {
    "gn:admin1_code":"19.0",
    "gn:asciiname":"Baka",
    "gn:country_code":"LR",
    "gn:dem":151,
    "gn:feature_class":"P",
    "gn:feature_code":"PPL",
    "gn:name":"Baka",
    "gn:population":0,
    "gn:timezone":"Africa/Monrovia",
    "iso:country":"LR",
    "wof:name":"Baka",
    "wof:placetype":"locality"
},
  "geometry": {"coordinates":[-8.78667,6.18417],"type":"Point"}
}