{
  "type": "Feature",
  "properties": {
    "gn:admin1_code":"22.0",
    "gn:asciiname":"Taryaken",
    "gn:country_code":"LR",
    "gn:dem":147,
    "gn:feature_class":"P",
    "gn:feature_code":"PPL",
    "gn:name":"Taryaken",
    "gn:population":0,
    "gn:timezone":"Africa/Monrovia",
    "iso:country":"LR",
    "name:und_x_variant":[
        "Tytiake",
        "Tyiaken",
        "Taryaken"
    ],
    "wof:name":"Taryaken",
    "wof:placetype":"locality"
},
  "geometry": {"coordinates":[-7.81911,4.9048],"type":"Point"}
}