{
  "type": "Feature",
  "properties": {
    "gn:admin1_code":"21.0",
    "gn:asciiname":"Kalata",
    "gn:country_code":"LR",
    "gn:dem":402,
    "gn:feature_class":"P",
    "gn:feature_code":"PPL",
    "gn:name":"Kalata",
    "gn:population":0,
    "gn:timezone":"Africa/Monrovia",
    "iso:country":"LR",
    "name:und_x_variant":[
        "Kahalta",
        "Kata",
        "Kalata"
    ],
    "wof:name":"Kalata",
    "wof:placetype":"locality"
},
  "geometry": {"coordinates":[-9.96667,7.68333],"type":"Point"}
}