{
  "type": "Feature",
  "properties": {
    "gn:admin1_code":"17.0",
    "gn:asciiname":"Peabody Farm",
    "gn:country_code":"LR",
    "gn:dem":12,
    "gn:feature_class":"P",
    "gn:feature_code":"PPL",
    "gn:name":"Peabody Farm",
    "gn:population":0,
    "gn:timezone":"Africa/Monrovia",
    "iso:country":"LR",
    "name:und_x_variant":[
        "Peabody Farm (1)",
        "Peabody Farm One"
    ],
    "wof:name":"Peabody Farm",
    "wof:placetype":"locality"
},
  "geometry": {"coordinates":[-10.34765,6.21886],"type":"Point"}
}