{
  "type": "Feature",
  "properties": {
    "gn:admin1_code":"11.0",
    "gn:asciiname":"Harlandsville",
    "gn:cc2":"LR",
    "gn:country_code":"LR",
    "gn:dem":17,
    "gn:feature_class":"P",
    "gn:feature_code":"PPL",
    "gn:name":"Harlandsville",
    "gn:population":0,
    "gn:timezone":"Africa/Monrovia",
    "iso:country":"LR",
    "name:und_x_variant":[
        "Hartlandsville",
        "Marlandville",
        "Harlandville",
        "Harlandsville"
    ],
    "wof:name":"Harlandsville",
    "wof:placetype":"locality"
},
  "geometry": {"coordinates":[-9.96667,5.88333],"type":"Point"}
}