{
  "type": "Feature",
  "properties": {
    "gn:admin1_code":"22.0",
    "gn:asciiname":"Geealke",
    "gn:country_code":"LR",
    "gn:dem":119,
    "gn:feature_class":"P",
    "gn:feature_code":"PPL",
    "gn:name":"Geealke",
    "gn:population":0,
    "gn:timezone":"Africa/Monrovia",
    "iso:country":"LR",
    "name:und_x_variant":[
        "Giake",
        "Geealke"
    ],
    "wof:name":"Geealke",
    "wof:placetype":"locality"
},
  "geometry": {"coordinates":[-7.69278,5.03306],"type":"Point"}
}