{
  "type": "Feature",
  "properties": {
    "gn:admin1_code":"12.0",
    "gn:asciiname":"Be Parker",
    "gn:country_code":"LR",
    "gn:dem":107,
    "gn:feature_class":"P",
    "gn:feature_code":"PPL",
    "gn:name":"Be Parker",
    "gn:population":0,
    "gn:timezone":"Africa/Monrovia",
    "iso:country":"LR",
    "wof:name":"Be Parker",
    "wof:placetype":"locality"
},
  "geometry": {"coordinates":[-10.86361,7.04389],"type":"Point"}
}