{
  "type": "Feature",
  "properties": {
    "gn:admin1_code":"18.0",
    "gn:asciiname":"Zargay Guah Town",
    "gn:country_code":"LR",
    "gn:dem":186,
    "gn:feature_class":"P",
    "gn:feature_code":"PPL",
    "gn:name":"Zargay Guah Town",
    "gn:population":0,
    "gn:timezone":"Africa/Monrovia",
    "iso:country":"LR",
    "name:und_x_variant":[
        "Zega",
        "Zeget",
        "Zargay Guah Town"
    ],
    "wof:name":"Zargay Guah Town",
    "wof:placetype":"locality"
},
  "geometry": {"coordinates":[-9.23043,6.18672],"type":"Point"}
}