{
  "type": "Feature",
  "properties": {
    "gn:admin1_code":"9.0",
    "gn:asciiname":"Nembo",
    "gn:country_code":"LR",
    "gn:dem":258,
    "gn:feature_class":"P",
    "gn:feature_code":"PPL",
    "gn:name":"Nembo",
    "gn:population":0,
    "gn:timezone":"Africa/Monrovia",
    "iso:country":"LR",
    "name:und_x_variant":[
        "Yriah",
        "Yreah"
    ],
    "wof:name":"Nembo",
    "wof:placetype":"locality"
},
  "geometry": {"coordinates":[-8.84408,6.52431],"type":"Point"}
}