{
  "type": "Feature",
  "properties": {
    "gn:admin1_code":"17.0",
    "gn:asciiname":"Harris",
    "gn:cc2":"LR",
    "gn:country_code":"LR",
    "gn:dem":216,
    "gn:feature_class":"P",
    "gn:feature_code":"PPL",
    "gn:name":"Harris",
    "gn:population":0,
    "gn:timezone":"Africa/Monrovia",
    "iso:country":"LR",
    "name:bel_x_preferred":[
        "\u0425\u0430\u0440\u044b\u0441"
    ],
    "name:bre_x_preferred":[
        "Harris"
    ],
    "name:cat_x_preferred":[
        "Harris"
    ],
    "name:ceb_x_preferred":[
        "Harris"
    ],
    "name:ces_x_preferred":[
        "Harris"
    ],
    "name:deu_x_preferred":[
        "Harris"
    ],
    "name:fin_x_preferred":[
        "Harris"
    ],
    "name:fra_x_preferred":[
        "Harris"
    ],
    "name:heb_x_preferred":[
        "\u05d4\u05d0\u05e8\u05d9\u05e1"
    ],
    "name:ita_x_preferred":[
        "Harris"
    ],
    "name:jpn_x_preferred":[
        "\u30cf\u30ea\u30b9"
    ],
    "name:kor_x_preferred":[
        "\ud574\ub9ac\uc2a4"
    ],
    "name:lav_x_preferred":[
        "Heriss"
    ],
    "name:nld_x_preferred":[
        "Harris"
    ],
    "name:pol_x_preferred":[
        "Harris"
    ],
    "name:por_x_preferred":[
        "Harris"
    ],
    "name:rus_x_preferred":[
        "\u0425\u0430\u0440\u0440\u0438\u0441"
    ],
    "name:spa_x_preferred":[
        "Harris"
    ],
    "name:swe_x_preferred":[
        "Harris"
    ],
    "name:ukr_x_preferred":[
        "\u0413\u0430\u0440\u0440\u0456\u0441"
    ],
    "name:und_x_variant":[
        "Harris Town",
        "Harris"
    ],
    "name:vie_x_preferred":[
        "Harris"
    ],
    "name:vol_x_preferred":[
        "Harris"
    ],
    "wof:name":"Harris",
    "wof:placetype":"locality"
},
  "geometry": {"coordinates":[-9.93333,6.66667],"type":"Point"}
}