{
  "type": "Feature",
  "properties": {
    "gn:admin1_code":"17.0",
    "gn:asciiname":"Harris",
    "gn:cc2":"LR",
    "gn:country_code":"LR",
    "gn:dem":216,
    "gn:feature_class":"P",
    "gn:feature_code":"PPL",
    "gn:name":"Harris",
    "gn:population":0,
    "gn:timezone":"Africa/Monrovia",
    "iso:country":"LR",
    "name:und_x_variant":[
        "Harris Town",
        "Harris"
    ],
    "wof:name":"Harris",
    "wof:placetype":"locality"
},
  "geometry": {"coordinates":[-9.93333,6.66667],"type":"Point"}
}