{
  "type": "Feature",
  "properties": {
    "gn:admin1_code":"1.0",
    "gn:asciiname":"Yokole",
    "gn:country_code":"LR",
    "gn:dem":304,
    "gn:feature_class":"P",
    "gn:feature_code":"PPL",
    "gn:name":"Yokole",
    "gn:population":0,
    "gn:timezone":"Africa/Monrovia",
    "iso:country":"LR",
    "wof:name":"Yokole",
    "wof:placetype":"locality"
},
  "geometry": {"coordinates":[-9.75694,6.96528],"type":"Point"}
}