{
  "type": "Feature",
  "properties": {
    "gn:admin1_code":"20.0",
    "gn:asciiname":"Bitiba",
    "gn:country_code":"LR",
    "gn:dem":570,
    "gn:feature_class":"P",
    "gn:feature_code":"PPL",
    "gn:name":"Bitiba",
    "gn:population":0,
    "gn:timezone":"Africa/Monrovia",
    "iso:country":"LR",
    "wof:name":"Bitiba",
    "wof:placetype":"locality"
},
  "geometry": {"coordinates":[-9.8375,8.245],"type":"Point"}
}