{
  "type": "Feature",
  "properties": {
    "gn:admin1_code":"1.0",
    "gn:asciiname":"Gomenay",
    "gn:country_code":"LR",
    "gn:dem":244,
    "gn:feature_class":"P",
    "gn:feature_code":"PPL",
    "gn:name":"Gomenay",
    "gn:population":0,
    "gn:timezone":"Africa/Monrovia",
    "iso:country":"LR",
    "name:eng_x_preferred":[
        "Gomenay"
    ],
    "wof:name":"Gomenay",
    "wof:placetype":"locality"
},
  "geometry": {"coordinates":[-9.42145,6.81658],"type":"Point"}
}