{
  "type": "Feature",
  "properties": {
    "gn:admin1_code":"22.0",
    "gn:asciiname":"Killepo Kanweaken",
    "gn:country_code":"LR",
    "gn:dem":262,
    "gn:feature_class":"P",
    "gn:feature_code":"PPL",
    "gn:name":"Killepo Kanweaken",
    "gn:population":0,
    "gn:timezone":"Africa/Monrovia",
    "iso:country":"LR",
    "name:und_x_variant":[
        "Siagbokohn",
        "Kelipo-Kanbueke",
        "Kelipo-Kanwiekehn",
        "Killepo Kanweaken"
    ],
    "wof:name":"Killepo Kanweaken",
    "wof:placetype":"locality"
},
  "geometry": {"coordinates":[-8.01977,5.49578],"type":"Point"}
}