{
  "type": "Feature",
  "properties": {
    "gn:admin1_code":"10.0",
    "gn:asciiname":"Gotu",
    "gn:country_code":"LR",
    "gn:dem":26,
    "gn:feature_class":"P",
    "gn:feature_code":"PPL",
    "gn:name":"Gotu",
    "gn:population":0,
    "gn:timezone":"Africa/Monrovia",
    "iso:country":"LR",
    "wof:name":"Gotu",
    "wof:placetype":"locality"
},
  "geometry": {"coordinates":[-8.71824,4.93883],"type":"Point"}
}