{
  "type": "Feature",
  "properties": {
    "gn:admin1_code":"16.0",
    "gn:asciiname":"Chenwrinken",
    "gn:country_code":"LR",
    "gn:dem":103,
    "gn:feature_class":"P",
    "gn:feature_code":"PPL",
    "gn:name":"Chenwrinken",
    "gn:population":0,
    "gn:timezone":"Africa/Monrovia",
    "iso:country":"LR",
    "name:und_x_variant":[
        "Chonlekehn",
        "Chonwlekehn",
        "Chewreken",
        "Chenwrinken",
        "Chonwiekehn"
    ],
    "wof:name":"Chenwrinken",
    "wof:placetype":"locality"
},
  "geometry": {"coordinates":[-8.1583,4.95826],"type":"Point"}
}