{
  "type": "Feature",
  "properties": {
    "gn:admin1_code":"19.0",
    "gn:asciiname":"Kwiti",
    "gn:country_code":"LR",
    "gn:dem":191,
    "gn:feature_class":"P",
    "gn:feature_code":"PPL",
    "gn:name":"Kwiti",
    "gn:population":0,
    "gn:timezone":"Africa/Monrovia",
    "iso:country":"LR",
    "wof:name":"Kwiti",
    "wof:placetype":"locality"
},
  "geometry": {"coordinates":[-7.53376,5.82876],"type":"Point"}
}