{
  "type": "Feature",
  "properties": {
    "gn:admin1_code":"15.0",
    "gn:asciiname":"Zomo",
    "gn:country_code":"LR",
    "gn:dem":55,
    "gn:feature_class":"P",
    "gn:feature_code":"PPL",
    "gn:name":"Zomo",
    "gn:population":0,
    "gn:timezone":"Africa/Monrovia",
    "iso:country":"LR",
    "wof:name":"Zomo",
    "wof:placetype":"locality"
},
  "geometry": {"coordinates":[-10.66699,6.62032],"type":"Point"}
}