{
  "type": "Feature",
  "properties": {
    "gn:admin1_code":"11.0",
    "gn:asciiname":"Bebli",
    "gn:cc2":"LR",
    "gn:country_code":"LR",
    "gn:dem":118,
    "gn:feature_class":"P",
    "gn:feature_code":"PPL",
    "gn:name":"Bebli",
    "gn:population":0,
    "gn:timezone":"Africa/Monrovia",
    "iso:country":"LR",
    "name:und_x_variant":[
        "Tipennybli",
        "Tepenibli",
        "Bebli"
    ],
    "wof:name":"Bebli",
    "wof:placetype":"locality"
},
  "geometry": {"coordinates":[-9.93333,6.28333],"type":"Point"}
}