{
  "type": "Feature",
  "properties": {
    "gn:admin1_code":"11.0",
    "gn:asciiname":"Begego",
    "gn:cc2":"LR",
    "gn:country_code":"LR",
    "gn:dem":18,
    "gn:feature_class":"P",
    "gn:feature_code":"PPL",
    "gn:name":"Begego",
    "gn:population":0,
    "gn:timezone":"Africa/Monrovia",
    "iso:country":"LR",
    "name:und_x_variant":[
        "Klo",
        "Bajego",
        "Begego"
    ],
    "wof:name":"Begego",
    "wof:placetype":"locality"
},
  "geometry": {"coordinates":[-10.23333,6.08333],"type":"Point"}
}