{
  "type": "Feature",
  "properties": {
    "gn:admin1_code":"13.0",
    "gn:asciiname":"Woleke Number Two",
    "gn:country_code":"LR",
    "gn:dem":13,
    "gn:feature_class":"P",
    "gn:feature_code":"PPL",
    "gn:name":"Woleke Number Two",
    "gn:population":0,
    "gn:timezone":"Africa/Monrovia",
    "iso:country":"LR",
    "name:und_x_variant":[
        "Woleke",
        "Waluke"
    ],
    "wof:name":"Woleke Number Two",
    "wof:placetype":"locality"
},
  "geometry": {"coordinates":[-7.55832,4.37442],"type":"Point"}
}