{
  "type": "Feature",
  "properties": {
    "gn:admin1_code":"1.0",
    "gn:asciiname":"Nyawellie",
    "gn:country_code":"LR",
    "gn:dem":216,
    "gn:feature_class":"P",
    "gn:feature_code":"PPL",
    "gn:name":"Nyawellie",
    "gn:population":0,
    "gn:timezone":"Africa/Monrovia",
    "iso:country":"LR",
    "wof:name":"Nyawellie",
    "wof:placetype":"locality"
},
  "geometry": {"coordinates":[-9.9193,7.12052],"type":"Point"}
}