{
  "type": "Feature",
  "properties": {
    "gn:admin1_code":"10.0",
    "gn:asciiname":"Cheplen",
    "gn:country_code":"LR",
    "gn:dem":57,
    "gn:feature_class":"P",
    "gn:feature_code":"PPL",
    "gn:name":"Cheplen",
    "gn:population":0,
    "gn:timezone":"Africa/Monrovia",
    "iso:country":"LR",
    "wof:name":"Cheplen",
    "wof:placetype":"locality"
},
  "geometry": {"coordinates":[-8.74316,5.03],"type":"Point"}
}