{
  "type": "Feature",
  "properties": {
    "gn:admin1_code":"18.0",
    "gn:asciiname":"Nibwabli",
    "gn:country_code":"LR",
    "gn:dem":9,
    "gn:feature_class":"P",
    "gn:feature_code":"PPL",
    "gn:name":"Nibwabli",
    "gn:population":0,
    "gn:timezone":"Africa/Monrovia",
    "iso:country":"LR",
    "name:und_x_variant":[
        "Gbissegi",
        "Gbesejibli",
        "Nibwabli"
    ],
    "wof:name":"Nibwabli",
    "wof:placetype":"locality"
},
  "geometry": {"coordinates":[-9.55043,5.47475],"type":"Point"}
}