{
  "type": "Feature",
  "properties": {
    "gn:admin1_code":"12.0",
    "gn:asciiname":"Najabo",
    "gn:country_code":"LR",
    "gn:dem":107,
    "gn:feature_class":"P",
    "gn:feature_code":"PPL",
    "gn:name":"Najabo",
    "gn:population":0,
    "gn:timezone":"Africa/Monrovia",
    "iso:country":"LR",
    "name:und_x_variant":[
        "Yaboi",
        "Yakpoi",
        "Najabo"
    ],
    "wof:name":"Najabo",
    "wof:placetype":"locality"
},
  "geometry": {"coordinates":[-10.80889,7.1075],"type":"Point"}
}