{
  "type": "Feature",
  "properties": {
    "gn:admin1_code":"20.0",
    "gn:asciiname":"Zalamai",
    "gn:cc2":"LR",
    "gn:country_code":"LR",
    "gn:dem":572,
    "gn:feature_class":"P",
    "gn:feature_code":"PPL",
    "gn:name":"Zalamai",
    "gn:population":0,
    "gn:timezone":"Africa/Monrovia",
    "iso:country":"LR",
    "name:und_x_variant":[
        "Jalamai",
        "Zalamai"
    ],
    "wof:name":"Zalamai",
    "wof:placetype":"locality"
},
  "geometry": {"coordinates":[-9.86167,8.35972],"type":"Point"}
}