{
  "type": "Feature",
  "properties": {
    "gn:admin1_code":"9.0",
    "gn:asciiname":"Makato",
    "gn:country_code":"LR",
    "gn:dem":450,
    "gn:feature_class":"P",
    "gn:feature_code":"PPL",
    "gn:name":"Makato",
    "gn:population":0,
    "gn:timezone":"Africa/Monrovia",
    "iso:country":"LR",
    "wof:name":"Makato",
    "wof:placetype":"locality"
},
  "geometry": {"coordinates":[-8.66278,7.41111],"type":"Point"}
}