{
  "type": "Feature",
  "properties": {
    "gn:admin1_code":"11.0",
    "gn:asciiname":"Koyta",
    "gn:country_code":"LR",
    "gn:dem":206,
    "gn:feature_class":"P",
    "gn:feature_code":"PPL",
    "gn:name":"Koyta",
    "gn:population":0,
    "gn:timezone":"Africa/Monrovia",
    "iso:country":"LR",
    "wof:name":"Koyta",
    "wof:placetype":"locality"
},
  "geometry": {"coordinates":[-9.69095,6.58237],"type":"Point"}
}