{
  "type": "Feature",
  "properties": {
    "gn:admin1_code":"11.0",
    "gn:asciiname":"Kahn",
    "gn:cc2":"LR",
    "gn:country_code":"LR",
    "gn:dem":181,
    "gn:feature_class":"P",
    "gn:feature_code":"PPL",
    "gn:name":"Kahn",
    "gn:population":0,
    "gn:timezone":"Africa/Monrovia",
    "iso:country":"LR",
    "name:und_x_variant":[
        "Karn",
        "Kondo",
        "Kahn"
    ],
    "wof:name":"Kahn",
    "wof:placetype":"locality"
},
  "geometry": {"coordinates":[-9.73333,6.51667],"type":"Point"}
}