{
  "type": "Feature",
  "properties": {
    "gn:admin1_code":"11.0",
    "gn:asciiname":"Bosibli",
    "gn:country_code":"LR",
    "gn:dem":173,
    "gn:feature_class":"P",
    "gn:feature_code":"PPL",
    "gn:name":"Bosibli",
    "gn:population":0,
    "gn:timezone":"Africa/Monrovia",
    "iso:country":"LR",
    "wof:name":"Bosibli",
    "wof:placetype":"locality"
},
  "geometry": {"coordinates":[-9.55,6.46667],"type":"Point"}
}