{
  "type": "Feature",
  "properties": {
    "gn:admin1_code":"17.0",
    "gn:asciiname":"Palmer Camp",
    "gn:country_code":"LR",
    "gn:dem":127,
    "gn:feature_class":"P",
    "gn:feature_code":"PPL",
    "gn:name":"Palmer Camp",
    "gn:population":0,
    "gn:timezone":"Africa/Monrovia",
    "iso:country":"LR",
    "name:eng_x_preferred":[
        "Palmer Camp"
    ],
    "wof:name":"Palmer Camp",
    "wof:placetype":"locality"
},
  "geometry": {"coordinates":[-10.36745,6.67705],"type":"Point"}
}