{
  "type": "Feature",
  "properties": {
    "gn:admin1_code":"21.0",
    "gn:asciiname":"Belle Yella",
    "gn:country_code":"LR",
    "gn:dem":223,
    "gn:feature_class":"P",
    "gn:feature_code":"PPL",
    "gn:name":"Belle Yella",
    "gn:population":0,
    "gn:timezone":"Africa/Monrovia",
    "iso:country":"LR",
    "name:und_x_variant":[
        "Belle Yela",
        "Belleyellah",
        "Belliyella",
        "Belliyela",
        "Beliyela",
        "Belle Yella"
    ],
    "wof:name":"Belle Yella",
    "wof:placetype":"locality"
},
  "geometry": {"coordinates":[-9.99833,7.37639],"type":"Point"}
}