{
  "type": "Feature",
  "properties": {
    "gn:admin1_code":"20.0",
    "gn:asciiname":"Vonema",
    "gn:cc2":"LR",
    "gn:country_code":"LR",
    "gn:dem":607,
    "gn:feature_class":"P",
    "gn:feature_code":"PPL",
    "gn:name":"Vonema",
    "gn:population":0,
    "gn:timezone":"Africa/Monrovia",
    "iso:country":"LR",
    "name:und_x_variant":[
        "Vonamai",
        "Vonema"
    ],
    "wof:name":"Vonema",
    "wof:placetype":"locality"
},
  "geometry": {"coordinates":[-9.75778,8.53361],"type":"Point"}
}