{
  "type": "Feature",
  "properties": {
    "gn:admin1_code":"13.0",
    "gn:asciiname":"Glofaken",
    "gn:country_code":"LR",
    "gn:dem":139,
    "gn:feature_class":"P",
    "gn:feature_code":"PPL",
    "gn:name":"Glofaken",
    "gn:population":0,
    "gn:timezone":"Africa/Monrovia",
    "iso:country":"LR",
    "name:und_x_variant":[
        "Grobake",
        "Gropake",
        "Glofaken",
        "Grobaken",
        "Camp King"
    ],
    "wof:name":"Glofaken",
    "wof:placetype":"locality"
},
  "geometry": {"coordinates":[-7.89908,4.94519],"type":"Point"}
}