{
  "type": "Feature",
  "properties": {
    "gn:admin1_code":"1.0",
    "gn:asciiname":"Gbarmue",
    "gn:country_code":"LR",
    "gn:dem":288,
    "gn:feature_class":"P",
    "gn:feature_code":"PPL",
    "gn:name":"Gbarmue",
    "gn:population":0,
    "gn:timezone":"Africa/Monrovia",
    "iso:country":"LR",
    "name:eng_x_preferred":[
        "Gbarmue"
    ],
    "name:und_x_variant":[
        "Bomo",
        "Gbarmu"
    ],
    "wof:name":"Gbarmue",
    "wof:placetype":"locality"
},
  "geometry": {"coordinates":[-9.40517,7.13251],"type":"Point"}
}