{
  "type": "Feature",
  "properties": {
    "gn:admin1_code":"11.0",
    "gn:asciiname":"Lisbli",
    "gn:country_code":"LR",
    "gn:dem":95,
    "gn:feature_class":"P",
    "gn:feature_code":"PPL",
    "gn:name":"Lisbli",
    "gn:population":0,
    "gn:timezone":"Africa/Monrovia",
    "iso:country":"LR",
    "wof:name":"Lisbli",
    "wof:placetype":"locality"
},
  "geometry": {"coordinates":[-10.04353,6.28045],"type":"Point"}
}