{
  "type": "Feature",
  "properties": {
    "gn:admin1_code":"19.0",
    "gn:asciiname":"Teetee",
    "gn:country_code":"LR",
    "gn:dem":261,
    "gn:feature_class":"P",
    "gn:feature_code":"PPL",
    "gn:name":"Teetee",
    "gn:population":0,
    "gn:timezone":"Africa/Monrovia",
    "iso:country":"LR",
    "wof:name":"Teetee",
    "wof:placetype":"locality"
},
  "geometry": {"coordinates":[-8.33006,6.19377],"type":"Point"}
}