{
  "type": "Feature",
  "properties": {
    "gn:admin1_code":"20.0",
    "gn:asciiname":"Bami",
    "gn:country_code":"LR",
    "gn:dem":487,
    "gn:feature_class":"P",
    "gn:feature_code":"PPL",
    "gn:name":"Bami",
    "gn:population":0,
    "gn:timezone":"Africa/Monrovia",
    "iso:country":"LR",
    "name:ceb_x_preferred":[
        "Bami"
    ],
    "name:swe_x_preferred":[
        "Bami"
    ],
    "wof:name":"Bami",
    "wof:placetype":"locality"
},
  "geometry": {"coordinates":[-10.06667,8.45],"type":"Point"}
}