{
  "type": "Feature",
  "properties": {
    "gn:admin1_code":"14.0",
    "gn:asciiname":"Laagbe",
    "gn:country_code":"LR",
    "gn:dem":15,
    "gn:feature_class":"P",
    "gn:feature_code":"PPL",
    "gn:name":"Laagbe",
    "gn:population":0,
    "gn:timezone":"Africa/Monrovia",
    "iso:country":"LR",
    "wof:name":"Laagbe",
    "wof:placetype":"locality"
},
  "geometry": {"coordinates":[-10.93333,6.55],"type":"Point"}
}