{
  "type": "Feature",
  "properties": {
    "gn:admin1_code":"15.0",
    "gn:asciiname":"Be Seke",
    "gn:country_code":"LR",
    "gn:dem":36,
    "gn:feature_class":"P",
    "gn:feature_code":"PPL",
    "gn:name":"Be Seke",
    "gn:population":0,
    "gn:timezone":"Africa/Monrovia",
    "iso:country":"LR",
    "wof:name":"Be Seke",
    "wof:placetype":"locality"
},
  "geometry": {"coordinates":[-10.91667,6.56667],"type":"Point"}
}