{
  "type": "Feature",
  "properties": {
    "gn:admin1_code":"20.0",
    "gn:asciiname":"Mbaloma",
    "gn:cc2":"LR",
    "gn:country_code":"LR",
    "gn:dem":463,
    "gn:feature_class":"P",
    "gn:feature_code":"PPL",
    "gn:name":"Mbaloma",
    "gn:population":0,
    "gn:timezone":"Africa/Monrovia",
    "iso:country":"LR",
    "name:und_x_variant":[
        "Baroma",
        "Mbaloma"
    ],
    "wof:name":"Mbaloma",
    "wof:placetype":"locality"
},
  "geometry": {"coordinates":[-10.12056,7.88556],"type":"Point"}
}