{
  "type": "Feature",
  "properties": {
    "gn:admin1_code":"11.0",
    "gn:asciiname":"Gagabli",
    "gn:country_code":"LR",
    "gn:dem":73,
    "gn:feature_class":"P",
    "gn:feature_code":"PPL",
    "gn:name":"Gagabli",
    "gn:population":0,
    "gn:timezone":"Africa/Monrovia",
    "iso:country":"LR",
    "wof:name":"Gagabli",
    "wof:placetype":"locality"
},
  "geometry": {"coordinates":[-9.77511,5.95675],"type":"Point"}
}