{
  "type": "Feature",
  "properties": {
    "gn:admin1_code":"21.0",
    "gn:asciiname":"Lowoma",
    "gn:country_code":"LR",
    "gn:dem":219,
    "gn:feature_class":"P",
    "gn:feature_code":"PPL",
    "gn:name":"Lowoma",
    "gn:population":0,
    "gn:timezone":"Africa/Monrovia",
    "iso:country":"LR",
    "name:und_x_variant":[
        "Flomo Town",
        "Lowoma"
    ],
    "wof:name":"Lowoma",
    "wof:placetype":"locality"
},
  "geometry": {"coordinates":[-10.16861,7.21306],"type":"Point"}
}