{
  "type": "Feature",
  "properties": {
    "gn:admin1_code":"16.0",
    "gn:asciiname":"Sasstown",
    "gn:country_code":"LR",
    "gn:dem":9,
    "gn:feature_class":"P",
    "gn:feature_code":"PPL",
    "gn:name":"Sasstown",
    "gn:population":0,
    "gn:timezone":"Africa/Monrovia",
    "iso:country":"LR",
    "name:und_x_variant":[
        "Sess Town",
        "Sasstown"
    ],
    "wof:name":"Sasstown",
    "wof:placetype":"locality"
},
  "geometry": {"coordinates":[-8.42819,4.66343],"type":"Point"}
}