{
  "type": "Feature",
  "properties": {
    "gn:admin1_code":"19.0",
    "gn:asciiname":"Gready",
    "gn:country_code":"LR",
    "gn:dem":218,
    "gn:feature_class":"P",
    "gn:feature_code":"PPL",
    "gn:name":"Gready",
    "gn:population":0,
    "gn:timezone":"Africa/Monrovia",
    "iso:country":"LR",
    "wof:name":"Gready",
    "wof:placetype":"locality"
},
  "geometry": {"coordinates":[-7.90923,6.22415],"type":"Point"}
}