{
  "type": "Feature",
  "properties": {
    "gn:admin1_code":"20.0",
    "gn:asciiname":"Tengbelahun",
    "gn:country_code":"LR",
    "gn:dem":498,
    "gn:feature_class":"P",
    "gn:feature_code":"PPL",
    "gn:name":"Tengbelahun",
    "gn:population":0,
    "gn:timezone":"Africa/Monrovia",
    "iso:country":"LR",
    "wof:name":"Tengbelahun",
    "wof:placetype":"locality"
},
  "geometry": {"coordinates":[-10.06667,8.05],"type":"Point"}
}