{
  "type": "Feature",
  "properties": {
    "gn:admin1_code":"1.0",
    "gn:asciiname":"Quoipa",
    "gn:country_code":"LR",
    "gn:dem":212,
    "gn:feature_class":"P",
    "gn:feature_code":"PPL",
    "gn:name":"Quoipa",
    "gn:population":0,
    "gn:timezone":"Africa/Monrovia",
    "iso:country":"LR",
    "name:eng_x_preferred":[
        "Quoipa"
    ],
    "name:und_x_variant":[
        "Kueipa",
        "Tuota"
    ],
    "wof:name":"Quoipa",
    "wof:placetype":"locality"
},
  "geometry": {"coordinates":[-9.13693,6.80756],"type":"Point"}
}