{
  "type": "Feature",
  "properties": {
    "gn:admin1_code":"15.0",
    "gn:asciiname":"Thompson Farm",
    "gn:country_code":"LR",
    "gn:dem":53,
    "gn:feature_class":"P",
    "gn:feature_code":"PPL",
    "gn:name":"Thompson Farm",
    "gn:population":0,
    "gn:timezone":"Africa/Monrovia",
    "iso:country":"LR",
    "name:deu_x_preferred":[
        "Thompson Farm"
    ],
    "wof:name":"Thompson Farm",
    "wof:placetype":"locality"
},
  "geometry": {"coordinates":[-10.85989,6.71246],"type":"Point"}
}