{
  "type": "Feature",
  "properties": {
    "gn:admin1_code":"20.0",
    "gn:asciiname":"Mosesta",
    "gn:country_code":"LR",
    "gn:dem":305,
    "gn:feature_class":"P",
    "gn:feature_code":"PPL",
    "gn:name":"Mosesta",
    "gn:population":0,
    "gn:timezone":"Africa/Monrovia",
    "iso:country":"LR",
    "name:eng_x_preferred":[
        "Mosesta"
    ],
    "wof:name":"Mosesta",
    "wof:placetype":"locality"
},
  "geometry": {"coordinates":[-9.48333,7.38333],"type":"Point"}
}