{
  "type": "Feature",
  "properties": {
    "gn:admin1_code":"16.0",
    "gn:asciiname":"Jarjloken",
    "gn:country_code":"LR",
    "gn:dem":142,
    "gn:feature_class":"P",
    "gn:feature_code":"PPL",
    "gn:name":"Jarjloken",
    "gn:population":0,
    "gn:timezone":"Africa/Monrovia",
    "iso:country":"LR",
    "name:und_x_variant":[
        "Jaahokehn",
        "Jeboken",
        "Jarjloken"
    ],
    "wof:name":"Jarjloken",
    "wof:placetype":"locality"
},
  "geometry": {"coordinates":[-8.11306,4.84417],"type":"Point"}
}