{
  "type": "Feature",
  "properties": {
    "gn:admin1_code":"17.0",
    "gn:asciiname":"Camp Waterfall",
    "gn:country_code":"LR",
    "gn:dem":218,
    "gn:feature_class":"P",
    "gn:feature_code":"PPL",
    "gn:name":"Camp Waterfall",
    "gn:population":0,
    "gn:timezone":"Africa/Monrovia",
    "iso:country":"LR",
    "name:eng_x_preferred":[
        "Camp Waterfall"
    ],
    "wof:name":"Camp Waterfall",
    "wof:placetype":"locality"
},
  "geometry": {"coordinates":[-10.32964,6.81142],"type":"Point"}
}