{
  "type": "Feature",
  "properties": {
    "gn:admin1_code":"19.0",
    "gn:asciiname":"Padeka Town",
    "gn:country_code":"LR",
    "gn:dem":238,
    "gn:feature_class":"P",
    "gn:feature_code":"PPL",
    "gn:name":"Padeka Town",
    "gn:population":0,
    "gn:timezone":"Africa/Monrovia",
    "iso:country":"LR",
    "wof:name":"Padeka Town",
    "wof:placetype":"locality"
},
  "geometry": {"coordinates":[-8.11091,6.21709],"type":"Point"}
}