{
  "type": "Feature",
  "properties": {
    "gn:admin1_code":"10.0",
    "gn:asciiname":"Droe",
    "gn:country_code":"LR",
    "gn:dem":34,
    "gn:feature_class":"P",
    "gn:feature_code":"PPL",
    "gn:name":"Droe",
    "gn:population":0,
    "gn:timezone":"Africa/Monrovia",
    "iso:country":"LR",
    "wof:name":"Droe",
    "wof:placetype":"locality"
},
  "geometry": {"coordinates":[-8.96667,5.11667],"type":"Point"}
}