{
  "type": "Feature",
  "properties": {
    "gn:admin1_code":"14.0",
    "gn:asciiname":"Gavlohn",
    "gn:country_code":"LR",
    "gn:dem":14,
    "gn:feature_class":"P",
    "gn:feature_code":"PPL",
    "gn:name":"Gavlohn",
    "gn:population":0,
    "gn:timezone":"Africa/Monrovia",
    "iso:country":"LR",
    "wof:name":"Gavlohn",
    "wof:placetype":"locality"
},
  "geometry": {"coordinates":[-10.65,6.35],"type":"Point"}
}