{
  "type": "Feature",
  "properties": {
    "gn:admin1_code":"12.0",
    "gn:asciiname":"Tolosine",
    "gn:country_code":"LR",
    "gn:dem":67,
    "gn:feature_class":"P",
    "gn:feature_code":"PPL",
    "gn:name":"Tolosine",
    "gn:population":0,
    "gn:timezone":"Africa/Monrovia",
    "iso:country":"LR",
    "wof:name":"Tolosine",
    "wof:placetype":"locality"
},
  "geometry": {"coordinates":[-11.05,6.88333],"type":"Point"}
}