{
  "type": "Feature",
  "properties": {
    "gn:admin1_code":"1.0",
    "gn:asciiname":"Goya",
    "gn:country_code":"LR",
    "gn:dem":249,
    "gn:feature_class":"P",
    "gn:feature_code":"PPL",
    "gn:name":"Goya",
    "gn:population":0,
    "gn:timezone":"Africa/Monrovia",
    "iso:country":"LR",
    "name:eng_x_preferred":[
        "Goya"
    ],
    "wof:name":"Goya",
    "wof:placetype":"locality"
},
  "geometry": {"coordinates":[-9.43333,6.86667],"type":"Point"}
}