{
  "type": "Feature",
  "properties": {
    "gn:admin1_code":"1.0",
    "gn:asciiname":"Goya",
    "gn:country_code":"LR",
    "gn:dem":249,
    "gn:feature_class":"P",
    "gn:feature_code":"PPL",
    "gn:name":"Goya",
    "gn:population":0,
    "gn:timezone":"Africa/Monrovia",
    "iso:country":"LR",
    "name:ben_x_preferred":[
        "\u0997\u09cb\u09df\u09be"
    ],
    "name:ell_x_preferred":[
        "\u0393\u03ba\u03cc\u03b3\u03b9\u03b1"
    ],
    "name:eng_x_preferred":[
        "Goya"
    ],
    "name:hin_x_preferred":[
        "\u0917\u094b\u092f\u093e"
    ],
    "name:ind_x_preferred":[
        "Goya"
    ],
    "name:kor_x_preferred":[
        "\uace0\uc57c"
    ],
    "name:urd_x_preferred":[
        "\u06af\u0648\u06cc\u0627"
    ],
    "name:vie_x_preferred":[
        "Goya"
    ],
    "wof:name":"Goya",
    "wof:placetype":"locality"
},
  "geometry": {"coordinates":[-9.43333,6.86667],"type":"Point"}
}