{
  "type": "Feature",
  "properties": {
    "gn:admin1_code":"15.0",
    "gn:asciiname":"Dasalamu",
    "gn:cc2":"LR",
    "gn:country_code":"LR",
    "gn:dem":65,
    "gn:feature_class":"P",
    "gn:feature_code":"PPL",
    "gn:name":"Dasalamu",
    "gn:population":0,
    "gn:timezone":"Africa/Monrovia",
    "iso:country":"LR",
    "name:und_x_variant":[
        "Dasalama",
        "Dasalamu"
    ],
    "wof:name":"Dasalamu",
    "wof:placetype":"locality"
},
  "geometry": {"coordinates":[-10.84556,6.91472],"type":"Point"}
}