{
  "type": "Feature",
  "properties": {
    "gn:admin1_code":"20.0",
    "gn:asciiname":"Genga",
    "gn:cc2":"LR",
    "gn:country_code":"LR",
    "gn:dem":422,
    "gn:feature_class":"P",
    "gn:feature_code":"PPL",
    "gn:name":"Genga",
    "gn:population":0,
    "gn:timezone":"Africa/Monrovia",
    "iso:country":"LR",
    "name:ceb_x_preferred":[
        "Genga"
    ],
    "name:deu_x_preferred":[
        "Genga"
    ],
    "name:fra_x_preferred":[
        "Genga"
    ],
    "name:swe_x_preferred":[
        "Genga"
    ],
    "name:und_x_variant":[
        "Geinga"
    ],
    "wof:name":"Genga",
    "wof:placetype":"locality"
},
  "geometry": {"coordinates":[-10.28194,8.37694],"type":"Point"}
}