{
  "type": "Feature",
  "properties": {
    "gn:admin1_code":"9.0",
    "gn:asciiname":"Tunbaye",
    "gn:country_code":"LR",
    "gn:dem":260,
    "gn:feature_class":"P",
    "gn:feature_code":"PPL",
    "gn:name":"Tunbaye",
    "gn:population":0,
    "gn:timezone":"Africa/Monrovia",
    "iso:country":"LR",
    "wof:name":"Tunbaye",
    "wof:placetype":"locality"
},
  "geometry": {"coordinates":[-9.00694,7.09472],"type":"Point"}
}