{
  "type": "Feature",
  "properties": {
    "gn:admin1_code":"11.0",
    "gn:asciiname":"Yammah Town",
    "gn:country_code":"LR",
    "gn:dem":153,
    "gn:feature_class":"P",
    "gn:feature_code":"PPL",
    "gn:name":"Yammah Town",
    "gn:population":0,
    "gn:timezone":"Africa/Monrovia",
    "iso:country":"LR",
    "wof:name":"Yammah Town",
    "wof:placetype":"locality"
},
  "geometry": {"coordinates":[-9.71211,6.23604],"type":"Point"}
}