{
  "type": "Feature",
  "properties": {
    "gn:admin1_code":"1.0",
    "gn:asciiname":"Se",
    "gn:country_code":"LR",
    "gn:dem":255,
    "gn:feature_class":"P",
    "gn:feature_code":"PPL",
    "gn:name":"Se",
    "gn:population":0,
    "gn:timezone":"Africa/Monrovia",
    "iso:country":"LR",
    "name:eng_x_preferred":[
        "Se"
    ],
    "wof:name":"Se",
    "wof:placetype":"locality"
},
  "geometry": {"coordinates":[-9.33333,6.91667],"type":"Point"}
}