{
  "type": "Feature",
  "properties": {
    "gn:admin1_code":"22.0",
    "gn:asciiname":"Mape Town",
    "gn:country_code":"LR",
    "gn:dem":176,
    "gn:feature_class":"P",
    "gn:feature_code":"PPL",
    "gn:name":"Mape Town",
    "gn:population":0,
    "gn:timezone":"Africa/Monrovia",
    "iso:country":"LR",
    "wof:name":"Mape Town",
    "wof:placetype":"locality"
},
  "geometry": {"coordinates":[-7.83111,5.23639],"type":"Point"}
}