{
  "type": "Feature",
  "properties": {
    "gn:admin1_code":"15.0",
    "gn:asciiname":"Moibasoni",
    "gn:country_code":"LR",
    "gn:dem":119,
    "gn:feature_class":"P",
    "gn:feature_code":"PPL",
    "gn:name":"Moibasoni",
    "gn:population":0,
    "gn:timezone":"Africa/Monrovia",
    "iso:country":"LR",
    "name:und_x_variant":[
        "Molubata",
        "Moluba",
        "Moibasoni"
    ],
    "wof:name":"Moibasoni",
    "wof:placetype":"locality"
},
  "geometry": {"coordinates":[-10.61689,6.75581],"type":"Point"}
}