{
  "type": "Feature",
  "properties": {
    "gn:admin1_code":"10.0",
    "gn:asciiname":"Zanwanwa",
    "gn:country_code":"LR",
    "gn:dem":83,
    "gn:feature_class":"P",
    "gn:feature_code":"PPL",
    "gn:name":"Zanwanwa",
    "gn:population":0,
    "gn:timezone":"Africa/Monrovia",
    "iso:country":"LR",
    "wof:name":"Zanwanwa",
    "wof:placetype":"locality"
},
  "geometry": {"coordinates":[-8.87063,5.49086],"type":"Point"}
}