{
  "type": "Feature",
  "properties": {
    "gn:admin1_code":"10.0",
    "gn:asciiname":"Jaday",
    "gn:country_code":"LR",
    "gn:dem":109,
    "gn:feature_class":"P",
    "gn:feature_code":"PPL",
    "gn:name":"Jaday",
    "gn:population":0,
    "gn:timezone":"Africa/Monrovia",
    "iso:country":"LR",
    "name:und_x_variant":[
        "Jelly",
        "Dijeli",
        "Jaday"
    ],
    "wof:name":"Jaday",
    "wof:placetype":"locality"
},
  "geometry": {"coordinates":[-8.71476,5.48667],"type":"Point"}
}