{
  "type": "Feature",
  "properties": {
    "gn:admin1_code":"11.0",
    "gn:asciiname":"Bawebli",
    "gn:country_code":"LR",
    "gn:dem":60,
    "gn:feature_class":"P",
    "gn:feature_code":"PPL",
    "gn:name":"Bawebli",
    "gn:population":0,
    "gn:timezone":"Africa/Monrovia",
    "iso:country":"LR",
    "wof:name":"Bawebli",
    "wof:placetype":"locality"
},
  "geometry": {"coordinates":[-9.75,5.88333],"type":"Point"}
}