{
  "type": "Feature",
  "properties": {
    "gn:admin1_code":"1.0",
    "gn:asciiname":"Momo Kolita",
    "gn:country_code":"LR",
    "gn:dem":131,
    "gn:feature_class":"P",
    "gn:feature_code":"PPL",
    "gn:name":"Momo Kolita",
    "gn:population":0,
    "gn:timezone":"Africa/Monrovia",
    "iso:country":"LR",
    "name:und_x_variant":[
        "Momolu Kolita",
        "Momo Kolita"
    ],
    "wof:name":"Momo Kolita",
    "wof:placetype":"locality"
},
  "geometry": {"coordinates":[-10.45025,6.8231],"type":"Point"}
}