{
  "type": "Feature",
  "properties": {
    "gn:admin1_code":"11.0",
    "gn:asciiname":"Johnny Gissi",
    "gn:country_code":"LR",
    "gn:dem":122,
    "gn:feature_class":"P",
    "gn:feature_code":"PPL",
    "gn:name":"Johnny Gissi",
    "gn:population":0,
    "gn:timezone":"Africa/Monrovia",
    "iso:country":"LR",
    "wof:name":"Johnny Gissi",
    "wof:placetype":"locality"
},
  "geometry": {"coordinates":[-10.11494,6.45197],"type":"Point"}
}