{
  "type": "Feature",
  "properties": {
    "gn:admin1_code":"12.0",
    "gn:asciiname":"Gboma",
    "gn:country_code":"LR",
    "gn:dem":17,
    "gn:feature_class":"P",
    "gn:feature_code":"PPL",
    "gn:name":"Gboma",
    "gn:population":0,
    "gn:timezone":"Africa/Monrovia",
    "iso:country":"LR",
    "name:und_x_variant":[
        "Boloma",
        "Baloma",
        "Gboma"
    ],
    "wof:name":"Gboma",
    "wof:placetype":"locality"
},
  "geometry": {"coordinates":[-11.37263,6.93336],"type":"Point"}
}