{
  "type": "Feature",
  "properties": {
    "gn:admin1_code":"14.0",
    "gn:asciiname":"Zepole",
    "gn:country_code":"LR",
    "gn:dem":11,
    "gn:feature_class":"P",
    "gn:feature_code":"PPL",
    "gn:name":"Zepole",
    "gn:population":0,
    "gn:timezone":"Africa/Monrovia",
    "iso:country":"LR",
    "wof:name":"Zepole",
    "wof:placetype":"locality"
},
  "geometry": {"coordinates":[-10.83333,6.43333],"type":"Point"}
}