{
  "type": "Feature",
  "properties": {
    "gn:admin1_code":"9.0",
    "gn:asciiname":"New Camp",
    "gn:country_code":"LR",
    "gn:dem":522,
    "gn:feature_class":"P",
    "gn:feature_code":"PPL",
    "gn:name":"New Camp",
    "gn:population":0,
    "gn:timezone":"Africa/Monrovia",
    "iso:country":"LR",
    "wof:name":"New Camp",
    "wof:placetype":"locality"
},
  "geometry": {"coordinates":[-8.57583,7.48111],"type":"Point"}
}