{
  "type": "Feature",
  "properties": {
    "gn:admin1_code":"11.0",
    "gn:asciiname":"Sumongar Village",
    "gn:country_code":"LR",
    "gn:dem":44,
    "gn:feature_class":"P",
    "gn:feature_code":"PPL",
    "gn:name":"Sumongar Village",
    "gn:population":0,
    "gn:timezone":"Africa/Monrovia",
    "iso:country":"LR",
    "wof:name":"Sumongar Village",
    "wof:placetype":"locality"
},
  "geometry": {"coordinates":[-10.19115,6.14777],"type":"Point"}
}