{
  "type": "Feature",
  "properties": {
    "gn:admin1_code":"12.0",
    "gn:asciiname":"Baja",
    "gn:cc2":"LR",
    "gn:country_code":"LR",
    "gn:dem":13,
    "gn:feature_class":"P",
    "gn:feature_code":"PPL",
    "gn:name":"Baja",
    "gn:population":0,
    "gn:timezone":"Africa/Monrovia",
    "iso:country":"LR",
    "name:und_x_variant":[
        "Zuani Kolinyindo",
        "Baja"
    ],
    "wof:name":"Baja",
    "wof:placetype":"locality"
},
  "geometry": {"coordinates":[-11.41167,6.95472],"type":"Point"}
}