{
  "type": "Feature",
  "properties": {
    "gn:admin1_code":"12.0",
    "gn:asciiname":"Baja",
    "gn:cc2":"LR",
    "gn:country_code":"LR",
    "gn:dem":13,
    "gn:feature_class":"P",
    "gn:feature_code":"PPL",
    "gn:name":"Baja",
    "gn:population":0,
    "gn:timezone":"Africa/Monrovia",
    "iso:country":"LR",
    "name:ceb_x_preferred":[
        "Baja"
    ],
    "name:deu_x_preferred":[
        "Baja"
    ],
    "name:fas_x_preferred":[
        "\u0628\u0627\u062e\u0627"
    ],
    "name:fra_x_preferred":[
        "Baja"
    ],
    "name:ita_x_preferred":[
        "Baja"
    ],
    "name:jpn_x_preferred":[
        "\u30d0\u30b8\u30e3"
    ],
    "name:lav_x_preferred":[
        "Baja"
    ],
    "name:lit_x_preferred":[
        "Baja"
    ],
    "name:nno_x_preferred":[
        "Baja"
    ],
    "name:nor_x_preferred":[
        "Baja"
    ],
    "name:pol_x_preferred":[
        "Baja"
    ],
    "name:por_x_preferred":[
        "Baja"
    ],
    "name:spa_x_preferred":[
        "Baja"
    ],
    "name:srp_x_preferred":[
        "Baja"
    ],
    "name:swe_x_preferred":[
        "Baja"
    ],
    "name:und_x_variant":[
        "Zuani Kolinyindo",
        "Baja"
    ],
    "wof:name":"Baja",
    "wof:placetype":"locality"
},
  "geometry": {"coordinates":[-11.41167,6.95472],"type":"Point"}
}