{
  "type": "Feature",
  "properties": {
    "gn:admin1_code":"22.0",
    "gn:asciiname":"River Gbe Estate",
    "gn:country_code":"LR",
    "gn:dem":105,
    "gn:feature_class":"P",
    "gn:feature_code":"PPL",
    "gn:name":"River Gbe Estate",
    "gn:population":0,
    "gn:timezone":"Africa/Monrovia",
    "iso:country":"LR",
    "wof:name":"River Gbe Estate",
    "wof:placetype":"locality"
},
  "geometry": {"coordinates":[-7.66361,5.21556],"type":"Point"}
}