{
  "type": "Feature",
  "properties": {
    "gn:admin1_code":"10.0",
    "gn:asciiname":"Talos",
    "gn:country_code":"LR",
    "gn:dem":101,
    "gn:feature_class":"P",
    "gn:feature_code":"PPL",
    "gn:name":"Talos",
    "gn:population":0,
    "gn:timezone":"Africa/Monrovia",
    "iso:country":"LR",
    "wof:name":"Talos",
    "wof:placetype":"locality"
},
  "geometry": {"coordinates":[-8.95,5.38333],"type":"Point"}
}