{
  "type": "Feature",
  "properties": {
    "gn:admin1_code":"21.0",
    "gn:asciiname":"Bolimo",
    "gn:country_code":"LR",
    "gn:dem":238,
    "gn:feature_class":"P",
    "gn:feature_code":"PPL",
    "gn:name":"Bolimo",
    "gn:population":0,
    "gn:timezone":"Africa/Monrovia",
    "iso:country":"LR",
    "name:und_x_variant":[
        "Bolima",
        "Bolimo"
    ],
    "wof:name":"Bolimo",
    "wof:placetype":"locality"
},
  "geometry": {"coordinates":[-10.28389,7.19944],"type":"Point"}
}