{
  "type": "Feature",
  "properties": {
    "gn:admin1_code":"14.0",
    "gn:asciiname":"Clay Ashland City",
    "gn:country_code":"LR",
    "gn:dem":31,
    "gn:feature_class":"P",
    "gn:feature_code":"PPL",
    "gn:name":"Clay Ashland City",
    "gn:population":0,
    "gn:timezone":"Africa/Monrovia",
    "iso:country":"LR",
    "name:und_x_variant":[
        "Buba Town",
        "Gboba",
        "Gbuba Town",
        "Konma Number One",
        "Clay Ashland City"
    ],
    "wof:name":"Clay Ashland City",
    "wof:placetype":"locality"
},
  "geometry": {"coordinates":[-10.75477,6.51112],"type":"Point"}
}