{
  "type": "Feature",
  "properties": {
    "gn:admin1_code":"1.0",
    "gn:asciiname":"Gbonkonima",
    "gn:cc2":"LR",
    "gn:country_code":"LR",
    "gn:dem":266,
    "gn:feature_class":"P",
    "gn:feature_code":"PPL",
    "gn:name":"Gbonkonima",
    "gn:population":0,
    "gn:timezone":"Africa/Monrovia",
    "iso:country":"LR",
    "name:und_x_variant":[
        "Bomganima",
        "Gbonkonema",
        "Bamganima",
        "Gbongkonima",
        "Gbonkonima"
    ],
    "wof:name":"Gbonkonima",
    "wof:placetype":"locality"
},
  "geometry": {"coordinates":[-9.84278,6.84028],"type":"Point"}
}