{
  "type": "Feature",
  "properties": {
    "gn:admin1_code":"9.0",
    "gn:asciiname":"Nyarnkiayee",
    "gn:cc2":"LR",
    "gn:country_code":"LR",
    "gn:dem":218,
    "gn:feature_class":"P",
    "gn:feature_code":"PPL",
    "gn:name":"Nyarnkiayee",
    "gn:population":0,
    "gn:timezone":"Africa/Monrovia",
    "iso:country":"LR",
    "name:und_x_variant":[
        "Yonieyie",
        "Nyoneayii",
        "Nyoneayie",
        "Nyarnkiayee"
    ],
    "wof:name":"Nyarnkiayee",
    "wof:placetype":"locality"
},
  "geometry": {"coordinates":[-9.04278,6.82472],"type":"Point"}
}