{
  "type": "Feature",
  "properties": {
    "gn:admin1_code":"1.0",
    "gn:asciiname":"Donya",
    "gn:country_code":"LR",
    "gn:dem":224,
    "gn:feature_class":"P",
    "gn:feature_code":"PPL",
    "gn:name":"Donya",
    "gn:population":0,
    "gn:timezone":"Africa/Monrovia",
    "iso:country":"LR",
    "name:eng_x_preferred":[
        "Donya"
    ],
    "name:fas_x_preferred":[
        "\u062f\u0646\u06cc\u0627"
    ],
    "wof:name":"Donya",
    "wof:placetype":"locality"
},
  "geometry": {"coordinates":[-9.51523,6.64901],"type":"Point"}
}