{
  "type": "Feature",
  "properties": {
    "gn:admin1_code":"14.0",
    "gn:asciiname":"Nyoje Town",
    "gn:country_code":"LR",
    "gn:dem":16,
    "gn:feature_class":"P",
    "gn:feature_code":"PPL",
    "gn:name":"Nyoje Town",
    "gn:population":0,
    "gn:timezone":"Africa/Monrovia",
    "iso:country":"LR",
    "wof:name":"Nyoje Town",
    "wof:placetype":"locality"
},
  "geometry": {"coordinates":[-10.69361,6.24111],"type":"Point"}
}