{
  "type": "Feature",
  "properties": {
    "gn:admin1_code":"1.0",
    "gn:asciiname":"Tugbata",
    "gn:country_code":"LR",
    "gn:dem":218,
    "gn:feature_class":"P",
    "gn:feature_code":"PPL",
    "gn:name":"Tugbata",
    "gn:population":0,
    "gn:timezone":"Africa/Monrovia",
    "iso:country":"LR",
    "name:und_x_variant":[
        "Tukpo",
        "Tukpa",
        "Tugbata",
        "Bota"
    ],
    "wof:name":"Tugbata",
    "wof:placetype":"locality"
},
  "geometry": {"coordinates":[-9.4292,6.5885],"type":"Point"}
}