{
  "type": "Feature",
  "properties": {
    "gn:admin1_code":"12.0",
    "gn:asciiname":"Camp Israel",
    "gn:country_code":"LR",
    "gn:dem":199,
    "gn:feature_class":"P",
    "gn:feature_code":"PPL",
    "gn:name":"Camp Israel",
    "gn:population":0,
    "gn:timezone":"Africa/Monrovia",
    "iso:country":"LR",
    "wof:name":"Camp Israel",
    "wof:placetype":"locality"
},
  "geometry": {"coordinates":[-10.85104,7.37914],"type":"Point"}
}