{
  "type": "Feature",
  "properties": {
    "gn:admin1_code":"9.0",
    "gn:asciiname":"Gbankoi",
    "gn:cc2":"LR",
    "gn:country_code":"LR",
    "gn:dem":247,
    "gn:feature_class":"P",
    "gn:feature_code":"PPL",
    "gn:name":"Gbankoi",
    "gn:population":0,
    "gn:timezone":"Africa/Monrovia",
    "iso:country":"LR",
    "name:und_x_variant":[
        "Yasien",
        "Gben-Quei",
        "Yasiohn",
        "Gbankoi"
    ],
    "wof:name":"Gbankoi",
    "wof:placetype":"locality"
},
  "geometry": {"coordinates":[-8.84389,6.91444],"type":"Point"}
}