{
  "type": "Feature",
  "properties": {
    "gn:admin1_code":"14.0",
    "gn:asciiname":"Yahkpai Quiwood",
    "gn:country_code":"LR",
    "gn:dem":127,
    "gn:feature_class":"P",
    "gn:feature_code":"PPL",
    "gn:name":"Yahkpai Quiwood",
    "gn:population":0,
    "gn:timezone":"Africa/Monrovia",
    "iso:country":"LR",
    "wof:name":"Yahkpai Quiwood",
    "wof:placetype":"locality"
},
  "geometry": {"coordinates":[-10.48531,6.7318],"type":"Point"}
}