{
  "type": "Feature",
  "properties": {
    "gn:admin1_code":"20.0",
    "gn:asciiname":"Loboba",
    "gn:country_code":"LR",
    "gn:dem":563,
    "gn:feature_class":"P",
    "gn:feature_code":"PPL",
    "gn:name":"Loboba",
    "gn:population":0,
    "gn:timezone":"Africa/Monrovia",
    "iso:country":"LR",
    "wof:name":"Loboba",
    "wof:placetype":"locality"
},
  "geometry": {"coordinates":[-9.90583,8.38722],"type":"Point"}
}