{
  "type": "Feature",
  "properties": {
    "gn:admin1_code":"10.0",
    "gn:asciiname":"Doe Town",
    "gn:country_code":"LR",
    "gn:dem":79,
    "gn:feature_class":"P",
    "gn:feature_code":"PPL",
    "gn:name":"Doe Town",
    "gn:population":0,
    "gn:timezone":"Africa/Monrovia",
    "iso:country":"LR",
    "wof:name":"Doe Town",
    "wof:placetype":"locality"
},
  "geometry": {"coordinates":[-8.99694,5.20694],"type":"Point"}
}