{
  "type": "Feature",
  "properties": {
    "gn:admin1_code":"9.0",
    "gn:asciiname":"Kpei-Lepula",
    "gn:cc2":"LR",
    "gn:country_code":"LR",
    "gn:dem":407,
    "gn:feature_class":"P",
    "gn:feature_code":"PPL",
    "gn:name":"Kpei-Lepula",
    "gn:population":0,
    "gn:timezone":"Africa/Monrovia",
    "iso:country":"LR",
    "name:und_x_variant":[
        "Be Town",
        "Kpelepula",
        "Kpayelepula",
        "Kpeilepula",
        "Kpeilepola",
        "Kpei-Lepula"
    ],
    "wof:name":"Kpei-Lepula",
    "wof:placetype":"locality"
},
  "geometry": {"coordinates":[-8.69222,7.22194],"type":"Point"}
}