{
  "type": "Feature",
  "properties": {
    "gn:admin1_code":"12.0",
    "gn:asciiname":"Sanjanamalo",
    "gn:country_code":"LR",
    "gn:dem":33,
    "gn:feature_class":"P",
    "gn:feature_code":"PPL",
    "gn:name":"Sanjanamalo",
    "gn:population":0,
    "gn:timezone":"Africa/Monrovia",
    "iso:country":"LR",
    "name:und_x_variant":[
        "Kumale Duko",
        "Sanjanamalo"
    ],
    "wof:name":"Sanjanamalo",
    "wof:placetype":"locality"
},
  "geometry": {"coordinates":[-11.13598,6.75213],"type":"Point"}
}