{
  "type": "Feature",
  "properties": {
    "gn:admin1_code":"21.0",
    "gn:asciiname":"Kato",
    "gn:country_code":"LR",
    "gn:dem":238,
    "gn:feature_class":"P",
    "gn:feature_code":"PPL",
    "gn:name":"Kato",
    "gn:population":0,
    "gn:timezone":"Africa/Monrovia",
    "iso:country":"LR",
    "wof:name":"Kato",
    "wof:placetype":"locality"
},
  "geometry": {"coordinates":[-10.23194,7.21472],"type":"Point"}
}