{
  "type": "Feature",
  "properties": {
    "gn:admin1_code":"11.0",
    "gn:asciiname":"Yukwebli",
    "gn:cc2":"LR",
    "gn:country_code":"LR",
    "gn:dem":142,
    "gn:feature_class":"P",
    "gn:feature_code":"PPL",
    "gn:name":"Yukwebli",
    "gn:population":0,
    "gn:timezone":"Africa/Monrovia",
    "iso:country":"LR",
    "name:und_x_variant":[
        "Yuk Bee Town",
        "Yukwebli"
    ],
    "wof:name":"Yukwebli",
    "wof:placetype":"locality"
},
  "geometry": {"coordinates":[-9.68333,6.23333],"type":"Point"}
}