{
  "type": "Feature",
  "properties": {
    "gn:admin1_code":"21.0",
    "gn:asciiname":"Fassama",
    "gn:country_code":"LR",
    "gn:dem":447,
    "gn:feature_class":"P",
    "gn:feature_code":"PPL",
    "gn:name":"Fassama",
    "gn:population":0,
    "gn:timezone":"Africa/Monrovia",
    "iso:country":"LR",
    "name:und_x_variant":[
        "Fasama",
        "Fasima",
        "Fassama"
    ],
    "wof:name":"Fassama",
    "wof:placetype":"locality"
},
  "geometry": {"coordinates":[-9.99944,7.52222],"type":"Point"}
}