{
  "type": "Feature",
  "properties": {
    "gn:admin1_code":"11.0",
    "gn:asciiname":"Koyata",
    "gn:country_code":"LR",
    "gn:dem":199,
    "gn:feature_class":"P",
    "gn:feature_code":"PPL",
    "gn:name":"Koyata",
    "gn:population":0,
    "gn:timezone":"Africa/Monrovia",
    "iso:country":"LR",
    "wof:name":"Koyata",
    "wof:placetype":"locality"
},
  "geometry": {"coordinates":[-9.31667,6.55],"type":"Point"}
}