{
  "type": "Feature",
  "properties": {
    "gn:admin1_code":"12.0",
    "gn:asciiname":"Sombaja",
    "gn:country_code":"LR",
    "gn:dem":19,
    "gn:feature_class":"P",
    "gn:feature_code":"PPL",
    "gn:name":"Sombaja",
    "gn:population":0,
    "gn:timezone":"Africa/Monrovia",
    "iso:country":"LR",
    "wof:name":"Sombaja",
    "wof:placetype":"locality"
},
  "geometry": {"coordinates":[-11.21705,6.88215],"type":"Point"}
}