{
  "type": "Feature",
  "properties": {
    "gn:admin1_code":"20.0",
    "gn:asciiname":"Wanlezu",
    "gn:cc2":"LR",
    "gn:country_code":"LR",
    "gn:dem":391,
    "gn:feature_class":"P",
    "gn:feature_code":"PPL",
    "gn:name":"Wanlezu",
    "gn:population":0,
    "gn:timezone":"Africa/Monrovia",
    "iso:country":"LR",
    "name:und_x_variant":[
        "Wanlema",
        "Wahnlemai",
        "Walema",
        "Wanlezu"
    ],
    "wof:name":"Wanlezu",
    "wof:placetype":"locality"
},
  "geometry": {"coordinates":[-9.91278,7.90639],"type":"Point"}
}