{
  "type": "Feature",
  "properties": {
    "gn:admin1_code":"1.0",
    "gn:asciiname":"Zayzayta",
    "gn:country_code":"LR",
    "gn:dem":231,
    "gn:feature_class":"P",
    "gn:feature_code":"PPL",
    "gn:name":"Zayzayta",
    "gn:population":0,
    "gn:timezone":"Africa/Monrovia",
    "iso:country":"LR",
    "name:eng_x_preferred":[
        "Zayzayta"
    ],
    "wof:name":"Zayzayta",
    "wof:placetype":"locality"
},
  "geometry": {"coordinates":[-9.2557,6.81671],"type":"Point"}
}