{
  "type": "Feature",
  "properties": {
    "gn:admin1_code":"16.0",
    "gn:asciiname":"Nifu",
    "gn:country_code":"LR",
    "gn:dem":12,
    "gn:feature_class":"P",
    "gn:feature_code":"PPL",
    "gn:name":"Nifu",
    "gn:population":0,
    "gn:timezone":"Africa/Monrovia",
    "iso:country":"LR",
    "name:und_x_variant":[
        "Nefu",
        "Nifo",
        "Nifu"
    ],
    "wof:name":"Nifu",
    "wof:placetype":"locality"
},
  "geometry": {"coordinates":[-8.53819,4.74509],"type":"Point"}
}