{
  "type": "Feature",
  "properties": {
    "gn:admin1_code":"15.0",
    "gn:asciiname":"Boola Bosou",
    "gn:country_code":"LR",
    "gn:dem":73,
    "gn:feature_class":"P",
    "gn:feature_code":"PPL",
    "gn:name":"Boola Bosou",
    "gn:population":0,
    "gn:timezone":"Africa/Monrovia",
    "iso:country":"LR",
    "wof:name":"Boola Bosou",
    "wof:placetype":"locality"
},
  "geometry": {"coordinates":[-10.68333,6.68333],"type":"Point"}
}