{
  "type": "Feature",
  "properties": {
    "gn:admin1_code":"12.0",
    "gn:asciiname":"Diopo",
    "gn:country_code":"LR",
    "gn:dem":105,
    "gn:feature_class":"P",
    "gn:feature_code":"PPL",
    "gn:name":"Diopo",
    "gn:population":0,
    "gn:timezone":"Africa/Monrovia",
    "iso:country":"LR",
    "wof:name":"Diopo",
    "wof:placetype":"locality"
},
  "geometry": {"coordinates":[-10.71667,7.18333],"type":"Point"}
}