{
  "type": "Feature",
  "properties": {
    "gn:admin1_code":"14.0",
    "gn:asciiname":"Steel Farm",
    "gn:country_code":"LR",
    "gn:dem":137,
    "gn:feature_class":"P",
    "gn:feature_code":"PPL",
    "gn:name":"Steel Farm",
    "gn:population":0,
    "gn:timezone":"Africa/Monrovia",
    "iso:country":"LR",
    "wof:name":"Steel Farm",
    "wof:placetype":"locality"
},
  "geometry": {"coordinates":[-10.43578,6.75254],"type":"Point"}
}