{
  "type": "Feature",
  "properties": {
    "gn:admin1_code":"19.0",
    "gn:asciiname":"Barwu",
    "gn:country_code":"LR",
    "gn:dem":214,
    "gn:feature_class":"P",
    "gn:feature_code":"PPL",
    "gn:name":"Barwu",
    "gn:population":0,
    "gn:timezone":"Africa/Monrovia",
    "iso:country":"LR",
    "wof:name":"Barwu",
    "wof:placetype":"locality"
},
  "geometry": {"coordinates":[-7.73289,5.85136],"type":"Point"}
}