{
  "type": "Feature",
  "properties": {
    "gn:admin1_code":"13.0",
    "gn:asciiname":"Jreake",
    "gn:country_code":"LR",
    "gn:dem":88,
    "gn:feature_class":"P",
    "gn:feature_code":"PPL",
    "gn:name":"Jreake",
    "gn:population":0,
    "gn:timezone":"Africa/Monrovia",
    "iso:country":"LR",
    "name:und_x_variant":[
        "Gbaiso"
    ],
    "wof:name":"Jreake",
    "wof:placetype":"locality"
},
  "geometry": {"coordinates":[-7.6918,4.69046],"type":"Point"}
}