{
  "type": "Feature",
  "properties": {
    "gn:admin1_code":"9.0",
    "gn:asciiname":"Fairplay",
    "gn:country_code":"LR",
    "gn:dem":245,
    "gn:feature_class":"P",
    "gn:feature_code":"PPL",
    "gn:name":"Fairplay",
    "gn:population":0,
    "gn:timezone":"Africa/Monrovia",
    "iso:country":"LR",
    "wof:name":"Fairplay",
    "wof:placetype":"locality"
},
  "geometry": {"coordinates":[-8.75333,6.96167],"type":"Point"}
}