{
  "type": "Feature",
  "properties": {
    "gn:admin1_code":"20.0",
    "gn:asciiname":"Ayema",
    "gn:cc2":"LR",
    "gn:country_code":"LR",
    "gn:dem":408,
    "gn:feature_class":"P",
    "gn:feature_code":"PPL",
    "gn:name":"Ayema",
    "gn:population":0,
    "gn:timezone":"Africa/Monrovia",
    "iso:country":"LR",
    "name:und_x_variant":[
        "Ayima",
        "Ayema"
    ],
    "wof:name":"Ayema",
    "wof:placetype":"locality"
},
  "geometry": {"coordinates":[-9.52556,8.24167],"type":"Point"}
}