{
  "type": "Feature",
  "properties": {
    "gn:admin1_code":"17.0",
    "gn:asciiname":"Bofeng",
    "gn:cc2":"LR",
    "gn:country_code":"LR",
    "gn:dem":129,
    "gn:feature_class":"P",
    "gn:feature_code":"PPL",
    "gn:name":"Bofeng",
    "gn:population":0,
    "gn:timezone":"Africa/Monrovia",
    "iso:country":"LR",
    "name:und_x_variant":[
        "Bawfeng",
        "Bofeng"
    ],
    "wof:name":"Bofeng",
    "wof:placetype":"locality"
},
  "geometry": {"coordinates":[-9.98333,6.61667],"type":"Point"}
}