{
  "type": "Feature",
  "properties": {
    "gn:admin1_code":"18.0",
    "gn:asciiname":"Chuwohnbli",
    "gn:country_code":"LR",
    "gn:dem":79,
    "gn:feature_class":"P",
    "gn:feature_code":"PPL",
    "gn:name":"Chuwohnbli",
    "gn:population":0,
    "gn:timezone":"Africa/Monrovia",
    "iso:country":"LR",
    "wof:name":"Chuwohnbli",
    "wof:placetype":"locality"
},
  "geometry": {"coordinates":[-9.62609,5.89795],"type":"Point"}
}