{
  "type": "Feature",
  "properties": {
    "gn:admin1_code":"10.0",
    "gn:asciiname":"Chatugba",
    "gn:country_code":"LR",
    "gn:dem":143,
    "gn:feature_class":"P",
    "gn:feature_code":"PPL",
    "gn:name":"Chatugba",
    "gn:population":0,
    "gn:timezone":"Africa/Monrovia",
    "iso:country":"LR",
    "wof:name":"Chatugba",
    "wof:placetype":"locality"
},
  "geometry": {"coordinates":[-8.59134,5.23812],"type":"Point"}
}