{
  "type": "Feature",
  "properties": {
    "gn:admin1_code":"1.0",
    "gn:asciiname":"Wonupolukai",
    "gn:country_code":"LR",
    "gn:dem":301,
    "gn:feature_class":"P",
    "gn:feature_code":"PPL",
    "gn:name":"Wonupolukai",
    "gn:population":0,
    "gn:timezone":"Africa/Monrovia",
    "iso:country":"LR",
    "name:eng_x_preferred":[
        "Wonupolukai"
    ],
    "wof:name":"Wonupolukai",
    "wof:placetype":"locality"
},
  "geometry": {"coordinates":[-9.48575,7.1389],"type":"Point"}
}