{
  "type": "Feature",
  "properties": {
    "gn:admin1_code":"1.0",
    "gn:asciiname":"Zangbiama",
    "gn:country_code":"LR",
    "gn:dem":159,
    "gn:feature_class":"P",
    "gn:feature_code":"PPL",
    "gn:name":"Zangbiama",
    "gn:population":0,
    "gn:timezone":"Africa/Monrovia",
    "iso:country":"LR",
    "name:eng_x_preferred":[
        "Zangbiama"
    ],
    "wof:name":"Zangbiama",
    "wof:placetype":"locality"
},
  "geometry": {"coordinates":[-10.40612,6.80112],"type":"Point"}
}