{
  "type": "Feature",
  "properties": {
    "gn:admin1_code":"21.0",
    "gn:asciiname":"Guyata",
    "gn:country_code":"LR",
    "gn:dem":146,
    "gn:feature_class":"P",
    "gn:feature_code":"PPL",
    "gn:name":"Guyata",
    "gn:population":0,
    "gn:timezone":"Africa/Monrovia",
    "iso:country":"LR",
    "name:und_x_variant":[
        "Gunyata",
        "Guyata"
    ],
    "wof:name":"Guyata",
    "wof:placetype":"locality"
},
  "geometry": {"coordinates":[-10.54222,7.0975],"type":"Point"}
}