{
  "type": "Feature",
  "properties": {
    "gn:admin1_code":"13.0",
    "gn:asciiname":"Nemeke",
    "gn:country_code":"LR",
    "gn:dem":15,
    "gn:feature_class":"P",
    "gn:feature_code":"PPL",
    "gn:name":"Nemeke",
    "gn:population":0,
    "gn:timezone":"Africa/Monrovia",
    "iso:country":"LR",
    "name:und_x_variant":[
        "Nemakehn"
    ],
    "wof:name":"Nemeke",
    "wof:placetype":"locality"
},
  "geometry": {"coordinates":[-7.57766,4.58848],"type":"Point"}
}