{
  "type": "Feature",
  "properties": {
    "gn:admin1_code":"11.0",
    "gn:asciiname":"Kpakon",
    "gn:country_code":"LR",
    "gn:dem":217,
    "gn:feature_class":"P",
    "gn:feature_code":"PPL",
    "gn:name":"Kpakon",
    "gn:population":0,
    "gn:timezone":"Africa/Monrovia",
    "iso:country":"LR",
    "name:und_x_variant":[
        "Bokta"
    ],
    "wof:name":"Kpakon",
    "wof:placetype":"locality"
},
  "geometry": {"coordinates":[-9.28828,6.57539],"type":"Point"}
}