{
  "type": "Feature",
  "properties": {
    "gn:admin1_code":"1.0",
    "gn:asciiname":"Nyangoi",
    "gn:country_code":"LR",
    "gn:dem":255,
    "gn:feature_class":"P",
    "gn:feature_code":"PPL",
    "gn:name":"Nyangoi",
    "gn:population":0,
    "gn:timezone":"Africa/Monrovia",
    "iso:country":"LR",
    "name:eng_x_preferred":[
        "Nyangoi"
    ],
    "name:und_x_variant":[
        "Ngangwoi",
        "Nyangele",
        "Nyangwele",
        "Nganagwoi",
        "Nyangoli",
        "Nyanweh"
    ],
    "wof:name":"Nyangoi",
    "wof:placetype":"locality"
},
  "geometry": {"coordinates":[-9.57668,6.94302],"type":"Point"}
}