{
  "type": "Feature",
  "properties": {
    "gn:admin1_code":"11.0",
    "gn:asciiname":"Tubmabli",
    "gn:country_code":"LR",
    "gn:dem":46,
    "gn:feature_class":"P",
    "gn:feature_code":"PPL",
    "gn:name":"Tubmabli",
    "gn:population":0,
    "gn:timezone":"Africa/Monrovia",
    "iso:country":"LR",
    "name:und_x_variant":[
        "Tubmanbli",
        "Tubmabli"
    ],
    "wof:name":"Tubmabli",
    "wof:placetype":"locality"
},
  "geometry": {"coordinates":[-9.91604,5.91623],"type":"Point"}
}