{
  "type": "Feature",
  "properties": {
    "gn:admin1_code":"14.0",
    "gn:asciiname":"Dupa Town",
    "gn:country_code":"LR",
    "gn:dem":27,
    "gn:feature_class":"P",
    "gn:feature_code":"PPL",
    "gn:name":"Dupa Town",
    "gn:population":0,
    "gn:timezone":"Africa/Monrovia",
    "iso:country":"LR",
    "name:und_x_variant":[
        "Dupa",
        "Dupa Town"
    ],
    "wof:name":"Dupa Town",
    "wof:placetype":"locality"
},
  "geometry": {"coordinates":[-10.66444,6.41284],"type":"Point"}
}