{
  "type": "Feature",
  "properties": {
    "gn:admin1_code":"19.0",
    "gn:asciiname":"Tarloken",
    "gn:country_code":"LR",
    "gn:dem":173,
    "gn:feature_class":"P",
    "gn:feature_code":"PPL",
    "gn:name":"Tarloken",
    "gn:population":0,
    "gn:timezone":"Africa/Monrovia",
    "iso:country":"LR",
    "name:und_x_variant":[
        "Tawrokehn",
        "Talokehn",
        "Tarwroken",
        "Tarloken"
    ],
    "wof:name":"Tarloken",
    "wof:placetype":"locality"
},
  "geometry": {"coordinates":[-7.58104,5.83858],"type":"Point"}
}