{
  "type": "Feature",
  "properties": {
    "gn:admin1_code":"20.0",
    "gn:asciiname":"Bunabo",
    "gn:country_code":"LR",
    "gn:dem":258,
    "gn:feature_class":"P",
    "gn:feature_code":"PPL",
    "gn:name":"Bunabo",
    "gn:population":0,
    "gn:timezone":"Africa/Monrovia",
    "iso:country":"LR",
    "wof:name":"Bunabo",
    "wof:placetype":"locality"
},
  "geometry": {"coordinates":[-10.50667,8.04611],"type":"Point"}
}