{
  "type": "Feature",
  "properties": {
    "gn:admin1_code":"14.0",
    "gn:asciiname":"Sinje",
    "gn:country_code":"LR",
    "gn:dem":30,
    "gn:feature_class":"P",
    "gn:feature_code":"PPL",
    "gn:name":"Sinje",
    "gn:population":0,
    "gn:timezone":"Africa/Monrovia",
    "iso:country":"LR",
    "wof:name":"Sinje",
    "wof:placetype":"locality"
},
  "geometry": {"coordinates":[-10.9475,6.54667],"type":"Point"}
}