{
  "type": "Feature",
  "properties": {
    "gn:admin1_code":"18.0",
    "gn:asciiname":"Fahn Dehgar Town",
    "gn:country_code":"LR",
    "gn:dem":227,
    "gn:feature_class":"P",
    "gn:feature_code":"PPL",
    "gn:name":"Fahn Dehgar Town",
    "gn:population":0,
    "gn:timezone":"Africa/Monrovia",
    "iso:country":"LR",
    "name:und_x_variant":[
        "Bii Town",
        "Fahn Dehgar Town"
    ],
    "wof:name":"Fahn Dehgar Town",
    "wof:placetype":"locality"
},
  "geometry": {"coordinates":[-9.17807,6.30961],"type":"Point"}
}