{
  "type": "Feature",
  "properties": {
    "gn:admin1_code":"1.0",
    "gn:asciiname":"Pepeta",
    "gn:country_code":"LR",
    "gn:dem":255,
    "gn:feature_class":"P",
    "gn:feature_code":"PPL",
    "gn:name":"Pepeta",
    "gn:population":0,
    "gn:timezone":"Africa/Monrovia",
    "iso:country":"LR",
    "name:eng_x_preferred":[
        "Pepeta"
    ],
    "wof:name":"Pepeta",
    "wof:placetype":"locality"
},
  "geometry": {"coordinates":[-9.41083,6.84306],"type":"Point"}
}