{
  "type": "Feature",
  "properties": {
    "gn:admin1_code":"11.0",
    "gn:asciiname":"Koyah",
    "gn:country_code":"LR",
    "gn:dem":169,
    "gn:feature_class":"P",
    "gn:feature_code":"PPL",
    "gn:name":"Koyah",
    "gn:population":0,
    "gn:timezone":"Africa/Monrovia",
    "iso:country":"LR",
    "wof:name":"Koyah",
    "wof:placetype":"locality"
},
  "geometry": {"coordinates":[-9.83983,6.37902],"type":"Point"}
}