{
  "type": "Feature",
  "properties": {
    "gn:admin1_code":"12.0",
    "gn:asciiname":"Lumbakai",
    "gn:country_code":"LR",
    "gn:dem":15,
    "gn:feature_class":"P",
    "gn:feature_code":"PPL",
    "gn:name":"Lumbakai",
    "gn:population":0,
    "gn:timezone":"Africa/Monrovia",
    "iso:country":"LR",
    "name:und_x_variant":[
        "Lumboko",
        "Lumbakae",
        "Lumbakai"
    ],
    "wof:name":"Lumbakai",
    "wof:placetype":"locality"
},
  "geometry": {"coordinates":[-11.41341,6.97283],"type":"Point"}
}