{
  "type": "Feature",
  "properties": {
    "gn:admin1_code":"12.0",
    "gn:asciiname":"Masale Camp",
    "gn:country_code":"LR",
    "gn:dem":102,
    "gn:feature_class":"P",
    "gn:feature_code":"PPL",
    "gn:name":"Masale Camp",
    "gn:population":0,
    "gn:timezone":"Africa/Monrovia",
    "iso:country":"LR",
    "wof:name":"Masale Camp",
    "wof:placetype":"locality"
},
  "geometry": {"coordinates":[-10.78333,7.13333],"type":"Point"}
}