{
  "type": "Feature",
  "properties": {
    "gn:admin1_code":"12.0",
    "gn:asciiname":"Tahn Mafa",
    "gn:country_code":"LR",
    "gn:dem":44,
    "gn:feature_class":"P",
    "gn:feature_code":"PPL",
    "gn:name":"Tahn Mafa",
    "gn:population":0,
    "gn:timezone":"Africa/Monrovia",
    "iso:country":"LR",
    "wof:name":"Tahn Mafa",
    "wof:placetype":"locality"
},
  "geometry": {"coordinates":[-11.22541,6.98055],"type":"Point"}
}