{
  "type": "Feature",
  "properties": {
    "gn:admin1_code":"1.0",
    "gn:asciiname":"Koryah",
    "gn:country_code":"LR",
    "gn:dem":288,
    "gn:feature_class":"P",
    "gn:feature_code":"PPL",
    "gn:name":"Koryah",
    "gn:population":0,
    "gn:timezone":"Africa/Monrovia",
    "iso:country":"LR",
    "name:eng_x_preferred":[
        "Koryah"
    ],
    "name:und_x_variant":[
        "Quoyah",
        "Kuoya"
    ],
    "wof:name":"Koryah",
    "wof:placetype":"locality"
},
  "geometry": {"coordinates":[-9.14956,7.24444],"type":"Point"}
}