{
  "type": "Feature",
  "properties": {
    "gn:admin1_code":"10.0",
    "gn:asciiname":"Nyearwken",
    "gn:country_code":"LR",
    "gn:dem":170,
    "gn:feature_class":"P",
    "gn:feature_code":"PPL",
    "gn:name":"Nyearwken",
    "gn:population":0,
    "gn:timezone":"Africa/Monrovia",
    "iso:country":"LR",
    "wof:name":"Nyearwken",
    "wof:placetype":"locality"
},
  "geometry": {"coordinates":[-8.53739,5.32666],"type":"Point"}
}