{
  "type": "Feature",
  "properties": {
    "gn:admin1_code":"1.0",
    "gn:asciiname":"Yazata",
    "gn:country_code":"LR",
    "gn:dem":233,
    "gn:feature_class":"P",
    "gn:feature_code":"PPL",
    "gn:name":"Yazata",
    "gn:population":0,
    "gn:timezone":"Africa/Monrovia",
    "iso:country":"LR",
    "name:ara_x_preferred":[
        "\u0627\u06cc\u0632\u062f\u0627\u0646"
    ],
    "name:ces_x_preferred":[
        "Jazata"
    ],
    "name:dan_x_preferred":[
        "Yazata"
    ],
    "name:deu_x_preferred":[
        "Yazata"
    ],
    "name:diq_x_preferred":[
        "Yazata"
    ],
    "name:eng_x_preferred":[
        "Yazata"
    ],
    "name:fas_x_preferred":[
        "\u0627\u06cc\u0632\u062f"
    ],
    "name:fra_x_preferred":[
        "Yazata"
    ],
    "name:hin_x_preferred":[
        "\u092f\u091c\u093c\u0924"
    ],
    "name:jpn_x_preferred":[
        "\u30e4\u30b6\u30bf"
    ],
    "name:kor_x_preferred":[
        "\uc57c\uc790\ud0c0"
    ],
    "name:lit_x_preferred":[
        "Jazatai"
    ],
    "name:mkd_x_preferred":[
        "\u0408\u0430\u0437\u0430\u0442\u0430"
    ],
    "name:nno_x_preferred":[
        "Yazata"
    ],
    "name:nor_x_preferred":[
        "Yazata"
    ],
    "name:pus_x_preferred":[
        "\u062e\u062f\u0627\u064a\u06af\u0648\u067c\u06cc"
    ],
    "name:ron_x_preferred":[
        "Yazatas"
    ],
    "name:rus_x_preferred":[
        "\u042f\u0437\u0430\u0442\u044b"
    ],
    "name:spa_x_preferred":[
        "Yazata"
    ],
    "name:zho_x_preferred":[
        "\u4e9a\u624e\u5854"
    ],
    "wof:name":"Yazata",
    "wof:placetype":"locality"
},
  "geometry": {"coordinates":[-9.69567,6.83663],"type":"Point"}
}